Workbook
Name LastActual: Inputs!$B$3
Name CPLHTol: Inputs!$B$7
Name WageDates: Inputs!$A$21:$A$28
Name WageRates: Inputs!$B$21:$B$28
Name PH_Roster: Inputs!$B$31
Name PH_Loading: Inputs!$B$32
Name SiteCodes: Inputs!$A$36:$A$45

Sheet README
A1: Warehouse payroll forecast model (simple version)
A2: Synthetic data only. Monthly, Jan 2025 to Dec 2028.
A4: THE MODEL (per site, per forecast month)
A5: Sales and payroll % come from the plan (Plan_Inputs). They drive everything.
A6: Total payroll = plan sales x plan payroll %.
A7: Leadership = total payroll x leadership share of total payroll in the same month last year.
A8: Staff payroll = total payroll - leadership.
A9: Cost per hour = same month last year's cost per hour, with last year's public holidays and wage index taken out
A10: and this month's put back in. Hours = staff payroll / cost per hour.
A11: Cases come from the Cases_Forecast tab: volume driver sales x cases per $ in the same month last year,
A12: plus your adjustments, or your override.
A13: CPLH = cases / hours. Cost per case = total payroll / cases.
... A30: Public holidays are generated by rule; check against the official state lists (AFL Grand Final Friday in particular).

Sheet Inputs
A1: Inputs
A3: Last actual month | B3: 46266
A5: Model status | B5: =Checks!B3
A7: Warn if forecast CPLH moves more than this vs LY | B7: 0.1
A19: Wage increases (staff cost per hour)
A20: Effective month | B20: Increase
A21: 46023 | B21: 0.04 | C21: Include past increases too: last year's cost per hour is divided by its wage index before this year's is applied.
A22: 46388 | B22: 0.045
A23: 46753 | B23: 0.045
A30: Public holidays
A31: Share of normal hours worked on a PH | B31: 0.5
A32: PH pay loading (1.5 = paid 250%) | B32: 1.5
A34: Sites | B34: Type your own codes in the Code column; every tab follows. Renaming the tabs to match is optional.
A35: Code | B35: Type | C35: State | D35: Payroll % basis | E35: In national sales? | F35: Volume driver
A36: NSW-1 | B36: Region | C36: NSW | D36: =A36 | E36: Yes | F36: =A36
A37: VIC-1 | B37: Region | C37: VIC | D37: =A37 | E37: Yes | F37: =A37
A38: QLD-1 | B38: Region | C38: QLD | D38: =A38 | E38: Yes | F38: =A38
A39: NSW-2 | B39: Region | C39: NSW | D39: =A39 | E39: Yes | F39: =A39
A40: VIC-2 | B40: Region | C40: VIC | D40: =A40 | E40: Yes | F40: =A40
A41: QLD-2 | B41: Region | C41: QLD | D41: =A41 | E41: Yes | F41: =A41
A42: SA-1 | B42: Region | C42: SA | D42: =A42 | E42: Yes | F42: =A42
A43: WA-1 | B43: Region | C43: WA | D43: =A43 | E43: Yes | F43: =A43
A44: IDC-NSW | B44: IDC | C44: NSW | D44: =A36 | E44: No | F44: =A36&"+"&A39
A45: IDC-VIC | B45: IDC | C45: VIC | D45: =A37 | E45: No | F45: =A37&"+"&A40

Sheet Data_Actuals
A1: Month | B1: Site | C1: Sales $ | D1: Cases picked | E1: WH hours worked | F1: Staff payroll $ | G1: Leadership payroll $
A2: 45658 | B2: =Inputs!$A$36 | C2: 145185523 | D2: 3043624 | E2: 40295 | F2: 2808121 | G2: 319183
A3: 45658 | B3: =Inputs!$A$37 | C3: 133443243 | D3: 2887489 | E3: 38547 | F3: 2623810 | G3: 302699
A4: 45658 | B4: =Inputs!$A$38 | C4: 111417052 | D4: 2452995 | E4: 34693 | F4: 2319628 | G4: 267794
A5: 45658 | B5: =Inputs!$A$39 | C5: 125154901 | D5: 2690106 | E5: 36126 | F5: 2481070 | G5: 301012
A6: 45658 | B6: =Inputs!$A$40 | C6: 129729431 | D6: 2666780 | E6: 34264 | F6: 2298653 | G6: 303403
A7: 45658 | B7: =Inputs!$A$41 | C7: 117129351 | D7: 2537615 | E7: 35430 | F7: 2331622 | G7: 266309
A8: 45658 | B8: =Inputs!$A$42 | C8: 78517402 | D8: 1794006 | E8: 26280 | F8: 1687827 | G8: 204809
A9: 45658 | B9: =Inputs!$A$43 | C9: 99253181 | D9: 2212340 | E9: 31507 | F9: 2336629 | G9: 248935
A10: 45658 | B10: =Inputs!$A$44 | D10: 814235 | E10: 7750 | F10: 564304 | G10: 149724
A11: 45658 | B11: =Inputs!$A$45 | D11: 745617 | E11: 7313 | F11: 524974 | G11: 142777
A12: 45689 | B12: =Inputs!$A$36 | C12: 132346726 | D12: 2785007 | E12: 36181 | F12: 2383806 | G12: 320742
A13: 45689 | B13: =Inputs!$A$37 | C13: 129246596 | D13: 2777283 | E13: 34519 | F13: 2236585 | G13: 295534
A14: 45689 | B14: =Inputs!$A$38 | C14: 100727414 | D14: 2181145 | E14: 29392 | F14: 1832372 | G14: 257979
A15: 45689 | B15: =Inputs!$A$39 | C15: 110794435 | D15: 2337164 | E15: 31366 | F15: 2097121 | G15: 282353
A16: 45689 | B16: =Inputs!$A$40 | C16: 122688392 | D16: 2600981 | E16: 33068 | F16: 2113994 | G16: 294983
A17: 45689 | B17: =Inputs!$A$41 | C17: 109162992 | D17: 2365350 | E17: 31471 | F17: 1991983 | G17: 275619
A18: 45689 | B18: =Inputs!$A$42 | C18: 70749655 | D18: 1615239 | E18: 22417 | F18: 1358641 | G18: 210920
A19: 45689 | B19: =Inputs!$A$43 | C19: 94123598 | D19: 2117036 | E19: 29338 | F19: 2028412 | G19: 245629
A20: 45689 | B20: =Inputs!$A$44 | D20: 736093 | E20: 6714 | F20: 471815 | G20: 145495
A21: 45689 | B21: =Inputs!$A$45 | D21: 699658 | E21: 6848 | F21: 467508 | G21: 140341
A22: 45717 | B22: =Inputs!$A$36 | C22: 151388181 | D22: 3208052 | E22: 40660 | F22: 2685948 | G22: 315275
A23: 45717 | B23: =Inputs!$A$37 | C23: 139380637 | D23: 3034799 | E23: 37316 | F23: 2494850 | G23: 319982
A24: 45717 | B24: =Inputs!$A$38 | C24: 115886017 | D24: 2560673 | E24: 34662 | F24: 2185396 | G24: 255961
A25: 45717 | B25: =Inputs!$A$39 | C25: 123027509 | D25: 2608583 | E25: 33988 | F25: 2237477 | G25: 273167
A26: 45717 | B26: =Inputs!$A$40 | C26: 135907959 | D26: 2829800 | E26: 35242 | F26: 2310290 | G26: 298020
A27: 45717 | B27: =Inputs!$A$41 | C27: 122320621 | D27: 2680744 | E27: 35277 | F27: 2213243 | G27: 268586
A28: 45717 | B28: =Inputs!$A$42 | C28: 81234768 | D28: 1826489 | E28: 24500 | F28: 1538671 | G28: 197429
A29: 45717 | B29: =Inputs!$A$43 | C29: 108067323 | D29: 2388750 | E29: 32485 | F29: 2317422 | G29: 248477
A30: 45717 | B30: =Inputs!$A$44 | D30: 809173 | E30: 7223 | F30: 505153 | G30: 146059
A31: 45717 | B31: =Inputs!$A$45 | D31: 778599 | E31: 7397 | F31: 527308 | G31: 140256
A32: 45748 | B32: =Inputs!$A$36 | C32: 147502978 | D32: 3093483 | E32: 39190 | F32: 2940258 | G32: 319320
A33: 45748 | B33: =Inputs!$A$37 | C33: 139729332 | D33: 3011417 | E33: 37754 | F33: 2783718 | G33: 313897
A34: 45748 | B34: =Inputs!$A$38 | C34: 117059467 | D34: 2552888 | E34: 34584 | F34: 2465776 | G34: 260553
A35: 45748 | B35: =Inputs!$A$39 | C35: 123461416 | D35: 2596120 | E35: 34407 | F35: 2569797 | G35: 284117
A36: 45748 | B36: =Inputs!$A$40 | C36: 136765517 | D36: 2877751 | E36: 35707 | F36: 2629214 | G36: 306586
A37: 45748 | B37: =Inputs!$A$41 | C37: 116536673 | D37: 2538303 | E37: 34449 | F37: 2474166 | G37: 272848
A38: 45748 | B38: =Inputs!$A$42 | C38: 79536351 | D38: 1769687 | E38: 24842 | F38: 1722163 | G38: 207265
A39: 45748 | B39: =Inputs!$A$43 | C39: 104847628 | D39: 2342946 | E39: 32011 | F39: 2424086 | G39: 250907
A40: 45748 | B40: =Inputs!$A$44 | D40: 816972 | E40: 7455 | F40: 606629 | G40: 153750
A41: 45748 | B41: =Inputs!$A$45 | D41: 767977 | E41: 7081 | F41: 562453 | G41: 140551
A42: 45778 | B42: =Inputs!$A$36 | C42: 149881462 | D42: 3086173 | E42: 39621 | F42: 2625238 | G42: 325590
A43: 45778 | B43: =Inputs!$A$37 | C43: 141918699 | D43: 2993432 | E43: 37519 | F43: 2447093 | G43: 304699
A44: 45778 | B44: =Inputs!$A$38 | C44: 113712227 | D44: 2485054 | E44: 33987 | F44: 2207839 | G44: 267353
A45: 45778 | B45: =Inputs!$A$39 | C45: 122147150 | D45: 2531897 | E45: 33577 | F45: 2239964 | G45: 276790
A46: 45778 | B46: =Inputs!$A$40 | C46: 137261905 | D46: 2874734 | E46: 35879 | F46: 2347584 | G46: 295261
A47: 45778 | B47: =Inputs!$A$41 | C47: 116543697 | D47: 2502257 | E47: 33428 | F47: 2148823 | G47: 270902
A48: 45778 | B48: =Inputs!$A$42 | C48: 78013621 | D48: 1770297 | E48: 24288 | F48: 1473644 | G48: 212855
A49: 45778 | B49: =Inputs!$A$43 | C49: 102610754 | D49: 2259751 | E49: 31156 | F49: 2170677 | G49: 257983
A50: 45778 | B50: =Inputs!$A$44 | D50: 814800 | E50: 7400 | F50: 518632 | G50: 149692
A51: 45778 | B51: =Inputs!$A$45 | D51: 771305 | E51: 7503 | F51: 518583 | G51: 139285
A52: 45809 | B52: =Inputs!$A$36 | C52: 145551686 | D52: 3048836 | E52: 38782 | F52: 2641082 | G52: 312875
A53: 45809 | B53: =Inputs!$A$37 | C53: 133582637 | D53: 2789624 | E53: 35748 | F53: 2381357 | G53: 299381
A54: 45809 | B54: =Inputs!$A$38 | C54: 112402328 | D54: 2475324 | E54: 32898 | F54: 2087983 | G54: 261577
A55: 45809 | B55: =Inputs!$A$39 | C55: 126006744 | D55: 2667620 | E55: 35576 | F55: 2391671 | G55: 281363
A56: 45809 | B56: =Inputs!$A$40 | C56: 128616983 | D56: 2684568 | E56: 34018 | F56: 2266901 | G56: 296528
A57: 45809 | B57: =Inputs!$A$41 | C57: 114837763 | D57: 2488921 | E57: 33907 | F57: 2099318 | G57: 273870
A58: 45809 | B58: =Inputs!$A$42 | C58: 78697811 | D58: 1781884 | E58: 25042 | F58: 1576197 | G58: 207447
A59: 45809 | B59: =Inputs!$A$43 | C59: 106251584 | D59: 2353205 | E59: 32513 | F59: 2282566 | G59: 258037
A60: 45809 | B60: =Inputs!$A$44 | D60: 797913 | E60: 7125 | F60: 512235 | G60: 141736
A61: 45809 | B61: =Inputs!$A$45 | D61: 732957 | E61: 6918 | F61: 490484 | G61: 143198
A62: 45839 | B62: =Inputs!$A$36 | C62: 150825108 | D62: 3095874 | E62: 41109 | F62: 2700039 | G62: 314139
A63: 45839 | B63: =Inputs!$A$37 | C63: 140303139 | D63: 2970766 | E63: 37642 | F63: 2407100 | G63: 301975
A64: 45839 | B64: =Inputs!$A$38 | C64: 115020335 | D64: 2533096 | E64: 34026 | F64: 2126937 | G64: 260124
A65: 45839 | B65: =Inputs!$A$39 | C65: 122423850 | D65: 2637012 | E65: 35046 | F65: 2325652 | G65: 288177
A66: 45839 | B66: =Inputs!$A$40 | C66: 133802087 | D66: 2768560 | E66: 35414 | F66: 2303169 | G66: 301476
A67: 45839 | B67: =Inputs!$A$41 | C67: 117297779 | D67: 2523631 | E67: 34209 | F67: 2130859 | G67: 267846
A68: 45839 | B68: =Inputs!$A$42 | C68: 81142099 | D68: 1808466 | E68: 25875 | F68: 1578800 | G68: 202507
A69: 45839 | B69: =Inputs!$A$43 | C69: 102269580 | D69: 2256268 | E69: 31018 | F69: 2170189 | G69: 244933
A70: 45839 | B70: =Inputs!$A$44 | D70: 808405 | E70: 7405 | F70: 522099 | G70: 149868
A71: 45839 | B71: =Inputs!$A$45 | D71: 764110 | E71: 7321 | F71: 501278 | G71: 141633
A72: 45870 | B72: =Inputs!$A$36 | C72: 150399966 | D72: 3151472 | E72: 40918 | F72: 2718887 | G72: 313586
A73: 45870 | B73: =Inputs!$A$37 | C73: 139321773 | D73: 2998609 | E73: 36829 | F73: 2390221 | G73: 308096
A74: 45870 | B74: =Inputs!$A$38 | C74: 110587301 | D74: 2411423 | E74: 32199 | F74: 2048566 | G74: 260787
A75: 45870 | B75: =Inputs!$A$39 | C75: 123505128 | D75: 2569481 | E75: 33752 | F75: 2234056 | G75: 284904
A76: 45870 | B76: =Inputs!$A$40 | C76: 133449358 | D76: 2730922 | E76: 33968 | F76: 2240982 | G76: 296393
A77: 45870 | B77: =Inputs!$A$41 | C77: 118028853 | D77: 2575504 | E77: 33913 | F77: 2132034 | G77: 274091
A78: 45870 | B78: =Inputs!$A$42 | C78: 78915082 | D78: 1758980 | E78: 24436 | F78: 1472864 | G78: 205314
A79: 45870 | B79: =Inputs!$A$43 | C79: 105631703 | D79: 2365576 | E79: 32298 | F79: 2236889 | G79: 242306
A80: 45870 | B80: =Inputs!$A$44 | D80: 826618 | E80: 7654 | F80: 530861 | G80: 153201
A81: 45870 | B81: =Inputs!$A$45 | D81: 748941 | E81: 7016 | F81: 486157 | G81: 139877
A82: 45901 | B82: =Inputs!$A$36 | C82: 147150090 | D82: 3050182 | E82: 38780 | F82: 2576228 | G82: 324086
A83: 45901 | B83: =Inputs!$A$37 | C83: 137236692 | D83: 2901706 | E83: 36315 | F83: 2409168 | G83: 287006
A84: 45901 | B84: =Inputs!$A$38 | C84: 114533859 | D84: 2494471 | E84: 34008 | F84: 2118331 | G84: 254957
A85: 45901 | B85: =Inputs!$A$39 | C85: 122888375 | D85: 2543002 | E85: 33218 | F85: 2180594 | G85: 267774
A86: 45901 | B86: =Inputs!$A$40 | C86: 135062098 | D86: 2805860 | E86: 36745 | F86: 2434219 | G86: 296185
A87: 45901 | B87: =Inputs!$A$41 | C87: 119846726 | D87: 2597104 | E87: 34610 | F87: 2198201 | G87: 279550
A88: 45901 | B88: =Inputs!$A$42 | C88: 77586165 | D88: 1723900 | E88: 23334 | F88: 1431434 | G88: 208017
A89: 45901 | B89: =Inputs!$A$43 | C89: 103002025 | D89: 2269028 | E89: 32120 | F89: 2280172 | G89: 251776
A90: 45901 | B90: =Inputs!$A$44 | D90: 796739 | E90: 7311 | F90: 509343 | G90: 147721
A91: 45901 | B91: =Inputs!$A$45 | D91: 748895 | E91: 7279 | F91: 509659 | G91: 135447
A92: 45931 | B92: =Inputs!$A$36 | C92: 154728337 | D92: 3233552 | E92: 40450 | F92: 2721618 | G92: 315409
A93: 45931 | B93: =Inputs!$A$37 | C93: 143996017 | D93: 3068669 | E93: 37902 | F93: 2449571 | G93: 302231
A94: 45931 | B94: =Inputs!$A$38 | C94: 115587533 | D94: 2530197 | E94: 33707 | F94: 2185659 | G94: 260382
A95: 45931 | B95: =Inputs!$A$39 | C95: 126924990 | D95: 2622371 | E95: 33613 | F95: 2308387 | G95: 290409
A96: 45931 | B96: =Inputs!$A$40 | C96: 140152932 | D96: 2887756 | E96: 35669 | F96: 2330290 | G96: 294606
A97: 45931 | B97: =Inputs!$A$41 | C97: 124356453 | D97: 2727876 | E97: 35254 | F97: 2291059 | G97: 264113
A98: 45931 | B98: =Inputs!$A$42 | C98: 83659551 | D98: 1835662 | E98: 24800 | F98: 1547850 | G98: 210993
A99: 45931 | B99: =Inputs!$A$43 | C99: 105007588 | D99: 2282578 | E99: 31078 | F99: 2135284 | G99: 248468
A100: 45931 | B100: =Inputs!$A$44 | D100: 839942 | E100: 7380 | F100: 522302 | G100: 149128
...

Sheet Plan_Inputs
A1: Month | B1: Site | C1: Sales forecast $ | D1: Payroll % of sales (total) | F1: From the long-range plan. IDC payroll % is a % of the host region's sales (see Sites on Inputs).
A2: 46023 | B2: =Inputs!$A$36 | C2: 153814000 | D2: 0.022
A3: 46023 | B3: =Inputs!$A$37 | C3: 142733000 | D3: 0.0209
A4: 46023 | B4: =Inputs!$A$38 | C4: 117343000 | D4: 0.0223
A5: 46023 | B5: =Inputs!$A$39 | C5: 126585000 | D5: 0.0222
A6: 46023 | B6: =Inputs!$A$40 | C6: 135910000 | D6: 0.021
A7: 46023 | B7: =Inputs!$A$41 | C7: 120851000 | D7: 0.0221
A8: 46023 | B8: =Inputs!$A$42 | C8: 79038000 | D8: 0.0231
A9: 46023 | B9: =Inputs!$A$43 | C9: 106821000 | D9: 0.0267
A10: 46023 | B10: =Inputs!$A$44 | D10: 0.0048
A11: 46023 | B11: =Inputs!$A$45 | D11: 0.005
A12: 46054 | B12: =Inputs!$A$36 | C12: 137092000 | D12: 0.0205
A13: 46054 | B13: =Inputs!$A$37 | C13: 131606000 | D13: 0.0196
A14: 46054 | B14: =Inputs!$A$38 | C14: 109672000 | D14: 0.0218
A15: 46054 | B15: =Inputs!$A$39 | C15: 120059000 | D15: 0.0213
A16: 46054 | B16: =Inputs!$A$40 | C16: 129364000 | D16: 0.0203
A17: 46054 | B17: =Inputs!$A$41 | C17: 114317000 | D17: 0.0211
A18: 46054 | B18: =Inputs!$A$42 | C18: 74441000 | D18: 0.0225
A19: 46054 | B19: =Inputs!$A$43 | C19: 96657000 | D19: 0.0245
A20: 46054 | B20: =Inputs!$A$44 | D20: 0.0048
A21: 46054 | B21: =Inputs!$A$45 | D21: 0.005
A22: 46082 | B22: =Inputs!$A$36 | C22: 157503000 | D22: 0.0202
A23: 46082 | B23: =Inputs!$A$37 | C23: 146942000 | D23: 0.0202
A24: 46082 | B24: =Inputs!$A$38 | C24: 118790000 | D24: 0.0208
A25: 46082 | B25: =Inputs!$A$39 | C25: 132170000 | D25: 0.0201
A26: 46082 | B26: =Inputs!$A$40 | C26: 140523000 | D26: 0.0201
A27: 46082 | B27: =Inputs!$A$41 | C27: 122798000 | D27: 0.0208
A28: 46082 | B28: =Inputs!$A$42 | C28: 81723000 | D28: 0.0222
A29: 46082 | B29: =Inputs!$A$43 | C29: 108203000 | D29: 0.0248
A30: 46082 | B30: =Inputs!$A$44 | D30: 0.0047
A31: 46082 | B31: =Inputs!$A$45 | D31: 0.0047
A32: 46113 | B32: =Inputs!$A$36 | C32: 153091000 | D32: 0.0231
A33: 46113 | B33: =Inputs!$A$37 | C33: 140264000 | D33: 0.0223
A34: 46113 | B34: =Inputs!$A$38 | C34: 116902000 | D34: 0.0238
A35: 46113 | B35: =Inputs!$A$39 | C35: 132565000 | D35: 0.0224
A36: 46113 | B36: =Inputs!$A$40 | C36: 139867000 | D36: 0.0218
A37: 46113 | B37: =Inputs!$A$41 | C37: 125887000 | D37: 0.0229
A38: 46113 | B38: =Inputs!$A$42 | C38: 84196000 | D38: 0.0244
A39: 46113 | B39: =Inputs!$A$43 | C39: 111697000 | D39: 0.0263
A40: 46113 | B40: =Inputs!$A$44 | D40: 0.0051
A41: 46113 | B41: =Inputs!$A$45 | D41: 0.0054
A42: 46143 | B42: =Inputs!$A$36 | C42: 152230000 | D42: 0.0203
A43: 46143 | B43: =Inputs!$A$37 | C43: 147525000 | D43: 0.0189
A44: 46143 | B44: =Inputs!$A$38 | C44: 116456000 | D44: 0.022
A45: 46143 | B45: =Inputs!$A$39 | C45: 127918000 | D45: 0.0215
A46: 46143 | B46: =Inputs!$A$40 | C46: 138378000 | D46: 0.0191
A47: 46143 | B47: =Inputs!$A$41 | C47: 123873000 | D47: 0.0212
A48: 46143 | B48: =Inputs!$A$42 | C48: 82081000 | D48: 0.0217
A49: 46143 | B49: =Inputs!$A$43 | C49: 106186000 | D49: 0.0235
A50: 46143 | B50: =Inputs!$A$44 | D50: 0.0046
A51: 46143 | B51: =Inputs!$A$45 | D51: 0.0045
A52: 46174 | B52: =Inputs!$A$36 | C52: 152135000 | D52: 0.0207
A53: 46174 | B53: =Inputs!$A$37 | C53: 141649000 | D53: 0.0195
A54: 46174 | B54: =Inputs!$A$38 | C54: 113294000 | D54: 0.0209
A55: 46174 | B55: =Inputs!$A$39 | C55: 126063000 | D55: 0.021
A56: 46174 | B56: =Inputs!$A$40 | C56: 133661000 | D56: 0.0199
A57: 46174 | B57: =Inputs!$A$41 | C57: 118337000 | D57: 0.0213
A58: 46174 | B58: =Inputs!$A$42 | C58: 81648000 | D58: 0.0216
A59: 46174 | B59: =Inputs!$A$43 | C59: 107863000 | D59: 0.0234
A60: 46174 | B60: =Inputs!$A$44 | D60: 0.0046
A61: 46174 | B61: =Inputs!$A$45 | D61: 0.0047
A62: 46204 | B62: =Inputs!$A$36 | C62: 157303000 | D62: 0.0199
A63: 46204 | B63: =Inputs!$A$37 | C63: 145102000 | D63: 0.0195
A64: 46204 | B64: =Inputs!$A$38 | C64: 118164000 | D64: 0.0205
A65: 46204 | B65: =Inputs!$A$39 | C65: 127349000 | D65: 0.0208
A66: 46204 | B66: =Inputs!$A$40 | C66: 140176000 | D66: 0.0193
A67: 46204 | B67: =Inputs!$A$41 | C67: 124914000 | D67: 0.0202
A68: 46204 | B68: =Inputs!$A$42 | C68: 81940000 | D68: 0.0224
A69: 46204 | B69: =Inputs!$A$43 | C69: 109023000 | D69: 0.0242
A70: 46204 | B70: =Inputs!$A$44 | D70: 0.0043
A71: 46204 | B71: =Inputs!$A$45 | D71: 0.0045
A72: 46235 | B72: =Inputs!$A$36 | C72: 154523000 | D72: 0.0204
A73: 46235 | B73: =Inputs!$A$37 | C73: 140341000 | D73: 0.0192
A74: 46235 | B74: =Inputs!$A$38 | C74: 120980000 | D74: 0.0206
A75: 46235 | B75: =Inputs!$A$39 | C75: 127427000 | D75: 0.0207
A76: 46235 | B76: =Inputs!$A$40 | C76: 138116000 | D76: 0.019
A77: 46235 | B77: =Inputs!$A$41 | C77: 124473000 | D77: 0.0207
A78: 46235 | B78: =Inputs!$A$42 | C78: 80868000 | D78: 0.0224
A79: 46235 | B79: =Inputs!$A$43 | C79: 106389000 | D79: 0.0232
A80: 46235 | B80: =Inputs!$A$44 | D80: 0.0045
A81: 46235 | B81: =Inputs!$A$45 | D81: 0.0046
A82: 46266 | B82: =Inputs!$A$36 | C82: 156142000 | D82: 0.0198
A83: 46266 | B83: =Inputs!$A$37 | C83: 142762000 | D83: 0.0197
A84: 46266 | B84: =Inputs!$A$38 | C84: 116520000 | D84: 0.0213
A85: 46266 | B85: =Inputs!$A$39 | C85: 127790000 | D85: 0.0206
A86: 46266 | B86: =Inputs!$A$40 | C86: 137926000 | D86: 0.0195
A87: 46266 | B87: =Inputs!$A$41 | C87: 123052000 | D87: 0.0199
A88: 46266 | B88: =Inputs!$A$42 | C88: 81937000 | D88: 0.0215
A89: 46266 | B89: =Inputs!$A$43 | C89: 109683000 | D89: 0.0232
A90: 46266 | B90: =Inputs!$A$44 | D90: 0.0045
A91: 46266 | B91: =Inputs!$A$45 | D91: 0.0047
A92: 46296 | B92: =Inputs!$A$36 | C92: 162709000 | D92: 0.0196
A93: 46296 | B93: =Inputs!$A$37 | C93: 152617000 | D93: 0.0193
A94: 46296 | B94: =Inputs!$A$38 | C94: 121209000 | D94: 0.0208
A95: 46296 | B95: =Inputs!$A$39 | C95: 132476000 | D95: 0.0206
A96: 46296 | B96: =Inputs!$A$40 | C96: 144069000 | D96: 0.0191
A97: 46296 | B97: =Inputs!$A$41 | C97: 125299000 | D97: 0.0208
A98: 46296 | B98: =Inputs!$A$42 | C98: 84261000 | D98: 0.0226
A99: 46296 | B99: =Inputs!$A$43 | C99: 112849000 | D99: 0.0232
A100: 46296 | B100: =Inputs!$A$44 | D100: 0.0045
...

Sheet Cases_Forecast
A1: Cases forecast
A2: 1. Run rate: volume driver sales x cases per $ of sales in the same month last year. Actual months show actuals.
A3: 2. Adjustments: type extra cases (or negative) for a site and month, e.g. a new store or volume moving between sites.
A4: 3. Override: type the cases you want for a site and month. It replaces 1 + 2. Leave blank to use the model.
A5: 4. Cases used = override if there is one, otherwise run rate + adjustment. This feeds Cases picked on each site tab.
C6: 1. Run-rate forecast | N6: 2. Adjustments (+/- cases) | Y6: 3. Override (replaces 1 + 2) | AJ6: 4. Cases forecast used
A7: Month | B7: Status | C7: =Inputs!$A$36 | D7: =Inputs!$A$37 | E7: =Inputs!$A$38 | F7: =Inputs!$A$39 | G7: =Inputs!$A$40 | H7: =Inputs!$A$41 | I7: =Inputs!$A$42 | J7: =Inputs!$A$43 | K7: =Inputs!$A$44 | L7: =Inputs!$A$45 | N7: =Inputs!$A$36 | O7: =Inputs!$A$37 | P7: =Inputs!$A$38 | Q7: =Inputs!$A$39 | R7: =Inputs!$A$40 | S7: =Inputs!$A$41 | T7: =Inputs!$A$42 | U7: =Inputs!$A$43 | V7: =Inputs!$A$44 | W7: =Inputs!$A$45 | Y7: =Inputs!$A$36 | Z7: =Inputs!$A$37 | AA7: =Inputs!$A$38 | AB7: =Inputs!$A$39 | AC7: =Inputs!$A$40 | AD7: =Inputs!$A$41 | AE7: =Inputs!$A$42 | AF7: =Inputs!$A$43 | AG7: =Inputs!$A$44 | AH7: =Inputs!$A$45 | AJ7: =Inputs!$A$36 | AK7: =Inputs!$A$37 | AL7: =Inputs!$A$38 | AM7: =Inputs!$A$39 | AN7: =Inputs!$A$40 | AO7: =Inputs!$A$41 | AP7: =Inputs!$A$42 | AQ7: =Inputs!$A$43 | AR7: =Inputs!$A$44 | AS7: =Inputs!$A$45
A8: 45658 | B8: =IF(A8<=LastActual,"Actual","Forecast") | C8: =IF($B8="Actual",'NSW-1'!S15,IFERROR('NSW-1'!Y15*'NSW-1'!AB15,0)) | D8: =IF($B8="Actual",'VIC-1'!S15,IFERROR('VIC-1'!Y15*'VIC-1'!AB15,0)) | E8: =IF($B8="Actual",'QLD-1'!S15,IFERROR('QLD-1'!Y15*'QLD-1'!AB15,0)) | F8: =IF($B8="Actual",'NSW-2'!S15,IFERROR('NSW-2'!Y15*'NSW-2'!AB15,0)) | G8: =IF($B8="Actual",'VIC-2'!S15,IFERROR('VIC-2'!Y15*'VIC-2'!AB15,0)) | H8: =IF($B8="Actual",'QLD-2'!S15,IFERROR('QLD-2'!Y15*'QLD-2'!AB15,0)) | I8: =IF($B8="Actual",'SA-1'!S15,IFERROR('SA-1'!Y15*'SA-1'!AB15,0)) | J8: =IF($B8="Actual",'WA-1'!S15,IFERROR('WA-1'!Y15*'WA-1'!AB15,0)) | K8: =IF($B8="Actual",'IDC-NSW'!S15,IFERROR('IDC-NSW'!Y15*'IDC-NSW'!AB15,0)) | L8: =IF($B8="Actual",'IDC-VIC'!S15,IFERROR('IDC-VIC'!Y15*'IDC-VIC'!AB15,0)) | AJ8: =IF($B8="Actual",C8,IF(Y8<>"",Y8,C8+N(N8))) | AK8: =IF($B8="Actual",D8,IF(Z8<>"",Z8,D8+N(O8))) | AL8: =IF($B8="Actual",E8,IF(AA8<>"",AA8,E8+N(P8))) | AM8: =IF($B8="Actual",F8,IF(AB8<>"",AB8,F8+N(Q8))) | AN8: =IF($B8="Actual",G8,IF(AC8<>"",AC8,G8+N(R8))) | AO8: =IF($B8="Actual",H8,IF(AD8<>"",AD8,H8+N(S8))) | AP8: =IF($B8="Actual",I8,IF(AE8<>"",AE8,I8+N(T8))) | AQ8: =IF($B8="Actual",J8,IF(AF8<>"",AF8,J8+N(U8))) | ... AS8: =IF($B8="Actual",L8,IF(AH8<>"",AH8,L8+N(W8)))
A9: 45689 | B9: =IF(A9<=LastActual,"Actual","Forecast") | C9: =IF($B9="Actual",'NSW-1'!S16,IFERROR('NSW-1'!Y16*'NSW-1'!AB16,0)) | D9: =IF($B9="Actual",'VIC-1'!S16,IFERROR('VIC-1'!Y16*'VIC-1'!AB16,0)) | E9: =IF($B9="Actual",'QLD-1'!S16,IFERROR('QLD-1'!Y16*'QLD-1'!AB16,0)) | F9: =IF($B9="Actual",'NSW-2'!S16,IFERROR('NSW-2'!Y16*'NSW-2'!AB16,0)) | G9: =IF($B9="Actual",'VIC-2'!S16,IFERROR('VIC-2'!Y16*'VIC-2'!AB16,0)) | H9: =IF($B9="Actual",'QLD-2'!S16,IFERROR('QLD-2'!Y16*'QLD-2'!AB16,0)) | I9: =IF($B9="Actual",'SA-1'!S16,IFERROR('SA-1'!Y16*'SA-1'!AB16,0)) | J9: =IF($B9="Actual",'WA-1'!S16,IFERROR('WA-1'!Y16*'WA-1'!AB16,0)) | K9: =IF($B9="Actual",'IDC-NSW'!S16,IFERROR('IDC-NSW'!Y16*'IDC-NSW'!AB16,0)) | L9: =IF($B9="Actual",'IDC-VIC'!S16,IFERROR('IDC-VIC'!Y16*'IDC-VIC'!AB16,0)) | AJ9: =IF($B9="Actual",C9,IF(Y9<>"",Y9,C9+N(N9))) | AK9: =IF($B9="Actual",D9,IF(Z9<>"",Z9,D9+N(O9))) | AL9: =IF($B9="Actual",E9,IF(AA9<>"",AA9,E9+N(P9))) | AM9: =IF($B9="Actual",F9,IF(AB9<>"",AB9,F9+N(Q9))) | AN9: =IF($B9="Actual",G9,IF(AC9<>"",AC9,G9+N(R9))) | AO9: =IF($B9="Actual",H9,IF(AD9<>"",AD9,H9+N(S9))) | AP9: =IF($B9="Actual",I9,IF(AE9<>"",AE9,I9+N(T9))) | AQ9: =IF($B9="Actual",J9,IF(AF9<>"",AF9,J9+N(U9))) | ... AS9: =IF($B9="Actual",L9,IF(AH9<>"",AH9,L9+N(W9)))
A10: 45717 | B10: =IF(A10<=LastActual,"Actual","Forecast") | C10: =IF($B10="Actual",'NSW-1'!S17,IFERROR('NSW-1'!Y17*'NSW-1'!AB17,0)) | D10: =IF($B10="Actual",'VIC-1'!S17,IFERROR('VIC-1'!Y17*'VIC-1'!AB17,0)) | E10: =IF($B10="Actual",'QLD-1'!S17,IFERROR('QLD-1'!Y17*'QLD-1'!AB17,0)) | F10: =IF($B10="Actual",'NSW-2'!S17,IFERROR('NSW-2'!Y17*'NSW-2'!AB17,0)) | G10: =IF($B10="Actual",'VIC-2'!S17,IFERROR('VIC-2'!Y17*'VIC-2'!AB17,0)) | H10: =IF($B10="Actual",'QLD-2'!S17,IFERROR('QLD-2'!Y17*'QLD-2'!AB17,0)) | I10: =IF($B10="Actual",'SA-1'!S17,IFERROR('SA-1'!Y17*'SA-1'!AB17,0)) | J10: =IF($B10="Actual",'WA-1'!S17,IFERROR('WA-1'!Y17*'WA-1'!AB17,0)) | K10: =IF($B10="Actual",'IDC-NSW'!S17,IFERROR('IDC-NSW'!Y17*'IDC-NSW'!AB17,0)) | L10: =IF($B10="Actual",'IDC-VIC'!S17,IFERROR('IDC-VIC'!Y17*'IDC-VIC'!AB17,0)) | AJ10: =IF($B10="Actual",C10,IF(Y10<>"",Y10,C10+N(N10))) | AK10: =IF($B10="Actual",D10,IF(Z10<>"",Z10,D10+N(O10))) | AL10: =IF($B10="Actual",E10,IF(AA10<>"",AA10,E10+N(P10))) | AM10: =IF($B10="Actual",F10,IF(AB10<>"",AB10,F10+N(Q10))) | AN10: =IF($B10="Actual",G10,IF(AC10<>"",AC10,G10+N(R10))) | AO10: =IF($B10="Actual",H10,IF(AD10<>"",AD10,H10+N(S10))) | AP10: =IF($B10="Actual",I10,IF(AE10<>"",AE10,I10+N(T10))) | AQ10: =IF($B10="Actual",J10,IF(AF10<>"",AF10,J10+N(U10))) | ... AS10: =IF($B10="Actual",L10,IF(AH10<>"",AH10,L10+N(W10)))
A11: 45748 | B11: =IF(A11<=LastActual,"Actual","Forecast") | C11: =IF($B11="Actual",'NSW-1'!S18,IFERROR('NSW-1'!Y18*'NSW-1'!AB18,0)) | D11: =IF($B11="Actual",'VIC-1'!S18,IFERROR('VIC-1'!Y18*'VIC-1'!AB18,0)) | E11: =IF($B11="Actual",'QLD-1'!S18,IFERROR('QLD-1'!Y18*'QLD-1'!AB18,0)) | F11: =IF($B11="Actual",'NSW-2'!S18,IFERROR('NSW-2'!Y18*'NSW-2'!AB18,0)) | G11: =IF($B11="Actual",'VIC-2'!S18,IFERROR('VIC-2'!Y18*'VIC-2'!AB18,0)) | H11: =IF($B11="Actual",'QLD-2'!S18,IFERROR('QLD-2'!Y18*'QLD-2'!AB18,0)) | I11: =IF($B11="Actual",'SA-1'!S18,IFERROR('SA-1'!Y18*'SA-1'!AB18,0)) | J11: =IF($B11="Actual",'WA-1'!S18,IFERROR('WA-1'!Y18*'WA-1'!AB18,0)) | K11: =IF($B11="Actual",'IDC-NSW'!S18,IFERROR('IDC-NSW'!Y18*'IDC-NSW'!AB18,0)) | L11: =IF($B11="Actual",'IDC-VIC'!S18,IFERROR('IDC-VIC'!Y18*'IDC-VIC'!AB18,0)) | AJ11: =IF($B11="Actual",C11,IF(Y11<>"",Y11,C11+N(N11))) | AK11: =IF($B11="Actual",D11,IF(Z11<>"",Z11,D11+N(O11))) | AL11: =IF($B11="Actual",E11,IF(AA11<>"",AA11,E11+N(P11))) | AM11: =IF($B11="Actual",F11,IF(AB11<>"",AB11,F11+N(Q11))) | AN11: =IF($B11="Actual",G11,IF(AC11<>"",AC11,G11+N(R11))) | AO11: =IF($B11="Actual",H11,IF(AD11<>"",AD11,H11+N(S11))) | AP11: =IF($B11="Actual",I11,IF(AE11<>"",AE11,I11+N(T11))) | AQ11: =IF($B11="Actual",J11,IF(AF11<>"",AF11,J11+N(U11))) | ... AS11: =IF($B11="Actual",L11,IF(AH11<>"",AH11,L11+N(W11)))
A12: 45778 | B12: =IF(A12<=LastActual,"Actual","Forecast") | C12: =IF($B12="Actual",'NSW-1'!S19,IFERROR('NSW-1'!Y19*'NSW-1'!AB19,0)) | D12: =IF($B12="Actual",'VIC-1'!S19,IFERROR('VIC-1'!Y19*'VIC-1'!AB19,0)) | E12: =IF($B12="Actual",'QLD-1'!S19,IFERROR('QLD-1'!Y19*'QLD-1'!AB19,0)) | F12: =IF($B12="Actual",'NSW-2'!S19,IFERROR('NSW-2'!Y19*'NSW-2'!AB19,0)) | G12: =IF($B12="Actual",'VIC-2'!S19,IFERROR('VIC-2'!Y19*'VIC-2'!AB19,0)) | H12: =IF($B12="Actual",'QLD-2'!S19,IFERROR('QLD-2'!Y19*'QLD-2'!AB19,0)) | I12: =IF($B12="Actual",'SA-1'!S19,IFERROR('SA-1'!Y19*'SA-1'!AB19,0)) | J12: =IF($B12="Actual",'WA-1'!S19,IFERROR('WA-1'!Y19*'WA-1'!AB19,0)) | K12: =IF($B12="Actual",'IDC-NSW'!S19,IFERROR('IDC-NSW'!Y19*'IDC-NSW'!AB19,0)) | L12: =IF($B12="Actual",'IDC-VIC'!S19,IFERROR('IDC-VIC'!Y19*'IDC-VIC'!AB19,0)) | AJ12: =IF($B12="Actual",C12,IF(Y12<>"",Y12,C12+N(N12))) | AK12: =IF($B12="Actual",D12,IF(Z12<>"",Z12,D12+N(O12))) | AL12: =IF($B12="Actual",E12,IF(AA12<>"",AA12,E12+N(P12))) | AM12: =IF($B12="Actual",F12,IF(AB12<>"",AB12,F12+N(Q12))) | AN12: =IF($B12="Actual",G12,IF(AC12<>"",AC12,G12+N(R12))) | AO12: =IF($B12="Actual",H12,IF(AD12<>"",AD12,H12+N(S12))) | AP12: =IF($B12="Actual",I12,IF(AE12<>"",AE12,I12+N(T12))) | AQ12: =IF($B12="Actual",J12,IF(AF12<>"",AF12,J12+N(U12))) | ... AS12: =IF($B12="Actual",L12,IF(AH12<>"",AH12,L12+N(W12)))
A13: 45809 | B13: =IF(A13<=LastActual,"Actual","Forecast") | C13: =IF($B13="Actual",'NSW-1'!S20,IFERROR('NSW-1'!Y20*'NSW-1'!AB20,0)) | D13: =IF($B13="Actual",'VIC-1'!S20,IFERROR('VIC-1'!Y20*'VIC-1'!AB20,0)) | E13: =IF($B13="Actual",'QLD-1'!S20,IFERROR('QLD-1'!Y20*'QLD-1'!AB20,0)) | F13: =IF($B13="Actual",'NSW-2'!S20,IFERROR('NSW-2'!Y20*'NSW-2'!AB20,0)) | G13: =IF($B13="Actual",'VIC-2'!S20,IFERROR('VIC-2'!Y20*'VIC-2'!AB20,0)) | H13: =IF($B13="Actual",'QLD-2'!S20,IFERROR('QLD-2'!Y20*'QLD-2'!AB20,0)) | I13: =IF($B13="Actual",'SA-1'!S20,IFERROR('SA-1'!Y20*'SA-1'!AB20,0)) | J13: =IF($B13="Actual",'WA-1'!S20,IFERROR('WA-1'!Y20*'WA-1'!AB20,0)) | K13: =IF($B13="Actual",'IDC-NSW'!S20,IFERROR('IDC-NSW'!Y20*'IDC-NSW'!AB20,0)) | L13: =IF($B13="Actual",'IDC-VIC'!S20,IFERROR('IDC-VIC'!Y20*'IDC-VIC'!AB20,0)) | AJ13: =IF($B13="Actual",C13,IF(Y13<>"",Y13,C13+N(N13))) | AK13: =IF($B13="Actual",D13,IF(Z13<>"",Z13,D13+N(O13))) | AL13: =IF($B13="Actual",E13,IF(AA13<>"",AA13,E13+N(P13))) | AM13: =IF($B13="Actual",F13,IF(AB13<>"",AB13,F13+N(Q13))) | AN13: =IF($B13="Actual",G13,IF(AC13<>"",AC13,G13+N(R13))) | AO13: =IF($B13="Actual",H13,IF(AD13<>"",AD13,H13+N(S13))) | AP13: =IF($B13="Actual",I13,IF(AE13<>"",AE13,I13+N(T13))) | AQ13: =IF($B13="Actual",J13,IF(AF13<>"",AF13,J13+N(U13))) | ... AS13: =IF($B13="Actual",L13,IF(AH13<>"",AH13,L13+N(W13)))
A14: 45839 | B14: =IF(A14<=LastActual,"Actual","Forecast") | C14: =IF($B14="Actual",'NSW-1'!S21,IFERROR('NSW-1'!Y21*'NSW-1'!AB21,0)) | D14: =IF($B14="Actual",'VIC-1'!S21,IFERROR('VIC-1'!Y21*'VIC-1'!AB21,0)) | E14: =IF($B14="Actual",'QLD-1'!S21,IFERROR('QLD-1'!Y21*'QLD-1'!AB21,0)) | F14: =IF($B14="Actual",'NSW-2'!S21,IFERROR('NSW-2'!Y21*'NSW-2'!AB21,0)) | G14: =IF($B14="Actual",'VIC-2'!S21,IFERROR('VIC-2'!Y21*'VIC-2'!AB21,0)) | H14: =IF($B14="Actual",'QLD-2'!S21,IFERROR('QLD-2'!Y21*'QLD-2'!AB21,0)) | I14: =IF($B14="Actual",'SA-1'!S21,IFERROR('SA-1'!Y21*'SA-1'!AB21,0)) | J14: =IF($B14="Actual",'WA-1'!S21,IFERROR('WA-1'!Y21*'WA-1'!AB21,0)) | K14: =IF($B14="Actual",'IDC-NSW'!S21,IFERROR('IDC-NSW'!Y21*'IDC-NSW'!AB21,0)) | L14: =IF($B14="Actual",'IDC-VIC'!S21,IFERROR('IDC-VIC'!Y21*'IDC-VIC'!AB21,0)) | AJ14: =IF($B14="Actual",C14,IF(Y14<>"",Y14,C14+N(N14))) | AK14: =IF($B14="Actual",D14,IF(Z14<>"",Z14,D14+N(O14))) | AL14: =IF($B14="Actual",E14,IF(AA14<>"",AA14,E14+N(P14))) | AM14: =IF($B14="Actual",F14,IF(AB14<>"",AB14,F14+N(Q14))) | AN14: =IF($B14="Actual",G14,IF(AC14<>"",AC14,G14+N(R14))) | AO14: =IF($B14="Actual",H14,IF(AD14<>"",AD14,H14+N(S14))) | AP14: =IF($B14="Actual",I14,IF(AE14<>"",AE14,I14+N(T14))) | AQ14: =IF($B14="Actual",J14,IF(AF14<>"",AF14,J14+N(U14))) | ... AS14: =IF($B14="Actual",L14,IF(AH14<>"",AH14,L14+N(W14)))
A15: 45870 | B15: =IF(A15<=LastActual,"Actual","Forecast") | C15: =IF($B15="Actual",'NSW-1'!S22,IFERROR('NSW-1'!Y22*'NSW-1'!AB22,0)) | D15: =IF($B15="Actual",'VIC-1'!S22,IFERROR('VIC-1'!Y22*'VIC-1'!AB22,0)) | E15: =IF($B15="Actual",'QLD-1'!S22,IFERROR('QLD-1'!Y22*'QLD-1'!AB22,0)) | F15: =IF($B15="Actual",'NSW-2'!S22,IFERROR('NSW-2'!Y22*'NSW-2'!AB22,0)) | G15: =IF($B15="Actual",'VIC-2'!S22,IFERROR('VIC-2'!Y22*'VIC-2'!AB22,0)) | H15: =IF($B15="Actual",'QLD-2'!S22,IFERROR('QLD-2'!Y22*'QLD-2'!AB22,0)) | I15: =IF($B15="Actual",'SA-1'!S22,IFERROR('SA-1'!Y22*'SA-1'!AB22,0)) | J15: =IF($B15="Actual",'WA-1'!S22,IFERROR('WA-1'!Y22*'WA-1'!AB22,0)) | K15: =IF($B15="Actual",'IDC-NSW'!S22,IFERROR('IDC-NSW'!Y22*'IDC-NSW'!AB22,0)) | L15: =IF($B15="Actual",'IDC-VIC'!S22,IFERROR('IDC-VIC'!Y22*'IDC-VIC'!AB22,0)) | AJ15: =IF($B15="Actual",C15,IF(Y15<>"",Y15,C15+N(N15))) | AK15: =IF($B15="Actual",D15,IF(Z15<>"",Z15,D15+N(O15))) | AL15: =IF($B15="Actual",E15,IF(AA15<>"",AA15,E15+N(P15))) | AM15: =IF($B15="Actual",F15,IF(AB15<>"",AB15,F15+N(Q15))) | AN15: =IF($B15="Actual",G15,IF(AC15<>"",AC15,G15+N(R15))) | AO15: =IF($B15="Actual",H15,IF(AD15<>"",AD15,H15+N(S15))) | AP15: =IF($B15="Actual",I15,IF(AE15<>"",AE15,I15+N(T15))) | AQ15: =IF($B15="Actual",J15,IF(AF15<>"",AF15,J15+N(U15))) | ... AS15: =IF($B15="Actual",L15,IF(AH15<>"",AH15,L15+N(W15)))
A16: 45901 | B16: =IF(A16<=LastActual,"Actual","Forecast") | C16: =IF($B16="Actual",'NSW-1'!S23,IFERROR('NSW-1'!Y23*'NSW-1'!AB23,0)) | D16: =IF($B16="Actual",'VIC-1'!S23,IFERROR('VIC-1'!Y23*'VIC-1'!AB23,0)) | E16: =IF($B16="Actual",'QLD-1'!S23,IFERROR('QLD-1'!Y23*'QLD-1'!AB23,0)) | F16: =IF($B16="Actual",'NSW-2'!S23,IFERROR('NSW-2'!Y23*'NSW-2'!AB23,0)) | G16: =IF($B16="Actual",'VIC-2'!S23,IFERROR('VIC-2'!Y23*'VIC-2'!AB23,0)) | H16: =IF($B16="Actual",'QLD-2'!S23,IFERROR('QLD-2'!Y23*'QLD-2'!AB23,0)) | I16: =IF($B16="Actual",'SA-1'!S23,IFERROR('SA-1'!Y23*'SA-1'!AB23,0)) | J16: =IF($B16="Actual",'WA-1'!S23,IFERROR('WA-1'!Y23*'WA-1'!AB23,0)) | K16: =IF($B16="Actual",'IDC-NSW'!S23,IFERROR('IDC-NSW'!Y23*'IDC-NSW'!AB23,0)) | L16: =IF($B16="Actual",'IDC-VIC'!S23,IFERROR('IDC-VIC'!Y23*'IDC-VIC'!AB23,0)) | AJ16: =IF($B16="Actual",C16,IF(Y16<>"",Y16,C16+N(N16))) | AK16: =IF($B16="Actual",D16,IF(Z16<>"",Z16,D16+N(O16))) | AL16: =IF($B16="Actual",E16,IF(AA16<>"",AA16,E16+N(P16))) | AM16: =IF($B16="Actual",F16,IF(AB16<>"",AB16,F16+N(Q16))) | AN16: =IF($B16="Actual",G16,IF(AC16<>"",AC16,G16+N(R16))) | AO16: =IF($B16="Actual",H16,IF(AD16<>"",AD16,H16+N(S16))) | AP16: =IF($B16="Actual",I16,IF(AE16<>"",AE16,I16+N(T16))) | AQ16: =IF($B16="Actual",J16,IF(AF16<>"",AF16,J16+N(U16))) | ... AS16: =IF($B16="Actual",L16,IF(AH16<>"",AH16,L16+N(W16)))
A17: 45931 | B17: =IF(A17<=LastActual,"Actual","Forecast") | C17: =IF($B17="Actual",'NSW-1'!S24,IFERROR('NSW-1'!Y24*'NSW-1'!AB24,0)) | D17: =IF($B17="Actual",'VIC-1'!S24,IFERROR('VIC-1'!Y24*'VIC-1'!AB24,0)) | E17: =IF($B17="Actual",'QLD-1'!S24,IFERROR('QLD-1'!Y24*'QLD-1'!AB24,0)) | F17: =IF($B17="Actual",'NSW-2'!S24,IFERROR('NSW-2'!Y24*'NSW-2'!AB24,0)) | G17: =IF($B17="Actual",'VIC-2'!S24,IFERROR('VIC-2'!Y24*'VIC-2'!AB24,0)) | H17: =IF($B17="Actual",'QLD-2'!S24,IFERROR('QLD-2'!Y24*'QLD-2'!AB24,0)) | I17: =IF($B17="Actual",'SA-1'!S24,IFERROR('SA-1'!Y24*'SA-1'!AB24,0)) | J17: =IF($B17="Actual",'WA-1'!S24,IFERROR('WA-1'!Y24*'WA-1'!AB24,0)) | K17: =IF($B17="Actual",'IDC-NSW'!S24,IFERROR('IDC-NSW'!Y24*'IDC-NSW'!AB24,0)) | L17: =IF($B17="Actual",'IDC-VIC'!S24,IFERROR('IDC-VIC'!Y24*'IDC-VIC'!AB24,0)) | AJ17: =IF($B17="Actual",C17,IF(Y17<>"",Y17,C17+N(N17))) | AK17: =IF($B17="Actual",D17,IF(Z17<>"",Z17,D17+N(O17))) | AL17: =IF($B17="Actual",E17,IF(AA17<>"",AA17,E17+N(P17))) | AM17: =IF($B17="Actual",F17,IF(AB17<>"",AB17,F17+N(Q17))) | AN17: =IF($B17="Actual",G17,IF(AC17<>"",AC17,G17+N(R17))) | AO17: =IF($B17="Actual",H17,IF(AD17<>"",AD17,H17+N(S17))) | AP17: =IF($B17="Actual",I17,IF(AE17<>"",AE17,I17+N(T17))) | AQ17: =IF($B17="Actual",J17,IF(AF17<>"",AF17,J17+N(U17))) | ... AS17: =IF($B17="Actual",L17,IF(AH17<>"",AH17,L17+N(W17)))
A18: 45962 | B18: =IF(A18<=LastActual,"Actual","Forecast") | C18: =IF($B18="Actual",'NSW-1'!S25,IFERROR('NSW-1'!Y25*'NSW-1'!AB25,0)) | D18: =IF($B18="Actual",'VIC-1'!S25,IFERROR('VIC-1'!Y25*'VIC-1'!AB25,0)) | E18: =IF($B18="Actual",'QLD-1'!S25,IFERROR('QLD-1'!Y25*'QLD-1'!AB25,0)) | F18: =IF($B18="Actual",'NSW-2'!S25,IFERROR('NSW-2'!Y25*'NSW-2'!AB25,0)) | G18: =IF($B18="Actual",'VIC-2'!S25,IFERROR('VIC-2'!Y25*'VIC-2'!AB25,0)) | H18: =IF($B18="Actual",'QLD-2'!S25,IFERROR('QLD-2'!Y25*'QLD-2'!AB25,0)) | I18: =IF($B18="Actual",'SA-1'!S25,IFERROR('SA-1'!Y25*'SA-1'!AB25,0)) | J18: =IF($B18="Actual",'WA-1'!S25,IFERROR('WA-1'!Y25*'WA-1'!AB25,0)) | K18: =IF($B18="Actual",'IDC-NSW'!S25,IFERROR('IDC-NSW'!Y25*'IDC-NSW'!AB25,0)) | L18: =IF($B18="Actual",'IDC-VIC'!S25,IFERROR('IDC-VIC'!Y25*'IDC-VIC'!AB25,0)) | AJ18: =IF($B18="Actual",C18,IF(Y18<>"",Y18,C18+N(N18))) | AK18: =IF($B18="Actual",D18,IF(Z18<>"",Z18,D18+N(O18))) | AL18: =IF($B18="Actual",E18,IF(AA18<>"",AA18,E18+N(P18))) | AM18: =IF($B18="Actual",F18,IF(AB18<>"",AB18,F18+N(Q18))) | AN18: =IF($B18="Actual",G18,IF(AC18<>"",AC18,G18+N(R18))) | AO18: =IF($B18="Actual",H18,IF(AD18<>"",AD18,H18+N(S18))) | AP18: =IF($B18="Actual",I18,IF(AE18<>"",AE18,I18+N(T18))) | AQ18: =IF($B18="Actual",J18,IF(AF18<>"",AF18,J18+N(U18))) | ... AS18: =IF($B18="Actual",L18,IF(AH18<>"",AH18,L18+N(W18)))
A19: 45992 | B19: =IF(A19<=LastActual,"Actual","Forecast") | C19: =IF($B19="Actual",'NSW-1'!S26,IFERROR('NSW-1'!Y26*'NSW-1'!AB26,0)) | D19: =IF($B19="Actual",'VIC-1'!S26,IFERROR('VIC-1'!Y26*'VIC-1'!AB26,0)) | E19: =IF($B19="Actual",'QLD-1'!S26,IFERROR('QLD-1'!Y26*'QLD-1'!AB26,0)) | F19: =IF($B19="Actual",'NSW-2'!S26,IFERROR('NSW-2'!Y26*'NSW-2'!AB26,0)) | G19: =IF($B19="Actual",'VIC-2'!S26,IFERROR('VIC-2'!Y26*'VIC-2'!AB26,0)) | H19: =IF($B19="Actual",'QLD-2'!S26,IFERROR('QLD-2'!Y26*'QLD-2'!AB26,0)) | I19: =IF($B19="Actual",'SA-1'!S26,IFERROR('SA-1'!Y26*'SA-1'!AB26,0)) | J19: =IF($B19="Actual",'WA-1'!S26,IFERROR('WA-1'!Y26*'WA-1'!AB26,0)) | K19: =IF($B19="Actual",'IDC-NSW'!S26,IFERROR('IDC-NSW'!Y26*'IDC-NSW'!AB26,0)) | L19: =IF($B19="Actual",'IDC-VIC'!S26,IFERROR('IDC-VIC'!Y26*'IDC-VIC'!AB26,0)) | AJ19: =IF($B19="Actual",C19,IF(Y19<>"",Y19,C19+N(N19))) | AK19: =IF($B19="Actual",D19,IF(Z19<>"",Z19,D19+N(O19))) | AL19: =IF($B19="Actual",E19,IF(AA19<>"",AA19,E19+N(P19))) | AM19: =IF($B19="Actual",F19,IF(AB19<>"",AB19,F19+N(Q19))) | AN19: =IF($B19="Actual",G19,IF(AC19<>"",AC19,G19+N(R19))) | AO19: =IF($B19="Actual",H19,IF(AD19<>"",AD19,H19+N(S19))) | AP19: =IF($B19="Actual",I19,IF(AE19<>"",AE19,I19+N(T19))) | AQ19: =IF($B19="Actual",J19,IF(AF19<>"",AF19,J19+N(U19))) | ... AS19: =IF($B19="Actual",L19,IF(AH19<>"",AH19,L19+N(W19)))
... A55: 47088 | B55: =IF(A55<=LastActual,"Actual","Forecast") | C55: =IF($B55="Actual",'NSW-1'!S62,IFERROR('NSW-1'!Y62*'NSW-1'!AB62,0)) | D55: =IF($B55="Actual",'VIC-1'!S62,IFERROR('VIC-1'!Y62*'VIC-1'!AB62,0)) | E55: =IF($B55="Actual",'QLD-1'!S62,IFERROR('QLD-1'!Y62*'QLD-1'!AB62,0)) | F55: =IF($B55="Actual",'NSW-2'!S62,IFERROR('NSW-2'!Y62*'NSW-2'!AB62,0)) | G55: =IF($B55="Actual",'VIC-2'!S62,IFERROR('VIC-2'!Y62*'VIC-2'!AB62,0)) | H55: =IF($B55="Actual",'QLD-2'!S62,IFERROR('QLD-2'!Y62*'QLD-2'!AB62,0)) | I55: =IF($B55="Actual",'SA-1'!S62,IFERROR('SA-1'!Y62*'SA-1'!AB62,0)) | J55: =IF($B55="Actual",'WA-1'!S62,IFERROR('WA-1'!Y62*'WA-1'!AB62,0)) | K55: =IF($B55="Actual",'IDC-NSW'!S62,IFERROR('IDC-NSW'!Y62*'IDC-NSW'!AB62,0)) | L55: =IF($B55="Actual",'IDC-VIC'!S62,IFERROR('IDC-VIC'!Y62*'IDC-VIC'!AB62,0)) | AJ55: =IF($B55="Actual",C55,IF(Y55<>"",Y55,C55+N(N55))) | AK55: =IF($B55="Actual",D55,IF(Z55<>"",Z55,D55+N(O55))) | AL55: =IF($B55="Actual",E55,IF(AA55<>"",AA55,E55+N(P55))) | AM55: =IF($B55="Actual",F55,IF(AB55<>"",AB55,F55+N(Q55))) | AN55: =IF($B55="Actual",G55,IF(AC55<>"",AC55,G55+N(R55))) | AO55: =IF($B55="Actual",H55,IF(AD55<>"",AD55,H55+N(S55))) | AP55: =IF($B55="Actual",I55,IF(AE55<>"",AE55,I55+N(T55))) | AQ55: =IF($B55="Actual",J55,IF(AF55<>"",AF55,J55+N(U55))) | ... AS55: =IF($B55="Actual",L55,IF(AH55<>"",AH55,L55+N(W55)))

Sheet CLR
A1: CLR: cost-saving initiatives (placeholder)
A2: Placeholder only. Nothing on this tab feeds the forecast yet.
A4: Initiative | B4: Site | C4: Type | D4: Value | E4: Start month | F4: Ramp-up months | G4: End month | H4: Active | I4: Owner / notes

Sheet Holidays
A1: Date | B1: Holiday | C1: State | E1: Generated by rule. Add, remove or move rows freely; the Calendar tab counts them by state and month.
A2: 45658 | B2: New Year's Day | C2: NSW
A3: 45684 | B3: Australia Day | C3: NSW
A4: 45765 | B4: Good Friday | C4: NSW
A5: 45766 | B5: Easter Saturday | C5: NSW
A6: 45767 | B6: Easter Sunday | C6: NSW
A7: 45768 | B7: Easter Monday | C7: NSW
A8: 45772 | B8: Anzac Day | C8: NSW
A9: 45817 | B9: King's Birthday | C9: NSW
A10: 45936 | B10: Labour Day | C10: NSW
A11: 46016 | B11: Christmas Day | C11: NSW
A12: 46017 | B12: Boxing Day | C12: NSW
A13: 46023 | B13: New Year's Day | C13: NSW
... A256: 47113 | B256: Boxing Day | C256: WA

Sheet Calendar
A1: Calendar: public holidays, PH cost factor, wage index
A2: PH factor = average cost per hour in the month vs a month with no public holidays.
C3: Public holidays (count) | H3: PH cost factor
A4: Month | B4: Days | C4: PH NSW | D4: PH VIC | E4: PH QLD | F4: PH SA | G4: PH WA | H4: NSW | I4: VIC | J4: QLD | K4: SA | L4: WA | M4: Wage index
A5: 45658 | B5: =DAY(EOMONTH(A5,0)) | C5: =COUNTIFS(Holidays!$A$2:$A$1000,">="&$A5,Holidays!$A$2:$A$1000,"<="&EOMONTH($A5,0),Holidays!$C$2:$C$1000,"NSW") | D5: =COUNTIFS(Holidays!$A$2:$A$1000,">="&$A5,Holidays!$A$2:$A$1000,"<="&EOMONTH($A5,0),Holidays!$C$2:$C$1000,"VIC") | E5: =COUNTIFS(Holidays!$A$2:$A$1000,">="&$A5,Holidays!$A$2:$A$1000,"<="&EOMONTH($A5,0),Holidays!$C$2:$C$1000,"QLD") | F5: =COUNTIFS(Holidays!$A$2:$A$1000,">="&$A5,Holidays!$A$2:$A$1000,"<="&EOMONTH($A5,0),Holidays!$C$2:$C$1000,"SA") | G5: =COUNTIFS(Holidays!$A$2:$A$1000,">="&$A5,Holidays!$A$2:$A$1000,"<="&EOMONTH($A5,0),Holidays!$C$2:$C$1000,"WA") | H5: =($B5-C5+C5*PH_Roster*(1+PH_Loading))/($B5-C5+C5*PH_Roster) | I5: =($B5-D5+D5*PH_Roster*(1+PH_Loading))/($B5-D5+D5*PH_Roster) | J5: =($B5-E5+E5*PH_Roster*(1+PH_Loading))/($B5-E5+E5*PH_Roster) | K5: =($B5-F5+F5*PH_Roster*(1+PH_Loading))/($B5-F5+F5*PH_Roster) | L5: =($B5-G5+G5*PH_Roster*(1+PH_Loading))/($B5-G5+G5*PH_Roster) | M5: =EXP(SUMPRODUCT((WageDates<=$A5)*(WageDates<>"")*LN(1+WageRates)))
A6: 45689 | B6: =DAY(EOMONTH(A6,0)) | C6: =COUNTIFS(Holidays!$A$2:$A$1000,">="&$A6,Holidays!$A$2:$A$1000,"<="&EOMONTH($A6,0),Holidays!$C$2:$C$1000,"NSW") | D6: =COUNTIFS(Holidays!$A$2:$A$1000,">="&$A6,Holidays!$A$2:$A$1000,"<="&EOMONTH($A6,0),Holidays!$C$2:$C$1000,"VIC") | E6: =COUNTIFS(Holidays!$A$2:$A$1000,">="&$A6,Holidays!$A$2:$A$1000,"<="&EOMONTH($A6,0),Holidays!$C$2:$C$1000,"QLD") | F6: =COUNTIFS(Holidays!$A$2:$A$1000,">="&$A6,Holidays!$A$2:$A$1000,"<="&EOMONTH($A6,0),Holidays!$C$2:$C$1000,"SA") | G6: =COUNTIFS(Holidays!$A$2:$A$1000,">="&$A6,Holidays!$A$2:$A$1000,"<="&EOMONTH($A6,0),Holidays!$C$2:$C$1000,"WA") | H6: =($B6-C6+C6*PH_Roster*(1+PH_Loading))/($B6-C6+C6*PH_Roster) | I6: =($B6-D6+D6*PH_Roster*(1+PH_Loading))/($B6-D6+D6*PH_Roster) | J6: =($B6-E6+E6*PH_Roster*(1+PH_Loading))/($B6-E6+E6*PH_Roster) | K6: =($B6-F6+F6*PH_Roster*(1+PH_Loading))/($B6-F6+F6*PH_Roster) | L6: =($B6-G6+G6*PH_Roster*(1+PH_Loading))/($B6-G6+G6*PH_Roster) | M6: =EXP(SUMPRODUCT((WageDates<=$A6)*(WageDates<>"")*LN(1+WageRates)))
A7: 45717 | B7: =DAY(EOMONTH(A7,0)) | C7: =COUNTIFS(Holidays!$A$2:$A$1000,">="&$A7,Holidays!$A$2:$A$1000,"<="&EOMONTH($A7,0),Holidays!$C$2:$C$1000,"NSW") | D7: =COUNTIFS(Holidays!$A$2:$A$1000,">="&$A7,Holidays!$A$2:$A$1000,"<="&EOMONTH($A7,0),Holidays!$C$2:$C$1000,"VIC") | E7: =COUNTIFS(Holidays!$A$2:$A$1000,">="&$A7,Holidays!$A$2:$A$1000,"<="&EOMONTH($A7,0),Holidays!$C$2:$C$1000,"QLD") | F7: =COUNTIFS(Holidays!$A$2:$A$1000,">="&$A7,Holidays!$A$2:$A$1000,"<="&EOMONTH($A7,0),Holidays!$C$2:$C$1000,"SA") | G7: =COUNTIFS(Holidays!$A$2:$A$1000,">="&$A7,Holidays!$A$2:$A$1000,"<="&EOMONTH($A7,0),Holidays!$C$2:$C$1000,"WA") | H7: =($B7-C7+C7*PH_Roster*(1+PH_Loading))/($B7-C7+C7*PH_Roster) | I7: =($B7-D7+D7*PH_Roster*(1+PH_Loading))/($B7-D7+D7*PH_Roster) | J7: =($B7-E7+E7*PH_Roster*(1+PH_Loading))/($B7-E7+E7*PH_Roster) | K7: =($B7-F7+F7*PH_Roster*(1+PH_Loading))/($B7-F7+F7*PH_Roster) | L7: =($B7-G7+G7*PH_Roster*(1+PH_Loading))/($B7-G7+G7*PH_Roster) | M7: =EXP(SUMPRODUCT((WageDates<=$A7)*(WageDates<>"")*LN(1+WageRates)))
A8: 45748 | B8: =DAY(EOMONTH(A8,0)) | C8: =COUNTIFS(Holidays!$A$2:$A$1000,">="&$A8,Holidays!$A$2:$A$1000,"<="&EOMONTH($A8,0),Holidays!$C$2:$C$1000,"NSW") | D8: =COUNTIFS(Holidays!$A$2:$A$1000,">="&$A8,Holidays!$A$2:$A$1000,"<="&EOMONTH($A8,0),Holidays!$C$2:$C$1000,"VIC") | E8: =COUNTIFS(Holidays!$A$2:$A$1000,">="&$A8,Holidays!$A$2:$A$1000,"<="&EOMONTH($A8,0),Holidays!$C$2:$C$1000,"QLD") | F8: =COUNTIFS(Holidays!$A$2:$A$1000,">="&$A8,Holidays!$A$2:$A$1000,"<="&EOMONTH($A8,0),Holidays!$C$2:$C$1000,"SA") | G8: =COUNTIFS(Holidays!$A$2:$A$1000,">="&$A8,Holidays!$A$2:$A$1000,"<="&EOMONTH($A8,0),Holidays!$C$2:$C$1000,"WA") | H8: =($B8-C8+C8*PH_Roster*(1+PH_Loading))/($B8-C8+C8*PH_Roster) | I8: =($B8-D8+D8*PH_Roster*(1+PH_Loading))/($B8-D8+D8*PH_Roster) | J8: =($B8-E8+E8*PH_Roster*(1+PH_Loading))/($B8-E8+E8*PH_Roster) | K8: =($B8-F8+F8*PH_Roster*(1+PH_Loading))/($B8-F8+F8*PH_Roster) | L8: =($B8-G8+G8*PH_Roster*(1+PH_Loading))/($B8-G8+G8*PH_Roster) | M8: =EXP(SUMPRODUCT((WageDates<=$A8)*(WageDates<>"")*LN(1+WageRates)))
A9: 45778 | B9: =DAY(EOMONTH(A9,0)) | C9: =COUNTIFS(Holidays!$A$2:$A$1000,">="&$A9,Holidays!$A$2:$A$1000,"<="&EOMONTH($A9,0),Holidays!$C$2:$C$1000,"NSW") | D9: =COUNTIFS(Holidays!$A$2:$A$1000,">="&$A9,Holidays!$A$2:$A$1000,"<="&EOMONTH($A9,0),Holidays!$C$2:$C$1000,"VIC") | E9: =COUNTIFS(Holidays!$A$2:$A$1000,">="&$A9,Holidays!$A$2:$A$1000,"<="&EOMONTH($A9,0),Holidays!$C$2:$C$1000,"QLD") | F9: =COUNTIFS(Holidays!$A$2:$A$1000,">="&$A9,Holidays!$A$2:$A$1000,"<="&EOMONTH($A9,0),Holidays!$C$2:$C$1000,"SA") | G9: =COUNTIFS(Holidays!$A$2:$A$1000,">="&$A9,Holidays!$A$2:$A$1000,"<="&EOMONTH($A9,0),Holidays!$C$2:$C$1000,"WA") | H9: =($B9-C9+C9*PH_Roster*(1+PH_Loading))/($B9-C9+C9*PH_Roster) | I9: =($B9-D9+D9*PH_Roster*(1+PH_Loading))/($B9-D9+D9*PH_Roster) | J9: =($B9-E9+E9*PH_Roster*(1+PH_Loading))/($B9-E9+E9*PH_Roster) | K9: =($B9-F9+F9*PH_Roster*(1+PH_Loading))/($B9-F9+F9*PH_Roster) | L9: =($B9-G9+G9*PH_Roster*(1+PH_Loading))/($B9-G9+G9*PH_Roster) | M9: =EXP(SUMPRODUCT((WageDates<=$A9)*(WageDates<>"")*LN(1+WageRates)))
A10: 45809 | B10: =DAY(EOMONTH(A10,0)) | C10: =COUNTIFS(Holidays!$A$2:$A$1000,">="&$A10,Holidays!$A$2:$A$1000,"<="&EOMONTH($A10,0),Holidays!$C$2:$C$1000,"NSW") | D10: =COUNTIFS(Holidays!$A$2:$A$1000,">="&$A10,Holidays!$A$2:$A$1000,"<="&EOMONTH($A10,0),Holidays!$C$2:$C$1000,"VIC") | E10: =COUNTIFS(Holidays!$A$2:$A$1000,">="&$A10,Holidays!$A$2:$A$1000,"<="&EOMONTH($A10,0),Holidays!$C$2:$C$1000,"QLD") | F10: =COUNTIFS(Holidays!$A$2:$A$1000,">="&$A10,Holidays!$A$2:$A$1000,"<="&EOMONTH($A10,0),Holidays!$C$2:$C$1000,"SA") | G10: =COUNTIFS(Holidays!$A$2:$A$1000,">="&$A10,Holidays!$A$2:$A$1000,"<="&EOMONTH($A10,0),Holidays!$C$2:$C$1000,"WA") | H10: =($B10-C10+C10*PH_Roster*(1+PH_Loading))/($B10-C10+C10*PH_Roster) | I10: =($B10-D10+D10*PH_Roster*(1+PH_Loading))/($B10-D10+D10*PH_Roster) | J10: =($B10-E10+E10*PH_Roster*(1+PH_Loading))/($B10-E10+E10*PH_Roster) | K10: =($B10-F10+F10*PH_Roster*(1+PH_Loading))/($B10-F10+F10*PH_Roster) | L10: =($B10-G10+G10*PH_Roster*(1+PH_Loading))/($B10-G10+G10*PH_Roster) | M10: =EXP(SUMPRODUCT((WageDates<=$A10)*(WageDates<>"")*LN(1+WageRates)))
A11: 45839 | B11: =DAY(EOMONTH(A11,0)) | C11: =COUNTIFS(Holidays!$A$2:$A$1000,">="&$A11,Holidays!$A$2:$A$1000,"<="&EOMONTH($A11,0),Holidays!$C$2:$C$1000,"NSW") | D11: =COUNTIFS(Holidays!$A$2:$A$1000,">="&$A11,Holidays!$A$2:$A$1000,"<="&EOMONTH($A11,0),Holidays!$C$2:$C$1000,"VIC") | E11: =COUNTIFS(Holidays!$A$2:$A$1000,">="&$A11,Holidays!$A$2:$A$1000,"<="&EOMONTH($A11,0),Holidays!$C$2:$C$1000,"QLD") | F11: =COUNTIFS(Holidays!$A$2:$A$1000,">="&$A11,Holidays!$A$2:$A$1000,"<="&EOMONTH($A11,0),Holidays!$C$2:$C$1000,"SA") | G11: =COUNTIFS(Holidays!$A$2:$A$1000,">="&$A11,Holidays!$A$2:$A$1000,"<="&EOMONTH($A11,0),Holidays!$C$2:$C$1000,"WA") | H11: =($B11-C11+C11*PH_Roster*(1+PH_Loading))/($B11-C11+C11*PH_Roster) | I11: =($B11-D11+D11*PH_Roster*(1+PH_Loading))/($B11-D11+D11*PH_Roster) | J11: =($B11-E11+E11*PH_Roster*(1+PH_Loading))/($B11-E11+E11*PH_Roster) | K11: =($B11-F11+F11*PH_Roster*(1+PH_Loading))/($B11-F11+F11*PH_Roster) | L11: =($B11-G11+G11*PH_Roster*(1+PH_Loading))/($B11-G11+G11*PH_Roster) | M11: =EXP(SUMPRODUCT((WageDates<=$A11)*(WageDates<>"")*LN(1+WageRates)))
A12: 45870 | B12: =DAY(EOMONTH(A12,0)) | C12: =COUNTIFS(Holidays!$A$2:$A$1000,">="&$A12,Holidays!$A$2:$A$1000,"<="&EOMONTH($A12,0),Holidays!$C$2:$C$1000,"NSW") | D12: =COUNTIFS(Holidays!$A$2:$A$1000,">="&$A12,Holidays!$A$2:$A$1000,"<="&EOMONTH($A12,0),Holidays!$C$2:$C$1000,"VIC") | E12: =COUNTIFS(Holidays!$A$2:$A$1000,">="&$A12,Holidays!$A$2:$A$1000,"<="&EOMONTH($A12,0),Holidays!$C$2:$C$1000,"QLD") | F12: =COUNTIFS(Holidays!$A$2:$A$1000,">="&$A12,Holidays!$A$2:$A$1000,"<="&EOMONTH($A12,0),Holidays!$C$2:$C$1000,"SA") | G12: =COUNTIFS(Holidays!$A$2:$A$1000,">="&$A12,Holidays!$A$2:$A$1000,"<="&EOMONTH($A12,0),Holidays!$C$2:$C$1000,"WA") | H12: =($B12-C12+C12*PH_Roster*(1+PH_Loading))/($B12-C12+C12*PH_Roster) | I12: =($B12-D12+D12*PH_Roster*(1+PH_Loading))/($B12-D12+D12*PH_Roster) | J12: =($B12-E12+E12*PH_Roster*(1+PH_Loading))/($B12-E12+E12*PH_Roster) | K12: =($B12-F12+F12*PH_Roster*(1+PH_Loading))/($B12-F12+F12*PH_Roster) | L12: =($B12-G12+G12*PH_Roster*(1+PH_Loading))/($B12-G12+G12*PH_Roster) | M12: =EXP(SUMPRODUCT((WageDates<=$A12)*(WageDates<>"")*LN(1+WageRates)))
A13: 45901 | B13: =DAY(EOMONTH(A13,0)) | C13: =COUNTIFS(Holidays!$A$2:$A$1000,">="&$A13,Holidays!$A$2:$A$1000,"<="&EOMONTH($A13,0),Holidays!$C$2:$C$1000,"NSW") | D13: =COUNTIFS(Holidays!$A$2:$A$1000,">="&$A13,Holidays!$A$2:$A$1000,"<="&EOMONTH($A13,0),Holidays!$C$2:$C$1000,"VIC") | E13: =COUNTIFS(Holidays!$A$2:$A$1000,">="&$A13,Holidays!$A$2:$A$1000,"<="&EOMONTH($A13,0),Holidays!$C$2:$C$1000,"QLD") | F13: =COUNTIFS(Holidays!$A$2:$A$1000,">="&$A13,Holidays!$A$2:$A$1000,"<="&EOMONTH($A13,0),Holidays!$C$2:$C$1000,"SA") | G13: =COUNTIFS(Holidays!$A$2:$A$1000,">="&$A13,Holidays!$A$2:$A$1000,"<="&EOMONTH($A13,0),Holidays!$C$2:$C$1000,"WA") | H13: =($B13-C13+C13*PH_Roster*(1+PH_Loading))/($B13-C13+C13*PH_Roster) | I13: =($B13-D13+D13*PH_Roster*(1+PH_Loading))/($B13-D13+D13*PH_Roster) | J13: =($B13-E13+E13*PH_Roster*(1+PH_Loading))/($B13-E13+E13*PH_Roster) | K13: =($B13-F13+F13*PH_Roster*(1+PH_Loading))/($B13-F13+F13*PH_Roster) | L13: =($B13-G13+G13*PH_Roster*(1+PH_Loading))/($B13-G13+G13*PH_Roster) | M13: =EXP(SUMPRODUCT((WageDates<=$A13)*(WageDates<>"")*LN(1+WageRates)))
A14: 45931 | B14: =DAY(EOMONTH(A14,0)) | C14: =COUNTIFS(Holidays!$A$2:$A$1000,">="&$A14,Holidays!$A$2:$A$1000,"<="&EOMONTH($A14,0),Holidays!$C$2:$C$1000,"NSW") | D14: =COUNTIFS(Holidays!$A$2:$A$1000,">="&$A14,Holidays!$A$2:$A$1000,"<="&EOMONTH($A14,0),Holidays!$C$2:$C$1000,"VIC") | E14: =COUNTIFS(Holidays!$A$2:$A$1000,">="&$A14,Holidays!$A$2:$A$1000,"<="&EOMONTH($A14,0),Holidays!$C$2:$C$1000,"QLD") | F14: =COUNTIFS(Holidays!$A$2:$A$1000,">="&$A14,Holidays!$A$2:$A$1000,"<="&EOMONTH($A14,0),Holidays!$C$2:$C$1000,"SA") | G14: =COUNTIFS(Holidays!$A$2:$A$1000,">="&$A14,Holidays!$A$2:$A$1000,"<="&EOMONTH($A14,0),Holidays!$C$2:$C$1000,"WA") | H14: =($B14-C14+C14*PH_Roster*(1+PH_Loading))/($B14-C14+C14*PH_Roster) | I14: =($B14-D14+D14*PH_Roster*(1+PH_Loading))/($B14-D14+D14*PH_Roster) | J14: =($B14-E14+E14*PH_Roster*(1+PH_Loading))/($B14-E14+E14*PH_Roster) | K14: =($B14-F14+F14*PH_Roster*(1+PH_Loading))/($B14-F14+F14*PH_Roster) | L14: =($B14-G14+G14*PH_Roster*(1+PH_Loading))/($B14-G14+G14*PH_Roster) | M14: =EXP(SUMPRODUCT((WageDates<=$A14)*(WageDates<>"")*LN(1+WageRates)))
A15: 45962 | B15: =DAY(EOMONTH(A15,0)) | C15: =COUNTIFS(Holidays!$A$2:$A$1000,">="&$A15,Holidays!$A$2:$A$1000,"<="&EOMONTH($A15,0),Holidays!$C$2:$C$1000,"NSW") | D15: =COUNTIFS(Holidays!$A$2:$A$1000,">="&$A15,Holidays!$A$2:$A$1000,"<="&EOMONTH($A15,0),Holidays!$C$2:$C$1000,"VIC") | E15: =COUNTIFS(Holidays!$A$2:$A$1000,">="&$A15,Holidays!$A$2:$A$1000,"<="&EOMONTH($A15,0),Holidays!$C$2:$C$1000,"QLD") | F15: =COUNTIFS(Holidays!$A$2:$A$1000,">="&$A15,Holidays!$A$2:$A$1000,"<="&EOMONTH($A15,0),Holidays!$C$2:$C$1000,"SA") | G15: =COUNTIFS(Holidays!$A$2:$A$1000,">="&$A15,Holidays!$A$2:$A$1000,"<="&EOMONTH($A15,0),Holidays!$C$2:$C$1000,"WA") | H15: =($B15-C15+C15*PH_Roster*(1+PH_Loading))/($B15-C15+C15*PH_Roster) | I15: =($B15-D15+D15*PH_Roster*(1+PH_Loading))/($B15-D15+D15*PH_Roster) | J15: =($B15-E15+E15*PH_Roster*(1+PH_Loading))/($B15-E15+E15*PH_Roster) | K15: =($B15-F15+F15*PH_Roster*(1+PH_Loading))/($B15-F15+F15*PH_Roster) | L15: =($B15-G15+G15*PH_Roster*(1+PH_Loading))/($B15-G15+G15*PH_Roster) | M15: =EXP(SUMPRODUCT((WageDates<=$A15)*(WageDates<>"")*LN(1+WageRates)))
A16: 45992 | B16: =DAY(EOMONTH(A16,0)) | C16: =COUNTIFS(Holidays!$A$2:$A$1000,">="&$A16,Holidays!$A$2:$A$1000,"<="&EOMONTH($A16,0),Holidays!$C$2:$C$1000,"NSW") | D16: =COUNTIFS(Holidays!$A$2:$A$1000,">="&$A16,Holidays!$A$2:$A$1000,"<="&EOMONTH($A16,0),Holidays!$C$2:$C$1000,"VIC") | E16: =COUNTIFS(Holidays!$A$2:$A$1000,">="&$A16,Holidays!$A$2:$A$1000,"<="&EOMONTH($A16,0),Holidays!$C$2:$C$1000,"QLD") | F16: =COUNTIFS(Holidays!$A$2:$A$1000,">="&$A16,Holidays!$A$2:$A$1000,"<="&EOMONTH($A16,0),Holidays!$C$2:$C$1000,"SA") | G16: =COUNTIFS(Holidays!$A$2:$A$1000,">="&$A16,Holidays!$A$2:$A$1000,"<="&EOMONTH($A16,0),Holidays!$C$2:$C$1000,"WA") | H16: =($B16-C16+C16*PH_Roster*(1+PH_Loading))/($B16-C16+C16*PH_Roster) | I16: =($B16-D16+D16*PH_Roster*(1+PH_Loading))/($B16-D16+D16*PH_Roster) | J16: =($B16-E16+E16*PH_Roster*(1+PH_Loading))/($B16-E16+E16*PH_Roster) | K16: =($B16-F16+F16*PH_Roster*(1+PH_Loading))/($B16-F16+F16*PH_Roster) | L16: =($B16-G16+G16*PH_Roster*(1+PH_Loading))/($B16-G16+G16*PH_Roster) | M16: =EXP(SUMPRODUCT((WageDates<=$A16)*(WageDates<>"")*LN(1+WageRates)))
... A52: 47088 | B52: =DAY(EOMONTH(A52,0)) | C52: =COUNTIFS(Holidays!$A$2:$A$1000,">="&$A52,Holidays!$A$2:$A$1000,"<="&EOMONTH($A52,0),Holidays!$C$2:$C$1000,"NSW") | D52: =COUNTIFS(Holidays!$A$2:$A$1000,">="&$A52,Holidays!$A$2:$A$1000,"<="&EOMONTH($A52,0),Holidays!$C$2:$C$1000,"VIC") | E52: =COUNTIFS(Holidays!$A$2:$A$1000,">="&$A52,Holidays!$A$2:$A$1000,"<="&EOMONTH($A52,0),Holidays!$C$2:$C$1000,"QLD") | F52: =COUNTIFS(Holidays!$A$2:$A$1000,">="&$A52,Holidays!$A$2:$A$1000,"<="&EOMONTH($A52,0),Holidays!$C$2:$C$1000,"SA") | G52: =COUNTIFS(Holidays!$A$2:$A$1000,">="&$A52,Holidays!$A$2:$A$1000,"<="&EOMONTH($A52,0),Holidays!$C$2:$C$1000,"WA") | H52: =($B52-C52+C52*PH_Roster*(1+PH_Loading))/($B52-C52+C52*PH_Roster) | I52: =($B52-D52+D52*PH_Roster*(1+PH_Loading))/($B52-D52+D52*PH_Roster) | J52: =($B52-E52+E52*PH_Roster*(1+PH_Loading))/($B52-E52+E52*PH_Roster) | K52: =($B52-F52+F52*PH_Roster*(1+PH_Loading))/($B52-F52+F52*PH_Roster) | L52: =($B52-G52+G52*PH_Roster*(1+PH_Loading))/($B52-G52+G52*PH_Roster) | M52: =EXP(SUMPRODUCT((WageDates<=$A52)*(WageDates<>"")*LN(1+WageRates)))

Sheet Checks
A1: Checks
A3: Overall | B3: =IF(COUNTIF(D6:D80,"ERROR")=0,"ALL CHECKS OK","CHECK ERRORS") | C3: =COUNTIF(D6:D80,"WARN")&" warning(s)"
A5: Check | B5: Value | C5: Expected | D5: Result
A6: =Inputs!$A$36&": actual rows in Data_Actuals (one per month)" | B6: =COUNTIFS(Data_Actuals!$B$2:$B$5000,Inputs!$A$36,Data_Actuals!$A$2:$A$5000,"<="&LastActual) | C6: =(YEAR(LastActual)-2025)*12+MONTH(LastActual) | D6: =IF(ABS(B6-C6)<=MAX(1,ABS(C6)*0.000001),"OK","ERROR")
A7: =Inputs!$A$37&": actual rows in Data_Actuals (one per month)" | B7: =COUNTIFS(Data_Actuals!$B$2:$B$5000,Inputs!$A$37,Data_Actuals!$A$2:$A$5000,"<="&LastActual) | C7: =(YEAR(LastActual)-2025)*12+MONTH(LastActual) | D7: =IF(ABS(B7-C7)<=MAX(1,ABS(C7)*0.000001),"OK","ERROR")
A8: =Inputs!$A$38&": actual rows in Data_Actuals (one per month)" | B8: =COUNTIFS(Data_Actuals!$B$2:$B$5000,Inputs!$A$38,Data_Actuals!$A$2:$A$5000,"<="&LastActual) | C8: =(YEAR(LastActual)-2025)*12+MONTH(LastActual) | D8: =IF(ABS(B8-C8)<=MAX(1,ABS(C8)*0.000001),"OK","ERROR")
A9: =Inputs!$A$39&": actual rows in Data_Actuals (one per month)" | B9: =COUNTIFS(Data_Actuals!$B$2:$B$5000,Inputs!$A$39,Data_Actuals!$A$2:$A$5000,"<="&LastActual) | C9: =(YEAR(LastActual)-2025)*12+MONTH(LastActual) | D9: =IF(ABS(B9-C9)<=MAX(1,ABS(C9)*0.000001),"OK","ERROR")
A10: =Inputs!$A$40&": actual rows in Data_Actuals (one per month)" | B10: =COUNTIFS(Data_Actuals!$B$2:$B$5000,Inputs!$A$40,Data_Actuals!$A$2:$A$5000,"<="&LastActual) | C10: =(YEAR(LastActual)-2025)*12+MONTH(LastActual) | D10: =IF(ABS(B10-C10)<=MAX(1,ABS(C10)*0.000001),"OK","ERROR")
A11: =Inputs!$A$41&": actual rows in Data_Actuals (one per month)" | B11: =COUNTIFS(Data_Actuals!$B$2:$B$5000,Inputs!$A$41,Data_Actuals!$A$2:$A$5000,"<="&LastActual) | C11: =(YEAR(LastActual)-2025)*12+MONTH(LastActual) | D11: =IF(ABS(B11-C11)<=MAX(1,ABS(C11)*0.000001),"OK","ERROR")
A12: =Inputs!$A$42&": actual rows in Data_Actuals (one per month)" | B12: =COUNTIFS(Data_Actuals!$B$2:$B$5000,Inputs!$A$42,Data_Actuals!$A$2:$A$5000,"<="&LastActual) | C12: =(YEAR(LastActual)-2025)*12+MONTH(LastActual) | D12: =IF(ABS(B12-C12)<=MAX(1,ABS(C12)*0.000001),"OK","ERROR")
A13: =Inputs!$A$43&": actual rows in Data_Actuals (one per month)" | B13: =COUNTIFS(Data_Actuals!$B$2:$B$5000,Inputs!$A$43,Data_Actuals!$A$2:$A$5000,"<="&LastActual) | C13: =(YEAR(LastActual)-2025)*12+MONTH(LastActual) | D13: =IF(ABS(B13-C13)<=MAX(1,ABS(C13)*0.000001),"OK","ERROR")
A14: =Inputs!$A$44&": actual rows in Data_Actuals (one per month)" | B14: =COUNTIFS(Data_Actuals!$B$2:$B$5000,Inputs!$A$44,Data_Actuals!$A$2:$A$5000,"<="&LastActual) | C14: =(YEAR(LastActual)-2025)*12+MONTH(LastActual) | D14: =IF(ABS(B14-C14)<=MAX(1,ABS(C14)*0.000001),"OK","ERROR")
A15: =Inputs!$A$45&": actual rows in Data_Actuals (one per month)" | B15: =COUNTIFS(Data_Actuals!$B$2:$B$5000,Inputs!$A$45,Data_Actuals!$A$2:$A$5000,"<="&LastActual) | C15: =(YEAR(LastActual)-2025)*12+MONTH(LastActual) | D15: =IF(ABS(B15-C15)<=MAX(1,ABS(C15)*0.000001),"OK","ERROR")
A16: =Inputs!$A$36&": plan payroll % present for every forecast month" | B16: =COUNTIFS(Plan_Inputs!$B$2:$B$5000,Inputs!$A$36,Plan_Inputs!$A$2:$A$5000,">"&LastActual,Plan_Inputs!$D$2:$D$5000,">0") | C16: =(2028-YEAR(LastActual))*12+12-MONTH(LastActual) | D16: =IF(ABS(B16-C16)<=MAX(1,ABS(C16)*0.000001),"OK","ERROR")
A17: =Inputs!$A$37&": plan payroll % present for every forecast month" | B17: =COUNTIFS(Plan_Inputs!$B$2:$B$5000,Inputs!$A$37,Plan_Inputs!$A$2:$A$5000,">"&LastActual,Plan_Inputs!$D$2:$D$5000,">0") | C17: =(2028-YEAR(LastActual))*12+12-MONTH(LastActual) | D17: =IF(ABS(B17-C17)<=MAX(1,ABS(C17)*0.000001),"OK","ERROR")
A18: =Inputs!$A$38&": plan payroll % present for every forecast month" | B18: =COUNTIFS(Plan_Inputs!$B$2:$B$5000,Inputs!$A$38,Plan_Inputs!$A$2:$A$5000,">"&LastActual,Plan_Inputs!$D$2:$D$5000,">0") | C18: =(2028-YEAR(LastActual))*12+12-MONTH(LastActual) | D18: =IF(ABS(B18-C18)<=MAX(1,ABS(C18)*0.000001),"OK","ERROR")
A19: =Inputs!$A$39&": plan payroll % present for every forecast month" | B19: =COUNTIFS(Plan_Inputs!$B$2:$B$5000,Inputs!$A$39,Plan_Inputs!$A$2:$A$5000,">"&LastActual,Plan_Inputs!$D$2:$D$5000,">0") | C19: =(2028-YEAR(LastActual))*12+12-MONTH(LastActual) | D19: =IF(ABS(B19-C19)<=MAX(1,ABS(C19)*0.000001),"OK","ERROR")
A20: =Inputs!$A$40&": plan payroll % present for every forecast month" | B20: =COUNTIFS(Plan_Inputs!$B$2:$B$5000,Inputs!$A$40,Plan_Inputs!$A$2:$A$5000,">"&LastActual,Plan_Inputs!$D$2:$D$5000,">0") | C20: =(2028-YEAR(LastActual))*12+12-MONTH(LastActual) | D20: =IF(ABS(B20-C20)<=MAX(1,ABS(C20)*0.000001),"OK","ERROR")
A21: =Inputs!$A$41&": plan payroll % present for every forecast month" | B21: =COUNTIFS(Plan_Inputs!$B$2:$B$5000,Inputs!$A$41,Plan_Inputs!$A$2:$A$5000,">"&LastActual,Plan_Inputs!$D$2:$D$5000,">0") | C21: =(2028-YEAR(LastActual))*12+12-MONTH(LastActual) | D21: =IF(ABS(B21-C21)<=MAX(1,ABS(C21)*0.000001),"OK","ERROR")
A22: =Inputs!$A$42&": plan payroll % present for every forecast month" | B22: =COUNTIFS(Plan_Inputs!$B$2:$B$5000,Inputs!$A$42,Plan_Inputs!$A$2:$A$5000,">"&LastActual,Plan_Inputs!$D$2:$D$5000,">0") | C22: =(2028-YEAR(LastActual))*12+12-MONTH(LastActual) | D22: =IF(ABS(B22-C22)<=MAX(1,ABS(C22)*0.000001),"OK","ERROR")
A23: =Inputs!$A$43&": plan payroll % present for every forecast month" | B23: =COUNTIFS(Plan_Inputs!$B$2:$B$5000,Inputs!$A$43,Plan_Inputs!$A$2:$A$5000,">"&LastActual,Plan_Inputs!$D$2:$D$5000,">0") | C23: =(2028-YEAR(LastActual))*12+12-MONTH(LastActual) | D23: =IF(ABS(B23-C23)<=MAX(1,ABS(C23)*0.000001),"OK","ERROR")
A24: =Inputs!$A$44&": plan payroll % present for every forecast month" | B24: =COUNTIFS(Plan_Inputs!$B$2:$B$5000,Inputs!$A$44,Plan_Inputs!$A$2:$A$5000,">"&LastActual,Plan_Inputs!$D$2:$D$5000,">0") | C24: =(2028-YEAR(LastActual))*12+12-MONTH(LastActual) | D24: =IF(ABS(B24-C24)<=MAX(1,ABS(C24)*0.000001),"OK","ERROR")
A25: =Inputs!$A$45&": plan payroll % present for every forecast month" | B25: =COUNTIFS(Plan_Inputs!$B$2:$B$5000,Inputs!$A$45,Plan_Inputs!$A$2:$A$5000,">"&LastActual,Plan_Inputs!$D$2:$D$5000,">0") | C25: =(2028-YEAR(LastActual))*12+12-MONTH(LastActual) | D25: =IF(ABS(B25-C25)<=MAX(1,ABS(C25)*0.000001),"OK","ERROR")
A26: Unknown site codes in Data_Actuals | B26: =SUMPRODUCT((Data_Actuals!$B$2:$B$5000<>"")*(COUNTIF(SiteCodes,Data_Actuals!$B$2:$B$5000)=0)) | C26: =0 | D26: =IF(ABS(B26-C26)<=MAX(1,ABS(C26)*0.000001),"OK","ERROR")
A27: At least 12 actual months (same month last year needs them) | B27: =(YEAR(LastActual)-2025)*12+MONTH(LastActual) | C27: =12 | D27: =IF(B27>=C27,"OK","ERROR")
A28: National sales = sum of 8 regions (IDCs excluded) | B28: =SUM(National!E15:E62) | C28: =SUM('NSW-1'!E15:E62)+SUM('VIC-1'!E15:E62)+SUM('QLD-1'!E15:E62)+SUM('NSW-2'!E15:E62)+SUM('VIC-2'!E15:E62)+SUM('QLD-2'!E15:E62)+SUM('SA-1'!E15:E62)+SUM('WA-1'!E15:E62) | D28: =IF(ABS(B28-C28)<=MAX(1,ABS(C28)*0.000001),"OK","ERROR")
A29: National total payroll = sum of all 10 sites | B29: =SUM(National!J15:J62) | C29: =SUM('NSW-1'!J15:J62)+SUM('VIC-1'!J15:J62)+SUM('QLD-1'!J15:J62)+SUM('NSW-2'!J15:J62)+SUM('VIC-2'!J15:J62)+SUM('QLD-2'!J15:J62)+SUM('SA-1'!J15:J62)+SUM('WA-1'!J15:J62)+SUM('IDC-NSW'!J15:J62)+SUM('IDC-VIC'!J15:J62) | D29: =IF(ABS(B29-C29)<=MAX(1,ABS(C29)*0.000001),"OK","ERROR")
A30: Staff + leadership = total payroll (national, all months) | B30: =SUM(National!H15:I62) | C30: =SUM(National!J15:J62) | D30: =IF(ABS(B30-C30)<=MAX(1,ABS(C30)*0.000001),"OK","ERROR")
A31: Cases_Forecast: adjustments typed in actual months (ignored) | B31: =SUMPRODUCT((Cases_Forecast!$B$8:$B$55="Actual")*(Cases_Forecast!$N$8:$W$55<>"")) | C31: =0 | D31: =IF(B31=C31,"OK","WARN")
A32: Cases_Forecast: overrides typed in actual months (ignored) | B32: =SUMPRODUCT((Cases_Forecast!$B$8:$B$55="Actual")*(Cases_Forecast!$Y$8:$AH$55<>"")) | C32: =0 | D32: =IF(B32=C32,"OK","WARN")
A33: =Inputs!$A$36&": forecast months where CPLH moves more than the tolerance vs LY" | B33: =COUNTIF('NSW-1'!AG15:AG62,">"&CPLHTol)+COUNTIF('NSW-1'!AG15:AG62,"<"&-CPLHTol) | C33: =0 | D33: =IF(B33=C33,"OK","WARN")
A34: =Inputs!$A$37&": forecast months where CPLH moves more than the tolerance vs LY" | B34: =COUNTIF('VIC-1'!AG15:AG62,">"&CPLHTol)+COUNTIF('VIC-1'!AG15:AG62,"<"&-CPLHTol) | C34: =0 | D34: =IF(B34=C34,"OK","WARN")
A35: =Inputs!$A$38&": forecast months where CPLH moves more than the tolerance vs LY" | B35: =COUNTIF('QLD-1'!AG15:AG62,">"&CPLHTol)+COUNTIF('QLD-1'!AG15:AG62,"<"&-CPLHTol) | C35: =0 | D35: =IF(B35=C35,"OK","WARN")
A36: =Inputs!$A$39&": forecast months where CPLH moves more than the tolerance vs LY" | B36: =COUNTIF('NSW-2'!AG15:AG62,">"&CPLHTol)+COUNTIF('NSW-2'!AG15:AG62,"<"&-CPLHTol) | C36: =0 | D36: =IF(B36=C36,"OK","WARN")
A37: =Inputs!$A$40&": forecast months where CPLH moves more than the tolerance vs LY" | B37: =COUNTIF('VIC-2'!AG15:AG62,">"&CPLHTol)+COUNTIF('VIC-2'!AG15:AG62,"<"&-CPLHTol) | C37: =0 | D37: =IF(B37=C37,"OK","WARN")
A38: =Inputs!$A$41&": forecast months where CPLH moves more than the tolerance vs LY" | B38: =COUNTIF('QLD-2'!AG15:AG62,">"&CPLHTol)+COUNTIF('QLD-2'!AG15:AG62,"<"&-CPLHTol) | C38: =0 | D38: =IF(B38=C38,"OK","WARN")
A39: =Inputs!$A$42&": forecast months where CPLH moves more than the tolerance vs LY" | B39: =COUNTIF('SA-1'!AG15:AG62,">"&CPLHTol)+COUNTIF('SA-1'!AG15:AG62,"<"&-CPLHTol) | C39: =0 | D39: =IF(B39=C39,"OK","WARN")
A40: =Inputs!$A$43&": forecast months where CPLH moves more than the tolerance vs LY" | B40: =COUNTIF('WA-1'!AG15:AG62,">"&CPLHTol)+COUNTIF('WA-1'!AG15:AG62,"<"&-CPLHTol) | C40: =0 | D40: =IF(B40=C40,"OK","WARN")
A41: =Inputs!$A$44&": forecast months where CPLH moves more than the tolerance vs LY" | B41: =COUNTIF('IDC-NSW'!AG15:AG62,">"&CPLHTol)+COUNTIF('IDC-NSW'!AG15:AG62,"<"&-CPLHTol) | C41: =0 | D41: =IF(B41=C41,"OK","WARN")
A42: =Inputs!$A$45&": forecast months where CPLH moves more than the tolerance vs LY" | B42: =COUNTIF('IDC-VIC'!AG15:AG62,">"&CPLHTol)+COUNTIF('IDC-VIC'!AG15:AG62,"<"&-CPLHTol) | C42: =0 | D42: =IF(B42=C42,"OK","WARN")

Sheet National
A1: National | 8 regions + 2 IDCs | sales exclude IDCs
A2: Model status | B2: =Checks!B3
R4: Total payroll ($m)
A5: FY | D5: Status | E5: Sales | F5: Cases picked | G5: WH hours worked | H5: Staff payroll | I5: Leadership payroll | J5: Total payroll | K5: CPLH (cases / hr) | L5: Cost per hour (staff) | M5: Cost per case (total payroll) | N5: Total payroll % sales | O5: Leadership % of total payroll | R5: Site | S5: FY2025 | T5: FY2026 | U5: FY2027 | V5: FY2028
A6: 2025 | D6: =IF(DATE(A6,12,1)<=LastActual,"Actual",IF(DATE(A6,1,1)>LastActual,"Forecast","Blended")) | E6: =SUMIFS($E$15:$E$62,$B$15:$B$62,$A6) | F6: =SUMIFS($F$15:$F$62,$B$15:$B$62,$A6) | G6: =SUMIFS($G$15:$G$62,$B$15:$B$62,$A6) | H6: =SUMIFS($H$15:$H$62,$B$15:$B$62,$A6) | I6: =SUMIFS($I$15:$I$62,$B$15:$B$62,$A6) | J6: =SUMIFS($J$15:$J$62,$B$15:$B$62,$A6) | K6: =IFERROR(F6/G6,0) | L6: =IFERROR(H6/G6,0) | M6: =IFERROR(J6/F6,0) | N6: =IFERROR(J6/E6,0) | O6: =IFERROR(I6/J6,0) | R6: =Inputs!$A$36 | S6: =SUMIFS('NSW-1'!$J$15:$J$62,'NSW-1'!$B$15:$B$62,2025) | T6: =SUMIFS('NSW-1'!$J$15:$J$62,'NSW-1'!$B$15:$B$62,2026) | U6: =SUMIFS('NSW-1'!$J$15:$J$62,'NSW-1'!$B$15:$B$62,2027) | V6: =SUMIFS('NSW-1'!$J$15:$J$62,'NSW-1'!$B$15:$B$62,2028)
A7: 2026 | D7: =IF(DATE(A7,12,1)<=LastActual,"Actual",IF(DATE(A7,1,1)>LastActual,"Forecast","Blended")) | E7: =SUMIFS($E$15:$E$62,$B$15:$B$62,$A7) | F7: =SUMIFS($F$15:$F$62,$B$15:$B$62,$A7) | G7: =SUMIFS($G$15:$G$62,$B$15:$B$62,$A7) | H7: =SUMIFS($H$15:$H$62,$B$15:$B$62,$A7) | I7: =SUMIFS($I$15:$I$62,$B$15:$B$62,$A7) | J7: =SUMIFS($J$15:$J$62,$B$15:$B$62,$A7) | K7: =IFERROR(F7/G7,0) | L7: =IFERROR(H7/G7,0) | M7: =IFERROR(J7/F7,0) | N7: =IFERROR(J7/E7,0) | O7: =IFERROR(I7/J7,0) | R7: =Inputs!$A$37 | S7: =SUMIFS('VIC-1'!$J$15:$J$62,'VIC-1'!$B$15:$B$62,2025) | T7: =SUMIFS('VIC-1'!$J$15:$J$62,'VIC-1'!$B$15:$B$62,2026) | U7: =SUMIFS('VIC-1'!$J$15:$J$62,'VIC-1'!$B$15:$B$62,2027) | V7: =SUMIFS('VIC-1'!$J$15:$J$62,'VIC-1'!$B$15:$B$62,2028)
A8: 2027 | D8: =IF(DATE(A8,12,1)<=LastActual,"Actual",IF(DATE(A8,1,1)>LastActual,"Forecast","Blended")) | E8: =SUMIFS($E$15:$E$62,$B$15:$B$62,$A8) | F8: =SUMIFS($F$15:$F$62,$B$15:$B$62,$A8) | G8: =SUMIFS($G$15:$G$62,$B$15:$B$62,$A8) | H8: =SUMIFS($H$15:$H$62,$B$15:$B$62,$A8) | I8: =SUMIFS($I$15:$I$62,$B$15:$B$62,$A8) | J8: =SUMIFS($J$15:$J$62,$B$15:$B$62,$A8) | K8: =IFERROR(F8/G8,0) | L8: =IFERROR(H8/G8,0) | M8: =IFERROR(J8/F8,0) | N8: =IFERROR(J8/E8,0) | O8: =IFERROR(I8/J8,0) | R8: =Inputs!$A$38 | S8: =SUMIFS('QLD-1'!$J$15:$J$62,'QLD-1'!$B$15:$B$62,2025) | T8: =SUMIFS('QLD-1'!$J$15:$J$62,'QLD-1'!$B$15:$B$62,2026) | U8: =SUMIFS('QLD-1'!$J$15:$J$62,'QLD-1'!$B$15:$B$62,2027) | V8: =SUMIFS('QLD-1'!$J$15:$J$62,'QLD-1'!$B$15:$B$62,2028)
A9: 2028 | D9: =IF(DATE(A9,12,1)<=LastActual,"Actual",IF(DATE(A9,1,1)>LastActual,"Forecast","Blended")) | E9: =SUMIFS($E$15:$E$62,$B$15:$B$62,$A9) | F9: =SUMIFS($F$15:$F$62,$B$15:$B$62,$A9) | G9: =SUMIFS($G$15:$G$62,$B$15:$B$62,$A9) | H9: =SUMIFS($H$15:$H$62,$B$15:$B$62,$A9) | I9: =SUMIFS($I$15:$I$62,$B$15:$B$62,$A9) | J9: =SUMIFS($J$15:$J$62,$B$15:$B$62,$A9) | K9: =IFERROR(F9/G9,0) | L9: =IFERROR(H9/G9,0) | M9: =IFERROR(J9/F9,0) | N9: =IFERROR(J9/E9,0) | O9: =IFERROR(I9/J9,0) | R9: =Inputs!$A$39 | S9: =SUMIFS('NSW-2'!$J$15:$J$62,'NSW-2'!$B$15:$B$62,2025) | T9: =SUMIFS('NSW-2'!$J$15:$J$62,'NSW-2'!$B$15:$B$62,2026) | U9: =SUMIFS('NSW-2'!$J$15:$J$62,'NSW-2'!$B$15:$B$62,2027) | V9: =SUMIFS('NSW-2'!$J$15:$J$62,'NSW-2'!$B$15:$B$62,2028)
R10: =Inputs!$A$40 | S10: =SUMIFS('VIC-2'!$J$15:$J$62,'VIC-2'!$B$15:$B$62,2025) | T10: =SUMIFS('VIC-2'!$J$15:$J$62,'VIC-2'!$B$15:$B$62,2026) | U10: =SUMIFS('VIC-2'!$J$15:$J$62,'VIC-2'!$B$15:$B$62,2027) | V10: =SUMIFS('VIC-2'!$J$15:$J$62,'VIC-2'!$B$15:$B$62,2028)
R11: =Inputs!$A$41 | S11: =SUMIFS('QLD-2'!$J$15:$J$62,'QLD-2'!$B$15:$B$62,2025) | T11: =SUMIFS('QLD-2'!$J$15:$J$62,'QLD-2'!$B$15:$B$62,2026) | U11: =SUMIFS('QLD-2'!$J$15:$J$62,'QLD-2'!$B$15:$B$62,2027) | V11: =SUMIFS('QLD-2'!$J$15:$J$62,'QLD-2'!$B$15:$B$62,2028)
E12: Drivers | K12: Metrics | R12: =Inputs!$A$42 | S12: =SUMIFS('SA-1'!$J$15:$J$62,'SA-1'!$B$15:$B$62,2025) | T12: =SUMIFS('SA-1'!$J$15:$J$62,'SA-1'!$B$15:$B$62,2026) | U12: =SUMIFS('SA-1'!$J$15:$J$62,'SA-1'!$B$15:$B$62,2027) | V12: =SUMIFS('SA-1'!$J$15:$J$62,'SA-1'!$B$15:$B$62,2028)
A13: Month | B13: Year | C13: Mth | D13: Status | E13: Sales | F13: Cases picked | G13: WH hours worked | H13: Staff payroll | I13: Leadership payroll | J13: Total payroll | K13: CPLH (cases / hr) | L13: Cost per hour (staff) | M13: Cost per case (total payroll) | N13: Total payroll % sales | O13: Leadership % of total payroll | R13: =Inputs!$A$43 | S13: =SUMIFS('WA-1'!$J$15:$J$62,'WA-1'!$B$15:$B$62,2025) | T13: =SUMIFS('WA-1'!$J$15:$J$62,'WA-1'!$B$15:$B$62,2026) | U13: =SUMIFS('WA-1'!$J$15:$J$62,'WA-1'!$B$15:$B$62,2027) | V13: =SUMIFS('WA-1'!$J$15:$J$62,'WA-1'!$B$15:$B$62,2028)
E14: $m | F14: m | G14: # | H14: $m | I14: $m | J14: $m | K14: # | L14: $ | M14: $ | N14: % | O14: % | R14: =Inputs!$A$44 | S14: =SUMIFS('IDC-NSW'!$J$15:$J$62,'IDC-NSW'!$B$15:$B$62,2025) | T14: =SUMIFS('IDC-NSW'!$J$15:$J$62,'IDC-NSW'!$B$15:$B$62,2026) | U14: =SUMIFS('IDC-NSW'!$J$15:$J$62,'IDC-NSW'!$B$15:$B$62,2027) | V14: =SUMIFS('IDC-NSW'!$J$15:$J$62,'IDC-NSW'!$B$15:$B$62,2028)
A15: 45658 | B15: =YEAR(A15) | C15: =MONTH(A15) | D15: =IF(A15<=LastActual,"Actual","Forecast") | E15: ='NSW-1'!E15+'VIC-1'!E15+'QLD-1'!E15+'NSW-2'!E15+'VIC-2'!E15+'QLD-2'!E15+'SA-1'!E15+'WA-1'!E15 | F15: ='NSW-1'!F15+'VIC-1'!F15+'QLD-1'!F15+'NSW-2'!F15+'VIC-2'!F15+'QLD-2'!F15+'SA-1'!F15+'WA-1'!F15+'IDC-NSW'!F15+'IDC-VIC'!F15 | G15: ='NSW-1'!G15+'VIC-1'!G15+'QLD-1'!G15+'NSW-2'!G15+'VIC-2'!G15+'QLD-2'!G15+'SA-1'!G15+'WA-1'!G15+'IDC-NSW'!G15+'IDC-VIC'!G15 | H15: ='NSW-1'!H15+'VIC-1'!H15+'QLD-1'!H15+'NSW-2'!H15+'VIC-2'!H15+'QLD-2'!H15+'SA-1'!H15+'WA-1'!H15+'IDC-NSW'!H15+'IDC-VIC'!H15 | I15: ='NSW-1'!I15+'VIC-1'!I15+'QLD-1'!I15+'NSW-2'!I15+'VIC-2'!I15+'QLD-2'!I15+'SA-1'!I15+'WA-1'!I15+'IDC-NSW'!I15+'IDC-VIC'!I15 | J15: ='NSW-1'!J15+'VIC-1'!J15+'QLD-1'!J15+'NSW-2'!J15+'VIC-2'!J15+'QLD-2'!J15+'SA-1'!J15+'WA-1'!J15+'IDC-NSW'!J15+'IDC-VIC'!J15 | K15: =IFERROR(F15/G15,0) | L15: =IFERROR(H15/G15,0) | M15: =IFERROR(J15/F15,0) | N15: =IFERROR(J15/E15,0) | O15: =IFERROR(I15/J15,0) | R15: =Inputs!$A$45 | S15: =SUMIFS('IDC-VIC'!$J$15:$J$62,'IDC-VIC'!$B$15:$B$62,2025) | T15: =SUMIFS('IDC-VIC'!$J$15:$J$62,'IDC-VIC'!$B$15:$B$62,2026) | U15: =SUMIFS('IDC-VIC'!$J$15:$J$62,'IDC-VIC'!$B$15:$B$62,2027) | V15: =SUMIFS('IDC-VIC'!$J$15:$J$62,'IDC-VIC'!$B$15:$B$62,2028)
A16: 45689 | B16: =YEAR(A16) | C16: =MONTH(A16) | D16: =IF(A16<=LastActual,"Actual","Forecast") | E16: ='NSW-1'!E16+'VIC-1'!E16+'QLD-1'!E16+'NSW-2'!E16+'VIC-2'!E16+'QLD-2'!E16+'SA-1'!E16+'WA-1'!E16 | F16: ='NSW-1'!F16+'VIC-1'!F16+'QLD-1'!F16+'NSW-2'!F16+'VIC-2'!F16+'QLD-2'!F16+'SA-1'!F16+'WA-1'!F16+'IDC-NSW'!F16+'IDC-VIC'!F16 | G16: ='NSW-1'!G16+'VIC-1'!G16+'QLD-1'!G16+'NSW-2'!G16+'VIC-2'!G16+'QLD-2'!G16+'SA-1'!G16+'WA-1'!G16+'IDC-NSW'!G16+'IDC-VIC'!G16 | H16: ='NSW-1'!H16+'VIC-1'!H16+'QLD-1'!H16+'NSW-2'!H16+'VIC-2'!H16+'QLD-2'!H16+'SA-1'!H16+'WA-1'!H16+'IDC-NSW'!H16+'IDC-VIC'!H16 | I16: ='NSW-1'!I16+'VIC-1'!I16+'QLD-1'!I16+'NSW-2'!I16+'VIC-2'!I16+'QLD-2'!I16+'SA-1'!I16+'WA-1'!I16+'IDC-NSW'!I16+'IDC-VIC'!I16 | J16: ='NSW-1'!J16+'VIC-1'!J16+'QLD-1'!J16+'NSW-2'!J16+'VIC-2'!J16+'QLD-2'!J16+'SA-1'!J16+'WA-1'!J16+'IDC-NSW'!J16+'IDC-VIC'!J16 | K16: =IFERROR(F16/G16,0) | L16: =IFERROR(H16/G16,0) | M16: =IFERROR(J16/F16,0) | N16: =IFERROR(J16/E16,0) | O16: =IFERROR(I16/J16,0)
A17: 45717 | B17: =YEAR(A17) | C17: =MONTH(A17) | D17: =IF(A17<=LastActual,"Actual","Forecast") | E17: ='NSW-1'!E17+'VIC-1'!E17+'QLD-1'!E17+'NSW-2'!E17+'VIC-2'!E17+'QLD-2'!E17+'SA-1'!E17+'WA-1'!E17 | F17: ='NSW-1'!F17+'VIC-1'!F17+'QLD-1'!F17+'NSW-2'!F17+'VIC-2'!F17+'QLD-2'!F17+'SA-1'!F17+'WA-1'!F17+'IDC-NSW'!F17+'IDC-VIC'!F17 | G17: ='NSW-1'!G17+'VIC-1'!G17+'QLD-1'!G17+'NSW-2'!G17+'VIC-2'!G17+'QLD-2'!G17+'SA-1'!G17+'WA-1'!G17+'IDC-NSW'!G17+'IDC-VIC'!G17 | H17: ='NSW-1'!H17+'VIC-1'!H17+'QLD-1'!H17+'NSW-2'!H17+'VIC-2'!H17+'QLD-2'!H17+'SA-1'!H17+'WA-1'!H17+'IDC-NSW'!H17+'IDC-VIC'!H17 | I17: ='NSW-1'!I17+'VIC-1'!I17+'QLD-1'!I17+'NSW-2'!I17+'VIC-2'!I17+'QLD-2'!I17+'SA-1'!I17+'WA-1'!I17+'IDC-NSW'!I17+'IDC-VIC'!I17 | J17: ='NSW-1'!J17+'VIC-1'!J17+'QLD-1'!J17+'NSW-2'!J17+'VIC-2'!J17+'QLD-2'!J17+'SA-1'!J17+'WA-1'!J17+'IDC-NSW'!J17+'IDC-VIC'!J17 | K17: =IFERROR(F17/G17,0) | L17: =IFERROR(H17/G17,0) | M17: =IFERROR(J17/F17,0) | N17: =IFERROR(J17/E17,0) | O17: =IFERROR(I17/J17,0)
A18: 45748 | B18: =YEAR(A18) | C18: =MONTH(A18) | D18: =IF(A18<=LastActual,"Actual","Forecast") | E18: ='NSW-1'!E18+'VIC-1'!E18+'QLD-1'!E18+'NSW-2'!E18+'VIC-2'!E18+'QLD-2'!E18+'SA-1'!E18+'WA-1'!E18 | F18: ='NSW-1'!F18+'VIC-1'!F18+'QLD-1'!F18+'NSW-2'!F18+'VIC-2'!F18+'QLD-2'!F18+'SA-1'!F18+'WA-1'!F18+'IDC-NSW'!F18+'IDC-VIC'!F18 | G18: ='NSW-1'!G18+'VIC-1'!G18+'QLD-1'!G18+'NSW-2'!G18+'VIC-2'!G18+'QLD-2'!G18+'SA-1'!G18+'WA-1'!G18+'IDC-NSW'!G18+'IDC-VIC'!G18 | H18: ='NSW-1'!H18+'VIC-1'!H18+'QLD-1'!H18+'NSW-2'!H18+'VIC-2'!H18+'QLD-2'!H18+'SA-1'!H18+'WA-1'!H18+'IDC-NSW'!H18+'IDC-VIC'!H18 | I18: ='NSW-1'!I18+'VIC-1'!I18+'QLD-1'!I18+'NSW-2'!I18+'VIC-2'!I18+'QLD-2'!I18+'SA-1'!I18+'WA-1'!I18+'IDC-NSW'!I18+'IDC-VIC'!I18 | J18: ='NSW-1'!J18+'VIC-1'!J18+'QLD-1'!J18+'NSW-2'!J18+'VIC-2'!J18+'QLD-2'!J18+'SA-1'!J18+'WA-1'!J18+'IDC-NSW'!J18+'IDC-VIC'!J18 | K18: =IFERROR(F18/G18,0) | L18: =IFERROR(H18/G18,0) | M18: =IFERROR(J18/F18,0) | N18: =IFERROR(J18/E18,0) | O18: =IFERROR(I18/J18,0) | R18: Cases picked (m)
A19: 45778 | B19: =YEAR(A19) | C19: =MONTH(A19) | D19: =IF(A19<=LastActual,"Actual","Forecast") | E19: ='NSW-1'!E19+'VIC-1'!E19+'QLD-1'!E19+'NSW-2'!E19+'VIC-2'!E19+'QLD-2'!E19+'SA-1'!E19+'WA-1'!E19 | F19: ='NSW-1'!F19+'VIC-1'!F19+'QLD-1'!F19+'NSW-2'!F19+'VIC-2'!F19+'QLD-2'!F19+'SA-1'!F19+'WA-1'!F19+'IDC-NSW'!F19+'IDC-VIC'!F19 | G19: ='NSW-1'!G19+'VIC-1'!G19+'QLD-1'!G19+'NSW-2'!G19+'VIC-2'!G19+'QLD-2'!G19+'SA-1'!G19+'WA-1'!G19+'IDC-NSW'!G19+'IDC-VIC'!G19 | H19: ='NSW-1'!H19+'VIC-1'!H19+'QLD-1'!H19+'NSW-2'!H19+'VIC-2'!H19+'QLD-2'!H19+'SA-1'!H19+'WA-1'!H19+'IDC-NSW'!H19+'IDC-VIC'!H19 | I19: ='NSW-1'!I19+'VIC-1'!I19+'QLD-1'!I19+'NSW-2'!I19+'VIC-2'!I19+'QLD-2'!I19+'SA-1'!I19+'WA-1'!I19+'IDC-NSW'!I19+'IDC-VIC'!I19 | J19: ='NSW-1'!J19+'VIC-1'!J19+'QLD-1'!J19+'NSW-2'!J19+'VIC-2'!J19+'QLD-2'!J19+'SA-1'!J19+'WA-1'!J19+'IDC-NSW'!J19+'IDC-VIC'!J19 | K19: =IFERROR(F19/G19,0) | L19: =IFERROR(H19/G19,0) | M19: =IFERROR(J19/F19,0) | N19: =IFERROR(J19/E19,0) | O19: =IFERROR(I19/J19,0) | R19: Site | S19: FY2025 | T19: FY2026 | U19: FY2027 | V19: FY2028
A20: 45809 | B20: =YEAR(A20) | C20: =MONTH(A20) | D20: =IF(A20<=LastActual,"Actual","Forecast") | E20: ='NSW-1'!E20+'VIC-1'!E20+'QLD-1'!E20+'NSW-2'!E20+'VIC-2'!E20+'QLD-2'!E20+'SA-1'!E20+'WA-1'!E20 | F20: ='NSW-1'!F20+'VIC-1'!F20+'QLD-1'!F20+'NSW-2'!F20+'VIC-2'!F20+'QLD-2'!F20+'SA-1'!F20+'WA-1'!F20+'IDC-NSW'!F20+'IDC-VIC'!F20 | G20: ='NSW-1'!G20+'VIC-1'!G20+'QLD-1'!G20+'NSW-2'!G20+'VIC-2'!G20+'QLD-2'!G20+'SA-1'!G20+'WA-1'!G20+'IDC-NSW'!G20+'IDC-VIC'!G20 | H20: ='NSW-1'!H20+'VIC-1'!H20+'QLD-1'!H20+'NSW-2'!H20+'VIC-2'!H20+'QLD-2'!H20+'SA-1'!H20+'WA-1'!H20+'IDC-NSW'!H20+'IDC-VIC'!H20 | I20: ='NSW-1'!I20+'VIC-1'!I20+'QLD-1'!I20+'NSW-2'!I20+'VIC-2'!I20+'QLD-2'!I20+'SA-1'!I20+'WA-1'!I20+'IDC-NSW'!I20+'IDC-VIC'!I20 | J20: ='NSW-1'!J20+'VIC-1'!J20+'QLD-1'!J20+'NSW-2'!J20+'VIC-2'!J20+'QLD-2'!J20+'SA-1'!J20+'WA-1'!J20+'IDC-NSW'!J20+'IDC-VIC'!J20 | K20: =IFERROR(F20/G20,0) | L20: =IFERROR(H20/G20,0) | M20: =IFERROR(J20/F20,0) | N20: =IFERROR(J20/E20,0) | O20: =IFERROR(I20/J20,0) | R20: =Inputs!$A$36 | S20: =SUMIFS('NSW-1'!$F$15:$F$62,'NSW-1'!$B$15:$B$62,2025) | T20: =SUMIFS('NSW-1'!$F$15:$F$62,'NSW-1'!$B$15:$B$62,2026) | U20: =SUMIFS('NSW-1'!$F$15:$F$62,'NSW-1'!$B$15:$B$62,2027) | V20: =SUMIFS('NSW-1'!$F$15:$F$62,'NSW-1'!$B$15:$B$62,2028)
A21: 45839 | B21: =YEAR(A21) | C21: =MONTH(A21) | D21: =IF(A21<=LastActual,"Actual","Forecast") | E21: ='NSW-1'!E21+'VIC-1'!E21+'QLD-1'!E21+'NSW-2'!E21+'VIC-2'!E21+'QLD-2'!E21+'SA-1'!E21+'WA-1'!E21 | F21: ='NSW-1'!F21+'VIC-1'!F21+'QLD-1'!F21+'NSW-2'!F21+'VIC-2'!F21+'QLD-2'!F21+'SA-1'!F21+'WA-1'!F21+'IDC-NSW'!F21+'IDC-VIC'!F21 | G21: ='NSW-1'!G21+'VIC-1'!G21+'QLD-1'!G21+'NSW-2'!G21+'VIC-2'!G21+'QLD-2'!G21+'SA-1'!G21+'WA-1'!G21+'IDC-NSW'!G21+'IDC-VIC'!G21 | H21: ='NSW-1'!H21+'VIC-1'!H21+'QLD-1'!H21+'NSW-2'!H21+'VIC-2'!H21+'QLD-2'!H21+'SA-1'!H21+'WA-1'!H21+'IDC-NSW'!H21+'IDC-VIC'!H21 | I21: ='NSW-1'!I21+'VIC-1'!I21+'QLD-1'!I21+'NSW-2'!I21+'VIC-2'!I21+'QLD-2'!I21+'SA-1'!I21+'WA-1'!I21+'IDC-NSW'!I21+'IDC-VIC'!I21 | J21: ='NSW-1'!J21+'VIC-1'!J21+'QLD-1'!J21+'NSW-2'!J21+'VIC-2'!J21+'QLD-2'!J21+'SA-1'!J21+'WA-1'!J21+'IDC-NSW'!J21+'IDC-VIC'!J21 | K21: =IFERROR(F21/G21,0) | L21: =IFERROR(H21/G21,0) | M21: =IFERROR(J21/F21,0) | N21: =IFERROR(J21/E21,0) | O21: =IFERROR(I21/J21,0) | R21: =Inputs!$A$37 | S21: =SUMIFS('VIC-1'!$F$15:$F$62,'VIC-1'!$B$15:$B$62,2025) | T21: =SUMIFS('VIC-1'!$F$15:$F$62,'VIC-1'!$B$15:$B$62,2026) | U21: =SUMIFS('VIC-1'!$F$15:$F$62,'VIC-1'!$B$15:$B$62,2027) | V21: =SUMIFS('VIC-1'!$F$15:$F$62,'VIC-1'!$B$15:$B$62,2028)
A22: 45870 | B22: =YEAR(A22) | C22: =MONTH(A22) | D22: =IF(A22<=LastActual,"Actual","Forecast") | E22: ='NSW-1'!E22+'VIC-1'!E22+'QLD-1'!E22+'NSW-2'!E22+'VIC-2'!E22+'QLD-2'!E22+'SA-1'!E22+'WA-1'!E22 | F22: ='NSW-1'!F22+'VIC-1'!F22+'QLD-1'!F22+'NSW-2'!F22+'VIC-2'!F22+'QLD-2'!F22+'SA-1'!F22+'WA-1'!F22+'IDC-NSW'!F22+'IDC-VIC'!F22 | G22: ='NSW-1'!G22+'VIC-1'!G22+'QLD-1'!G22+'NSW-2'!G22+'VIC-2'!G22+'QLD-2'!G22+'SA-1'!G22+'WA-1'!G22+'IDC-NSW'!G22+'IDC-VIC'!G22 | H22: ='NSW-1'!H22+'VIC-1'!H22+'QLD-1'!H22+'NSW-2'!H22+'VIC-2'!H22+'QLD-2'!H22+'SA-1'!H22+'WA-1'!H22+'IDC-NSW'!H22+'IDC-VIC'!H22 | I22: ='NSW-1'!I22+'VIC-1'!I22+'QLD-1'!I22+'NSW-2'!I22+'VIC-2'!I22+'QLD-2'!I22+'SA-1'!I22+'WA-1'!I22+'IDC-NSW'!I22+'IDC-VIC'!I22 | J22: ='NSW-1'!J22+'VIC-1'!J22+'QLD-1'!J22+'NSW-2'!J22+'VIC-2'!J22+'QLD-2'!J22+'SA-1'!J22+'WA-1'!J22+'IDC-NSW'!J22+'IDC-VIC'!J22 | K22: =IFERROR(F22/G22,0) | L22: =IFERROR(H22/G22,0) | M22: =IFERROR(J22/F22,0) | N22: =IFERROR(J22/E22,0) | O22: =IFERROR(I22/J22,0) | R22: =Inputs!$A$38 | S22: =SUMIFS('QLD-1'!$F$15:$F$62,'QLD-1'!$B$15:$B$62,2025) | T22: =SUMIFS('QLD-1'!$F$15:$F$62,'QLD-1'!$B$15:$B$62,2026) | U22: =SUMIFS('QLD-1'!$F$15:$F$62,'QLD-1'!$B$15:$B$62,2027) | V22: =SUMIFS('QLD-1'!$F$15:$F$62,'QLD-1'!$B$15:$B$62,2028)
A23: 45901 | B23: =YEAR(A23) | C23: =MONTH(A23) | D23: =IF(A23<=LastActual,"Actual","Forecast") | E23: ='NSW-1'!E23+'VIC-1'!E23+'QLD-1'!E23+'NSW-2'!E23+'VIC-2'!E23+'QLD-2'!E23+'SA-1'!E23+'WA-1'!E23 | F23: ='NSW-1'!F23+'VIC-1'!F23+'QLD-1'!F23+'NSW-2'!F23+'VIC-2'!F23+'QLD-2'!F23+'SA-1'!F23+'WA-1'!F23+'IDC-NSW'!F23+'IDC-VIC'!F23 | G23: ='NSW-1'!G23+'VIC-1'!G23+'QLD-1'!G23+'NSW-2'!G23+'VIC-2'!G23+'QLD-2'!G23+'SA-1'!G23+'WA-1'!G23+'IDC-NSW'!G23+'IDC-VIC'!G23 | H23: ='NSW-1'!H23+'VIC-1'!H23+'QLD-1'!H23+'NSW-2'!H23+'VIC-2'!H23+'QLD-2'!H23+'SA-1'!H23+'WA-1'!H23+'IDC-NSW'!H23+'IDC-VIC'!H23 | I23: ='NSW-1'!I23+'VIC-1'!I23+'QLD-1'!I23+'NSW-2'!I23+'VIC-2'!I23+'QLD-2'!I23+'SA-1'!I23+'WA-1'!I23+'IDC-NSW'!I23+'IDC-VIC'!I23 | J23: ='NSW-1'!J23+'VIC-1'!J23+'QLD-1'!J23+'NSW-2'!J23+'VIC-2'!J23+'QLD-2'!J23+'SA-1'!J23+'WA-1'!J23+'IDC-NSW'!J23+'IDC-VIC'!J23 | K23: =IFERROR(F23/G23,0) | L23: =IFERROR(H23/G23,0) | M23: =IFERROR(J23/F23,0) | N23: =IFERROR(J23/E23,0) | O23: =IFERROR(I23/J23,0) | R23: =Inputs!$A$39 | S23: =SUMIFS('NSW-2'!$F$15:$F$62,'NSW-2'!$B$15:$B$62,2025) | T23: =SUMIFS('NSW-2'!$F$15:$F$62,'NSW-2'!$B$15:$B$62,2026) | U23: =SUMIFS('NSW-2'!$F$15:$F$62,'NSW-2'!$B$15:$B$62,2027) | V23: =SUMIFS('NSW-2'!$F$15:$F$62,'NSW-2'!$B$15:$B$62,2028)
A24: 45931 | B24: =YEAR(A24) | C24: =MONTH(A24) | D24: =IF(A24<=LastActual,"Actual","Forecast") | E24: ='NSW-1'!E24+'VIC-1'!E24+'QLD-1'!E24+'NSW-2'!E24+'VIC-2'!E24+'QLD-2'!E24+'SA-1'!E24+'WA-1'!E24 | F24: ='NSW-1'!F24+'VIC-1'!F24+'QLD-1'!F24+'NSW-2'!F24+'VIC-2'!F24+'QLD-2'!F24+'SA-1'!F24+'WA-1'!F24+'IDC-NSW'!F24+'IDC-VIC'!F24 | G24: ='NSW-1'!G24+'VIC-1'!G24+'QLD-1'!G24+'NSW-2'!G24+'VIC-2'!G24+'QLD-2'!G24+'SA-1'!G24+'WA-1'!G24+'IDC-NSW'!G24+'IDC-VIC'!G24 | H24: ='NSW-1'!H24+'VIC-1'!H24+'QLD-1'!H24+'NSW-2'!H24+'VIC-2'!H24+'QLD-2'!H24+'SA-1'!H24+'WA-1'!H24+'IDC-NSW'!H24+'IDC-VIC'!H24 | I24: ='NSW-1'!I24+'VIC-1'!I24+'QLD-1'!I24+'NSW-2'!I24+'VIC-2'!I24+'QLD-2'!I24+'SA-1'!I24+'WA-1'!I24+'IDC-NSW'!I24+'IDC-VIC'!I24 | J24: ='NSW-1'!J24+'VIC-1'!J24+'QLD-1'!J24+'NSW-2'!J24+'VIC-2'!J24+'QLD-2'!J24+'SA-1'!J24+'WA-1'!J24+'IDC-NSW'!J24+'IDC-VIC'!J24 | K24: =IFERROR(F24/G24,0) | L24: =IFERROR(H24/G24,0) | M24: =IFERROR(J24/F24,0) | N24: =IFERROR(J24/E24,0) | O24: =IFERROR(I24/J24,0) | R24: =Inputs!$A$40 | S24: =SUMIFS('VIC-2'!$F$15:$F$62,'VIC-2'!$B$15:$B$62,2025) | T24: =SUMIFS('VIC-2'!$F$15:$F$62,'VIC-2'!$B$15:$B$62,2026) | U24: =SUMIFS('VIC-2'!$F$15:$F$62,'VIC-2'!$B$15:$B$62,2027) | V24: =SUMIFS('VIC-2'!$F$15:$F$62,'VIC-2'!$B$15:$B$62,2028)
A25: 45962 | B25: =YEAR(A25) | C25: =MONTH(A25) | D25: =IF(A25<=LastActual,"Actual","Forecast") | E25: ='NSW-1'!E25+'VIC-1'!E25+'QLD-1'!E25+'NSW-2'!E25+'VIC-2'!E25+'QLD-2'!E25+'SA-1'!E25+'WA-1'!E25 | F25: ='NSW-1'!F25+'VIC-1'!F25+'QLD-1'!F25+'NSW-2'!F25+'VIC-2'!F25+'QLD-2'!F25+'SA-1'!F25+'WA-1'!F25+'IDC-NSW'!F25+'IDC-VIC'!F25 | G25: ='NSW-1'!G25+'VIC-1'!G25+'QLD-1'!G25+'NSW-2'!G25+'VIC-2'!G25+'QLD-2'!G25+'SA-1'!G25+'WA-1'!G25+'IDC-NSW'!G25+'IDC-VIC'!G25 | H25: ='NSW-1'!H25+'VIC-1'!H25+'QLD-1'!H25+'NSW-2'!H25+'VIC-2'!H25+'QLD-2'!H25+'SA-1'!H25+'WA-1'!H25+'IDC-NSW'!H25+'IDC-VIC'!H25 | I25: ='NSW-1'!I25+'VIC-1'!I25+'QLD-1'!I25+'NSW-2'!I25+'VIC-2'!I25+'QLD-2'!I25+'SA-1'!I25+'WA-1'!I25+'IDC-NSW'!I25+'IDC-VIC'!I25 | J25: ='NSW-1'!J25+'VIC-1'!J25+'QLD-1'!J25+'NSW-2'!J25+'VIC-2'!J25+'QLD-2'!J25+'SA-1'!J25+'WA-1'!J25+'IDC-NSW'!J25+'IDC-VIC'!J25 | K25: =IFERROR(F25/G25,0) | L25: =IFERROR(H25/G25,0) | M25: =IFERROR(J25/F25,0) | N25: =IFERROR(J25/E25,0) | O25: =IFERROR(I25/J25,0) | R25: =Inputs!$A$41 | S25: =SUMIFS('QLD-2'!$F$15:$F$62,'QLD-2'!$B$15:$B$62,2025) | T25: =SUMIFS('QLD-2'!$F$15:$F$62,'QLD-2'!$B$15:$B$62,2026) | U25: =SUMIFS('QLD-2'!$F$15:$F$62,'QLD-2'!$B$15:$B$62,2027) | V25: =SUMIFS('QLD-2'!$F$15:$F$62,'QLD-2'!$B$15:$B$62,2028)
A26: 45992 | B26: =YEAR(A26) | C26: =MONTH(A26) | D26: =IF(A26<=LastActual,"Actual","Forecast") | E26: ='NSW-1'!E26+'VIC-1'!E26+'QLD-1'!E26+'NSW-2'!E26+'VIC-2'!E26+'QLD-2'!E26+'SA-1'!E26+'WA-1'!E26 | F26: ='NSW-1'!F26+'VIC-1'!F26+'QLD-1'!F26+'NSW-2'!F26+'VIC-2'!F26+'QLD-2'!F26+'SA-1'!F26+'WA-1'!F26+'IDC-NSW'!F26+'IDC-VIC'!F26 | G26: ='NSW-1'!G26+'VIC-1'!G26+'QLD-1'!G26+'NSW-2'!G26+'VIC-2'!G26+'QLD-2'!G26+'SA-1'!G26+'WA-1'!G26+'IDC-NSW'!G26+'IDC-VIC'!G26 | H26: ='NSW-1'!H26+'VIC-1'!H26+'QLD-1'!H26+'NSW-2'!H26+'VIC-2'!H26+'QLD-2'!H26+'SA-1'!H26+'WA-1'!H26+'IDC-NSW'!H26+'IDC-VIC'!H26 | I26: ='NSW-1'!I26+'VIC-1'!I26+'QLD-1'!I26+'NSW-2'!I26+'VIC-2'!I26+'QLD-2'!I26+'SA-1'!I26+'WA-1'!I26+'IDC-NSW'!I26+'IDC-VIC'!I26 | J26: ='NSW-1'!J26+'VIC-1'!J26+'QLD-1'!J26+'NSW-2'!J26+'VIC-2'!J26+'QLD-2'!J26+'SA-1'!J26+'WA-1'!J26+'IDC-NSW'!J26+'IDC-VIC'!J26 | K26: =IFERROR(F26/G26,0) | L26: =IFERROR(H26/G26,0) | M26: =IFERROR(J26/F26,0) | N26: =IFERROR(J26/E26,0) | O26: =IFERROR(I26/J26,0) | R26: =Inputs!$A$42 | S26: =SUMIFS('SA-1'!$F$15:$F$62,'SA-1'!$B$15:$B$62,2025) | T26: =SUMIFS('SA-1'!$F$15:$F$62,'SA-1'!$B$15:$B$62,2026) | U26: =SUMIFS('SA-1'!$F$15:$F$62,'SA-1'!$B$15:$B$62,2027) | V26: =SUMIFS('SA-1'!$F$15:$F$62,'SA-1'!$B$15:$B$62,2028)
A27: 46023 | B27: =YEAR(A27) | C27: =MONTH(A27) | D27: =IF(A27<=LastActual,"Actual","Forecast") | E27: ='NSW-1'!E27+'VIC-1'!E27+'QLD-1'!E27+'NSW-2'!E27+'VIC-2'!E27+'QLD-2'!E27+'SA-1'!E27+'WA-1'!E27 | F27: ='NSW-1'!F27+'VIC-1'!F27+'QLD-1'!F27+'NSW-2'!F27+'VIC-2'!F27+'QLD-2'!F27+'SA-1'!F27+'WA-1'!F27+'IDC-NSW'!F27+'IDC-VIC'!F27 | G27: ='NSW-1'!G27+'VIC-1'!G27+'QLD-1'!G27+'NSW-2'!G27+'VIC-2'!G27+'QLD-2'!G27+'SA-1'!G27+'WA-1'!G27+'IDC-NSW'!G27+'IDC-VIC'!G27 | H27: ='NSW-1'!H27+'VIC-1'!H27+'QLD-1'!H27+'NSW-2'!H27+'VIC-2'!H27+'QLD-2'!H27+'SA-1'!H27+'WA-1'!H27+'IDC-NSW'!H27+'IDC-VIC'!H27 | I27: ='NSW-1'!I27+'VIC-1'!I27+'QLD-1'!I27+'NSW-2'!I27+'VIC-2'!I27+'QLD-2'!I27+'SA-1'!I27+'WA-1'!I27+'IDC-NSW'!I27+'IDC-VIC'!I27 | J27: ='NSW-1'!J27+'VIC-1'!J27+'QLD-1'!J27+'NSW-2'!J27+'VIC-2'!J27+'QLD-2'!J27+'SA-1'!J27+'WA-1'!J27+'IDC-NSW'!J27+'IDC-VIC'!J27 | K27: =IFERROR(F27/G27,0) | L27: =IFERROR(H27/G27,0) | M27: =IFERROR(J27/F27,0) | N27: =IFERROR(J27/E27,0) | O27: =IFERROR(I27/J27,0) | R27: =Inputs!$A$43 | S27: =SUMIFS('WA-1'!$F$15:$F$62,'WA-1'!$B$15:$B$62,2025) | T27: =SUMIFS('WA-1'!$F$15:$F$62,'WA-1'!$B$15:$B$62,2026) | U27: =SUMIFS('WA-1'!$F$15:$F$62,'WA-1'!$B$15:$B$62,2027) | V27: =SUMIFS('WA-1'!$F$15:$F$62,'WA-1'!$B$15:$B$62,2028)
A28: 46054 | B28: =YEAR(A28) | C28: =MONTH(A28) | D28: =IF(A28<=LastActual,"Actual","Forecast") | E28: ='NSW-1'!E28+'VIC-1'!E28+'QLD-1'!E28+'NSW-2'!E28+'VIC-2'!E28+'QLD-2'!E28+'SA-1'!E28+'WA-1'!E28 | F28: ='NSW-1'!F28+'VIC-1'!F28+'QLD-1'!F28+'NSW-2'!F28+'VIC-2'!F28+'QLD-2'!F28+'SA-1'!F28+'WA-1'!F28+'IDC-NSW'!F28+'IDC-VIC'!F28 | G28: ='NSW-1'!G28+'VIC-1'!G28+'QLD-1'!G28+'NSW-2'!G28+'VIC-2'!G28+'QLD-2'!G28+'SA-1'!G28+'WA-1'!G28+'IDC-NSW'!G28+'IDC-VIC'!G28 | H28: ='NSW-1'!H28+'VIC-1'!H28+'QLD-1'!H28+'NSW-2'!H28+'VIC-2'!H28+'QLD-2'!H28+'SA-1'!H28+'WA-1'!H28+'IDC-NSW'!H28+'IDC-VIC'!H28 | I28: ='NSW-1'!I28+'VIC-1'!I28+'QLD-1'!I28+'NSW-2'!I28+'VIC-2'!I28+'QLD-2'!I28+'SA-1'!I28+'WA-1'!I28+'IDC-NSW'!I28+'IDC-VIC'!I28 | J28: ='NSW-1'!J28+'VIC-1'!J28+'QLD-1'!J28+'NSW-2'!J28+'VIC-2'!J28+'QLD-2'!J28+'SA-1'!J28+'WA-1'!J28+'IDC-NSW'!J28+'IDC-VIC'!J28 | K28: =IFERROR(F28/G28,0) | L28: =IFERROR(H28/G28,0) | M28: =IFERROR(J28/F28,0) | N28: =IFERROR(J28/E28,0) | O28: =IFERROR(I28/J28,0) | R28: =Inputs!$A$44 | S28: =SUMIFS('IDC-NSW'!$F$15:$F$62,'IDC-NSW'!$B$15:$B$62,2025) | T28: =SUMIFS('IDC-NSW'!$F$15:$F$62,'IDC-NSW'!$B$15:$B$62,2026) | U28: =SUMIFS('IDC-NSW'!$F$15:$F$62,'IDC-NSW'!$B$15:$B$62,2027) | V28: =SUMIFS('IDC-NSW'!$F$15:$F$62,'IDC-NSW'!$B$15:$B$62,2028)
A29: 46082 | B29: =YEAR(A29) | C29: =MONTH(A29) | D29: =IF(A29<=LastActual,"Actual","Forecast") | E29: ='NSW-1'!E29+'VIC-1'!E29+'QLD-1'!E29+'NSW-2'!E29+'VIC-2'!E29+'QLD-2'!E29+'SA-1'!E29+'WA-1'!E29 | F29: ='NSW-1'!F29+'VIC-1'!F29+'QLD-1'!F29+'NSW-2'!F29+'VIC-2'!F29+'QLD-2'!F29+'SA-1'!F29+'WA-1'!F29+'IDC-NSW'!F29+'IDC-VIC'!F29 | G29: ='NSW-1'!G29+'VIC-1'!G29+'QLD-1'!G29+'NSW-2'!G29+'VIC-2'!G29+'QLD-2'!G29+'SA-1'!G29+'WA-1'!G29+'IDC-NSW'!G29+'IDC-VIC'!G29 | H29: ='NSW-1'!H29+'VIC-1'!H29+'QLD-1'!H29+'NSW-2'!H29+'VIC-2'!H29+'QLD-2'!H29+'SA-1'!H29+'WA-1'!H29+'IDC-NSW'!H29+'IDC-VIC'!H29 | I29: ='NSW-1'!I29+'VIC-1'!I29+'QLD-1'!I29+'NSW-2'!I29+'VIC-2'!I29+'QLD-2'!I29+'SA-1'!I29+'WA-1'!I29+'IDC-NSW'!I29+'IDC-VIC'!I29 | J29: ='NSW-1'!J29+'VIC-1'!J29+'QLD-1'!J29+'NSW-2'!J29+'VIC-2'!J29+'QLD-2'!J29+'SA-1'!J29+'WA-1'!J29+'IDC-NSW'!J29+'IDC-VIC'!J29 | K29: =IFERROR(F29/G29,0) | L29: =IFERROR(H29/G29,0) | M29: =IFERROR(J29/F29,0) | N29: =IFERROR(J29/E29,0) | O29: =IFERROR(I29/J29,0) | R29: =Inputs!$A$45 | S29: =SUMIFS('IDC-VIC'!$F$15:$F$62,'IDC-VIC'!$B$15:$B$62,2025) | T29: =SUMIFS('IDC-VIC'!$F$15:$F$62,'IDC-VIC'!$B$15:$B$62,2026) | U29: =SUMIFS('IDC-VIC'!$F$15:$F$62,'IDC-VIC'!$B$15:$B$62,2027) | V29: =SUMIFS('IDC-VIC'!$F$15:$F$62,'IDC-VIC'!$B$15:$B$62,2028)
A30: 46113 | B30: =YEAR(A30) | C30: =MONTH(A30) | D30: =IF(A30<=LastActual,"Actual","Forecast") | E30: ='NSW-1'!E30+'VIC-1'!E30+'QLD-1'!E30+'NSW-2'!E30+'VIC-2'!E30+'QLD-2'!E30+'SA-1'!E30+'WA-1'!E30 | F30: ='NSW-1'!F30+'VIC-1'!F30+'QLD-1'!F30+'NSW-2'!F30+'VIC-2'!F30+'QLD-2'!F30+'SA-1'!F30+'WA-1'!F30+'IDC-NSW'!F30+'IDC-VIC'!F30 | G30: ='NSW-1'!G30+'VIC-1'!G30+'QLD-1'!G30+'NSW-2'!G30+'VIC-2'!G30+'QLD-2'!G30+'SA-1'!G30+'WA-1'!G30+'IDC-NSW'!G30+'IDC-VIC'!G30 | H30: ='NSW-1'!H30+'VIC-1'!H30+'QLD-1'!H30+'NSW-2'!H30+'VIC-2'!H30+'QLD-2'!H30+'SA-1'!H30+'WA-1'!H30+'IDC-NSW'!H30+'IDC-VIC'!H30 | I30: ='NSW-1'!I30+'VIC-1'!I30+'QLD-1'!I30+'NSW-2'!I30+'VIC-2'!I30+'QLD-2'!I30+'SA-1'!I30+'WA-1'!I30+'IDC-NSW'!I30+'IDC-VIC'!I30 | J30: ='NSW-1'!J30+'VIC-1'!J30+'QLD-1'!J30+'NSW-2'!J30+'VIC-2'!J30+'QLD-2'!J30+'SA-1'!J30+'WA-1'!J30+'IDC-NSW'!J30+'IDC-VIC'!J30 | K30: =IFERROR(F30/G30,0) | L30: =IFERROR(H30/G30,0) | M30: =IFERROR(J30/F30,0) | N30: =IFERROR(J30/E30,0) | O30: =IFERROR(I30/J30,0)
A31: 46143 | B31: =YEAR(A31) | C31: =MONTH(A31) | D31: =IF(A31<=LastActual,"Actual","Forecast") | E31: ='NSW-1'!E31+'VIC-1'!E31+'QLD-1'!E31+'NSW-2'!E31+'VIC-2'!E31+'QLD-2'!E31+'SA-1'!E31+'WA-1'!E31 | F31: ='NSW-1'!F31+'VIC-1'!F31+'QLD-1'!F31+'NSW-2'!F31+'VIC-2'!F31+'QLD-2'!F31+'SA-1'!F31+'WA-1'!F31+'IDC-NSW'!F31+'IDC-VIC'!F31 | G31: ='NSW-1'!G31+'VIC-1'!G31+'QLD-1'!G31+'NSW-2'!G31+'VIC-2'!G31+'QLD-2'!G31+'SA-1'!G31+'WA-1'!G31+'IDC-NSW'!G31+'IDC-VIC'!G31 | H31: ='NSW-1'!H31+'VIC-1'!H31+'QLD-1'!H31+'NSW-2'!H31+'VIC-2'!H31+'QLD-2'!H31+'SA-1'!H31+'WA-1'!H31+'IDC-NSW'!H31+'IDC-VIC'!H31 | I31: ='NSW-1'!I31+'VIC-1'!I31+'QLD-1'!I31+'NSW-2'!I31+'VIC-2'!I31+'QLD-2'!I31+'SA-1'!I31+'WA-1'!I31+'IDC-NSW'!I31+'IDC-VIC'!I31 | J31: ='NSW-1'!J31+'VIC-1'!J31+'QLD-1'!J31+'NSW-2'!J31+'VIC-2'!J31+'QLD-2'!J31+'SA-1'!J31+'WA-1'!J31+'IDC-NSW'!J31+'IDC-VIC'!J31 | K31: =IFERROR(F31/G31,0) | L31: =IFERROR(H31/G31,0) | M31: =IFERROR(J31/F31,0) | N31: =IFERROR(J31/E31,0) | O31: =IFERROR(I31/J31,0)
A32: 46174 | B32: =YEAR(A32) | C32: =MONTH(A32) | D32: =IF(A32<=LastActual,"Actual","Forecast") | E32: ='NSW-1'!E32+'VIC-1'!E32+'QLD-1'!E32+'NSW-2'!E32+'VIC-2'!E32+'QLD-2'!E32+'SA-1'!E32+'WA-1'!E32 | F32: ='NSW-1'!F32+'VIC-1'!F32+'QLD-1'!F32+'NSW-2'!F32+'VIC-2'!F32+'QLD-2'!F32+'SA-1'!F32+'WA-1'!F32+'IDC-NSW'!F32+'IDC-VIC'!F32 | G32: ='NSW-1'!G32+'VIC-1'!G32+'QLD-1'!G32+'NSW-2'!G32+'VIC-2'!G32+'QLD-2'!G32+'SA-1'!G32+'WA-1'!G32+'IDC-NSW'!G32+'IDC-VIC'!G32 | H32: ='NSW-1'!H32+'VIC-1'!H32+'QLD-1'!H32+'NSW-2'!H32+'VIC-2'!H32+'QLD-2'!H32+'SA-1'!H32+'WA-1'!H32+'IDC-NSW'!H32+'IDC-VIC'!H32 | I32: ='NSW-1'!I32+'VIC-1'!I32+'QLD-1'!I32+'NSW-2'!I32+'VIC-2'!I32+'QLD-2'!I32+'SA-1'!I32+'WA-1'!I32+'IDC-NSW'!I32+'IDC-VIC'!I32 | J32: ='NSW-1'!J32+'VIC-1'!J32+'QLD-1'!J32+'NSW-2'!J32+'VIC-2'!J32+'QLD-2'!J32+'SA-1'!J32+'WA-1'!J32+'IDC-NSW'!J32+'IDC-VIC'!J32 | K32: =IFERROR(F32/G32,0) | L32: =IFERROR(H32/G32,0) | M32: =IFERROR(J32/F32,0) | N32: =IFERROR(J32/E32,0) | O32: =IFERROR(I32/J32,0) | R32: Payroll % of sales (IDC: % of host sales)
A33: 46204 | B33: =YEAR(A33) | C33: =MONTH(A33) | D33: =IF(A33<=LastActual,"Actual","Forecast") | E33: ='NSW-1'!E33+'VIC-1'!E33+'QLD-1'!E33+'NSW-2'!E33+'VIC-2'!E33+'QLD-2'!E33+'SA-1'!E33+'WA-1'!E33 | F33: ='NSW-1'!F33+'VIC-1'!F33+'QLD-1'!F33+'NSW-2'!F33+'VIC-2'!F33+'QLD-2'!F33+'SA-1'!F33+'WA-1'!F33+'IDC-NSW'!F33+'IDC-VIC'!F33 | G33: ='NSW-1'!G33+'VIC-1'!G33+'QLD-1'!G33+'NSW-2'!G33+'VIC-2'!G33+'QLD-2'!G33+'SA-1'!G33+'WA-1'!G33+'IDC-NSW'!G33+'IDC-VIC'!G33 | H33: ='NSW-1'!H33+'VIC-1'!H33+'QLD-1'!H33+'NSW-2'!H33+'VIC-2'!H33+'QLD-2'!H33+'SA-1'!H33+'WA-1'!H33+'IDC-NSW'!H33+'IDC-VIC'!H33 | I33: ='NSW-1'!I33+'VIC-1'!I33+'QLD-1'!I33+'NSW-2'!I33+'VIC-2'!I33+'QLD-2'!I33+'SA-1'!I33+'WA-1'!I33+'IDC-NSW'!I33+'IDC-VIC'!I33 | J33: ='NSW-1'!J33+'VIC-1'!J33+'QLD-1'!J33+'NSW-2'!J33+'VIC-2'!J33+'QLD-2'!J33+'SA-1'!J33+'WA-1'!J33+'IDC-NSW'!J33+'IDC-VIC'!J33 | K33: =IFERROR(F33/G33,0) | L33: =IFERROR(H33/G33,0) | M33: =IFERROR(J33/F33,0) | N33: =IFERROR(J33/E33,0) | O33: =IFERROR(I33/J33,0) | R33: Site | S33: FY2025 | T33: FY2026 | U33: FY2027 | V33: FY2028
A34: 46235 | B34: =YEAR(A34) | C34: =MONTH(A34) | D34: =IF(A34<=LastActual,"Actual","Forecast") | E34: ='NSW-1'!E34+'VIC-1'!E34+'QLD-1'!E34+'NSW-2'!E34+'VIC-2'!E34+'QLD-2'!E34+'SA-1'!E34+'WA-1'!E34 | F34: ='NSW-1'!F34+'VIC-1'!F34+'QLD-1'!F34+'NSW-2'!F34+'VIC-2'!F34+'QLD-2'!F34+'SA-1'!F34+'WA-1'!F34+'IDC-NSW'!F34+'IDC-VIC'!F34 | G34: ='NSW-1'!G34+'VIC-1'!G34+'QLD-1'!G34+'NSW-2'!G34+'VIC-2'!G34+'QLD-2'!G34+'SA-1'!G34+'WA-1'!G34+'IDC-NSW'!G34+'IDC-VIC'!G34 | H34: ='NSW-1'!H34+'VIC-1'!H34+'QLD-1'!H34+'NSW-2'!H34+'VIC-2'!H34+'QLD-2'!H34+'SA-1'!H34+'WA-1'!H34+'IDC-NSW'!H34+'IDC-VIC'!H34 | I34: ='NSW-1'!I34+'VIC-1'!I34+'QLD-1'!I34+'NSW-2'!I34+'VIC-2'!I34+'QLD-2'!I34+'SA-1'!I34+'WA-1'!I34+'IDC-NSW'!I34+'IDC-VIC'!I34 | J34: ='NSW-1'!J34+'VIC-1'!J34+'QLD-1'!J34+'NSW-2'!J34+'VIC-2'!J34+'QLD-2'!J34+'SA-1'!J34+'WA-1'!J34+'IDC-NSW'!J34+'IDC-VIC'!J34 | K34: =IFERROR(F34/G34,0) | L34: =IFERROR(H34/G34,0) | M34: =IFERROR(J34/F34,0) | N34: =IFERROR(J34/E34,0) | O34: =IFERROR(I34/J34,0) | R34: =Inputs!$A$36 | S34: =IFERROR(SUMIFS('NSW-1'!$J$15:$J$62,'NSW-1'!$B$15:$B$62,2025)/SUMIFS('NSW-1'!$E$15:$E$62,'NSW-1'!$B$15:$B$62,2025),0) | T34: =IFERROR(SUMIFS('NSW-1'!$J$15:$J$62,'NSW-1'!$B$15:$B$62,2026)/SUMIFS('NSW-1'!$E$15:$E$62,'NSW-1'!$B$15:$B$62,2026),0) | U34: =IFERROR(SUMIFS('NSW-1'!$J$15:$J$62,'NSW-1'!$B$15:$B$62,2027)/SUMIFS('NSW-1'!$E$15:$E$62,'NSW-1'!$B$15:$B$62,2027),0) | V34: =IFERROR(SUMIFS('NSW-1'!$J$15:$J$62,'NSW-1'!$B$15:$B$62,2028)/SUMIFS('NSW-1'!$E$15:$E$62,'NSW-1'!$B$15:$B$62,2028),0)
A35: 46266 | B35: =YEAR(A35) | C35: =MONTH(A35) | D35: =IF(A35<=LastActual,"Actual","Forecast") | E35: ='NSW-1'!E35+'VIC-1'!E35+'QLD-1'!E35+'NSW-2'!E35+'VIC-2'!E35+'QLD-2'!E35+'SA-1'!E35+'WA-1'!E35 | F35: ='NSW-1'!F35+'VIC-1'!F35+'QLD-1'!F35+'NSW-2'!F35+'VIC-2'!F35+'QLD-2'!F35+'SA-1'!F35+'WA-1'!F35+'IDC-NSW'!F35+'IDC-VIC'!F35 | G35: ='NSW-1'!G35+'VIC-1'!G35+'QLD-1'!G35+'NSW-2'!G35+'VIC-2'!G35+'QLD-2'!G35+'SA-1'!G35+'WA-1'!G35+'IDC-NSW'!G35+'IDC-VIC'!G35 | H35: ='NSW-1'!H35+'VIC-1'!H35+'QLD-1'!H35+'NSW-2'!H35+'VIC-2'!H35+'QLD-2'!H35+'SA-1'!H35+'WA-1'!H35+'IDC-NSW'!H35+'IDC-VIC'!H35 | I35: ='NSW-1'!I35+'VIC-1'!I35+'QLD-1'!I35+'NSW-2'!I35+'VIC-2'!I35+'QLD-2'!I35+'SA-1'!I35+'WA-1'!I35+'IDC-NSW'!I35+'IDC-VIC'!I35 | J35: ='NSW-1'!J35+'VIC-1'!J35+'QLD-1'!J35+'NSW-2'!J35+'VIC-2'!J35+'QLD-2'!J35+'SA-1'!J35+'WA-1'!J35+'IDC-NSW'!J35+'IDC-VIC'!J35 | K35: =IFERROR(F35/G35,0) | L35: =IFERROR(H35/G35,0) | M35: =IFERROR(J35/F35,0) | N35: =IFERROR(J35/E35,0) | O35: =IFERROR(I35/J35,0) | R35: =Inputs!$A$37 | S35: =IFERROR(SUMIFS('VIC-1'!$J$15:$J$62,'VIC-1'!$B$15:$B$62,2025)/SUMIFS('VIC-1'!$E$15:$E$62,'VIC-1'!$B$15:$B$62,2025),0) | T35: =IFERROR(SUMIFS('VIC-1'!$J$15:$J$62,'VIC-1'!$B$15:$B$62,2026)/SUMIFS('VIC-1'!$E$15:$E$62,'VIC-1'!$B$15:$B$62,2026),0) | U35: =IFERROR(SUMIFS('VIC-1'!$J$15:$J$62,'VIC-1'!$B$15:$B$62,2027)/SUMIFS('VIC-1'!$E$15:$E$62,'VIC-1'!$B$15:$B$62,2027),0) | V35: =IFERROR(SUMIFS('VIC-1'!$J$15:$J$62,'VIC-1'!$B$15:$B$62,2028)/SUMIFS('VIC-1'!$E$15:$E$62,'VIC-1'!$B$15:$B$62,2028),0)
A36: 46296 | B36: =YEAR(A36) | C36: =MONTH(A36) | D36: =IF(A36<=LastActual,"Actual","Forecast") | E36: ='NSW-1'!E36+'VIC-1'!E36+'QLD-1'!E36+'NSW-2'!E36+'VIC-2'!E36+'QLD-2'!E36+'SA-1'!E36+'WA-1'!E36 | F36: ='NSW-1'!F36+'VIC-1'!F36+'QLD-1'!F36+'NSW-2'!F36+'VIC-2'!F36+'QLD-2'!F36+'SA-1'!F36+'WA-1'!F36+'IDC-NSW'!F36+'IDC-VIC'!F36 | G36: ='NSW-1'!G36+'VIC-1'!G36+'QLD-1'!G36+'NSW-2'!G36+'VIC-2'!G36+'QLD-2'!G36+'SA-1'!G36+'WA-1'!G36+'IDC-NSW'!G36+'IDC-VIC'!G36 | H36: ='NSW-1'!H36+'VIC-1'!H36+'QLD-1'!H36+'NSW-2'!H36+'VIC-2'!H36+'QLD-2'!H36+'SA-1'!H36+'WA-1'!H36+'IDC-NSW'!H36+'IDC-VIC'!H36 | I36: ='NSW-1'!I36+'VIC-1'!I36+'QLD-1'!I36+'NSW-2'!I36+'VIC-2'!I36+'QLD-2'!I36+'SA-1'!I36+'WA-1'!I36+'IDC-NSW'!I36+'IDC-VIC'!I36 | J36: ='NSW-1'!J36+'VIC-1'!J36+'QLD-1'!J36+'NSW-2'!J36+'VIC-2'!J36+'QLD-2'!J36+'SA-1'!J36+'WA-1'!J36+'IDC-NSW'!J36+'IDC-VIC'!J36 | K36: =IFERROR(F36/G36,0) | L36: =IFERROR(H36/G36,0) | M36: =IFERROR(J36/F36,0) | N36: =IFERROR(J36/E36,0) | O36: =IFERROR(I36/J36,0) | R36: =Inputs!$A$38 | S36: =IFERROR(SUMIFS('QLD-1'!$J$15:$J$62,'QLD-1'!$B$15:$B$62,2025)/SUMIFS('QLD-1'!$E$15:$E$62,'QLD-1'!$B$15:$B$62,2025),0) | T36: =IFERROR(SUMIFS('QLD-1'!$J$15:$J$62,'QLD-1'!$B$15:$B$62,2026)/SUMIFS('QLD-1'!$E$15:$E$62,'QLD-1'!$B$15:$B$62,2026),0) | U36: =IFERROR(SUMIFS('QLD-1'!$J$15:$J$62,'QLD-1'!$B$15:$B$62,2027)/SUMIFS('QLD-1'!$E$15:$E$62,'QLD-1'!$B$15:$B$62,2027),0) | V36: =IFERROR(SUMIFS('QLD-1'!$J$15:$J$62,'QLD-1'!$B$15:$B$62,2028)/SUMIFS('QLD-1'!$E$15:$E$62,'QLD-1'!$B$15:$B$62,2028),0)
A37: 46327 | B37: =YEAR(A37) | C37: =MONTH(A37) | D37: =IF(A37<=LastActual,"Actual","Forecast") | E37: ='NSW-1'!E37+'VIC-1'!E37+'QLD-1'!E37+'NSW-2'!E37+'VIC-2'!E37+'QLD-2'!E37+'SA-1'!E37+'WA-1'!E37 | F37: ='NSW-1'!F37+'VIC-1'!F37+'QLD-1'!F37+'NSW-2'!F37+'VIC-2'!F37+'QLD-2'!F37+'SA-1'!F37+'WA-1'!F37+'IDC-NSW'!F37+'IDC-VIC'!F37 | G37: ='NSW-1'!G37+'VIC-1'!G37+'QLD-1'!G37+'NSW-2'!G37+'VIC-2'!G37+'QLD-2'!G37+'SA-1'!G37+'WA-1'!G37+'IDC-NSW'!G37+'IDC-VIC'!G37 | H37: ='NSW-1'!H37+'VIC-1'!H37+'QLD-1'!H37+'NSW-2'!H37+'VIC-2'!H37+'QLD-2'!H37+'SA-1'!H37+'WA-1'!H37+'IDC-NSW'!H37+'IDC-VIC'!H37 | I37: ='NSW-1'!I37+'VIC-1'!I37+'QLD-1'!I37+'NSW-2'!I37+'VIC-2'!I37+'QLD-2'!I37+'SA-1'!I37+'WA-1'!I37+'IDC-NSW'!I37+'IDC-VIC'!I37 | J37: ='NSW-1'!J37+'VIC-1'!J37+'QLD-1'!J37+'NSW-2'!J37+'VIC-2'!J37+'QLD-2'!J37+'SA-1'!J37+'WA-1'!J37+'IDC-NSW'!J37+'IDC-VIC'!J37 | K37: =IFERROR(F37/G37,0) | L37: =IFERROR(H37/G37,0) | M37: =IFERROR(J37/F37,0) | N37: =IFERROR(J37/E37,0) | O37: =IFERROR(I37/J37,0) | R37: =Inputs!$A$39 | S37: =IFERROR(SUMIFS('NSW-2'!$J$15:$J$62,'NSW-2'!$B$15:$B$62,2025)/SUMIFS('NSW-2'!$E$15:$E$62,'NSW-2'!$B$15:$B$62,2025),0) | T37: =IFERROR(SUMIFS('NSW-2'!$J$15:$J$62,'NSW-2'!$B$15:$B$62,2026)/SUMIFS('NSW-2'!$E$15:$E$62,'NSW-2'!$B$15:$B$62,2026),0) | U37: =IFERROR(SUMIFS('NSW-2'!$J$15:$J$62,'NSW-2'!$B$15:$B$62,2027)/SUMIFS('NSW-2'!$E$15:$E$62,'NSW-2'!$B$15:$B$62,2027),0) | V37: =IFERROR(SUMIFS('NSW-2'!$J$15:$J$62,'NSW-2'!$B$15:$B$62,2028)/SUMIFS('NSW-2'!$E$15:$E$62,'NSW-2'!$B$15:$B$62,2028),0)
A38: 46357 | B38: =YEAR(A38) | C38: =MONTH(A38) | D38: =IF(A38<=LastActual,"Actual","Forecast") | E38: ='NSW-1'!E38+'VIC-1'!E38+'QLD-1'!E38+'NSW-2'!E38+'VIC-2'!E38+'QLD-2'!E38+'SA-1'!E38+'WA-1'!E38 | F38: ='NSW-1'!F38+'VIC-1'!F38+'QLD-1'!F38+'NSW-2'!F38+'VIC-2'!F38+'QLD-2'!F38+'SA-1'!F38+'WA-1'!F38+'IDC-NSW'!F38+'IDC-VIC'!F38 | G38: ='NSW-1'!G38+'VIC-1'!G38+'QLD-1'!G38+'NSW-2'!G38+'VIC-2'!G38+'QLD-2'!G38+'SA-1'!G38+'WA-1'!G38+'IDC-NSW'!G38+'IDC-VIC'!G38 | H38: ='NSW-1'!H38+'VIC-1'!H38+'QLD-1'!H38+'NSW-2'!H38+'VIC-2'!H38+'QLD-2'!H38+'SA-1'!H38+'WA-1'!H38+'IDC-NSW'!H38+'IDC-VIC'!H38 | I38: ='NSW-1'!I38+'VIC-1'!I38+'QLD-1'!I38+'NSW-2'!I38+'VIC-2'!I38+'QLD-2'!I38+'SA-1'!I38+'WA-1'!I38+'IDC-NSW'!I38+'IDC-VIC'!I38 | J38: ='NSW-1'!J38+'VIC-1'!J38+'QLD-1'!J38+'NSW-2'!J38+'VIC-2'!J38+'QLD-2'!J38+'SA-1'!J38+'WA-1'!J38+'IDC-NSW'!J38+'IDC-VIC'!J38 | K38: =IFERROR(F38/G38,0) | L38: =IFERROR(H38/G38,0) | M38: =IFERROR(J38/F38,0) | N38: =IFERROR(J38/E38,0) | O38: =IFERROR(I38/J38,0) | R38: =Inputs!$A$40 | S38: =IFERROR(SUMIFS('VIC-2'!$J$15:$J$62,'VIC-2'!$B$15:$B$62,2025)/SUMIFS('VIC-2'!$E$15:$E$62,'VIC-2'!$B$15:$B$62,2025),0) | T38: =IFERROR(SUMIFS('VIC-2'!$J$15:$J$62,'VIC-2'!$B$15:$B$62,2026)/SUMIFS('VIC-2'!$E$15:$E$62,'VIC-2'!$B$15:$B$62,2026),0) | U38: =IFERROR(SUMIFS('VIC-2'!$J$15:$J$62,'VIC-2'!$B$15:$B$62,2027)/SUMIFS('VIC-2'!$E$15:$E$62,'VIC-2'!$B$15:$B$62,2027),0) | V38: =IFERROR(SUMIFS('VIC-2'!$J$15:$J$62,'VIC-2'!$B$15:$B$62,2028)/SUMIFS('VIC-2'!$E$15:$E$62,'VIC-2'!$B$15:$B$62,2028),0)
A39: 46388 | B39: =YEAR(A39) | C39: =MONTH(A39) | D39: =IF(A39<=LastActual,"Actual","Forecast") | E39: ='NSW-1'!E39+'VIC-1'!E39+'QLD-1'!E39+'NSW-2'!E39+'VIC-2'!E39+'QLD-2'!E39+'SA-1'!E39+'WA-1'!E39 | F39: ='NSW-1'!F39+'VIC-1'!F39+'QLD-1'!F39+'NSW-2'!F39+'VIC-2'!F39+'QLD-2'!F39+'SA-1'!F39+'WA-1'!F39+'IDC-NSW'!F39+'IDC-VIC'!F39 | G39: ='NSW-1'!G39+'VIC-1'!G39+'QLD-1'!G39+'NSW-2'!G39+'VIC-2'!G39+'QLD-2'!G39+'SA-1'!G39+'WA-1'!G39+'IDC-NSW'!G39+'IDC-VIC'!G39 | H39: ='NSW-1'!H39+'VIC-1'!H39+'QLD-1'!H39+'NSW-2'!H39+'VIC-2'!H39+'QLD-2'!H39+'SA-1'!H39+'WA-1'!H39+'IDC-NSW'!H39+'IDC-VIC'!H39 | I39: ='NSW-1'!I39+'VIC-1'!I39+'QLD-1'!I39+'NSW-2'!I39+'VIC-2'!I39+'QLD-2'!I39+'SA-1'!I39+'WA-1'!I39+'IDC-NSW'!I39+'IDC-VIC'!I39 | J39: ='NSW-1'!J39+'VIC-1'!J39+'QLD-1'!J39+'NSW-2'!J39+'VIC-2'!J39+'QLD-2'!J39+'SA-1'!J39+'WA-1'!J39+'IDC-NSW'!J39+'IDC-VIC'!J39 | K39: =IFERROR(F39/G39,0) | L39: =IFERROR(H39/G39,0) | M39: =IFERROR(J39/F39,0) | N39: =IFERROR(J39/E39,0) | O39: =IFERROR(I39/J39,0) | R39: =Inputs!$A$41 | S39: =IFERROR(SUMIFS('QLD-2'!$J$15:$J$62,'QLD-2'!$B$15:$B$62,2025)/SUMIFS('QLD-2'!$E$15:$E$62,'QLD-2'!$B$15:$B$62,2025),0) | T39: =IFERROR(SUMIFS('QLD-2'!$J$15:$J$62,'QLD-2'!$B$15:$B$62,2026)/SUMIFS('QLD-2'!$E$15:$E$62,'QLD-2'!$B$15:$B$62,2026),0) | U39: =IFERROR(SUMIFS('QLD-2'!$J$15:$J$62,'QLD-2'!$B$15:$B$62,2027)/SUMIFS('QLD-2'!$E$15:$E$62,'QLD-2'!$B$15:$B$62,2027),0) | V39: =IFERROR(SUMIFS('QLD-2'!$J$15:$J$62,'QLD-2'!$B$15:$B$62,2028)/SUMIFS('QLD-2'!$E$15:$E$62,'QLD-2'!$B$15:$B$62,2028),0)
A40: 46419 | B40: =YEAR(A40) | C40: =MONTH(A40) | D40: =IF(A40<=LastActual,"Actual","Forecast") | E40: ='NSW-1'!E40+'VIC-1'!E40+'QLD-1'!E40+'NSW-2'!E40+'VIC-2'!E40+'QLD-2'!E40+'SA-1'!E40+'WA-1'!E40 | F40: ='NSW-1'!F40+'VIC-1'!F40+'QLD-1'!F40+'NSW-2'!F40+'VIC-2'!F40+'QLD-2'!F40+'SA-1'!F40+'WA-1'!F40+'IDC-NSW'!F40+'IDC-VIC'!F40 | G40: ='NSW-1'!G40+'VIC-1'!G40+'QLD-1'!G40+'NSW-2'!G40+'VIC-2'!G40+'QLD-2'!G40+'SA-1'!G40+'WA-1'!G40+'IDC-NSW'!G40+'IDC-VIC'!G40 | H40: ='NSW-1'!H40+'VIC-1'!H40+'QLD-1'!H40+'NSW-2'!H40+'VIC-2'!H40+'QLD-2'!H40+'SA-1'!H40+'WA-1'!H40+'IDC-NSW'!H40+'IDC-VIC'!H40 | I40: ='NSW-1'!I40+'VIC-1'!I40+'QLD-1'!I40+'NSW-2'!I40+'VIC-2'!I40+'QLD-2'!I40+'SA-1'!I40+'WA-1'!I40+'IDC-NSW'!I40+'IDC-VIC'!I40 | J40: ='NSW-1'!J40+'VIC-1'!J40+'QLD-1'!J40+'NSW-2'!J40+'VIC-2'!J40+'QLD-2'!J40+'SA-1'!J40+'WA-1'!J40+'IDC-NSW'!J40+'IDC-VIC'!J40 | K40: =IFERROR(F40/G40,0) | L40: =IFERROR(H40/G40,0) | M40: =IFERROR(J40/F40,0) | N40: =IFERROR(J40/E40,0) | O40: =IFERROR(I40/J40,0) | R40: =Inputs!$A$42 | S40: =IFERROR(SUMIFS('SA-1'!$J$15:$J$62,'SA-1'!$B$15:$B$62,2025)/SUMIFS('SA-1'!$E$15:$E$62,'SA-1'!$B$15:$B$62,2025),0) | T40: =IFERROR(SUMIFS('SA-1'!$J$15:$J$62,'SA-1'!$B$15:$B$62,2026)/SUMIFS('SA-1'!$E$15:$E$62,'SA-1'!$B$15:$B$62,2026),0) | U40: =IFERROR(SUMIFS('SA-1'!$J$15:$J$62,'SA-1'!$B$15:$B$62,2027)/SUMIFS('SA-1'!$E$15:$E$62,'SA-1'!$B$15:$B$62,2027),0) | V40: =IFERROR(SUMIFS('SA-1'!$J$15:$J$62,'SA-1'!$B$15:$B$62,2028)/SUMIFS('SA-1'!$E$15:$E$62,'SA-1'!$B$15:$B$62,2028),0)
A41: 46447 | B41: =YEAR(A41) | C41: =MONTH(A41) | D41: =IF(A41<=LastActual,"Actual","Forecast") | E41: ='NSW-1'!E41+'VIC-1'!E41+'QLD-1'!E41+'NSW-2'!E41+'VIC-2'!E41+'QLD-2'!E41+'SA-1'!E41+'WA-1'!E41 | F41: ='NSW-1'!F41+'VIC-1'!F41+'QLD-1'!F41+'NSW-2'!F41+'VIC-2'!F41+'QLD-2'!F41+'SA-1'!F41+'WA-1'!F41+'IDC-NSW'!F41+'IDC-VIC'!F41 | G41: ='NSW-1'!G41+'VIC-1'!G41+'QLD-1'!G41+'NSW-2'!G41+'VIC-2'!G41+'QLD-2'!G41+'SA-1'!G41+'WA-1'!G41+'IDC-NSW'!G41+'IDC-VIC'!G41 | H41: ='NSW-1'!H41+'VIC-1'!H41+'QLD-1'!H41+'NSW-2'!H41+'VIC-2'!H41+'QLD-2'!H41+'SA-1'!H41+'WA-1'!H41+'IDC-NSW'!H41+'IDC-VIC'!H41 | I41: ='NSW-1'!I41+'VIC-1'!I41+'QLD-1'!I41+'NSW-2'!I41+'VIC-2'!I41+'QLD-2'!I41+'SA-1'!I41+'WA-1'!I41+'IDC-NSW'!I41+'IDC-VIC'!I41 | J41: ='NSW-1'!J41+'VIC-1'!J41+'QLD-1'!J41+'NSW-2'!J41+'VIC-2'!J41+'QLD-2'!J41+'SA-1'!J41+'WA-1'!J41+'IDC-NSW'!J41+'IDC-VIC'!J41 | K41: =IFERROR(F41/G41,0) | L41: =IFERROR(H41/G41,0) | M41: =IFERROR(J41/F41,0) | N41: =IFERROR(J41/E41,0) | O41: =IFERROR(I41/J41,0) | R41: =Inputs!$A$43 | S41: =IFERROR(SUMIFS('WA-1'!$J$15:$J$62,'WA-1'!$B$15:$B$62,2025)/SUMIFS('WA-1'!$E$15:$E$62,'WA-1'!$B$15:$B$62,2025),0) | T41: =IFERROR(SUMIFS('WA-1'!$J$15:$J$62,'WA-1'!$B$15:$B$62,2026)/SUMIFS('WA-1'!$E$15:$E$62,'WA-1'!$B$15:$B$62,2026),0) | U41: =IFERROR(SUMIFS('WA-1'!$J$15:$J$62,'WA-1'!$B$15:$B$62,2027)/SUMIFS('WA-1'!$E$15:$E$62,'WA-1'!$B$15:$B$62,2027),0) | V41: =IFERROR(SUMIFS('WA-1'!$J$15:$J$62,'WA-1'!$B$15:$B$62,2028)/SUMIFS('WA-1'!$E$15:$E$62,'WA-1'!$B$15:$B$62,2028),0)
A42: 46478 | B42: =YEAR(A42) | C42: =MONTH(A42) | D42: =IF(A42<=LastActual,"Actual","Forecast") | E42: ='NSW-1'!E42+'VIC-1'!E42+'QLD-1'!E42+'NSW-2'!E42+'VIC-2'!E42+'QLD-2'!E42+'SA-1'!E42+'WA-1'!E42 | F42: ='NSW-1'!F42+'VIC-1'!F42+'QLD-1'!F42+'NSW-2'!F42+'VIC-2'!F42+'QLD-2'!F42+'SA-1'!F42+'WA-1'!F42+'IDC-NSW'!F42+'IDC-VIC'!F42 | G42: ='NSW-1'!G42+'VIC-1'!G42+'QLD-1'!G42+'NSW-2'!G42+'VIC-2'!G42+'QLD-2'!G42+'SA-1'!G42+'WA-1'!G42+'IDC-NSW'!G42+'IDC-VIC'!G42 | H42: ='NSW-1'!H42+'VIC-1'!H42+'QLD-1'!H42+'NSW-2'!H42+'VIC-2'!H42+'QLD-2'!H42+'SA-1'!H42+'WA-1'!H42+'IDC-NSW'!H42+'IDC-VIC'!H42 | I42: ='NSW-1'!I42+'VIC-1'!I42+'QLD-1'!I42+'NSW-2'!I42+'VIC-2'!I42+'QLD-2'!I42+'SA-1'!I42+'WA-1'!I42+'IDC-NSW'!I42+'IDC-VIC'!I42 | J42: ='NSW-1'!J42+'VIC-1'!J42+'QLD-1'!J42+'NSW-2'!J42+'VIC-2'!J42+'QLD-2'!J42+'SA-1'!J42+'WA-1'!J42+'IDC-NSW'!J42+'IDC-VIC'!J42 | K42: =IFERROR(F42/G42,0) | L42: =IFERROR(H42/G42,0) | M42: =IFERROR(J42/F42,0) | N42: =IFERROR(J42/E42,0) | O42: =IFERROR(I42/J42,0) | R42: =Inputs!$A$44 | S42: =IFERROR(SUMIFS('IDC-NSW'!$J$15:$J$62,'IDC-NSW'!$B$15:$B$62,2025)/SUMIFS('IDC-NSW'!$E$15:$E$62,'IDC-NSW'!$B$15:$B$62,2025),0) | T42: =IFERROR(SUMIFS('IDC-NSW'!$J$15:$J$62,'IDC-NSW'!$B$15:$B$62,2026)/SUMIFS('IDC-NSW'!$E$15:$E$62,'IDC-NSW'!$B$15:$B$62,2026),0) | U42: =IFERROR(SUMIFS('IDC-NSW'!$J$15:$J$62,'IDC-NSW'!$B$15:$B$62,2027)/SUMIFS('IDC-NSW'!$E$15:$E$62,'IDC-NSW'!$B$15:$B$62,2027),0) | V42: =IFERROR(SUMIFS('IDC-NSW'!$J$15:$J$62,'IDC-NSW'!$B$15:$B$62,2028)/SUMIFS('IDC-NSW'!$E$15:$E$62,'IDC-NSW'!$B$15:$B$62,2028),0)
A43: 46508 | B43: =YEAR(A43) | C43: =MONTH(A43) | D43: =IF(A43<=LastActual,"Actual","Forecast") | E43: ='NSW-1'!E43+'VIC-1'!E43+'QLD-1'!E43+'NSW-2'!E43+'VIC-2'!E43+'QLD-2'!E43+'SA-1'!E43+'WA-1'!E43 | F43: ='NSW-1'!F43+'VIC-1'!F43+'QLD-1'!F43+'NSW-2'!F43+'VIC-2'!F43+'QLD-2'!F43+'SA-1'!F43+'WA-1'!F43+'IDC-NSW'!F43+'IDC-VIC'!F43 | G43: ='NSW-1'!G43+'VIC-1'!G43+'QLD-1'!G43+'NSW-2'!G43+'VIC-2'!G43+'QLD-2'!G43+'SA-1'!G43+'WA-1'!G43+'IDC-NSW'!G43+'IDC-VIC'!G43 | H43: ='NSW-1'!H43+'VIC-1'!H43+'QLD-1'!H43+'NSW-2'!H43+'VIC-2'!H43+'QLD-2'!H43+'SA-1'!H43+'WA-1'!H43+'IDC-NSW'!H43+'IDC-VIC'!H43 | I43: ='NSW-1'!I43+'VIC-1'!I43+'QLD-1'!I43+'NSW-2'!I43+'VIC-2'!I43+'QLD-2'!I43+'SA-1'!I43+'WA-1'!I43+'IDC-NSW'!I43+'IDC-VIC'!I43 | J43: ='NSW-1'!J43+'VIC-1'!J43+'QLD-1'!J43+'NSW-2'!J43+'VIC-2'!J43+'QLD-2'!J43+'SA-1'!J43+'WA-1'!J43+'IDC-NSW'!J43+'IDC-VIC'!J43 | K43: =IFERROR(F43/G43,0) | L43: =IFERROR(H43/G43,0) | M43: =IFERROR(J43/F43,0) | N43: =IFERROR(J43/E43,0) | O43: =IFERROR(I43/J43,0) | R43: =Inputs!$A$45 | S43: =IFERROR(SUMIFS('IDC-VIC'!$J$15:$J$62,'IDC-VIC'!$B$15:$B$62,2025)/SUMIFS('IDC-VIC'!$E$15:$E$62,'IDC-VIC'!$B$15:$B$62,2025),0) | T43: =IFERROR(SUMIFS('IDC-VIC'!$J$15:$J$62,'IDC-VIC'!$B$15:$B$62,2026)/SUMIFS('IDC-VIC'!$E$15:$E$62,'IDC-VIC'!$B$15:$B$62,2026),0) | U43: =IFERROR(SUMIFS('IDC-VIC'!$J$15:$J$62,'IDC-VIC'!$B$15:$B$62,2027)/SUMIFS('IDC-VIC'!$E$15:$E$62,'IDC-VIC'!$B$15:$B$62,2027),0) | V43: =IFERROR(SUMIFS('IDC-VIC'!$J$15:$J$62,'IDC-VIC'!$B$15:$B$62,2028)/SUMIFS('IDC-VIC'!$E$15:$E$62,'IDC-VIC'!$B$15:$B$62,2028),0)
A44: 46539 | B44: =YEAR(A44) | C44: =MONTH(A44) | D44: =IF(A44<=LastActual,"Actual","Forecast") | E44: ='NSW-1'!E44+'VIC-1'!E44+'QLD-1'!E44+'NSW-2'!E44+'VIC-2'!E44+'QLD-2'!E44+'SA-1'!E44+'WA-1'!E44 | F44: ='NSW-1'!F44+'VIC-1'!F44+'QLD-1'!F44+'NSW-2'!F44+'VIC-2'!F44+'QLD-2'!F44+'SA-1'!F44+'WA-1'!F44+'IDC-NSW'!F44+'IDC-VIC'!F44 | G44: ='NSW-1'!G44+'VIC-1'!G44+'QLD-1'!G44+'NSW-2'!G44+'VIC-2'!G44+'QLD-2'!G44+'SA-1'!G44+'WA-1'!G44+'IDC-NSW'!G44+'IDC-VIC'!G44 | H44: ='NSW-1'!H44+'VIC-1'!H44+'QLD-1'!H44+'NSW-2'!H44+'VIC-2'!H44+'QLD-2'!H44+'SA-1'!H44+'WA-1'!H44+'IDC-NSW'!H44+'IDC-VIC'!H44 | I44: ='NSW-1'!I44+'VIC-1'!I44+'QLD-1'!I44+'NSW-2'!I44+'VIC-2'!I44+'QLD-2'!I44+'SA-1'!I44+'WA-1'!I44+'IDC-NSW'!I44+'IDC-VIC'!I44 | J44: ='NSW-1'!J44+'VIC-1'!J44+'QLD-1'!J44+'NSW-2'!J44+'VIC-2'!J44+'QLD-2'!J44+'SA-1'!J44+'WA-1'!J44+'IDC-NSW'!J44+'IDC-VIC'!J44 | K44: =IFERROR(F44/G44,0) | L44: =IFERROR(H44/G44,0) | M44: =IFERROR(J44/F44,0) | N44: =IFERROR(J44/E44,0) | O44: =IFERROR(I44/J44,0)
A45: 46569 | B45: =YEAR(A45) | C45: =MONTH(A45) | D45: =IF(A45<=LastActual,"Actual","Forecast") | E45: ='NSW-1'!E45+'VIC-1'!E45+'QLD-1'!E45+'NSW-2'!E45+'VIC-2'!E45+'QLD-2'!E45+'SA-1'!E45+'WA-1'!E45 | F45: ='NSW-1'!F45+'VIC-1'!F45+'QLD-1'!F45+'NSW-2'!F45+'VIC-2'!F45+'QLD-2'!F45+'SA-1'!F45+'WA-1'!F45+'IDC-NSW'!F45+'IDC-VIC'!F45 | G45: ='NSW-1'!G45+'VIC-1'!G45+'QLD-1'!G45+'NSW-2'!G45+'VIC-2'!G45+'QLD-2'!G45+'SA-1'!G45+'WA-1'!G45+'IDC-NSW'!G45+'IDC-VIC'!G45 | H45: ='NSW-1'!H45+'VIC-1'!H45+'QLD-1'!H45+'NSW-2'!H45+'VIC-2'!H45+'QLD-2'!H45+'SA-1'!H45+'WA-1'!H45+'IDC-NSW'!H45+'IDC-VIC'!H45 | I45: ='NSW-1'!I45+'VIC-1'!I45+'QLD-1'!I45+'NSW-2'!I45+'VIC-2'!I45+'QLD-2'!I45+'SA-1'!I45+'WA-1'!I45+'IDC-NSW'!I45+'IDC-VIC'!I45 | J45: ='NSW-1'!J45+'VIC-1'!J45+'QLD-1'!J45+'NSW-2'!J45+'VIC-2'!J45+'QLD-2'!J45+'SA-1'!J45+'WA-1'!J45+'IDC-NSW'!J45+'IDC-VIC'!J45 | K45: =IFERROR(F45/G45,0) | L45: =IFERROR(H45/G45,0) | M45: =IFERROR(J45/F45,0) | N45: =IFERROR(J45/E45,0) | O45: =IFERROR(I45/J45,0)
A46: 46600 | B46: =YEAR(A46) | C46: =MONTH(A46) | D46: =IF(A46<=LastActual,"Actual","Forecast") | E46: ='NSW-1'!E46+'VIC-1'!E46+'QLD-1'!E46+'NSW-2'!E46+'VIC-2'!E46+'QLD-2'!E46+'SA-1'!E46+'WA-1'!E46 | F46: ='NSW-1'!F46+'VIC-1'!F46+'QLD-1'!F46+'NSW-2'!F46+'VIC-2'!F46+'QLD-2'!F46+'SA-1'!F46+'WA-1'!F46+'IDC-NSW'!F46+'IDC-VIC'!F46 | G46: ='NSW-1'!G46+'VIC-1'!G46+'QLD-1'!G46+'NSW-2'!G46+'VIC-2'!G46+'QLD-2'!G46+'SA-1'!G46+'WA-1'!G46+'IDC-NSW'!G46+'IDC-VIC'!G46 | H46: ='NSW-1'!H46+'VIC-1'!H46+'QLD-1'!H46+'NSW-2'!H46+'VIC-2'!H46+'QLD-2'!H46+'SA-1'!H46+'WA-1'!H46+'IDC-NSW'!H46+'IDC-VIC'!H46 | I46: ='NSW-1'!I46+'VIC-1'!I46+'QLD-1'!I46+'NSW-2'!I46+'VIC-2'!I46+'QLD-2'!I46+'SA-1'!I46+'WA-1'!I46+'IDC-NSW'!I46+'IDC-VIC'!I46 | J46: ='NSW-1'!J46+'VIC-1'!J46+'QLD-1'!J46+'NSW-2'!J46+'VIC-2'!J46+'QLD-2'!J46+'SA-1'!J46+'WA-1'!J46+'IDC-NSW'!J46+'IDC-VIC'!J46 | K46: =IFERROR(F46/G46,0) | L46: =IFERROR(H46/G46,0) | M46: =IFERROR(J46/F46,0) | N46: =IFERROR(J46/E46,0) | O46: =IFERROR(I46/J46,0) | R46: CPLH (cases / hr)
A47: 46631 | B47: =YEAR(A47) | C47: =MONTH(A47) | D47: =IF(A47<=LastActual,"Actual","Forecast") | E47: ='NSW-1'!E47+'VIC-1'!E47+'QLD-1'!E47+'NSW-2'!E47+'VIC-2'!E47+'QLD-2'!E47+'SA-1'!E47+'WA-1'!E47 | F47: ='NSW-1'!F47+'VIC-1'!F47+'QLD-1'!F47+'NSW-2'!F47+'VIC-2'!F47+'QLD-2'!F47+'SA-1'!F47+'WA-1'!F47+'IDC-NSW'!F47+'IDC-VIC'!F47 | G47: ='NSW-1'!G47+'VIC-1'!G47+'QLD-1'!G47+'NSW-2'!G47+'VIC-2'!G47+'QLD-2'!G47+'SA-1'!G47+'WA-1'!G47+'IDC-NSW'!G47+'IDC-VIC'!G47 | H47: ='NSW-1'!H47+'VIC-1'!H47+'QLD-1'!H47+'NSW-2'!H47+'VIC-2'!H47+'QLD-2'!H47+'SA-1'!H47+'WA-1'!H47+'IDC-NSW'!H47+'IDC-VIC'!H47 | I47: ='NSW-1'!I47+'VIC-1'!I47+'QLD-1'!I47+'NSW-2'!I47+'VIC-2'!I47+'QLD-2'!I47+'SA-1'!I47+'WA-1'!I47+'IDC-NSW'!I47+'IDC-VIC'!I47 | J47: ='NSW-1'!J47+'VIC-1'!J47+'QLD-1'!J47+'NSW-2'!J47+'VIC-2'!J47+'QLD-2'!J47+'SA-1'!J47+'WA-1'!J47+'IDC-NSW'!J47+'IDC-VIC'!J47 | K47: =IFERROR(F47/G47,0) | L47: =IFERROR(H47/G47,0) | M47: =IFERROR(J47/F47,0) | N47: =IFERROR(J47/E47,0) | O47: =IFERROR(I47/J47,0) | R47: Site | S47: FY2025 | T47: FY2026 | U47: FY2027 | V47: FY2028
A48: 46661 | B48: =YEAR(A48) | C48: =MONTH(A48) | D48: =IF(A48<=LastActual,"Actual","Forecast") | E48: ='NSW-1'!E48+'VIC-1'!E48+'QLD-1'!E48+'NSW-2'!E48+'VIC-2'!E48+'QLD-2'!E48+'SA-1'!E48+'WA-1'!E48 | F48: ='NSW-1'!F48+'VIC-1'!F48+'QLD-1'!F48+'NSW-2'!F48+'VIC-2'!F48+'QLD-2'!F48+'SA-1'!F48+'WA-1'!F48+'IDC-NSW'!F48+'IDC-VIC'!F48 | G48: ='NSW-1'!G48+'VIC-1'!G48+'QLD-1'!G48+'NSW-2'!G48+'VIC-2'!G48+'QLD-2'!G48+'SA-1'!G48+'WA-1'!G48+'IDC-NSW'!G48+'IDC-VIC'!G48 | H48: ='NSW-1'!H48+'VIC-1'!H48+'QLD-1'!H48+'NSW-2'!H48+'VIC-2'!H48+'QLD-2'!H48+'SA-1'!H48+'WA-1'!H48+'IDC-NSW'!H48+'IDC-VIC'!H48 | I48: ='NSW-1'!I48+'VIC-1'!I48+'QLD-1'!I48+'NSW-2'!I48+'VIC-2'!I48+'QLD-2'!I48+'SA-1'!I48+'WA-1'!I48+'IDC-NSW'!I48+'IDC-VIC'!I48 | J48: ='NSW-1'!J48+'VIC-1'!J48+'QLD-1'!J48+'NSW-2'!J48+'VIC-2'!J48+'QLD-2'!J48+'SA-1'!J48+'WA-1'!J48+'IDC-NSW'!J48+'IDC-VIC'!J48 | K48: =IFERROR(F48/G48,0) | L48: =IFERROR(H48/G48,0) | M48: =IFERROR(J48/F48,0) | N48: =IFERROR(J48/E48,0) | O48: =IFERROR(I48/J48,0) | R48: =Inputs!$A$36 | S48: =IFERROR(SUMIFS('NSW-1'!$F$15:$F$62,'NSW-1'!$B$15:$B$62,2025)/SUMIFS('NSW-1'!$G$15:$G$62,'NSW-1'!$B$15:$B$62,2025),0) | T48: =IFERROR(SUMIFS('NSW-1'!$F$15:$F$62,'NSW-1'!$B$15:$B$62,2026)/SUMIFS('NSW-1'!$G$15:$G$62,'NSW-1'!$B$15:$B$62,2026),0) | U48: =IFERROR(SUMIFS('NSW-1'!$F$15:$F$62,'NSW-1'!$B$15:$B$62,2027)/SUMIFS('NSW-1'!$G$15:$G$62,'NSW-1'!$B$15:$B$62,2027),0) | V48: =IFERROR(SUMIFS('NSW-1'!$F$15:$F$62,'NSW-1'!$B$15:$B$62,2028)/SUMIFS('NSW-1'!$G$15:$G$62,'NSW-1'!$B$15:$B$62,2028),0)
A49: 46692 | B49: =YEAR(A49) | C49: =MONTH(A49) | D49: =IF(A49<=LastActual,"Actual","Forecast") | E49: ='NSW-1'!E49+'VIC-1'!E49+'QLD-1'!E49+'NSW-2'!E49+'VIC-2'!E49+'QLD-2'!E49+'SA-1'!E49+'WA-1'!E49 | F49: ='NSW-1'!F49+'VIC-1'!F49+'QLD-1'!F49+'NSW-2'!F49+'VIC-2'!F49+'QLD-2'!F49+'SA-1'!F49+'WA-1'!F49+'IDC-NSW'!F49+'IDC-VIC'!F49 | G49: ='NSW-1'!G49+'VIC-1'!G49+'QLD-1'!G49+'NSW-2'!G49+'VIC-2'!G49+'QLD-2'!G49+'SA-1'!G49+'WA-1'!G49+'IDC-NSW'!G49+'IDC-VIC'!G49 | H49: ='NSW-1'!H49+'VIC-1'!H49+'QLD-1'!H49+'NSW-2'!H49+'VIC-2'!H49+'QLD-2'!H49+'SA-1'!H49+'WA-1'!H49+'IDC-NSW'!H49+'IDC-VIC'!H49 | I49: ='NSW-1'!I49+'VIC-1'!I49+'QLD-1'!I49+'NSW-2'!I49+'VIC-2'!I49+'QLD-2'!I49+'SA-1'!I49+'WA-1'!I49+'IDC-NSW'!I49+'IDC-VIC'!I49 | J49: ='NSW-1'!J49+'VIC-1'!J49+'QLD-1'!J49+'NSW-2'!J49+'VIC-2'!J49+'QLD-2'!J49+'SA-1'!J49+'WA-1'!J49+'IDC-NSW'!J49+'IDC-VIC'!J49 | K49: =IFERROR(F49/G49,0) | L49: =IFERROR(H49/G49,0) | M49: =IFERROR(J49/F49,0) | N49: =IFERROR(J49/E49,0) | O49: =IFERROR(I49/J49,0) | R49: =Inputs!$A$37 | S49: =IFERROR(SUMIFS('VIC-1'!$F$15:$F$62,'VIC-1'!$B$15:$B$62,2025)/SUMIFS('VIC-1'!$G$15:$G$62,'VIC-1'!$B$15:$B$62,2025),0) | T49: =IFERROR(SUMIFS('VIC-1'!$F$15:$F$62,'VIC-1'!$B$15:$B$62,2026)/SUMIFS('VIC-1'!$G$15:$G$62,'VIC-1'!$B$15:$B$62,2026),0) | U49: =IFERROR(SUMIFS('VIC-1'!$F$15:$F$62,'VIC-1'!$B$15:$B$62,2027)/SUMIFS('VIC-1'!$G$15:$G$62,'VIC-1'!$B$15:$B$62,2027),0) | V49: =IFERROR(SUMIFS('VIC-1'!$F$15:$F$62,'VIC-1'!$B$15:$B$62,2028)/SUMIFS('VIC-1'!$G$15:$G$62,'VIC-1'!$B$15:$B$62,2028),0)
A50: 46722 | B50: =YEAR(A50) | C50: =MONTH(A50) | D50: =IF(A50<=LastActual,"Actual","Forecast") | E50: ='NSW-1'!E50+'VIC-1'!E50+'QLD-1'!E50+'NSW-2'!E50+'VIC-2'!E50+'QLD-2'!E50+'SA-1'!E50+'WA-1'!E50 | F50: ='NSW-1'!F50+'VIC-1'!F50+'QLD-1'!F50+'NSW-2'!F50+'VIC-2'!F50+'QLD-2'!F50+'SA-1'!F50+'WA-1'!F50+'IDC-NSW'!F50+'IDC-VIC'!F50 | G50: ='NSW-1'!G50+'VIC-1'!G50+'QLD-1'!G50+'NSW-2'!G50+'VIC-2'!G50+'QLD-2'!G50+'SA-1'!G50+'WA-1'!G50+'IDC-NSW'!G50+'IDC-VIC'!G50 | H50: ='NSW-1'!H50+'VIC-1'!H50+'QLD-1'!H50+'NSW-2'!H50+'VIC-2'!H50+'QLD-2'!H50+'SA-1'!H50+'WA-1'!H50+'IDC-NSW'!H50+'IDC-VIC'!H50 | I50: ='NSW-1'!I50+'VIC-1'!I50+'QLD-1'!I50+'NSW-2'!I50+'VIC-2'!I50+'QLD-2'!I50+'SA-1'!I50+'WA-1'!I50+'IDC-NSW'!I50+'IDC-VIC'!I50 | J50: ='NSW-1'!J50+'VIC-1'!J50+'QLD-1'!J50+'NSW-2'!J50+'VIC-2'!J50+'QLD-2'!J50+'SA-1'!J50+'WA-1'!J50+'IDC-NSW'!J50+'IDC-VIC'!J50 | K50: =IFERROR(F50/G50,0) | L50: =IFERROR(H50/G50,0) | M50: =IFERROR(J50/F50,0) | N50: =IFERROR(J50/E50,0) | O50: =IFERROR(I50/J50,0) | R50: =Inputs!$A$38 | S50: =IFERROR(SUMIFS('QLD-1'!$F$15:$F$62,'QLD-1'!$B$15:$B$62,2025)/SUMIFS('QLD-1'!$G$15:$G$62,'QLD-1'!$B$15:$B$62,2025),0) | T50: =IFERROR(SUMIFS('QLD-1'!$F$15:$F$62,'QLD-1'!$B$15:$B$62,2026)/SUMIFS('QLD-1'!$G$15:$G$62,'QLD-1'!$B$15:$B$62,2026),0) | U50: =IFERROR(SUMIFS('QLD-1'!$F$15:$F$62,'QLD-1'!$B$15:$B$62,2027)/SUMIFS('QLD-1'!$G$15:$G$62,'QLD-1'!$B$15:$B$62,2027),0) | V50: =IFERROR(SUMIFS('QLD-1'!$F$15:$F$62,'QLD-1'!$B$15:$B$62,2028)/SUMIFS('QLD-1'!$G$15:$G$62,'QLD-1'!$B$15:$B$62,2028),0)
A51: 46753 | B51: =YEAR(A51) | C51: =MONTH(A51) | D51: =IF(A51<=LastActual,"Actual","Forecast") | E51: ='NSW-1'!E51+'VIC-1'!E51+'QLD-1'!E51+'NSW-2'!E51+'VIC-2'!E51+'QLD-2'!E51+'SA-1'!E51+'WA-1'!E51 | F51: ='NSW-1'!F51+'VIC-1'!F51+'QLD-1'!F51+'NSW-2'!F51+'VIC-2'!F51+'QLD-2'!F51+'SA-1'!F51+'WA-1'!F51+'IDC-NSW'!F51+'IDC-VIC'!F51 | G51: ='NSW-1'!G51+'VIC-1'!G51+'QLD-1'!G51+'NSW-2'!G51+'VIC-2'!G51+'QLD-2'!G51+'SA-1'!G51+'WA-1'!G51+'IDC-NSW'!G51+'IDC-VIC'!G51 | H51: ='NSW-1'!H51+'VIC-1'!H51+'QLD-1'!H51+'NSW-2'!H51+'VIC-2'!H51+'QLD-2'!H51+'SA-1'!H51+'WA-1'!H51+'IDC-NSW'!H51+'IDC-VIC'!H51 | I51: ='NSW-1'!I51+'VIC-1'!I51+'QLD-1'!I51+'NSW-2'!I51+'VIC-2'!I51+'QLD-2'!I51+'SA-1'!I51+'WA-1'!I51+'IDC-NSW'!I51+'IDC-VIC'!I51 | J51: ='NSW-1'!J51+'VIC-1'!J51+'QLD-1'!J51+'NSW-2'!J51+'VIC-2'!J51+'QLD-2'!J51+'SA-1'!J51+'WA-1'!J51+'IDC-NSW'!J51+'IDC-VIC'!J51 | K51: =IFERROR(F51/G51,0) | L51: =IFERROR(H51/G51,0) | M51: =IFERROR(J51/F51,0) | N51: =IFERROR(J51/E51,0) | O51: =IFERROR(I51/J51,0) | R51: =Inputs!$A$39 | S51: =IFERROR(SUMIFS('NSW-2'!$F$15:$F$62,'NSW-2'!$B$15:$B$62,2025)/SUMIFS('NSW-2'!$G$15:$G$62,'NSW-2'!$B$15:$B$62,2025),0) | T51: =IFERROR(SUMIFS('NSW-2'!$F$15:$F$62,'NSW-2'!$B$15:$B$62,2026)/SUMIFS('NSW-2'!$G$15:$G$62,'NSW-2'!$B$15:$B$62,2026),0) | U51: =IFERROR(SUMIFS('NSW-2'!$F$15:$F$62,'NSW-2'!$B$15:$B$62,2027)/SUMIFS('NSW-2'!$G$15:$G$62,'NSW-2'!$B$15:$B$62,2027),0) | V51: =IFERROR(SUMIFS('NSW-2'!$F$15:$F$62,'NSW-2'!$B$15:$B$62,2028)/SUMIFS('NSW-2'!$G$15:$G$62,'NSW-2'!$B$15:$B$62,2028),0)
A52: 46784 | B52: =YEAR(A52) | C52: =MONTH(A52) | D52: =IF(A52<=LastActual,"Actual","Forecast") | E52: ='NSW-1'!E52+'VIC-1'!E52+'QLD-1'!E52+'NSW-2'!E52+'VIC-2'!E52+'QLD-2'!E52+'SA-1'!E52+'WA-1'!E52 | F52: ='NSW-1'!F52+'VIC-1'!F52+'QLD-1'!F52+'NSW-2'!F52+'VIC-2'!F52+'QLD-2'!F52+'SA-1'!F52+'WA-1'!F52+'IDC-NSW'!F52+'IDC-VIC'!F52 | G52: ='NSW-1'!G52+'VIC-1'!G52+'QLD-1'!G52+'NSW-2'!G52+'VIC-2'!G52+'QLD-2'!G52+'SA-1'!G52+'WA-1'!G52+'IDC-NSW'!G52+'IDC-VIC'!G52 | H52: ='NSW-1'!H52+'VIC-1'!H52+'QLD-1'!H52+'NSW-2'!H52+'VIC-2'!H52+'QLD-2'!H52+'SA-1'!H52+'WA-1'!H52+'IDC-NSW'!H52+'IDC-VIC'!H52 | I52: ='NSW-1'!I52+'VIC-1'!I52+'QLD-1'!I52+'NSW-2'!I52+'VIC-2'!I52+'QLD-2'!I52+'SA-1'!I52+'WA-1'!I52+'IDC-NSW'!I52+'IDC-VIC'!I52 | J52: ='NSW-1'!J52+'VIC-1'!J52+'QLD-1'!J52+'NSW-2'!J52+'VIC-2'!J52+'QLD-2'!J52+'SA-1'!J52+'WA-1'!J52+'IDC-NSW'!J52+'IDC-VIC'!J52 | K52: =IFERROR(F52/G52,0) | L52: =IFERROR(H52/G52,0) | M52: =IFERROR(J52/F52,0) | N52: =IFERROR(J52/E52,0) | O52: =IFERROR(I52/J52,0) | R52: =Inputs!$A$40 | S52: =IFERROR(SUMIFS('VIC-2'!$F$15:$F$62,'VIC-2'!$B$15:$B$62,2025)/SUMIFS('VIC-2'!$G$15:$G$62,'VIC-2'!$B$15:$B$62,2025),0) | T52: =IFERROR(SUMIFS('VIC-2'!$F$15:$F$62,'VIC-2'!$B$15:$B$62,2026)/SUMIFS('VIC-2'!$G$15:$G$62,'VIC-2'!$B$15:$B$62,2026),0) | U52: =IFERROR(SUMIFS('VIC-2'!$F$15:$F$62,'VIC-2'!$B$15:$B$62,2027)/SUMIFS('VIC-2'!$G$15:$G$62,'VIC-2'!$B$15:$B$62,2027),0) | V52: =IFERROR(SUMIFS('VIC-2'!$F$15:$F$62,'VIC-2'!$B$15:$B$62,2028)/SUMIFS('VIC-2'!$G$15:$G$62,'VIC-2'!$B$15:$B$62,2028),0)
A53: 46813 | B53: =YEAR(A53) | C53: =MONTH(A53) | D53: =IF(A53<=LastActual,"Actual","Forecast") | E53: ='NSW-1'!E53+'VIC-1'!E53+'QLD-1'!E53+'NSW-2'!E53+'VIC-2'!E53+'QLD-2'!E53+'SA-1'!E53+'WA-1'!E53 | F53: ='NSW-1'!F53+'VIC-1'!F53+'QLD-1'!F53+'NSW-2'!F53+'VIC-2'!F53+'QLD-2'!F53+'SA-1'!F53+'WA-1'!F53+'IDC-NSW'!F53+'IDC-VIC'!F53 | G53: ='NSW-1'!G53+'VIC-1'!G53+'QLD-1'!G53+'NSW-2'!G53+'VIC-2'!G53+'QLD-2'!G53+'SA-1'!G53+'WA-1'!G53+'IDC-NSW'!G53+'IDC-VIC'!G53 | H53: ='NSW-1'!H53+'VIC-1'!H53+'QLD-1'!H53+'NSW-2'!H53+'VIC-2'!H53+'QLD-2'!H53+'SA-1'!H53+'WA-1'!H53+'IDC-NSW'!H53+'IDC-VIC'!H53 | I53: ='NSW-1'!I53+'VIC-1'!I53+'QLD-1'!I53+'NSW-2'!I53+'VIC-2'!I53+'QLD-2'!I53+'SA-1'!I53+'WA-1'!I53+'IDC-NSW'!I53+'IDC-VIC'!I53 | J53: ='NSW-1'!J53+'VIC-1'!J53+'QLD-1'!J53+'NSW-2'!J53+'VIC-2'!J53+'QLD-2'!J53+'SA-1'!J53+'WA-1'!J53+'IDC-NSW'!J53+'IDC-VIC'!J53 | K53: =IFERROR(F53/G53,0) | L53: =IFERROR(H53/G53,0) | M53: =IFERROR(J53/F53,0) | N53: =IFERROR(J53/E53,0) | O53: =IFERROR(I53/J53,0) | R53: =Inputs!$A$41 | S53: =IFERROR(SUMIFS('QLD-2'!$F$15:$F$62,'QLD-2'!$B$15:$B$62,2025)/SUMIFS('QLD-2'!$G$15:$G$62,'QLD-2'!$B$15:$B$62,2025),0) | T53: =IFERROR(SUMIFS('QLD-2'!$F$15:$F$62,'QLD-2'!$B$15:$B$62,2026)/SUMIFS('QLD-2'!$G$15:$G$62,'QLD-2'!$B$15:$B$62,2026),0) | U53: =IFERROR(SUMIFS('QLD-2'!$F$15:$F$62,'QLD-2'!$B$15:$B$62,2027)/SUMIFS('QLD-2'!$G$15:$G$62,'QLD-2'!$B$15:$B$62,2027),0) | V53: =IFERROR(SUMIFS('QLD-2'!$F$15:$F$62,'QLD-2'!$B$15:$B$62,2028)/SUMIFS('QLD-2'!$G$15:$G$62,'QLD-2'!$B$15:$B$62,2028),0)
A54: 46844 | B54: =YEAR(A54) | C54: =MONTH(A54) | D54: =IF(A54<=LastActual,"Actual","Forecast") | E54: ='NSW-1'!E54+'VIC-1'!E54+'QLD-1'!E54+'NSW-2'!E54+'VIC-2'!E54+'QLD-2'!E54+'SA-1'!E54+'WA-1'!E54 | F54: ='NSW-1'!F54+'VIC-1'!F54+'QLD-1'!F54+'NSW-2'!F54+'VIC-2'!F54+'QLD-2'!F54+'SA-1'!F54+'WA-1'!F54+'IDC-NSW'!F54+'IDC-VIC'!F54 | G54: ='NSW-1'!G54+'VIC-1'!G54+'QLD-1'!G54+'NSW-2'!G54+'VIC-2'!G54+'QLD-2'!G54+'SA-1'!G54+'WA-1'!G54+'IDC-NSW'!G54+'IDC-VIC'!G54 | H54: ='NSW-1'!H54+'VIC-1'!H54+'QLD-1'!H54+'NSW-2'!H54+'VIC-2'!H54+'QLD-2'!H54+'SA-1'!H54+'WA-1'!H54+'IDC-NSW'!H54+'IDC-VIC'!H54 | I54: ='NSW-1'!I54+'VIC-1'!I54+'QLD-1'!I54+'NSW-2'!I54+'VIC-2'!I54+'QLD-2'!I54+'SA-1'!I54+'WA-1'!I54+'IDC-NSW'!I54+'IDC-VIC'!I54 | J54: ='NSW-1'!J54+'VIC-1'!J54+'QLD-1'!J54+'NSW-2'!J54+'VIC-2'!J54+'QLD-2'!J54+'SA-1'!J54+'WA-1'!J54+'IDC-NSW'!J54+'IDC-VIC'!J54 | K54: =IFERROR(F54/G54,0) | L54: =IFERROR(H54/G54,0) | M54: =IFERROR(J54/F54,0) | N54: =IFERROR(J54/E54,0) | O54: =IFERROR(I54/J54,0) | R54: =Inputs!$A$42 | S54: =IFERROR(SUMIFS('SA-1'!$F$15:$F$62,'SA-1'!$B$15:$B$62,2025)/SUMIFS('SA-1'!$G$15:$G$62,'SA-1'!$B$15:$B$62,2025),0) | T54: =IFERROR(SUMIFS('SA-1'!$F$15:$F$62,'SA-1'!$B$15:$B$62,2026)/SUMIFS('SA-1'!$G$15:$G$62,'SA-1'!$B$15:$B$62,2026),0) | U54: =IFERROR(SUMIFS('SA-1'!$F$15:$F$62,'SA-1'!$B$15:$B$62,2027)/SUMIFS('SA-1'!$G$15:$G$62,'SA-1'!$B$15:$B$62,2027),0) | V54: =IFERROR(SUMIFS('SA-1'!$F$15:$F$62,'SA-1'!$B$15:$B$62,2028)/SUMIFS('SA-1'!$G$15:$G$62,'SA-1'!$B$15:$B$62,2028),0)
A55: 46874 | B55: =YEAR(A55) | C55: =MONTH(A55) | D55: =IF(A55<=LastActual,"Actual","Forecast") | E55: ='NSW-1'!E55+'VIC-1'!E55+'QLD-1'!E55+'NSW-2'!E55+'VIC-2'!E55+'QLD-2'!E55+'SA-1'!E55+'WA-1'!E55 | F55: ='NSW-1'!F55+'VIC-1'!F55+'QLD-1'!F55+'NSW-2'!F55+'VIC-2'!F55+'QLD-2'!F55+'SA-1'!F55+'WA-1'!F55+'IDC-NSW'!F55+'IDC-VIC'!F55 | G55: ='NSW-1'!G55+'VIC-1'!G55+'QLD-1'!G55+'NSW-2'!G55+'VIC-2'!G55+'QLD-2'!G55+'SA-1'!G55+'WA-1'!G55+'IDC-NSW'!G55+'IDC-VIC'!G55 | H55: ='NSW-1'!H55+'VIC-1'!H55+'QLD-1'!H55+'NSW-2'!H55+'VIC-2'!H55+'QLD-2'!H55+'SA-1'!H55+'WA-1'!H55+'IDC-NSW'!H55+'IDC-VIC'!H55 | I55: ='NSW-1'!I55+'VIC-1'!I55+'QLD-1'!I55+'NSW-2'!I55+'VIC-2'!I55+'QLD-2'!I55+'SA-1'!I55+'WA-1'!I55+'IDC-NSW'!I55+'IDC-VIC'!I55 | J55: ='NSW-1'!J55+'VIC-1'!J55+'QLD-1'!J55+'NSW-2'!J55+'VIC-2'!J55+'QLD-2'!J55+'SA-1'!J55+'WA-1'!J55+'IDC-NSW'!J55+'IDC-VIC'!J55 | K55: =IFERROR(F55/G55,0) | L55: =IFERROR(H55/G55,0) | M55: =IFERROR(J55/F55,0) | N55: =IFERROR(J55/E55,0) | O55: =IFERROR(I55/J55,0) | R55: =Inputs!$A$43 | S55: =IFERROR(SUMIFS('WA-1'!$F$15:$F$62,'WA-1'!$B$15:$B$62,2025)/SUMIFS('WA-1'!$G$15:$G$62,'WA-1'!$B$15:$B$62,2025),0) | T55: =IFERROR(SUMIFS('WA-1'!$F$15:$F$62,'WA-1'!$B$15:$B$62,2026)/SUMIFS('WA-1'!$G$15:$G$62,'WA-1'!$B$15:$B$62,2026),0) | U55: =IFERROR(SUMIFS('WA-1'!$F$15:$F$62,'WA-1'!$B$15:$B$62,2027)/SUMIFS('WA-1'!$G$15:$G$62,'WA-1'!$B$15:$B$62,2027),0) | V55: =IFERROR(SUMIFS('WA-1'!$F$15:$F$62,'WA-1'!$B$15:$B$62,2028)/SUMIFS('WA-1'!$G$15:$G$62,'WA-1'!$B$15:$B$62,2028),0)
A56: 46905 | B56: =YEAR(A56) | C56: =MONTH(A56) | D56: =IF(A56<=LastActual,"Actual","Forecast") | E56: ='NSW-1'!E56+'VIC-1'!E56+'QLD-1'!E56+'NSW-2'!E56+'VIC-2'!E56+'QLD-2'!E56+'SA-1'!E56+'WA-1'!E56 | F56: ='NSW-1'!F56+'VIC-1'!F56+'QLD-1'!F56+'NSW-2'!F56+'VIC-2'!F56+'QLD-2'!F56+'SA-1'!F56+'WA-1'!F56+'IDC-NSW'!F56+'IDC-VIC'!F56 | G56: ='NSW-1'!G56+'VIC-1'!G56+'QLD-1'!G56+'NSW-2'!G56+'VIC-2'!G56+'QLD-2'!G56+'SA-1'!G56+'WA-1'!G56+'IDC-NSW'!G56+'IDC-VIC'!G56 | H56: ='NSW-1'!H56+'VIC-1'!H56+'QLD-1'!H56+'NSW-2'!H56+'VIC-2'!H56+'QLD-2'!H56+'SA-1'!H56+'WA-1'!H56+'IDC-NSW'!H56+'IDC-VIC'!H56 | I56: ='NSW-1'!I56+'VIC-1'!I56+'QLD-1'!I56+'NSW-2'!I56+'VIC-2'!I56+'QLD-2'!I56+'SA-1'!I56+'WA-1'!I56+'IDC-NSW'!I56+'IDC-VIC'!I56 | J56: ='NSW-1'!J56+'VIC-1'!J56+'QLD-1'!J56+'NSW-2'!J56+'VIC-2'!J56+'QLD-2'!J56+'SA-1'!J56+'WA-1'!J56+'IDC-NSW'!J56+'IDC-VIC'!J56 | K56: =IFERROR(F56/G56,0) | L56: =IFERROR(H56/G56,0) | M56: =IFERROR(J56/F56,0) | N56: =IFERROR(J56/E56,0) | O56: =IFERROR(I56/J56,0) | R56: =Inputs!$A$44 | S56: =IFERROR(SUMIFS('IDC-NSW'!$F$15:$F$62,'IDC-NSW'!$B$15:$B$62,2025)/SUMIFS('IDC-NSW'!$G$15:$G$62,'IDC-NSW'!$B$15:$B$62,2025),0) | T56: =IFERROR(SUMIFS('IDC-NSW'!$F$15:$F$62,'IDC-NSW'!$B$15:$B$62,2026)/SUMIFS('IDC-NSW'!$G$15:$G$62,'IDC-NSW'!$B$15:$B$62,2026),0) | U56: =IFERROR(SUMIFS('IDC-NSW'!$F$15:$F$62,'IDC-NSW'!$B$15:$B$62,2027)/SUMIFS('IDC-NSW'!$G$15:$G$62,'IDC-NSW'!$B$15:$B$62,2027),0) | V56: =IFERROR(SUMIFS('IDC-NSW'!$F$15:$F$62,'IDC-NSW'!$B$15:$B$62,2028)/SUMIFS('IDC-NSW'!$G$15:$G$62,'IDC-NSW'!$B$15:$B$62,2028),0)
A57: 46935 | B57: =YEAR(A57) | C57: =MONTH(A57) | D57: =IF(A57<=LastActual,"Actual","Forecast") | E57: ='NSW-1'!E57+'VIC-1'!E57+'QLD-1'!E57+'NSW-2'!E57+'VIC-2'!E57+'QLD-2'!E57+'SA-1'!E57+'WA-1'!E57 | F57: ='NSW-1'!F57+'VIC-1'!F57+'QLD-1'!F57+'NSW-2'!F57+'VIC-2'!F57+'QLD-2'!F57+'SA-1'!F57+'WA-1'!F57+'IDC-NSW'!F57+'IDC-VIC'!F57 | G57: ='NSW-1'!G57+'VIC-1'!G57+'QLD-1'!G57+'NSW-2'!G57+'VIC-2'!G57+'QLD-2'!G57+'SA-1'!G57+'WA-1'!G57+'IDC-NSW'!G57+'IDC-VIC'!G57 | H57: ='NSW-1'!H57+'VIC-1'!H57+'QLD-1'!H57+'NSW-2'!H57+'VIC-2'!H57+'QLD-2'!H57+'SA-1'!H57+'WA-1'!H57+'IDC-NSW'!H57+'IDC-VIC'!H57 | I57: ='NSW-1'!I57+'VIC-1'!I57+'QLD-1'!I57+'NSW-2'!I57+'VIC-2'!I57+'QLD-2'!I57+'SA-1'!I57+'WA-1'!I57+'IDC-NSW'!I57+'IDC-VIC'!I57 | J57: ='NSW-1'!J57+'VIC-1'!J57+'QLD-1'!J57+'NSW-2'!J57+'VIC-2'!J57+'QLD-2'!J57+'SA-1'!J57+'WA-1'!J57+'IDC-NSW'!J57+'IDC-VIC'!J57 | K57: =IFERROR(F57/G57,0) | L57: =IFERROR(H57/G57,0) | M57: =IFERROR(J57/F57,0) | N57: =IFERROR(J57/E57,0) | O57: =IFERROR(I57/J57,0) | R57: =Inputs!$A$45 | S57: =IFERROR(SUMIFS('IDC-VIC'!$F$15:$F$62,'IDC-VIC'!$B$15:$B$62,2025)/SUMIFS('IDC-VIC'!$G$15:$G$62,'IDC-VIC'!$B$15:$B$62,2025),0) | T57: =IFERROR(SUMIFS('IDC-VIC'!$F$15:$F$62,'IDC-VIC'!$B$15:$B$62,2026)/SUMIFS('IDC-VIC'!$G$15:$G$62,'IDC-VIC'!$B$15:$B$62,2026),0) | U57: =IFERROR(SUMIFS('IDC-VIC'!$F$15:$F$62,'IDC-VIC'!$B$15:$B$62,2027)/SUMIFS('IDC-VIC'!$G$15:$G$62,'IDC-VIC'!$B$15:$B$62,2027),0) | V57: =IFERROR(SUMIFS('IDC-VIC'!$F$15:$F$62,'IDC-VIC'!$B$15:$B$62,2028)/SUMIFS('IDC-VIC'!$G$15:$G$62,'IDC-VIC'!$B$15:$B$62,2028),0)
A58: 46966 | B58: =YEAR(A58) | C58: =MONTH(A58) | D58: =IF(A58<=LastActual,"Actual","Forecast") | E58: ='NSW-1'!E58+'VIC-1'!E58+'QLD-1'!E58+'NSW-2'!E58+'VIC-2'!E58+'QLD-2'!E58+'SA-1'!E58+'WA-1'!E58 | F58: ='NSW-1'!F58+'VIC-1'!F58+'QLD-1'!F58+'NSW-2'!F58+'VIC-2'!F58+'QLD-2'!F58+'SA-1'!F58+'WA-1'!F58+'IDC-NSW'!F58+'IDC-VIC'!F58 | G58: ='NSW-1'!G58+'VIC-1'!G58+'QLD-1'!G58+'NSW-2'!G58+'VIC-2'!G58+'QLD-2'!G58+'SA-1'!G58+'WA-1'!G58+'IDC-NSW'!G58+'IDC-VIC'!G58 | H58: ='NSW-1'!H58+'VIC-1'!H58+'QLD-1'!H58+'NSW-2'!H58+'VIC-2'!H58+'QLD-2'!H58+'SA-1'!H58+'WA-1'!H58+'IDC-NSW'!H58+'IDC-VIC'!H58 | I58: ='NSW-1'!I58+'VIC-1'!I58+'QLD-1'!I58+'NSW-2'!I58+'VIC-2'!I58+'QLD-2'!I58+'SA-1'!I58+'WA-1'!I58+'IDC-NSW'!I58+'IDC-VIC'!I58 | J58: ='NSW-1'!J58+'VIC-1'!J58+'QLD-1'!J58+'NSW-2'!J58+'VIC-2'!J58+'QLD-2'!J58+'SA-1'!J58+'WA-1'!J58+'IDC-NSW'!J58+'IDC-VIC'!J58 | K58: =IFERROR(F58/G58,0) | L58: =IFERROR(H58/G58,0) | M58: =IFERROR(J58/F58,0) | N58: =IFERROR(J58/E58,0) | O58: =IFERROR(I58/J58,0)
A59: 46997 | B59: =YEAR(A59) | C59: =MONTH(A59) | D59: =IF(A59<=LastActual,"Actual","Forecast") | E59: ='NSW-1'!E59+'VIC-1'!E59+'QLD-1'!E59+'NSW-2'!E59+'VIC-2'!E59+'QLD-2'!E59+'SA-1'!E59+'WA-1'!E59 | F59: ='NSW-1'!F59+'VIC-1'!F59+'QLD-1'!F59+'NSW-2'!F59+'VIC-2'!F59+'QLD-2'!F59+'SA-1'!F59+'WA-1'!F59+'IDC-NSW'!F59+'IDC-VIC'!F59 | G59: ='NSW-1'!G59+'VIC-1'!G59+'QLD-1'!G59+'NSW-2'!G59+'VIC-2'!G59+'QLD-2'!G59+'SA-1'!G59+'WA-1'!G59+'IDC-NSW'!G59+'IDC-VIC'!G59 | H59: ='NSW-1'!H59+'VIC-1'!H59+'QLD-1'!H59+'NSW-2'!H59+'VIC-2'!H59+'QLD-2'!H59+'SA-1'!H59+'WA-1'!H59+'IDC-NSW'!H59+'IDC-VIC'!H59 | I59: ='NSW-1'!I59+'VIC-1'!I59+'QLD-1'!I59+'NSW-2'!I59+'VIC-2'!I59+'QLD-2'!I59+'SA-1'!I59+'WA-1'!I59+'IDC-NSW'!I59+'IDC-VIC'!I59 | J59: ='NSW-1'!J59+'VIC-1'!J59+'QLD-1'!J59+'NSW-2'!J59+'VIC-2'!J59+'QLD-2'!J59+'SA-1'!J59+'WA-1'!J59+'IDC-NSW'!J59+'IDC-VIC'!J59 | K59: =IFERROR(F59/G59,0) | L59: =IFERROR(H59/G59,0) | M59: =IFERROR(J59/F59,0) | N59: =IFERROR(J59/E59,0) | O59: =IFERROR(I59/J59,0)
A60: 47027 | B60: =YEAR(A60) | C60: =MONTH(A60) | D60: =IF(A60<=LastActual,"Actual","Forecast") | E60: ='NSW-1'!E60+'VIC-1'!E60+'QLD-1'!E60+'NSW-2'!E60+'VIC-2'!E60+'QLD-2'!E60+'SA-1'!E60+'WA-1'!E60 | F60: ='NSW-1'!F60+'VIC-1'!F60+'QLD-1'!F60+'NSW-2'!F60+'VIC-2'!F60+'QLD-2'!F60+'SA-1'!F60+'WA-1'!F60+'IDC-NSW'!F60+'IDC-VIC'!F60 | G60: ='NSW-1'!G60+'VIC-1'!G60+'QLD-1'!G60+'NSW-2'!G60+'VIC-2'!G60+'QLD-2'!G60+'SA-1'!G60+'WA-1'!G60+'IDC-NSW'!G60+'IDC-VIC'!G60 | H60: ='NSW-1'!H60+'VIC-1'!H60+'QLD-1'!H60+'NSW-2'!H60+'VIC-2'!H60+'QLD-2'!H60+'SA-1'!H60+'WA-1'!H60+'IDC-NSW'!H60+'IDC-VIC'!H60 | I60: ='NSW-1'!I60+'VIC-1'!I60+'QLD-1'!I60+'NSW-2'!I60+'VIC-2'!I60+'QLD-2'!I60+'SA-1'!I60+'WA-1'!I60+'IDC-NSW'!I60+'IDC-VIC'!I60 | J60: ='NSW-1'!J60+'VIC-1'!J60+'QLD-1'!J60+'NSW-2'!J60+'VIC-2'!J60+'QLD-2'!J60+'SA-1'!J60+'WA-1'!J60+'IDC-NSW'!J60+'IDC-VIC'!J60 | K60: =IFERROR(F60/G60,0) | L60: =IFERROR(H60/G60,0) | M60: =IFERROR(J60/F60,0) | N60: =IFERROR(J60/E60,0) | O60: =IFERROR(I60/J60,0) | R60: Cost per case ($, total payroll)
A61: 47058 | B61: =YEAR(A61) | C61: =MONTH(A61) | D61: =IF(A61<=LastActual,"Actual","Forecast") | E61: ='NSW-1'!E61+'VIC-1'!E61+'QLD-1'!E61+'NSW-2'!E61+'VIC-2'!E61+'QLD-2'!E61+'SA-1'!E61+'WA-1'!E61 | F61: ='NSW-1'!F61+'VIC-1'!F61+'QLD-1'!F61+'NSW-2'!F61+'VIC-2'!F61+'QLD-2'!F61+'SA-1'!F61+'WA-1'!F61+'IDC-NSW'!F61+'IDC-VIC'!F61 | G61: ='NSW-1'!G61+'VIC-1'!G61+'QLD-1'!G61+'NSW-2'!G61+'VIC-2'!G61+'QLD-2'!G61+'SA-1'!G61+'WA-1'!G61+'IDC-NSW'!G61+'IDC-VIC'!G61 | H61: ='NSW-1'!H61+'VIC-1'!H61+'QLD-1'!H61+'NSW-2'!H61+'VIC-2'!H61+'QLD-2'!H61+'SA-1'!H61+'WA-1'!H61+'IDC-NSW'!H61+'IDC-VIC'!H61 | I61: ='NSW-1'!I61+'VIC-1'!I61+'QLD-1'!I61+'NSW-2'!I61+'VIC-2'!I61+'QLD-2'!I61+'SA-1'!I61+'WA-1'!I61+'IDC-NSW'!I61+'IDC-VIC'!I61 | J61: ='NSW-1'!J61+'VIC-1'!J61+'QLD-1'!J61+'NSW-2'!J61+'VIC-2'!J61+'QLD-2'!J61+'SA-1'!J61+'WA-1'!J61+'IDC-NSW'!J61+'IDC-VIC'!J61 | K61: =IFERROR(F61/G61,0) | L61: =IFERROR(H61/G61,0) | M61: =IFERROR(J61/F61,0) | N61: =IFERROR(J61/E61,0) | O61: =IFERROR(I61/J61,0) | R61: Site | S61: FY2025 | T61: FY2026 | U61: FY2027 | V61: FY2028
A62: 47088 | B62: =YEAR(A62) | C62: =MONTH(A62) | D62: =IF(A62<=LastActual,"Actual","Forecast") | E62: ='NSW-1'!E62+'VIC-1'!E62+'QLD-1'!E62+'NSW-2'!E62+'VIC-2'!E62+'QLD-2'!E62+'SA-1'!E62+'WA-1'!E62 | F62: ='NSW-1'!F62+'VIC-1'!F62+'QLD-1'!F62+'NSW-2'!F62+'VIC-2'!F62+'QLD-2'!F62+'SA-1'!F62+'WA-1'!F62+'IDC-NSW'!F62+'IDC-VIC'!F62 | G62: ='NSW-1'!G62+'VIC-1'!G62+'QLD-1'!G62+'NSW-2'!G62+'VIC-2'!G62+'QLD-2'!G62+'SA-1'!G62+'WA-1'!G62+'IDC-NSW'!G62+'IDC-VIC'!G62 | H62: ='NSW-1'!H62+'VIC-1'!H62+'QLD-1'!H62+'NSW-2'!H62+'VIC-2'!H62+'QLD-2'!H62+'SA-1'!H62+'WA-1'!H62+'IDC-NSW'!H62+'IDC-VIC'!H62 | I62: ='NSW-1'!I62+'VIC-1'!I62+'QLD-1'!I62+'NSW-2'!I62+'VIC-2'!I62+'QLD-2'!I62+'SA-1'!I62+'WA-1'!I62+'IDC-NSW'!I62+'IDC-VIC'!I62 | J62: ='NSW-1'!J62+'VIC-1'!J62+'QLD-1'!J62+'NSW-2'!J62+'VIC-2'!J62+'QLD-2'!J62+'SA-1'!J62+'WA-1'!J62+'IDC-NSW'!J62+'IDC-VIC'!J62 | K62: =IFERROR(F62/G62,0) | L62: =IFERROR(H62/G62,0) | M62: =IFERROR(J62/F62,0) | N62: =IFERROR(J62/E62,0) | O62: =IFERROR(I62/J62,0) | R62: =Inputs!$A$36 | S62: =IFERROR(SUMIFS('NSW-1'!$J$15:$J$62,'NSW-1'!$B$15:$B$62,2025)/SUMIFS('NSW-1'!$F$15:$F$62,'NSW-1'!$B$15:$B$62,2025),0) | T62: =IFERROR(SUMIFS('NSW-1'!$J$15:$J$62,'NSW-1'!$B$15:$B$62,2026)/SUMIFS('NSW-1'!$F$15:$F$62,'NSW-1'!$B$15:$B$62,2026),0) | U62: =IFERROR(SUMIFS('NSW-1'!$J$15:$J$62,'NSW-1'!$B$15:$B$62,2027)/SUMIFS('NSW-1'!$F$15:$F$62,'NSW-1'!$B$15:$B$62,2027),0) | V62: =IFERROR(SUMIFS('NSW-1'!$J$15:$J$62,'NSW-1'!$B$15:$B$62,2028)/SUMIFS('NSW-1'!$F$15:$F$62,'NSW-1'!$B$15:$B$62,2028),0)
R63: =Inputs!$A$37 | S63: =IFERROR(SUMIFS('VIC-1'!$J$15:$J$62,'VIC-1'!$B$15:$B$62,2025)/SUMIFS('VIC-1'!$F$15:$F$62,'VIC-1'!$B$15:$B$62,2025),0) | T63: =IFERROR(SUMIFS('VIC-1'!$J$15:$J$62,'VIC-1'!$B$15:$B$62,2026)/SUMIFS('VIC-1'!$F$15:$F$62,'VIC-1'!$B$15:$B$62,2026),0) | U63: =IFERROR(SUMIFS('VIC-1'!$J$15:$J$62,'VIC-1'!$B$15:$B$62,2027)/SUMIFS('VIC-1'!$F$15:$F$62,'VIC-1'!$B$15:$B$62,2027),0) | V63: =IFERROR(SUMIFS('VIC-1'!$J$15:$J$62,'VIC-1'!$B$15:$B$62,2028)/SUMIFS('VIC-1'!$F$15:$F$62,'VIC-1'!$B$15:$B$62,2028),0)
R64: =Inputs!$A$38 | S64: =IFERROR(SUMIFS('QLD-1'!$J$15:$J$62,'QLD-1'!$B$15:$B$62,2025)/SUMIFS('QLD-1'!$F$15:$F$62,'QLD-1'!$B$15:$B$62,2025),0) | T64: =IFERROR(SUMIFS('QLD-1'!$J$15:$J$62,'QLD-1'!$B$15:$B$62,2026)/SUMIFS('QLD-1'!$F$15:$F$62,'QLD-1'!$B$15:$B$62,2026),0) | U64: =IFERROR(SUMIFS('QLD-1'!$J$15:$J$62,'QLD-1'!$B$15:$B$62,2027)/SUMIFS('QLD-1'!$F$15:$F$62,'QLD-1'!$B$15:$B$62,2027),0) | V64: =IFERROR(SUMIFS('QLD-1'!$J$15:$J$62,'QLD-1'!$B$15:$B$62,2028)/SUMIFS('QLD-1'!$F$15:$F$62,'QLD-1'!$B$15:$B$62,2028),0)
R65: =Inputs!$A$39 | S65: =IFERROR(SUMIFS('NSW-2'!$J$15:$J$62,'NSW-2'!$B$15:$B$62,2025)/SUMIFS('NSW-2'!$F$15:$F$62,'NSW-2'!$B$15:$B$62,2025),0) | T65: =IFERROR(SUMIFS('NSW-2'!$J$15:$J$62,'NSW-2'!$B$15:$B$62,2026)/SUMIFS('NSW-2'!$F$15:$F$62,'NSW-2'!$B$15:$B$62,2026),0) | U65: =IFERROR(SUMIFS('NSW-2'!$J$15:$J$62,'NSW-2'!$B$15:$B$62,2027)/SUMIFS('NSW-2'!$F$15:$F$62,'NSW-2'!$B$15:$B$62,2027),0) | V65: =IFERROR(SUMIFS('NSW-2'!$J$15:$J$62,'NSW-2'!$B$15:$B$62,2028)/SUMIFS('NSW-2'!$F$15:$F$62,'NSW-2'!$B$15:$B$62,2028),0)
R66: =Inputs!$A$40 | S66: =IFERROR(SUMIFS('VIC-2'!$J$15:$J$62,'VIC-2'!$B$15:$B$62,2025)/SUMIFS('VIC-2'!$F$15:$F$62,'VIC-2'!$B$15:$B$62,2025),0) | T66: =IFERROR(SUMIFS('VIC-2'!$J$15:$J$62,'VIC-2'!$B$15:$B$62,2026)/SUMIFS('VIC-2'!$F$15:$F$62,'VIC-2'!$B$15:$B$62,2026),0) | U66: =IFERROR(SUMIFS('VIC-2'!$J$15:$J$62,'VIC-2'!$B$15:$B$62,2027)/SUMIFS('VIC-2'!$F$15:$F$62,'VIC-2'!$B$15:$B$62,2027),0) | V66: =IFERROR(SUMIFS('VIC-2'!$J$15:$J$62,'VIC-2'!$B$15:$B$62,2028)/SUMIFS('VIC-2'!$F$15:$F$62,'VIC-2'!$B$15:$B$62,2028),0)
R67: =Inputs!$A$41 | S67: =IFERROR(SUMIFS('QLD-2'!$J$15:$J$62,'QLD-2'!$B$15:$B$62,2025)/SUMIFS('QLD-2'!$F$15:$F$62,'QLD-2'!$B$15:$B$62,2025),0) | T67: =IFERROR(SUMIFS('QLD-2'!$J$15:$J$62,'QLD-2'!$B$15:$B$62,2026)/SUMIFS('QLD-2'!$F$15:$F$62,'QLD-2'!$B$15:$B$62,2026),0) | U67: =IFERROR(SUMIFS('QLD-2'!$J$15:$J$62,'QLD-2'!$B$15:$B$62,2027)/SUMIFS('QLD-2'!$F$15:$F$62,'QLD-2'!$B$15:$B$62,2027),0) | V67: =IFERROR(SUMIFS('QLD-2'!$J$15:$J$62,'QLD-2'!$B$15:$B$62,2028)/SUMIFS('QLD-2'!$F$15:$F$62,'QLD-2'!$B$15:$B$62,2028),0)
R68: =Inputs!$A$42 | S68: =IFERROR(SUMIFS('SA-1'!$J$15:$J$62,'SA-1'!$B$15:$B$62,2025)/SUMIFS('SA-1'!$F$15:$F$62,'SA-1'!$B$15:$B$62,2025),0) | T68: =IFERROR(SUMIFS('SA-1'!$J$15:$J$62,'SA-1'!$B$15:$B$62,2026)/SUMIFS('SA-1'!$F$15:$F$62,'SA-1'!$B$15:$B$62,2026),0) | U68: =IFERROR(SUMIFS('SA-1'!$J$15:$J$62,'SA-1'!$B$15:$B$62,2027)/SUMIFS('SA-1'!$F$15:$F$62,'SA-1'!$B$15:$B$62,2027),0) | V68: =IFERROR(SUMIFS('SA-1'!$J$15:$J$62,'SA-1'!$B$15:$B$62,2028)/SUMIFS('SA-1'!$F$15:$F$62,'SA-1'!$B$15:$B$62,2028),0)
R69: =Inputs!$A$43 | S69: =IFERROR(SUMIFS('WA-1'!$J$15:$J$62,'WA-1'!$B$15:$B$62,2025)/SUMIFS('WA-1'!$F$15:$F$62,'WA-1'!$B$15:$B$62,2025),0) | T69: =IFERROR(SUMIFS('WA-1'!$J$15:$J$62,'WA-1'!$B$15:$B$62,2026)/SUMIFS('WA-1'!$F$15:$F$62,'WA-1'!$B$15:$B$62,2026),0) | U69: =IFERROR(SUMIFS('WA-1'!$J$15:$J$62,'WA-1'!$B$15:$B$62,2027)/SUMIFS('WA-1'!$F$15:$F$62,'WA-1'!$B$15:$B$62,2027),0) | V69: =IFERROR(SUMIFS('WA-1'!$J$15:$J$62,'WA-1'!$B$15:$B$62,2028)/SUMIFS('WA-1'!$F$15:$F$62,'WA-1'!$B$15:$B$62,2028),0)
R70: =Inputs!$A$44 | S70: =IFERROR(SUMIFS('IDC-NSW'!$J$15:$J$62,'IDC-NSW'!$B$15:$B$62,2025)/SUMIFS('IDC-NSW'!$F$15:$F$62,'IDC-NSW'!$B$15:$B$62,2025),0) | T70: =IFERROR(SUMIFS('IDC-NSW'!$J$15:$J$62,'IDC-NSW'!$B$15:$B$62,2026)/SUMIFS('IDC-NSW'!$F$15:$F$62,'IDC-NSW'!$B$15:$B$62,2026),0) | U70: =IFERROR(SUMIFS('IDC-NSW'!$J$15:$J$62,'IDC-NSW'!$B$15:$B$62,2027)/SUMIFS('IDC-NSW'!$F$15:$F$62,'IDC-NSW'!$B$15:$B$62,2027),0) | V70: =IFERROR(SUMIFS('IDC-NSW'!$J$15:$J$62,'IDC-NSW'!$B$15:$B$62,2028)/SUMIFS('IDC-NSW'!$F$15:$F$62,'IDC-NSW'!$B$15:$B$62,2028),0)
R71: =Inputs!$A$45 | S71: =IFERROR(SUMIFS('IDC-VIC'!$J$15:$J$62,'IDC-VIC'!$B$15:$B$62,2025)/SUMIFS('IDC-VIC'!$F$15:$F$62,'IDC-VIC'!$B$15:$B$62,2025),0) | T71: =IFERROR(SUMIFS('IDC-VIC'!$J$15:$J$62,'IDC-VIC'!$B$15:$B$62,2026)/SUMIFS('IDC-VIC'!$F$15:$F$62,'IDC-VIC'!$B$15:$B$62,2026),0) | U71: =IFERROR(SUMIFS('IDC-VIC'!$J$15:$J$62,'IDC-VIC'!$B$15:$B$62,2027)/SUMIFS('IDC-VIC'!$F$15:$F$62,'IDC-VIC'!$B$15:$B$62,2027),0) | V71: =IFERROR(SUMIFS('IDC-VIC'!$J$15:$J$62,'IDC-VIC'!$B$15:$B$62,2028)/SUMIFS('IDC-VIC'!$F$15:$F$62,'IDC-VIC'!$B$15:$B$62,2028),0)

Sheet NSW-1
A1: =$B$2&" | Region | NSW"
A2: Code | B2: =Inputs!$A$36 | C2: State | D2: NSW
A5: FY | D5: Status | E5: Sales | F5: Cases picked | G5: WH hours worked | H5: Staff payroll | I5: Leadership payroll | J5: Total payroll | K5: CPLH (cases / hr) | L5: Cost per hour (staff) | M5: Cost per case (total payroll) | N5: Total payroll % sales | O5: Leadership % of total payroll
A6: 2025 | D6: =IF(DATE(A6,12,1)<=LastActual,"Actual",IF(DATE(A6,1,1)>LastActual,"Forecast","Blended")) | E6: =SUMIFS($E$15:$E$62,$B$15:$B$62,$A6) | F6: =SUMIFS($F$15:$F$62,$B$15:$B$62,$A6) | G6: =SUMIFS($G$15:$G$62,$B$15:$B$62,$A6) | H6: =SUMIFS($H$15:$H$62,$B$15:$B$62,$A6) | I6: =SUMIFS($I$15:$I$62,$B$15:$B$62,$A6) | J6: =SUMIFS($J$15:$J$62,$B$15:$B$62,$A6) | K6: =IFERROR(F6/G6,0) | L6: =IFERROR(H6/G6,0) | M6: =IFERROR(J6/F6,0) | N6: =IFERROR(J6/E6,0) | O6: =IFERROR(I6/J6,0)
A7: 2026 | D7: =IF(DATE(A7,12,1)<=LastActual,"Actual",IF(DATE(A7,1,1)>LastActual,"Forecast","Blended")) | E7: =SUMIFS($E$15:$E$62,$B$15:$B$62,$A7) | F7: =SUMIFS($F$15:$F$62,$B$15:$B$62,$A7) | G7: =SUMIFS($G$15:$G$62,$B$15:$B$62,$A7) | H7: =SUMIFS($H$15:$H$62,$B$15:$B$62,$A7) | I7: =SUMIFS($I$15:$I$62,$B$15:$B$62,$A7) | J7: =SUMIFS($J$15:$J$62,$B$15:$B$62,$A7) | K7: =IFERROR(F7/G7,0) | L7: =IFERROR(H7/G7,0) | M7: =IFERROR(J7/F7,0) | N7: =IFERROR(J7/E7,0) | O7: =IFERROR(I7/J7,0)
A8: 2027 | D8: =IF(DATE(A8,12,1)<=LastActual,"Actual",IF(DATE(A8,1,1)>LastActual,"Forecast","Blended")) | E8: =SUMIFS($E$15:$E$62,$B$15:$B$62,$A8) | F8: =SUMIFS($F$15:$F$62,$B$15:$B$62,$A8) | G8: =SUMIFS($G$15:$G$62,$B$15:$B$62,$A8) | H8: =SUMIFS($H$15:$H$62,$B$15:$B$62,$A8) | I8: =SUMIFS($I$15:$I$62,$B$15:$B$62,$A8) | J8: =SUMIFS($J$15:$J$62,$B$15:$B$62,$A8) | K8: =IFERROR(F8/G8,0) | L8: =IFERROR(H8/G8,0) | M8: =IFERROR(J8/F8,0) | N8: =IFERROR(J8/E8,0) | O8: =IFERROR(I8/J8,0)
A9: 2028 | D9: =IF(DATE(A9,12,1)<=LastActual,"Actual",IF(DATE(A9,1,1)>LastActual,"Forecast","Blended")) | E9: =SUMIFS($E$15:$E$62,$B$15:$B$62,$A9) | F9: =SUMIFS($F$15:$F$62,$B$15:$B$62,$A9) | G9: =SUMIFS($G$15:$G$62,$B$15:$B$62,$A9) | H9: =SUMIFS($H$15:$H$62,$B$15:$B$62,$A9) | I9: =SUMIFS($I$15:$I$62,$B$15:$B$62,$A9) | J9: =SUMIFS($J$15:$J$62,$B$15:$B$62,$A9) | K9: =IFERROR(F9/G9,0) | L9: =IFERROR(H9/G9,0) | M9: =IFERROR(J9/F9,0) | N9: =IFERROR(J9/E9,0) | O9: =IFERROR(I9/J9,0)
E12: Drivers | K12: Metrics | R12: Helper calculations (actuals, plan, same-month-last-year rates)
A13: Month | B13: Year | C13: Mth | D13: Status | E13: Sales | F13: Cases picked | G13: WH hours worked | H13: Staff payroll | I13: Leadership payroll | J13: Total payroll | K13: CPLH (cases / hr) | L13: Cost per hour (staff) | M13: Cost per case (total payroll) | N13: Total payroll % sales | O13: Leadership % of total payroll | R13: Act sales | S13: Act cases | T13: Act hours | U13: Act staff $ | V13: Act leadership $ | W13: Plan sales | X13: Plan payroll % | Y13: Volume driver sales | Z13: PH factor | AA13: Wage index | AB13: Cases per $ (actual, else same month LY) | AC13: Cost per hour ex PH & wage (actual, else same month LY) | AD13: Leadership share of total payroll (actual, else same month LY) | AE13: Fcst cost per hour (AC x PH x wage) | AF13: LY CPLH (same month) | AG13: Fcst CPLH vs LY
E14: $m | F14: m | G14: # | H14: $m | I14: $m | J14: $m | K14: # | L14: $ | M14: $ | N14: % | O14: %
A15: 45658 | B15: =YEAR(A15) | C15: =MONTH(A15) | D15: =IF(A15<=LastActual,"Actual","Forecast") | E15: =IF($D15="Actual",R15,W15) | F15: =IF($D15="Actual",S15,Cases_Forecast!AJ8) | G15: =IF($D15="Actual",T15,IFERROR(H15/AE15,0)) | H15: =IF($D15="Actual",U15,J15-I15) | I15: =IF($D15="Actual",V15,IFERROR(J15*AD15,0)) | J15: =IF($D15="Actual",U15+V15,E15*X15) | K15: =IFERROR(F15/G15,0) | L15: =IFERROR(H15/G15,0) | M15: =IFERROR(J15/F15,0) | N15: =IFERROR(J15/E15,0) | O15: =IFERROR(I15/J15,0) | R15: =IF($D15="Actual",SUMIFS(Data_Actuals!$C$2:$C$5000,Data_Actuals!$A$2:$A$5000,$A15,Data_Actuals!$B$2:$B$5000,$B$2),"") | S15: =IF($D15="Actual",SUMIFS(Data_Actuals!$D$2:$D$5000,Data_Actuals!$A$2:$A$5000,$A15,Data_Actuals!$B$2:$B$5000,$B$2),"") | T15: =IF($D15="Actual",SUMIFS(Data_Actuals!$E$2:$E$5000,Data_Actuals!$A$2:$A$5000,$A15,Data_Actuals!$B$2:$B$5000,$B$2),"") | U15: =IF($D15="Actual",SUMIFS(Data_Actuals!$F$2:$F$5000,Data_Actuals!$A$2:$A$5000,$A15,Data_Actuals!$B$2:$B$5000,$B$2),"") | V15: =IF($D15="Actual",SUMIFS(Data_Actuals!$G$2:$G$5000,Data_Actuals!$A$2:$A$5000,$A15,Data_Actuals!$B$2:$B$5000,$B$2),"") | W15: =SUMIFS(Plan_Inputs!$C$2:$C$5000,Plan_Inputs!$A$2:$A$5000,$A15,Plan_Inputs!$B$2:$B$5000,$B$2) | X15: =SUMIFS(Plan_Inputs!$D$2:$D$5000,Plan_Inputs!$A$2:$A$5000,$A15,Plan_Inputs!$B$2:$B$5000,$B$2) | Y15: =E15 | Z15: =INDEX(Calendar!$H$5:$L$52,MATCH($A15,Calendar!$A$5:$A$52,0),MATCH($D$2,Calendar!$H$4:$L$4,0)) | AA15: =INDEX(Calendar!$M$5:$M$52,MATCH($A15,Calendar!$A$5:$A$52,0)) | AB15: =IF($D15="Actual",IFERROR(S15/Y15,""),"") | AC15: =IF($D15="Actual",IFERROR(U15/T15/Z15/AA15,""),"") | AD15: =IF($D15="Actual",IFERROR(V15/(U15+V15),""),"") | AE15: =IFERROR(AC15*Z15*AA15,"") | AG15: =IF($D15="Forecast",IFERROR(K15/AF15-1,""),"")
A16: 45689 | B16: =YEAR(A16) | C16: =MONTH(A16) | D16: =IF(A16<=LastActual,"Actual","Forecast") | E16: =IF($D16="Actual",R16,W16) | F16: =IF($D16="Actual",S16,Cases_Forecast!AJ9) | G16: =IF($D16="Actual",T16,IFERROR(H16/AE16,0)) | H16: =IF($D16="Actual",U16,J16-I16) | I16: =IF($D16="Actual",V16,IFERROR(J16*AD16,0)) | J16: =IF($D16="Actual",U16+V16,E16*X16) | K16: =IFERROR(F16/G16,0) | L16: =IFERROR(H16/G16,0) | M16: =IFERROR(J16/F16,0) | N16: =IFERROR(J16/E16,0) | O16: =IFERROR(I16/J16,0) | R16: =IF($D16="Actual",SUMIFS(Data_Actuals!$C$2:$C$5000,Data_Actuals!$A$2:$A$5000,$A16,Data_Actuals!$B$2:$B$5000,$B$2),"") | S16: =IF($D16="Actual",SUMIFS(Data_Actuals!$D$2:$D$5000,Data_Actuals!$A$2:$A$5000,$A16,Data_Actuals!$B$2:$B$5000,$B$2),"") | T16: =IF($D16="Actual",SUMIFS(Data_Actuals!$E$2:$E$5000,Data_Actuals!$A$2:$A$5000,$A16,Data_Actuals!$B$2:$B$5000,$B$2),"") | U16: =IF($D16="Actual",SUMIFS(Data_Actuals!$F$2:$F$5000,Data_Actuals!$A$2:$A$5000,$A16,Data_Actuals!$B$2:$B$5000,$B$2),"") | V16: =IF($D16="Actual",SUMIFS(Data_Actuals!$G$2:$G$5000,Data_Actuals!$A$2:$A$5000,$A16,Data_Actuals!$B$2:$B$5000,$B$2),"") | W16: =SUMIFS(Plan_Inputs!$C$2:$C$5000,Plan_Inputs!$A$2:$A$5000,$A16,Plan_Inputs!$B$2:$B$5000,$B$2) | X16: =SUMIFS(Plan_Inputs!$D$2:$D$5000,Plan_Inputs!$A$2:$A$5000,$A16,Plan_Inputs!$B$2:$B$5000,$B$2) | Y16: =E16 | Z16: =INDEX(Calendar!$H$5:$L$52,MATCH($A16,Calendar!$A$5:$A$52,0),MATCH($D$2,Calendar!$H$4:$L$4,0)) | AA16: =INDEX(Calendar!$M$5:$M$52,MATCH($A16,Calendar!$A$5:$A$52,0)) | AB16: =IF($D16="Actual",IFERROR(S16/Y16,""),"") | AC16: =IF($D16="Actual",IFERROR(U16/T16/Z16/AA16,""),"") | AD16: =IF($D16="Actual",IFERROR(V16/(U16+V16),""),"") | AE16: =IFERROR(AC16*Z16*AA16,"") | AG16: =IF($D16="Forecast",IFERROR(K16/AF16-1,""),"")
A17: 45717 | B17: =YEAR(A17) | C17: =MONTH(A17) | D17: =IF(A17<=LastActual,"Actual","Forecast") | E17: =IF($D17="Actual",R17,W17) | F17: =IF($D17="Actual",S17,Cases_Forecast!AJ10) | G17: =IF($D17="Actual",T17,IFERROR(H17/AE17,0)) | H17: =IF($D17="Actual",U17,J17-I17) | I17: =IF($D17="Actual",V17,IFERROR(J17*AD17,0)) | J17: =IF($D17="Actual",U17+V17,E17*X17) | K17: =IFERROR(F17/G17,0) | L17: =IFERROR(H17/G17,0) | M17: =IFERROR(J17/F17,0) | N17: =IFERROR(J17/E17,0) | O17: =IFERROR(I17/J17,0) | R17: =IF($D17="Actual",SUMIFS(Data_Actuals!$C$2:$C$5000,Data_Actuals!$A$2:$A$5000,$A17,Data_Actuals!$B$2:$B$5000,$B$2),"") | S17: =IF($D17="Actual",SUMIFS(Data_Actuals!$D$2:$D$5000,Data_Actuals!$A$2:$A$5000,$A17,Data_Actuals!$B$2:$B$5000,$B$2),"") | T17: =IF($D17="Actual",SUMIFS(Data_Actuals!$E$2:$E$5000,Data_Actuals!$A$2:$A$5000,$A17,Data_Actuals!$B$2:$B$5000,$B$2),"") | U17: =IF($D17="Actual",SUMIFS(Data_Actuals!$F$2:$F$5000,Data_Actuals!$A$2:$A$5000,$A17,Data_Actuals!$B$2:$B$5000,$B$2),"") | V17: =IF($D17="Actual",SUMIFS(Data_Actuals!$G$2:$G$5000,Data_Actuals!$A$2:$A$5000,$A17,Data_Actuals!$B$2:$B$5000,$B$2),"") | W17: =SUMIFS(Plan_Inputs!$C$2:$C$5000,Plan_Inputs!$A$2:$A$5000,$A17,Plan_Inputs!$B$2:$B$5000,$B$2) | X17: =SUMIFS(Plan_Inputs!$D$2:$D$5000,Plan_Inputs!$A$2:$A$5000,$A17,Plan_Inputs!$B$2:$B$5000,$B$2) | Y17: =E17 | Z17: =INDEX(Calendar!$H$5:$L$52,MATCH($A17,Calendar!$A$5:$A$52,0),MATCH($D$2,Calendar!$H$4:$L$4,0)) | AA17: =INDEX(Calendar!$M$5:$M$52,MATCH($A17,Calendar!$A$5:$A$52,0)) | AB17: =IF($D17="Actual",IFERROR(S17/Y17,""),"") | AC17: =IF($D17="Actual",IFERROR(U17/T17/Z17/AA17,""),"") | AD17: =IF($D17="Actual",IFERROR(V17/(U17+V17),""),"") | AE17: =IFERROR(AC17*Z17*AA17,"") | AG17: =IF($D17="Forecast",IFERROR(K17/AF17-1,""),"")
A18: 45748 | B18: =YEAR(A18) | C18: =MONTH(A18) | D18: =IF(A18<=LastActual,"Actual","Forecast") | E18: =IF($D18="Actual",R18,W18) | F18: =IF($D18="Actual",S18,Cases_Forecast!AJ11) | G18: =IF($D18="Actual",T18,IFERROR(H18/AE18,0)) | H18: =IF($D18="Actual",U18,J18-I18) | I18: =IF($D18="Actual",V18,IFERROR(J18*AD18,0)) | J18: =IF($D18="Actual",U18+V18,E18*X18) | K18: =IFERROR(F18/G18,0) | L18: =IFERROR(H18/G18,0) | M18: =IFERROR(J18/F18,0) | N18: =IFERROR(J18/E18,0) | O18: =IFERROR(I18/J18,0) | R18: =IF($D18="Actual",SUMIFS(Data_Actuals!$C$2:$C$5000,Data_Actuals!$A$2:$A$5000,$A18,Data_Actuals!$B$2:$B$5000,$B$2),"") | S18: =IF($D18="Actual",SUMIFS(Data_Actuals!$D$2:$D$5000,Data_Actuals!$A$2:$A$5000,$A18,Data_Actuals!$B$2:$B$5000,$B$2),"") | T18: =IF($D18="Actual",SUMIFS(Data_Actuals!$E$2:$E$5000,Data_Actuals!$A$2:$A$5000,$A18,Data_Actuals!$B$2:$B$5000,$B$2),"") | U18: =IF($D18="Actual",SUMIFS(Data_Actuals!$F$2:$F$5000,Data_Actuals!$A$2:$A$5000,$A18,Data_Actuals!$B$2:$B$5000,$B$2),"") | V18: =IF($D18="Actual",SUMIFS(Data_Actuals!$G$2:$G$5000,Data_Actuals!$A$2:$A$5000,$A18,Data_Actuals!$B$2:$B$5000,$B$2),"") | W18: =SUMIFS(Plan_Inputs!$C$2:$C$5000,Plan_Inputs!$A$2:$A$5000,$A18,Plan_Inputs!$B$2:$B$5000,$B$2) | X18: =SUMIFS(Plan_Inputs!$D$2:$D$5000,Plan_Inputs!$A$2:$A$5000,$A18,Plan_Inputs!$B$2:$B$5000,$B$2) | Y18: =E18 | Z18: =INDEX(Calendar!$H$5:$L$52,MATCH($A18,Calendar!$A$5:$A$52,0),MATCH($D$2,Calendar!$H$4:$L$4,0)) | AA18: =INDEX(Calendar!$M$5:$M$52,MATCH($A18,Calendar!$A$5:$A$52,0)) | AB18: =IF($D18="Actual",IFERROR(S18/Y18,""),"") | AC18: =IF($D18="Actual",IFERROR(U18/T18/Z18/AA18,""),"") | AD18: =IF($D18="Actual",IFERROR(V18/(U18+V18),""),"") | AE18: =IFERROR(AC18*Z18*AA18,"") | AG18: =IF($D18="Forecast",IFERROR(K18/AF18-1,""),"")
A19: 45778 | B19: =YEAR(A19) | C19: =MONTH(A19) | D19: =IF(A19<=LastActual,"Actual","Forecast") | E19: =IF($D19="Actual",R19,W19) | F19: =IF($D19="Actual",S19,Cases_Forecast!AJ12) | G19: =IF($D19="Actual",T19,IFERROR(H19/AE19,0)) | H19: =IF($D19="Actual",U19,J19-I19) | I19: =IF($D19="Actual",V19,IFERROR(J19*AD19,0)) | J19: =IF($D19="Actual",U19+V19,E19*X19) | K19: =IFERROR(F19/G19,0) | L19: =IFERROR(H19/G19,0) | M19: =IFERROR(J19/F19,0) | N19: =IFERROR(J19/E19,0) | O19: =IFERROR(I19/J19,0) | R19: =IF($D19="Actual",SUMIFS(Data_Actuals!$C$2:$C$5000,Data_Actuals!$A$2:$A$5000,$A19,Data_Actuals!$B$2:$B$5000,$B$2),"") | S19: =IF($D19="Actual",SUMIFS(Data_Actuals!$D$2:$D$5000,Data_Actuals!$A$2:$A$5000,$A19,Data_Actuals!$B$2:$B$5000,$B$2),"") | T19: =IF($D19="Actual",SUMIFS(Data_Actuals!$E$2:$E$5000,Data_Actuals!$A$2:$A$5000,$A19,Data_Actuals!$B$2:$B$5000,$B$2),"") | U19: =IF($D19="Actual",SUMIFS(Data_Actuals!$F$2:$F$5000,Data_Actuals!$A$2:$A$5000,$A19,Data_Actuals!$B$2:$B$5000,$B$2),"") | V19: =IF($D19="Actual",SUMIFS(Data_Actuals!$G$2:$G$5000,Data_Actuals!$A$2:$A$5000,$A19,Data_Actuals!$B$2:$B$5000,$B$2),"") | W19: =SUMIFS(Plan_Inputs!$C$2:$C$5000,Plan_Inputs!$A$2:$A$5000,$A19,Plan_Inputs!$B$2:$B$5000,$B$2) | X19: =SUMIFS(Plan_Inputs!$D$2:$D$5000,Plan_Inputs!$A$2:$A$5000,$A19,Plan_Inputs!$B$2:$B$5000,$B$2) | Y19: =E19 | Z19: =INDEX(Calendar!$H$5:$L$52,MATCH($A19,Calendar!$A$5:$A$52,0),MATCH($D$2,Calendar!$H$4:$L$4,0)) | AA19: =INDEX(Calendar!$M$5:$M$52,MATCH($A19,Calendar!$A$5:$A$52,0)) | AB19: =IF($D19="Actual",IFERROR(S19/Y19,""),"") | AC19: =IF($D19="Actual",IFERROR(U19/T19/Z19/AA19,""),"") | AD19: =IF($D19="Actual",IFERROR(V19/(U19+V19),""),"") | AE19: =IFERROR(AC19*Z19*AA19,"") | AG19: =IF($D19="Forecast",IFERROR(K19/AF19-1,""),"")
A20: 45809 | B20: =YEAR(A20) | C20: =MONTH(A20) | D20: =IF(A20<=LastActual,"Actual","Forecast") | E20: =IF($D20="Actual",R20,W20) | F20: =IF($D20="Actual",S20,Cases_Forecast!AJ13) | G20: =IF($D20="Actual",T20,IFERROR(H20/AE20,0)) | H20: =IF($D20="Actual",U20,J20-I20) | I20: =IF($D20="Actual",V20,IFERROR(J20*AD20,0)) | J20: =IF($D20="Actual",U20+V20,E20*X20) | K20: =IFERROR(F20/G20,0) | L20: =IFERROR(H20/G20,0) | M20: =IFERROR(J20/F20,0) | N20: =IFERROR(J20/E20,0) | O20: =IFERROR(I20/J20,0) | R20: =IF($D20="Actual",SUMIFS(Data_Actuals!$C$2:$C$5000,Data_Actuals!$A$2:$A$5000,$A20,Data_Actuals!$B$2:$B$5000,$B$2),"") | S20: =IF($D20="Actual",SUMIFS(Data_Actuals!$D$2:$D$5000,Data_Actuals!$A$2:$A$5000,$A20,Data_Actuals!$B$2:$B$5000,$B$2),"") | T20: =IF($D20="Actual",SUMIFS(Data_Actuals!$E$2:$E$5000,Data_Actuals!$A$2:$A$5000,$A20,Data_Actuals!$B$2:$B$5000,$B$2),"") | U20: =IF($D20="Actual",SUMIFS(Data_Actuals!$F$2:$F$5000,Data_Actuals!$A$2:$A$5000,$A20,Data_Actuals!$B$2:$B$5000,$B$2),"") | V20: =IF($D20="Actual",SUMIFS(Data_Actuals!$G$2:$G$5000,Data_Actuals!$A$2:$A$5000,$A20,Data_Actuals!$B$2:$B$5000,$B$2),"") | W20: =SUMIFS(Plan_Inputs!$C$2:$C$5000,Plan_Inputs!$A$2:$A$5000,$A20,Plan_Inputs!$B$2:$B$5000,$B$2) | X20: =SUMIFS(Plan_Inputs!$D$2:$D$5000,Plan_Inputs!$A$2:$A$5000,$A20,Plan_Inputs!$B$2:$B$5000,$B$2) | Y20: =E20 | Z20: =INDEX(Calendar!$H$5:$L$52,MATCH($A20,Calendar!$A$5:$A$52,0),MATCH($D$2,Calendar!$H$4:$L$4,0)) | AA20: =INDEX(Calendar!$M$5:$M$52,MATCH($A20,Calendar!$A$5:$A$52,0)) | AB20: =IF($D20="Actual",IFERROR(S20/Y20,""),"") | AC20: =IF($D20="Actual",IFERROR(U20/T20/Z20/AA20,""),"") | AD20: =IF($D20="Actual",IFERROR(V20/(U20+V20),""),"") | AE20: =IFERROR(AC20*Z20*AA20,"") | AG20: =IF($D20="Forecast",IFERROR(K20/AF20-1,""),"")
A21: 45839 | B21: =YEAR(A21) | C21: =MONTH(A21) | D21: =IF(A21<=LastActual,"Actual","Forecast") | E21: =IF($D21="Actual",R21,W21) | F21: =IF($D21="Actual",S21,Cases_Forecast!AJ14) | G21: =IF($D21="Actual",T21,IFERROR(H21/AE21,0)) | H21: =IF($D21="Actual",U21,J21-I21) | I21: =IF($D21="Actual",V21,IFERROR(J21*AD21,0)) | J21: =IF($D21="Actual",U21+V21,E21*X21) | K21: =IFERROR(F21/G21,0) | L21: =IFERROR(H21/G21,0) | M21: =IFERROR(J21/F21,0) | N21: =IFERROR(J21/E21,0) | O21: =IFERROR(I21/J21,0) | R21: =IF($D21="Actual",SUMIFS(Data_Actuals!$C$2:$C$5000,Data_Actuals!$A$2:$A$5000,$A21,Data_Actuals!$B$2:$B$5000,$B$2),"") | S21: =IF($D21="Actual",SUMIFS(Data_Actuals!$D$2:$D$5000,Data_Actuals!$A$2:$A$5000,$A21,Data_Actuals!$B$2:$B$5000,$B$2),"") | T21: =IF($D21="Actual",SUMIFS(Data_Actuals!$E$2:$E$5000,Data_Actuals!$A$2:$A$5000,$A21,Data_Actuals!$B$2:$B$5000,$B$2),"") | U21: =IF($D21="Actual",SUMIFS(Data_Actuals!$F$2:$F$5000,Data_Actuals!$A$2:$A$5000,$A21,Data_Actuals!$B$2:$B$5000,$B$2),"") | V21: =IF($D21="Actual",SUMIFS(Data_Actuals!$G$2:$G$5000,Data_Actuals!$A$2:$A$5000,$A21,Data_Actuals!$B$2:$B$5000,$B$2),"") | W21: =SUMIFS(Plan_Inputs!$C$2:$C$5000,Plan_Inputs!$A$2:$A$5000,$A21,Plan_Inputs!$B$2:$B$5000,$B$2) | X21: =SUMIFS(Plan_Inputs!$D$2:$D$5000,Plan_Inputs!$A$2:$A$5000,$A21,Plan_Inputs!$B$2:$B$5000,$B$2) | Y21: =E21 | Z21: =INDEX(Calendar!$H$5:$L$52,MATCH($A21,Calendar!$A$5:$A$52,0),MATCH($D$2,Calendar!$H$4:$L$4,0)) | AA21: =INDEX(Calendar!$M$5:$M$52,MATCH($A21,Calendar!$A$5:$A$52,0)) | AB21: =IF($D21="Actual",IFERROR(S21/Y21,""),"") | AC21: =IF($D21="Actual",IFERROR(U21/T21/Z21/AA21,""),"") | AD21: =IF($D21="Actual",IFERROR(V21/(U21+V21),""),"") | AE21: =IFERROR(AC21*Z21*AA21,"") | AG21: =IF($D21="Forecast",IFERROR(K21/AF21-1,""),"")
A22: 45870 | B22: =YEAR(A22) | C22: =MONTH(A22) | D22: =IF(A22<=LastActual,"Actual","Forecast") | E22: =IF($D22="Actual",R22,W22) | F22: =IF($D22="Actual",S22,Cases_Forecast!AJ15) | G22: =IF($D22="Actual",T22,IFERROR(H22/AE22,0)) | H22: =IF($D22="Actual",U22,J22-I22) | I22: =IF($D22="Actual",V22,IFERROR(J22*AD22,0)) | J22: =IF($D22="Actual",U22+V22,E22*X22) | K22: =IFERROR(F22/G22,0) | L22: =IFERROR(H22/G22,0) | M22: =IFERROR(J22/F22,0) | N22: =IFERROR(J22/E22,0) | O22: =IFERROR(I22/J22,0) | R22: =IF($D22="Actual",SUMIFS(Data_Actuals!$C$2:$C$5000,Data_Actuals!$A$2:$A$5000,$A22,Data_Actuals!$B$2:$B$5000,$B$2),"") | S22: =IF($D22="Actual",SUMIFS(Data_Actuals!$D$2:$D$5000,Data_Actuals!$A$2:$A$5000,$A22,Data_Actuals!$B$2:$B$5000,$B$2),"") | T22: =IF($D22="Actual",SUMIFS(Data_Actuals!$E$2:$E$5000,Data_Actuals!$A$2:$A$5000,$A22,Data_Actuals!$B$2:$B$5000,$B$2),"") | U22: =IF($D22="Actual",SUMIFS(Data_Actuals!$F$2:$F$5000,Data_Actuals!$A$2:$A$5000,$A22,Data_Actuals!$B$2:$B$5000,$B$2),"") | V22: =IF($D22="Actual",SUMIFS(Data_Actuals!$G$2:$G$5000,Data_Actuals!$A$2:$A$5000,$A22,Data_Actuals!$B$2:$B$5000,$B$2),"") | W22: =SUMIFS(Plan_Inputs!$C$2:$C$5000,Plan_Inputs!$A$2:$A$5000,$A22,Plan_Inputs!$B$2:$B$5000,$B$2) | X22: =SUMIFS(Plan_Inputs!$D$2:$D$5000,Plan_Inputs!$A$2:$A$5000,$A22,Plan_Inputs!$B$2:$B$5000,$B$2) | Y22: =E22 | Z22: =INDEX(Calendar!$H$5:$L$52,MATCH($A22,Calendar!$A$5:$A$52,0),MATCH($D$2,Calendar!$H$4:$L$4,0)) | AA22: =INDEX(Calendar!$M$5:$M$52,MATCH($A22,Calendar!$A$5:$A$52,0)) | AB22: =IF($D22="Actual",IFERROR(S22/Y22,""),"") | AC22: =IF($D22="Actual",IFERROR(U22/T22/Z22/AA22,""),"") | AD22: =IF($D22="Actual",IFERROR(V22/(U22+V22),""),"") | AE22: =IFERROR(AC22*Z22*AA22,"") | AG22: =IF($D22="Forecast",IFERROR(K22/AF22-1,""),"")
A23: 45901 | B23: =YEAR(A23) | C23: =MONTH(A23) | D23: =IF(A23<=LastActual,"Actual","Forecast") | E23: =IF($D23="Actual",R23,W23) | F23: =IF($D23="Actual",S23,Cases_Forecast!AJ16) | G23: =IF($D23="Actual",T23,IFERROR(H23/AE23,0)) | H23: =IF($D23="Actual",U23,J23-I23) | I23: =IF($D23="Actual",V23,IFERROR(J23*AD23,0)) | J23: =IF($D23="Actual",U23+V23,E23*X23) | K23: =IFERROR(F23/G23,0) | L23: =IFERROR(H23/G23,0) | M23: =IFERROR(J23/F23,0) | N23: =IFERROR(J23/E23,0) | O23: =IFERROR(I23/J23,0) | R23: =IF($D23="Actual",SUMIFS(Data_Actuals!$C$2:$C$5000,Data_Actuals!$A$2:$A$5000,$A23,Data_Actuals!$B$2:$B$5000,$B$2),"") | S23: =IF($D23="Actual",SUMIFS(Data_Actuals!$D$2:$D$5000,Data_Actuals!$A$2:$A$5000,$A23,Data_Actuals!$B$2:$B$5000,$B$2),"") | T23: =IF($D23="Actual",SUMIFS(Data_Actuals!$E$2:$E$5000,Data_Actuals!$A$2:$A$5000,$A23,Data_Actuals!$B$2:$B$5000,$B$2),"") | U23: =IF($D23="Actual",SUMIFS(Data_Actuals!$F$2:$F$5000,Data_Actuals!$A$2:$A$5000,$A23,Data_Actuals!$B$2:$B$5000,$B$2),"") | V23: =IF($D23="Actual",SUMIFS(Data_Actuals!$G$2:$G$5000,Data_Actuals!$A$2:$A$5000,$A23,Data_Actuals!$B$2:$B$5000,$B$2),"") | W23: =SUMIFS(Plan_Inputs!$C$2:$C$5000,Plan_Inputs!$A$2:$A$5000,$A23,Plan_Inputs!$B$2:$B$5000,$B$2) | X23: =SUMIFS(Plan_Inputs!$D$2:$D$5000,Plan_Inputs!$A$2:$A$5000,$A23,Plan_Inputs!$B$2:$B$5000,$B$2) | Y23: =E23 | Z23: =INDEX(Calendar!$H$5:$L$52,MATCH($A23,Calendar!$A$5:$A$52,0),MATCH($D$2,Calendar!$H$4:$L$4,0)) | AA23: =INDEX(Calendar!$M$5:$M$52,MATCH($A23,Calendar!$A$5:$A$52,0)) | AB23: =IF($D23="Actual",IFERROR(S23/Y23,""),"") | AC23: =IF($D23="Actual",IFERROR(U23/T23/Z23/AA23,""),"") | AD23: =IF($D23="Actual",IFERROR(V23/(U23+V23),""),"") | AE23: =IFERROR(AC23*Z23*AA23,"") | AG23: =IF($D23="Forecast",IFERROR(K23/AF23-1,""),"")
A24: 45931 | B24: =YEAR(A24) | C24: =MONTH(A24) | D24: =IF(A24<=LastActual,"Actual","Forecast") | E24: =IF($D24="Actual",R24,W24) | F24: =IF($D24="Actual",S24,Cases_Forecast!AJ17) | G24: =IF($D24="Actual",T24,IFERROR(H24/AE24,0)) | H24: =IF($D24="Actual",U24,J24-I24) | I24: =IF($D24="Actual",V24,IFERROR(J24*AD24,0)) | J24: =IF($D24="Actual",U24+V24,E24*X24) | K24: =IFERROR(F24/G24,0) | L24: =IFERROR(H24/G24,0) | M24: =IFERROR(J24/F24,0) | N24: =IFERROR(J24/E24,0) | O24: =IFERROR(I24/J24,0) | R24: =IF($D24="Actual",SUMIFS(Data_Actuals!$C$2:$C$5000,Data_Actuals!$A$2:$A$5000,$A24,Data_Actuals!$B$2:$B$5000,$B$2),"") | S24: =IF($D24="Actual",SUMIFS(Data_Actuals!$D$2:$D$5000,Data_Actuals!$A$2:$A$5000,$A24,Data_Actuals!$B$2:$B$5000,$B$2),"") | T24: =IF($D24="Actual",SUMIFS(Data_Actuals!$E$2:$E$5000,Data_Actuals!$A$2:$A$5000,$A24,Data_Actuals!$B$2:$B$5000,$B$2),"") | U24: =IF($D24="Actual",SUMIFS(Data_Actuals!$F$2:$F$5000,Data_Actuals!$A$2:$A$5000,$A24,Data_Actuals!$B$2:$B$5000,$B$2),"") | V24: =IF($D24="Actual",SUMIFS(Data_Actuals!$G$2:$G$5000,Data_Actuals!$A$2:$A$5000,$A24,Data_Actuals!$B$2:$B$5000,$B$2),"") | W24: =SUMIFS(Plan_Inputs!$C$2:$C$5000,Plan_Inputs!$A$2:$A$5000,$A24,Plan_Inputs!$B$2:$B$5000,$B$2) | X24: =SUMIFS(Plan_Inputs!$D$2:$D$5000,Plan_Inputs!$A$2:$A$5000,$A24,Plan_Inputs!$B$2:$B$5000,$B$2) | Y24: =E24 | Z24: =INDEX(Calendar!$H$5:$L$52,MATCH($A24,Calendar!$A$5:$A$52,0),MATCH($D$2,Calendar!$H$4:$L$4,0)) | AA24: =INDEX(Calendar!$M$5:$M$52,MATCH($A24,Calendar!$A$5:$A$52,0)) | AB24: =IF($D24="Actual",IFERROR(S24/Y24,""),"") | AC24: =IF($D24="Actual",IFERROR(U24/T24/Z24/AA24,""),"") | AD24: =IF($D24="Actual",IFERROR(V24/(U24+V24),""),"") | AE24: =IFERROR(AC24*Z24*AA24,"") | AG24: =IF($D24="Forecast",IFERROR(K24/AF24-1,""),"")
A25: 45962 | B25: =YEAR(A25) | C25: =MONTH(A25) | D25: =IF(A25<=LastActual,"Actual","Forecast") | E25: =IF($D25="Actual",R25,W25) | F25: =IF($D25="Actual",S25,Cases_Forecast!AJ18) | G25: =IF($D25="Actual",T25,IFERROR(H25/AE25,0)) | H25: =IF($D25="Actual",U25,J25-I25) | I25: =IF($D25="Actual",V25,IFERROR(J25*AD25,0)) | J25: =IF($D25="Actual",U25+V25,E25*X25) | K25: =IFERROR(F25/G25,0) | L25: =IFERROR(H25/G25,0) | M25: =IFERROR(J25/F25,0) | N25: =IFERROR(J25/E25,0) | O25: =IFERROR(I25/J25,0) | R25: =IF($D25="Actual",SUMIFS(Data_Actuals!$C$2:$C$5000,Data_Actuals!$A$2:$A$5000,$A25,Data_Actuals!$B$2:$B$5000,$B$2),"") | S25: =IF($D25="Actual",SUMIFS(Data_Actuals!$D$2:$D$5000,Data_Actuals!$A$2:$A$5000,$A25,Data_Actuals!$B$2:$B$5000,$B$2),"") | T25: =IF($D25="Actual",SUMIFS(Data_Actuals!$E$2:$E$5000,Data_Actuals!$A$2:$A$5000,$A25,Data_Actuals!$B$2:$B$5000,$B$2),"") | U25: =IF($D25="Actual",SUMIFS(Data_Actuals!$F$2:$F$5000,Data_Actuals!$A$2:$A$5000,$A25,Data_Actuals!$B$2:$B$5000,$B$2),"") | V25: =IF($D25="Actual",SUMIFS(Data_Actuals!$G$2:$G$5000,Data_Actuals!$A$2:$A$5000,$A25,Data_Actuals!$B$2:$B$5000,$B$2),"") | W25: =SUMIFS(Plan_Inputs!$C$2:$C$5000,Plan_Inputs!$A$2:$A$5000,$A25,Plan_Inputs!$B$2:$B$5000,$B$2) | X25: =SUMIFS(Plan_Inputs!$D$2:$D$5000,Plan_Inputs!$A$2:$A$5000,$A25,Plan_Inputs!$B$2:$B$5000,$B$2) | Y25: =E25 | Z25: =INDEX(Calendar!$H$5:$L$52,MATCH($A25,Calendar!$A$5:$A$52,0),MATCH($D$2,Calendar!$H$4:$L$4,0)) | AA25: =INDEX(Calendar!$M$5:$M$52,MATCH($A25,Calendar!$A$5:$A$52,0)) | AB25: =IF($D25="Actual",IFERROR(S25/Y25,""),"") | AC25: =IF($D25="Actual",IFERROR(U25/T25/Z25/AA25,""),"") | AD25: =IF($D25="Actual",IFERROR(V25/(U25+V25),""),"") | AE25: =IFERROR(AC25*Z25*AA25,"") | AG25: =IF($D25="Forecast",IFERROR(K25/AF25-1,""),"")
A26: 45992 | B26: =YEAR(A26) | C26: =MONTH(A26) | D26: =IF(A26<=LastActual,"Actual","Forecast") | E26: =IF($D26="Actual",R26,W26) | F26: =IF($D26="Actual",S26,Cases_Forecast!AJ19) | G26: =IF($D26="Actual",T26,IFERROR(H26/AE26,0)) | H26: =IF($D26="Actual",U26,J26-I26) | I26: =IF($D26="Actual",V26,IFERROR(J26*AD26,0)) | J26: =IF($D26="Actual",U26+V26,E26*X26) | K26: =IFERROR(F26/G26,0) | L26: =IFERROR(H26/G26,0) | M26: =IFERROR(J26/F26,0) | N26: =IFERROR(J26/E26,0) | O26: =IFERROR(I26/J26,0) | R26: =IF($D26="Actual",SUMIFS(Data_Actuals!$C$2:$C$5000,Data_Actuals!$A$2:$A$5000,$A26,Data_Actuals!$B$2:$B$5000,$B$2),"") | S26: =IF($D26="Actual",SUMIFS(Data_Actuals!$D$2:$D$5000,Data_Actuals!$A$2:$A$5000,$A26,Data_Actuals!$B$2:$B$5000,$B$2),"") | T26: =IF($D26="Actual",SUMIFS(Data_Actuals!$E$2:$E$5000,Data_Actuals!$A$2:$A$5000,$A26,Data_Actuals!$B$2:$B$5000,$B$2),"") | U26: =IF($D26="Actual",SUMIFS(Data_Actuals!$F$2:$F$5000,Data_Actuals!$A$2:$A$5000,$A26,Data_Actuals!$B$2:$B$5000,$B$2),"") | V26: =IF($D26="Actual",SUMIFS(Data_Actuals!$G$2:$G$5000,Data_Actuals!$A$2:$A$5000,$A26,Data_Actuals!$B$2:$B$5000,$B$2),"") | W26: =SUMIFS(Plan_Inputs!$C$2:$C$5000,Plan_Inputs!$A$2:$A$5000,$A26,Plan_Inputs!$B$2:$B$5000,$B$2) | X26: =SUMIFS(Plan_Inputs!$D$2:$D$5000,Plan_Inputs!$A$2:$A$5000,$A26,Plan_Inputs!$B$2:$B$5000,$B$2) | Y26: =E26 | Z26: =INDEX(Calendar!$H$5:$L$52,MATCH($A26,Calendar!$A$5:$A$52,0),MATCH($D$2,Calendar!$H$4:$L$4,0)) | AA26: =INDEX(Calendar!$M$5:$M$52,MATCH($A26,Calendar!$A$5:$A$52,0)) | AB26: =IF($D26="Actual",IFERROR(S26/Y26,""),"") | AC26: =IF($D26="Actual",IFERROR(U26/T26/Z26/AA26,""),"") | AD26: =IF($D26="Actual",IFERROR(V26/(U26+V26),""),"") | AE26: =IFERROR(AC26*Z26*AA26,"") | AG26: =IF($D26="Forecast",IFERROR(K26/AF26-1,""),"")
A27: 46023 | B27: =YEAR(A27) | C27: =MONTH(A27) | D27: =IF(A27<=LastActual,"Actual","Forecast") | E27: =IF($D27="Actual",R27,W27) | F27: =IF($D27="Actual",S27,Cases_Forecast!AJ20) | G27: =IF($D27="Actual",T27,IFERROR(H27/AE27,0)) | H27: =IF($D27="Actual",U27,J27-I27) | I27: =IF($D27="Actual",V27,IFERROR(J27*AD27,0)) | J27: =IF($D27="Actual",U27+V27,E27*X27) | K27: =IFERROR(F27/G27,0) | L27: =IFERROR(H27/G27,0) | M27: =IFERROR(J27/F27,0) | N27: =IFERROR(J27/E27,0) | O27: =IFERROR(I27/J27,0) | R27: =IF($D27="Actual",SUMIFS(Data_Actuals!$C$2:$C$5000,Data_Actuals!$A$2:$A$5000,$A27,Data_Actuals!$B$2:$B$5000,$B$2),"") | S27: =IF($D27="Actual",SUMIFS(Data_Actuals!$D$2:$D$5000,Data_Actuals!$A$2:$A$5000,$A27,Data_Actuals!$B$2:$B$5000,$B$2),"") | T27: =IF($D27="Actual",SUMIFS(Data_Actuals!$E$2:$E$5000,Data_Actuals!$A$2:$A$5000,$A27,Data_Actuals!$B$2:$B$5000,$B$2),"") | U27: =IF($D27="Actual",SUMIFS(Data_Actuals!$F$2:$F$5000,Data_Actuals!$A$2:$A$5000,$A27,Data_Actuals!$B$2:$B$5000,$B$2),"") | V27: =IF($D27="Actual",SUMIFS(Data_Actuals!$G$2:$G$5000,Data_Actuals!$A$2:$A$5000,$A27,Data_Actuals!$B$2:$B$5000,$B$2),"") | W27: =SUMIFS(Plan_Inputs!$C$2:$C$5000,Plan_Inputs!$A$2:$A$5000,$A27,Plan_Inputs!$B$2:$B$5000,$B$2) | X27: =SUMIFS(Plan_Inputs!$D$2:$D$5000,Plan_Inputs!$A$2:$A$5000,$A27,Plan_Inputs!$B$2:$B$5000,$B$2) | Y27: =E27 | Z27: =INDEX(Calendar!$H$5:$L$52,MATCH($A27,Calendar!$A$5:$A$52,0),MATCH($D$2,Calendar!$H$4:$L$4,0)) | AA27: =INDEX(Calendar!$M$5:$M$52,MATCH($A27,Calendar!$A$5:$A$52,0)) | AB27: =IF($D27="Actual",IFERROR(S27/Y27,""),AB15) | AC27: =IF($D27="Actual",IFERROR(U27/T27/Z27/AA27,""),AC15) | AD27: =IF($D27="Actual",IFERROR(V27/(U27+V27),""),AD15) | AE27: =IFERROR(AC27*Z27*AA27,"") | AF27: =K15 | AG27: =IF($D27="Forecast",IFERROR(K27/AF27-1,""),"")
A28: 46054 | B28: =YEAR(A28) | C28: =MONTH(A28) | D28: =IF(A28<=LastActual,"Actual","Forecast") | E28: =IF($D28="Actual",R28,W28) | F28: =IF($D28="Actual",S28,Cases_Forecast!AJ21) | G28: =IF($D28="Actual",T28,IFERROR(H28/AE28,0)) | H28: =IF($D28="Actual",U28,J28-I28) | I28: =IF($D28="Actual",V28,IFERROR(J28*AD28,0)) | J28: =IF($D28="Actual",U28+V28,E28*X28) | K28: =IFERROR(F28/G28,0) | L28: =IFERROR(H28/G28,0) | M28: =IFERROR(J28/F28,0) | N28: =IFERROR(J28/E28,0) | O28: =IFERROR(I28/J28,0) | R28: =IF($D28="Actual",SUMIFS(Data_Actuals!$C$2:$C$5000,Data_Actuals!$A$2:$A$5000,$A28,Data_Actuals!$B$2:$B$5000,$B$2),"") | S28: =IF($D28="Actual",SUMIFS(Data_Actuals!$D$2:$D$5000,Data_Actuals!$A$2:$A$5000,$A28,Data_Actuals!$B$2:$B$5000,$B$2),"") | T28: =IF($D28="Actual",SUMIFS(Data_Actuals!$E$2:$E$5000,Data_Actuals!$A$2:$A$5000,$A28,Data_Actuals!$B$2:$B$5000,$B$2),"") | U28: =IF($D28="Actual",SUMIFS(Data_Actuals!$F$2:$F$5000,Data_Actuals!$A$2:$A$5000,$A28,Data_Actuals!$B$2:$B$5000,$B$2),"") | V28: =IF($D28="Actual",SUMIFS(Data_Actuals!$G$2:$G$5000,Data_Actuals!$A$2:$A$5000,$A28,Data_Actuals!$B$2:$B$5000,$B$2),"") | W28: =SUMIFS(Plan_Inputs!$C$2:$C$5000,Plan_Inputs!$A$2:$A$5000,$A28,Plan_Inputs!$B$2:$B$5000,$B$2) | X28: =SUMIFS(Plan_Inputs!$D$2:$D$5000,Plan_Inputs!$A$2:$A$5000,$A28,Plan_Inputs!$B$2:$B$5000,$B$2) | Y28: =E28 | Z28: =INDEX(Calendar!$H$5:$L$52,MATCH($A28,Calendar!$A$5:$A$52,0),MATCH($D$2,Calendar!$H$4:$L$4,0)) | AA28: =INDEX(Calendar!$M$5:$M$52,MATCH($A28,Calendar!$A$5:$A$52,0)) | AB28: =IF($D28="Actual",IFERROR(S28/Y28,""),AB16) | AC28: =IF($D28="Actual",IFERROR(U28/T28/Z28/AA28,""),AC16) | AD28: =IF($D28="Actual",IFERROR(V28/(U28+V28),""),AD16) | AE28: =IFERROR(AC28*Z28*AA28,"") | AF28: =K16 | AG28: =IF($D28="Forecast",IFERROR(K28/AF28-1,""),"")
A29: 46082 | B29: =YEAR(A29) | C29: =MONTH(A29) | D29: =IF(A29<=LastActual,"Actual","Forecast") | E29: =IF($D29="Actual",R29,W29) | F29: =IF($D29="Actual",S29,Cases_Forecast!AJ22) | G29: =IF($D29="Actual",T29,IFERROR(H29/AE29,0)) | H29: =IF($D29="Actual",U29,J29-I29) | I29: =IF($D29="Actual",V29,IFERROR(J29*AD29,0)) | J29: =IF($D29="Actual",U29+V29,E29*X29) | K29: =IFERROR(F29/G29,0) | L29: =IFERROR(H29/G29,0) | M29: =IFERROR(J29/F29,0) | N29: =IFERROR(J29/E29,0) | O29: =IFERROR(I29/J29,0) | R29: =IF($D29="Actual",SUMIFS(Data_Actuals!$C$2:$C$5000,Data_Actuals!$A$2:$A$5000,$A29,Data_Actuals!$B$2:$B$5000,$B$2),"") | S29: =IF($D29="Actual",SUMIFS(Data_Actuals!$D$2:$D$5000,Data_Actuals!$A$2:$A$5000,$A29,Data_Actuals!$B$2:$B$5000,$B$2),"") | T29: =IF($D29="Actual",SUMIFS(Data_Actuals!$E$2:$E$5000,Data_Actuals!$A$2:$A$5000,$A29,Data_Actuals!$B$2:$B$5000,$B$2),"") | U29: =IF($D29="Actual",SUMIFS(Data_Actuals!$F$2:$F$5000,Data_Actuals!$A$2:$A$5000,$A29,Data_Actuals!$B$2:$B$5000,$B$2),"") | V29: =IF($D29="Actual",SUMIFS(Data_Actuals!$G$2:$G$5000,Data_Actuals!$A$2:$A$5000,$A29,Data_Actuals!$B$2:$B$5000,$B$2),"") | W29: =SUMIFS(Plan_Inputs!$C$2:$C$5000,Plan_Inputs!$A$2:$A$5000,$A29,Plan_Inputs!$B$2:$B$5000,$B$2) | X29: =SUMIFS(Plan_Inputs!$D$2:$D$5000,Plan_Inputs!$A$2:$A$5000,$A29,Plan_Inputs!$B$2:$B$5000,$B$2) | Y29: =E29 | Z29: =INDEX(Calendar!$H$5:$L$52,MATCH($A29,Calendar!$A$5:$A$52,0),MATCH($D$2,Calendar!$H$4:$L$4,0)) | AA29: =INDEX(Calendar!$M$5:$M$52,MATCH($A29,Calendar!$A$5:$A$52,0)) | AB29: =IF($D29="Actual",IFERROR(S29/Y29,""),AB17) | AC29: =IF($D29="Actual",IFERROR(U29/T29/Z29/AA29,""),AC17) | AD29: =IF($D29="Actual",IFERROR(V29/(U29+V29),""),AD17) | AE29: =IFERROR(AC29*Z29*AA29,"") | AF29: =K17 | AG29: =IF($D29="Forecast",IFERROR(K29/AF29-1,""),"")
A30: 46113 | B30: =YEAR(A30) | C30: =MONTH(A30) | D30: =IF(A30<=LastActual,"Actual","Forecast") | E30: =IF($D30="Actual",R30,W30) | F30: =IF($D30="Actual",S30,Cases_Forecast!AJ23) | G30: =IF($D30="Actual",T30,IFERROR(H30/AE30,0)) | H30: =IF($D30="Actual",U30,J30-I30) | I30: =IF($D30="Actual",V30,IFERROR(J30*AD30,0)) | J30: =IF($D30="Actual",U30+V30,E30*X30) | K30: =IFERROR(F30/G30,0) | L30: =IFERROR(H30/G30,0) | M30: =IFERROR(J30/F30,0) | N30: =IFERROR(J30/E30,0) | O30: =IFERROR(I30/J30,0) | R30: =IF($D30="Actual",SUMIFS(Data_Actuals!$C$2:$C$5000,Data_Actuals!$A$2:$A$5000,$A30,Data_Actuals!$B$2:$B$5000,$B$2),"") | S30: =IF($D30="Actual",SUMIFS(Data_Actuals!$D$2:$D$5000,Data_Actuals!$A$2:$A$5000,$A30,Data_Actuals!$B$2:$B$5000,$B$2),"") | T30: =IF($D30="Actual",SUMIFS(Data_Actuals!$E$2:$E$5000,Data_Actuals!$A$2:$A$5000,$A30,Data_Actuals!$B$2:$B$5000,$B$2),"") | U30: =IF($D30="Actual",SUMIFS(Data_Actuals!$F$2:$F$5000,Data_Actuals!$A$2:$A$5000,$A30,Data_Actuals!$B$2:$B$5000,$B$2),"") | V30: =IF($D30="Actual",SUMIFS(Data_Actuals!$G$2:$G$5000,Data_Actuals!$A$2:$A$5000,$A30,Data_Actuals!$B$2:$B$5000,$B$2),"") | W30: =SUMIFS(Plan_Inputs!$C$2:$C$5000,Plan_Inputs!$A$2:$A$5000,$A30,Plan_Inputs!$B$2:$B$5000,$B$2) | X30: =SUMIFS(Plan_Inputs!$D$2:$D$5000,Plan_Inputs!$A$2:$A$5000,$A30,Plan_Inputs!$B$2:$B$5000,$B$2) | Y30: =E30 | Z30: =INDEX(Calendar!$H$5:$L$52,MATCH($A30,Calendar!$A$5:$A$52,0),MATCH($D$2,Calendar!$H$4:$L$4,0)) | AA30: =INDEX(Calendar!$M$5:$M$52,MATCH($A30,Calendar!$A$5:$A$52,0)) | AB30: =IF($D30="Actual",IFERROR(S30/Y30,""),AB18) | AC30: =IF($D30="Actual",IFERROR(U30/T30/Z30/AA30,""),AC18) | AD30: =IF($D30="Actual",IFERROR(V30/(U30+V30),""),AD18) | AE30: =IFERROR(AC30*Z30*AA30,"") | AF30: =K18 | AG30: =IF($D30="Forecast",IFERROR(K30/AF30-1,""),"")
A31: 46143 | B31: =YEAR(A31) | C31: =MONTH(A31) | D31: =IF(A31<=LastActual,"Actual","Forecast") | E31: =IF($D31="Actual",R31,W31) | F31: =IF($D31="Actual",S31,Cases_Forecast!AJ24) | G31: =IF($D31="Actual",T31,IFERROR(H31/AE31,0)) | H31: =IF($D31="Actual",U31,J31-I31) | I31: =IF($D31="Actual",V31,IFERROR(J31*AD31,0)) | J31: =IF($D31="Actual",U31+V31,E31*X31) | K31: =IFERROR(F31/G31,0) | L31: =IFERROR(H31/G31,0) | M31: =IFERROR(J31/F31,0) | N31: =IFERROR(J31/E31,0) | O31: =IFERROR(I31/J31,0) | R31: =IF($D31="Actual",SUMIFS(Data_Actuals!$C$2:$C$5000,Data_Actuals!$A$2:$A$5000,$A31,Data_Actuals!$B$2:$B$5000,$B$2),"") | S31: =IF($D31="Actual",SUMIFS(Data_Actuals!$D$2:$D$5000,Data_Actuals!$A$2:$A$5000,$A31,Data_Actuals!$B$2:$B$5000,$B$2),"") | T31: =IF($D31="Actual",SUMIFS(Data_Actuals!$E$2:$E$5000,Data_Actuals!$A$2:$A$5000,$A31,Data_Actuals!$B$2:$B$5000,$B$2),"") | U31: =IF($D31="Actual",SUMIFS(Data_Actuals!$F$2:$F$5000,Data_Actuals!$A$2:$A$5000,$A31,Data_Actuals!$B$2:$B$5000,$B$2),"") | V31: =IF($D31="Actual",SUMIFS(Data_Actuals!$G$2:$G$5000,Data_Actuals!$A$2:$A$5000,$A31,Data_Actuals!$B$2:$B$5000,$B$2),"") | W31: =SUMIFS(Plan_Inputs!$C$2:$C$5000,Plan_Inputs!$A$2:$A$5000,$A31,Plan_Inputs!$B$2:$B$5000,$B$2) | X31: =SUMIFS(Plan_Inputs!$D$2:$D$5000,Plan_Inputs!$A$2:$A$5000,$A31,Plan_Inputs!$B$2:$B$5000,$B$2) | Y31: =E31 | Z31: =INDEX(Calendar!$H$5:$L$52,MATCH($A31,Calendar!$A$5:$A$52,0),MATCH($D$2,Calendar!$H$4:$L$4,0)) | AA31: =INDEX(Calendar!$M$5:$M$52,MATCH($A31,Calendar!$A$5:$A$52,0)) | AB31: =IF($D31="Actual",IFERROR(S31/Y31,""),AB19) | AC31: =IF($D31="Actual",IFERROR(U31/T31/Z31/AA31,""),AC19) | AD31: =IF($D31="Actual",IFERROR(V31/(U31+V31),""),AD19) | AE31: =IFERROR(AC31*Z31*AA31,"") | AF31: =K19 | AG31: =IF($D31="Forecast",IFERROR(K31/AF31-1,""),"")
A32: 46174 | B32: =YEAR(A32) | C32: =MONTH(A32) | D32: =IF(A32<=LastActual,"Actual","Forecast") | E32: =IF($D32="Actual",R32,W32) | F32: =IF($D32="Actual",S32,Cases_Forecast!AJ25) | G32: =IF($D32="Actual",T32,IFERROR(H32/AE32,0)) | H32: =IF($D32="Actual",U32,J32-I32) | I32: =IF($D32="Actual",V32,IFERROR(J32*AD32,0)) | J32: =IF($D32="Actual",U32+V32,E32*X32) | K32: =IFERROR(F32/G32,0) | L32: =IFERROR(H32/G32,0) | M32: =IFERROR(J32/F32,0) | N32: =IFERROR(J32/E32,0) | O32: =IFERROR(I32/J32,0) | R32: =IF($D32="Actual",SUMIFS(Data_Actuals!$C$2:$C$5000,Data_Actuals!$A$2:$A$5000,$A32,Data_Actuals!$B$2:$B$5000,$B$2),"") | S32: =IF($D32="Actual",SUMIFS(Data_Actuals!$D$2:$D$5000,Data_Actuals!$A$2:$A$5000,$A32,Data_Actuals!$B$2:$B$5000,$B$2),"") | T32: =IF($D32="Actual",SUMIFS(Data_Actuals!$E$2:$E$5000,Data_Actuals!$A$2:$A$5000,$A32,Data_Actuals!$B$2:$B$5000,$B$2),"") | U32: =IF($D32="Actual",SUMIFS(Data_Actuals!$F$2:$F$5000,Data_Actuals!$A$2:$A$5000,$A32,Data_Actuals!$B$2:$B$5000,$B$2),"") | V32: =IF($D32="Actual",SUMIFS(Data_Actuals!$G$2:$G$5000,Data_Actuals!$A$2:$A$5000,$A32,Data_Actuals!$B$2:$B$5000,$B$2),"") | W32: =SUMIFS(Plan_Inputs!$C$2:$C$5000,Plan_Inputs!$A$2:$A$5000,$A32,Plan_Inputs!$B$2:$B$5000,$B$2) | X32: =SUMIFS(Plan_Inputs!$D$2:$D$5000,Plan_Inputs!$A$2:$A$5000,$A32,Plan_Inputs!$B$2:$B$5000,$B$2) | Y32: =E32 | Z32: =INDEX(Calendar!$H$5:$L$52,MATCH($A32,Calendar!$A$5:$A$52,0),MATCH($D$2,Calendar!$H$4:$L$4,0)) | AA32: =INDEX(Calendar!$M$5:$M$52,MATCH($A32,Calendar!$A$5:$A$52,0)) | AB32: =IF($D32="Actual",IFERROR(S32/Y32,""),AB20) | AC32: =IF($D32="Actual",IFERROR(U32/T32/Z32/AA32,""),AC20) | AD32: =IF($D32="Actual",IFERROR(V32/(U32+V32),""),AD20) | AE32: =IFERROR(AC32*Z32*AA32,"") | AF32: =K20 | AG32: =IF($D32="Forecast",IFERROR(K32/AF32-1,""),"")
A33: 46204 | B33: =YEAR(A33) | C33: =MONTH(A33) | D33: =IF(A33<=LastActual,"Actual","Forecast") | E33: =IF($D33="Actual",R33,W33) | F33: =IF($D33="Actual",S33,Cases_Forecast!AJ26) | G33: =IF($D33="Actual",T33,IFERROR(H33/AE33,0)) | H33: =IF($D33="Actual",U33,J33-I33) | I33: =IF($D33="Actual",V33,IFERROR(J33*AD33,0)) | J33: =IF($D33="Actual",U33+V33,E33*X33) | K33: =IFERROR(F33/G33,0) | L33: =IFERROR(H33/G33,0) | M33: =IFERROR(J33/F33,0) | N33: =IFERROR(J33/E33,0) | O33: =IFERROR(I33/J33,0) | R33: =IF($D33="Actual",SUMIFS(Data_Actuals!$C$2:$C$5000,Data_Actuals!$A$2:$A$5000,$A33,Data_Actuals!$B$2:$B$5000,$B$2),"") | S33: =IF($D33="Actual",SUMIFS(Data_Actuals!$D$2:$D$5000,Data_Actuals!$A$2:$A$5000,$A33,Data_Actuals!$B$2:$B$5000,$B$2),"") | T33: =IF($D33="Actual",SUMIFS(Data_Actuals!$E$2:$E$5000,Data_Actuals!$A$2:$A$5000,$A33,Data_Actuals!$B$2:$B$5000,$B$2),"") | U33: =IF($D33="Actual",SUMIFS(Data_Actuals!$F$2:$F$5000,Data_Actuals!$A$2:$A$5000,$A33,Data_Actuals!$B$2:$B$5000,$B$2),"") | V33: =IF($D33="Actual",SUMIFS(Data_Actuals!$G$2:$G$5000,Data_Actuals!$A$2:$A$5000,$A33,Data_Actuals!$B$2:$B$5000,$B$2),"") | W33: =SUMIFS(Plan_Inputs!$C$2:$C$5000,Plan_Inputs!$A$2:$A$5000,$A33,Plan_Inputs!$B$2:$B$5000,$B$2) | X33: =SUMIFS(Plan_Inputs!$D$2:$D$5000,Plan_Inputs!$A$2:$A$5000,$A33,Plan_Inputs!$B$2:$B$5000,$B$2) | Y33: =E33 | Z33: =INDEX(Calendar!$H$5:$L$52,MATCH($A33,Calendar!$A$5:$A$52,0),MATCH($D$2,Calendar!$H$4:$L$4,0)) | AA33: =INDEX(Calendar!$M$5:$M$52,MATCH($A33,Calendar!$A$5:$A$52,0)) | AB33: =IF($D33="Actual",IFERROR(S33/Y33,""),AB21) | AC33: =IF($D33="Actual",IFERROR(U33/T33/Z33/AA33,""),AC21) | AD33: =IF($D33="Actual",IFERROR(V33/(U33+V33),""),AD21) | AE33: =IFERROR(AC33*Z33*AA33,"") | AF33: =K21 | AG33: =IF($D33="Forecast",IFERROR(K33/AF33-1,""),"")
A34: 46235 | B34: =YEAR(A34) | C34: =MONTH(A34) | D34: =IF(A34<=LastActual,"Actual","Forecast") | E34: =IF($D34="Actual",R34,W34) | F34: =IF($D34="Actual",S34,Cases_Forecast!AJ27) | G34: =IF($D34="Actual",T34,IFERROR(H34/AE34,0)) | H34: =IF($D34="Actual",U34,J34-I34) | I34: =IF($D34="Actual",V34,IFERROR(J34*AD34,0)) | J34: =IF($D34="Actual",U34+V34,E34*X34) | K34: =IFERROR(F34/G34,0) | L34: =IFERROR(H34/G34,0) | M34: =IFERROR(J34/F34,0) | N34: =IFERROR(J34/E34,0) | O34: =IFERROR(I34/J34,0) | R34: =IF($D34="Actual",SUMIFS(Data_Actuals!$C$2:$C$5000,Data_Actuals!$A$2:$A$5000,$A34,Data_Actuals!$B$2:$B$5000,$B$2),"") | S34: =IF($D34="Actual",SUMIFS(Data_Actuals!$D$2:$D$5000,Data_Actuals!$A$2:$A$5000,$A34,Data_Actuals!$B$2:$B$5000,$B$2),"") | T34: =IF($D34="Actual",SUMIFS(Data_Actuals!$E$2:$E$5000,Data_Actuals!$A$2:$A$5000,$A34,Data_Actuals!$B$2:$B$5000,$B$2),"") | U34: =IF($D34="Actual",SUMIFS(Data_Actuals!$F$2:$F$5000,Data_Actuals!$A$2:$A$5000,$A34,Data_Actuals!$B$2:$B$5000,$B$2),"") | V34: =IF($D34="Actual",SUMIFS(Data_Actuals!$G$2:$G$5000,Data_Actuals!$A$2:$A$5000,$A34,Data_Actuals!$B$2:$B$5000,$B$2),"") | W34: =SUMIFS(Plan_Inputs!$C$2:$C$5000,Plan_Inputs!$A$2:$A$5000,$A34,Plan_Inputs!$B$2:$B$5000,$B$2) | X34: =SUMIFS(Plan_Inputs!$D$2:$D$5000,Plan_Inputs!$A$2:$A$5000,$A34,Plan_Inputs!$B$2:$B$5000,$B$2) | Y34: =E34 | Z34: =INDEX(Calendar!$H$5:$L$52,MATCH($A34,Calendar!$A$5:$A$52,0),MATCH($D$2,Calendar!$H$4:$L$4,0)) | AA34: =INDEX(Calendar!$M$5:$M$52,MATCH($A34,Calendar!$A$5:$A$52,0)) | AB34: =IF($D34="Actual",IFERROR(S34/Y34,""),AB22) | AC34: =IF($D34="Actual",IFERROR(U34/T34/Z34/AA34,""),AC22) | AD34: =IF($D34="Actual",IFERROR(V34/(U34+V34),""),AD22) | AE34: =IFERROR(AC34*Z34*AA34,"") | AF34: =K22 | AG34: =IF($D34="Forecast",IFERROR(K34/AF34-1,""),"")
A35: 46266 | B35: =YEAR(A35) | C35: =MONTH(A35) | D35: =IF(A35<=LastActual,"Actual","Forecast") | E35: =IF($D35="Actual",R35,W35) | F35: =IF($D35="Actual",S35,Cases_Forecast!AJ28) | G35: =IF($D35="Actual",T35,IFERROR(H35/AE35,0)) | H35: =IF($D35="Actual",U35,J35-I35) | I35: =IF($D35="Actual",V35,IFERROR(J35*AD35,0)) | J35: =IF($D35="Actual",U35+V35,E35*X35) | K35: =IFERROR(F35/G35,0) | L35: =IFERROR(H35/G35,0) | M35: =IFERROR(J35/F35,0) | N35: =IFERROR(J35/E35,0) | O35: =IFERROR(I35/J35,0) | R35: =IF($D35="Actual",SUMIFS(Data_Actuals!$C$2:$C$5000,Data_Actuals!$A$2:$A$5000,$A35,Data_Actuals!$B$2:$B$5000,$B$2),"") | S35: =IF($D35="Actual",SUMIFS(Data_Actuals!$D$2:$D$5000,Data_Actuals!$A$2:$A$5000,$A35,Data_Actuals!$B$2:$B$5000,$B$2),"") | T35: =IF($D35="Actual",SUMIFS(Data_Actuals!$E$2:$E$5000,Data_Actuals!$A$2:$A$5000,$A35,Data_Actuals!$B$2:$B$5000,$B$2),"") | U35: =IF($D35="Actual",SUMIFS(Data_Actuals!$F$2:$F$5000,Data_Actuals!$A$2:$A$5000,$A35,Data_Actuals!$B$2:$B$5000,$B$2),"") | V35: =IF($D35="Actual",SUMIFS(Data_Actuals!$G$2:$G$5000,Data_Actuals!$A$2:$A$5000,$A35,Data_Actuals!$B$2:$B$5000,$B$2),"") | W35: =SUMIFS(Plan_Inputs!$C$2:$C$5000,Plan_Inputs!$A$2:$A$5000,$A35,Plan_Inputs!$B$2:$B$5000,$B$2) | X35: =SUMIFS(Plan_Inputs!$D$2:$D$5000,Plan_Inputs!$A$2:$A$5000,$A35,Plan_Inputs!$B$2:$B$5000,$B$2) | Y35: =E35 | Z35: =INDEX(Calendar!$H$5:$L$52,MATCH($A35,Calendar!$A$5:$A$52,0),MATCH($D$2,Calendar!$H$4:$L$4,0)) | AA35: =INDEX(Calendar!$M$5:$M$52,MATCH($A35,Calendar!$A$5:$A$52,0)) | AB35: =IF($D35="Actual",IFERROR(S35/Y35,""),AB23) | AC35: =IF($D35="Actual",IFERROR(U35/T35/Z35/AA35,""),AC23) | AD35: =IF($D35="Actual",IFERROR(V35/(U35+V35),""),AD23) | AE35: =IFERROR(AC35*Z35*AA35,"") | AF35: =K23 | AG35: =IF($D35="Forecast",IFERROR(K35/AF35-1,""),"")
A36: 46296 | B36: =YEAR(A36) | C36: =MONTH(A36) | D36: =IF(A36<=LastActual,"Actual","Forecast") | E36: =IF($D36="Actual",R36,W36) | F36: =IF($D36="Actual",S36,Cases_Forecast!AJ29) | G36: =IF($D36="Actual",T36,IFERROR(H36/AE36,0)) | H36: =IF($D36="Actual",U36,J36-I36) | I36: =IF($D36="Actual",V36,IFERROR(J36*AD36,0)) | J36: =IF($D36="Actual",U36+V36,E36*X36) | K36: =IFERROR(F36/G36,0) | L36: =IFERROR(H36/G36,0) | M36: =IFERROR(J36/F36,0) | N36: =IFERROR(J36/E36,0) | O36: =IFERROR(I36/J36,0) | R36: =IF($D36="Actual",SUMIFS(Data_Actuals!$C$2:$C$5000,Data_Actuals!$A$2:$A$5000,$A36,Data_Actuals!$B$2:$B$5000,$B$2),"") | S36: =IF($D36="Actual",SUMIFS(Data_Actuals!$D$2:$D$5000,Data_Actuals!$A$2:$A$5000,$A36,Data_Actuals!$B$2:$B$5000,$B$2),"") | T36: =IF($D36="Actual",SUMIFS(Data_Actuals!$E$2:$E$5000,Data_Actuals!$A$2:$A$5000,$A36,Data_Actuals!$B$2:$B$5000,$B$2),"") | U36: =IF($D36="Actual",SUMIFS(Data_Actuals!$F$2:$F$5000,Data_Actuals!$A$2:$A$5000,$A36,Data_Actuals!$B$2:$B$5000,$B$2),"") | V36: =IF($D36="Actual",SUMIFS(Data_Actuals!$G$2:$G$5000,Data_Actuals!$A$2:$A$5000,$A36,Data_Actuals!$B$2:$B$5000,$B$2),"") | W36: =SUMIFS(Plan_Inputs!$C$2:$C$5000,Plan_Inputs!$A$2:$A$5000,$A36,Plan_Inputs!$B$2:$B$5000,$B$2) | X36: =SUMIFS(Plan_Inputs!$D$2:$D$5000,Plan_Inputs!$A$2:$A$5000,$A36,Plan_Inputs!$B$2:$B$5000,$B$2) | Y36: =E36 | Z36: =INDEX(Calendar!$H$5:$L$52,MATCH($A36,Calendar!$A$5:$A$52,0),MATCH($D$2,Calendar!$H$4:$L$4,0)) | AA36: =INDEX(Calendar!$M$5:$M$52,MATCH($A36,Calendar!$A$5:$A$52,0)) | AB36: =IF($D36="Actual",IFERROR(S36/Y36,""),AB24) | AC36: =IF($D36="Actual",IFERROR(U36/T36/Z36/AA36,""),AC24) | AD36: =IF($D36="Actual",IFERROR(V36/(U36+V36),""),AD24) | AE36: =IFERROR(AC36*Z36*AA36,"") | AF36: =K24 | AG36: =IF($D36="Forecast",IFERROR(K36/AF36-1,""),"")
A37: 46327 | B37: =YEAR(A37) | C37: =MONTH(A37) | D37: =IF(A37<=LastActual,"Actual","Forecast") | E37: =IF($D37="Actual",R37,W37) | F37: =IF($D37="Actual",S37,Cases_Forecast!AJ30) | G37: =IF($D37="Actual",T37,IFERROR(H37/AE37,0)) | H37: =IF($D37="Actual",U37,J37-I37) | I37: =IF($D37="Actual",V37,IFERROR(J37*AD37,0)) | J37: =IF($D37="Actual",U37+V37,E37*X37) | K37: =IFERROR(F37/G37,0) | L37: =IFERROR(H37/G37,0) | M37: =IFERROR(J37/F37,0) | N37: =IFERROR(J37/E37,0) | O37: =IFERROR(I37/J37,0) | R37: =IF($D37="Actual",SUMIFS(Data_Actuals!$C$2:$C$5000,Data_Actuals!$A$2:$A$5000,$A37,Data_Actuals!$B$2:$B$5000,$B$2),"") | S37: =IF($D37="Actual",SUMIFS(Data_Actuals!$D$2:$D$5000,Data_Actuals!$A$2:$A$5000,$A37,Data_Actuals!$B$2:$B$5000,$B$2),"") | T37: =IF($D37="Actual",SUMIFS(Data_Actuals!$E$2:$E$5000,Data_Actuals!$A$2:$A$5000,$A37,Data_Actuals!$B$2:$B$5000,$B$2),"") | U37: =IF($D37="Actual",SUMIFS(Data_Actuals!$F$2:$F$5000,Data_Actuals!$A$2:$A$5000,$A37,Data_Actuals!$B$2:$B$5000,$B$2),"") | V37: =IF($D37="Actual",SUMIFS(Data_Actuals!$G$2:$G$5000,Data_Actuals!$A$2:$A$5000,$A37,Data_Actuals!$B$2:$B$5000,$B$2),"") | W37: =SUMIFS(Plan_Inputs!$C$2:$C$5000,Plan_Inputs!$A$2:$A$5000,$A37,Plan_Inputs!$B$2:$B$5000,$B$2) | X37: =SUMIFS(Plan_Inputs!$D$2:$D$5000,Plan_Inputs!$A$2:$A$5000,$A37,Plan_Inputs!$B$2:$B$5000,$B$2) | Y37: =E37 | Z37: =INDEX(Calendar!$H$5:$L$52,MATCH($A37,Calendar!$A$5:$A$52,0),MATCH($D$2,Calendar!$H$4:$L$4,0)) | AA37: =INDEX(Calendar!$M$5:$M$52,MATCH($A37,Calendar!$A$5:$A$52,0)) | AB37: =IF($D37="Actual",IFERROR(S37/Y37,""),AB25) | AC37: =IF($D37="Actual",IFERROR(U37/T37/Z37/AA37,""),AC25) | AD37: =IF($D37="Actual",IFERROR(V37/(U37+V37),""),AD25) | AE37: =IFERROR(AC37*Z37*AA37,"") | AF37: =K25 | AG37: =IF($D37="Forecast",IFERROR(K37/AF37-1,""),"")
A38: 46357 | B38: =YEAR(A38) | C38: =MONTH(A38) | D38: =IF(A38<=LastActual,"Actual","Forecast") | E38: =IF($D38="Actual",R38,W38) | F38: =IF($D38="Actual",S38,Cases_Forecast!AJ31) | G38: =IF($D38="Actual",T38,IFERROR(H38/AE38,0)) | H38: =IF($D38="Actual",U38,J38-I38) | I38: =IF($D38="Actual",V38,IFERROR(J38*AD38,0)) | J38: =IF($D38="Actual",U38+V38,E38*X38) | K38: =IFERROR(F38/G38,0) | L38: =IFERROR(H38/G38,0) | M38: =IFERROR(J38/F38,0) | N38: =IFERROR(J38/E38,0) | O38: =IFERROR(I38/J38,0) | R38: =IF($D38="Actual",SUMIFS(Data_Actuals!$C$2:$C$5000,Data_Actuals!$A$2:$A$5000,$A38,Data_Actuals!$B$2:$B$5000,$B$2),"") | S38: =IF($D38="Actual",SUMIFS(Data_Actuals!$D$2:$D$5000,Data_Actuals!$A$2:$A$5000,$A38,Data_Actuals!$B$2:$B$5000,$B$2),"") | T38: =IF($D38="Actual",SUMIFS(Data_Actuals!$E$2:$E$5000,Data_Actuals!$A$2:$A$5000,$A38,Data_Actuals!$B$2:$B$5000,$B$2),"") | U38: =IF($D38="Actual",SUMIFS(Data_Actuals!$F$2:$F$5000,Data_Actuals!$A$2:$A$5000,$A38,Data_Actuals!$B$2:$B$5000,$B$2),"") | V38: =IF($D38="Actual",SUMIFS(Data_Actuals!$G$2:$G$5000,Data_Actuals!$A$2:$A$5000,$A38,Data_Actuals!$B$2:$B$5000,$B$2),"") | W38: =SUMIFS(Plan_Inputs!$C$2:$C$5000,Plan_Inputs!$A$2:$A$5000,$A38,Plan_Inputs!$B$2:$B$5000,$B$2) | X38: =SUMIFS(Plan_Inputs!$D$2:$D$5000,Plan_Inputs!$A$2:$A$5000,$A38,Plan_Inputs!$B$2:$B$5000,$B$2) | Y38: =E38 | Z38: =INDEX(Calendar!$H$5:$L$52,MATCH($A38,Calendar!$A$5:$A$52,0),MATCH($D$2,Calendar!$H$4:$L$4,0)) | AA38: =INDEX(Calendar!$M$5:$M$52,MATCH($A38,Calendar!$A$5:$A$52,0)) | AB38: =IF($D38="Actual",IFERROR(S38/Y38,""),AB26) | AC38: =IF($D38="Actual",IFERROR(U38/T38/Z38/AA38,""),AC26) | AD38: =IF($D38="Actual",IFERROR(V38/(U38+V38),""),AD26) | AE38: =IFERROR(AC38*Z38*AA38,"") | AF38: =K26 | AG38: =IF($D38="Forecast",IFERROR(K38/AF38-1,""),"")
... A62: 47088 | B62: =YEAR(A62) | C62: =MONTH(A62) | D62: =IF(A62<=LastActual,"Actual","Forecast") | E62: =IF($D62="Actual",R62,W62) | F62: =IF($D62="Actual",S62,Cases_Forecast!AJ55) | G62: =IF($D62="Actual",T62,IFERROR(H62/AE62,0)) | H62: =IF($D62="Actual",U62,J62-I62) | I62: =IF($D62="Actual",V62,IFERROR(J62*AD62,0)) | J62: =IF($D62="Actual",U62+V62,E62*X62) | K62: =IFERROR(F62/G62,0) | L62: =IFERROR(H62/G62,0) | M62: =IFERROR(J62/F62,0) | N62: =IFERROR(J62/E62,0) | O62: =IFERROR(I62/J62,0) | R62: =IF($D62="Actual",SUMIFS(Data_Actuals!$C$2:$C$5000,Data_Actuals!$A$2:$A$5000,$A62,Data_Actuals!$B$2:$B$5000,$B$2),"") | S62: =IF($D62="Actual",SUMIFS(Data_Actuals!$D$2:$D$5000,Data_Actuals!$A$2:$A$5000,$A62,Data_Actuals!$B$2:$B$5000,$B$2),"") | T62: =IF($D62="Actual",SUMIFS(Data_Actuals!$E$2:$E$5000,Data_Actuals!$A$2:$A$5000,$A62,Data_Actuals!$B$2:$B$5000,$B$2),"") | U62: =IF($D62="Actual",SUMIFS(Data_Actuals!$F$2:$F$5000,Data_Actuals!$A$2:$A$5000,$A62,Data_Actuals!$B$2:$B$5000,$B$2),"") | V62: =IF($D62="Actual",SUMIFS(Data_Actuals!$G$2:$G$5000,Data_Actuals!$A$2:$A$5000,$A62,Data_Actuals!$B$2:$B$5000,$B$2),"") | W62: =SUMIFS(Plan_Inputs!$C$2:$C$5000,Plan_Inputs!$A$2:$A$5000,$A62,Plan_Inputs!$B$2:$B$5000,$B$2) | X62: =SUMIFS(Plan_Inputs!$D$2:$D$5000,Plan_Inputs!$A$2:$A$5000,$A62,Plan_Inputs!$B$2:$B$5000,$B$2) | Y62: =E62 | Z62: =INDEX(Calendar!$H$5:$L$52,MATCH($A62,Calendar!$A$5:$A$52,0),MATCH($D$2,Calendar!$H$4:$L$4,0)) | AA62: =INDEX(Calendar!$M$5:$M$52,MATCH($A62,Calendar!$A$5:$A$52,0)) | AB62: =IF($D62="Actual",IFERROR(S62/Y62,""),AB50) | AC62: =IF($D62="Actual",IFERROR(U62/T62/Z62/AA62,""),AC50) | AD62: =IF($D62="Actual",IFERROR(V62/(U62+V62),""),AD50) | AE62: =IFERROR(AC62*Z62*AA62,"") | AF62: =K50 | AG62: =IF($D62="Forecast",IFERROR(K62/AF62-1,""),"")

Sheet VIC-1
A1: =$B$2&" | Region | VIC"
A2: Code | B2: =Inputs!$A$37 | C2: State | D2: VIC
A5: FY | D5: Status | E5: Sales | F5: Cases picked | G5: WH hours worked | H5: Staff payroll | I5: Leadership payroll | J5: Total payroll | K5: CPLH (cases / hr) | L5: Cost per hour (staff) | M5: Cost per case (total payroll) | N5: Total payroll % sales | O5: Leadership % of total payroll
A6: 2025 | D6: =IF(DATE(A6,12,1)<=LastActual,"Actual",IF(DATE(A6,1,1)>LastActual,"Forecast","Blended")) | E6: =SUMIFS($E$15:$E$62,$B$15:$B$62,$A6) | F6: =SUMIFS($F$15:$F$62,$B$15:$B$62,$A6) | G6: =SUMIFS($G$15:$G$62,$B$15:$B$62,$A6) | H6: =SUMIFS($H$15:$H$62,$B$15:$B$62,$A6) | I6: =SUMIFS($I$15:$I$62,$B$15:$B$62,$A6) | J6: =SUMIFS($J$15:$J$62,$B$15:$B$62,$A6) | K6: =IFERROR(F6/G6,0) | L6: =IFERROR(H6/G6,0) | M6: =IFERROR(J6/F6,0) | N6: =IFERROR(J6/E6,0) | O6: =IFERROR(I6/J6,0)
A7: 2026 | D7: =IF(DATE(A7,12,1)<=LastActual,"Actual",IF(DATE(A7,1,1)>LastActual,"Forecast","Blended")) | E7: =SUMIFS($E$15:$E$62,$B$15:$B$62,$A7) | F7: =SUMIFS($F$15:$F$62,$B$15:$B$62,$A7) | G7: =SUMIFS($G$15:$G$62,$B$15:$B$62,$A7) | H7: =SUMIFS($H$15:$H$62,$B$15:$B$62,$A7) | I7: =SUMIFS($I$15:$I$62,$B$15:$B$62,$A7) | J7: =SUMIFS($J$15:$J$62,$B$15:$B$62,$A7) | K7: =IFERROR(F7/G7,0) | L7: =IFERROR(H7/G7,0) | M7: =IFERROR(J7/F7,0) | N7: =IFERROR(J7/E7,0) | O7: =IFERROR(I7/J7,0)
A8: 2027 | D8: =IF(DATE(A8,12,1)<=LastActual,"Actual",IF(DATE(A8,1,1)>LastActual,"Forecast","Blended")) | E8: =SUMIFS($E$15:$E$62,$B$15:$B$62,$A8) | F8: =SUMIFS($F$15:$F$62,$B$15:$B$62,$A8) | G8: =SUMIFS($G$15:$G$62,$B$15:$B$62,$A8) | H8: =SUMIFS($H$15:$H$62,$B$15:$B$62,$A8) | I8: =SUMIFS($I$15:$I$62,$B$15:$B$62,$A8) | J8: =SUMIFS($J$15:$J$62,$B$15:$B$62,$A8) | K8: =IFERROR(F8/G8,0) | L8: =IFERROR(H8/G8,0) | M8: =IFERROR(J8/F8,0) | N8: =IFERROR(J8/E8,0) | O8: =IFERROR(I8/J8,0)
A9: 2028 | D9: =IF(DATE(A9,12,1)<=LastActual,"Actual",IF(DATE(A9,1,1)>LastActual,"Forecast","Blended")) | E9: =SUMIFS($E$15:$E$62,$B$15:$B$62,$A9) | F9: =SUMIFS($F$15:$F$62,$B$15:$B$62,$A9) | G9: =SUMIFS($G$15:$G$62,$B$15:$B$62,$A9) | H9: =SUMIFS($H$15:$H$62,$B$15:$B$62,$A9) | I9: =SUMIFS($I$15:$I$62,$B$15:$B$62,$A9) | J9: =SUMIFS($J$15:$J$62,$B$15:$B$62,$A9) | K9: =IFERROR(F9/G9,0) | L9: =IFERROR(H9/G9,0) | M9: =IFERROR(J9/F9,0) | N9: =IFERROR(J9/E9,0) | O9: =IFERROR(I9/J9,0)
E12: Drivers | K12: Metrics | R12: Helper calculations (actuals, plan, same-month-last-year rates)
A13: Month | B13: Year | C13: Mth | D13: Status | E13: Sales | F13: Cases picked | G13: WH hours worked | H13: Staff payroll | I13: Leadership payroll | J13: Total payroll | K13: CPLH (cases / hr) | L13: Cost per hour (staff) | M13: Cost per case (total payroll) | N13: Total payroll % sales | O13: Leadership % of total payroll | R13: Act sales | S13: Act cases | T13: Act hours | U13: Act staff $ | V13: Act leadership $ | W13: Plan sales | X13: Plan payroll % | Y13: Volume driver sales | Z13: PH factor | AA13: Wage index | AB13: Cases per $ (actual, else same month LY) | AC13: Cost per hour ex PH & wage (actual, else same month LY) | AD13: Leadership share of total payroll (actual, else same month LY) | AE13: Fcst cost per hour (AC x PH x wage) | AF13: LY CPLH (same month) | AG13: Fcst CPLH vs LY
E14: $m | F14: m | G14: # | H14: $m | I14: $m | J14: $m | K14: # | L14: $ | M14: $ | N14: % | O14: %
A15: 45658 | B15: =YEAR(A15) | C15: =MONTH(A15) | D15: =IF(A15<=LastActual,"Actual","Forecast") | E15: =IF($D15="Actual",R15,W15) | F15: =IF($D15="Actual",S15,Cases_Forecast!AK8) | G15: =IF($D15="Actual",T15,IFERROR(H15/AE15,0)) | H15: =IF($D15="Actual",U15,J15-I15) | I15: =IF($D15="Actual",V15,IFERROR(J15*AD15,0)) | J15: =IF($D15="Actual",U15+V15,E15*X15) | K15: =IFERROR(F15/G15,0) | L15: =IFERROR(H15/G15,0) | M15: =IFERROR(J15/F15,0) | N15: =IFERROR(J15/E15,0) | O15: =IFERROR(I15/J15,0) | R15: =IF($D15="Actual",SUMIFS(Data_Actuals!$C$2:$C$5000,Data_Actuals!$A$2:$A$5000,$A15,Data_Actuals!$B$2:$B$5000,$B$2),"") | S15: =IF($D15="Actual",SUMIFS(Data_Actuals!$D$2:$D$5000,Data_Actuals!$A$2:$A$5000,$A15,Data_Actuals!$B$2:$B$5000,$B$2),"") | T15: =IF($D15="Actual",SUMIFS(Data_Actuals!$E$2:$E$5000,Data_Actuals!$A$2:$A$5000,$A15,Data_Actuals!$B$2:$B$5000,$B$2),"") | U15: =IF($D15="Actual",SUMIFS(Data_Actuals!$F$2:$F$5000,Data_Actuals!$A$2:$A$5000,$A15,Data_Actuals!$B$2:$B$5000,$B$2),"") | V15: =IF($D15="Actual",SUMIFS(Data_Actuals!$G$2:$G$5000,Data_Actuals!$A$2:$A$5000,$A15,Data_Actuals!$B$2:$B$5000,$B$2),"") | W15: =SUMIFS(Plan_Inputs!$C$2:$C$5000,Plan_Inputs!$A$2:$A$5000,$A15,Plan_Inputs!$B$2:$B$5000,$B$2) | X15: =SUMIFS(Plan_Inputs!$D$2:$D$5000,Plan_Inputs!$A$2:$A$5000,$A15,Plan_Inputs!$B$2:$B$5000,$B$2) | Y15: =E15 | Z15: =INDEX(Calendar!$H$5:$L$52,MATCH($A15,Calendar!$A$5:$A$52,0),MATCH($D$2,Calendar!$H$4:$L$4,0)) | AA15: =INDEX(Calendar!$M$5:$M$52,MATCH($A15,Calendar!$A$5:$A$52,0)) | AB15: =IF($D15="Actual",IFERROR(S15/Y15,""),"") | AC15: =IF($D15="Actual",IFERROR(U15/T15/Z15/AA15,""),"") | AD15: =IF($D15="Actual",IFERROR(V15/(U15+V15),""),"") | AE15: =IFERROR(AC15*Z15*AA15,"") | AG15: =IF($D15="Forecast",IFERROR(K15/AF15-1,""),"")
A16: 45689 | B16: =YEAR(A16) | C16: =MONTH(A16) | D16: =IF(A16<=LastActual,"Actual","Forecast") | E16: =IF($D16="Actual",R16,W16) | F16: =IF($D16="Actual",S16,Cases_Forecast!AK9) | G16: =IF($D16="Actual",T16,IFERROR(H16/AE16,0)) | H16: =IF($D16="Actual",U16,J16-I16) | I16: =IF($D16="Actual",V16,IFERROR(J16*AD16,0)) | J16: =IF($D16="Actual",U16+V16,E16*X16) | K16: =IFERROR(F16/G16,0) | L16: =IFERROR(H16/G16,0) | M16: =IFERROR(J16/F16,0) | N16: =IFERROR(J16/E16,0) | O16: =IFERROR(I16/J16,0) | R16: =IF($D16="Actual",SUMIFS(Data_Actuals!$C$2:$C$5000,Data_Actuals!$A$2:$A$5000,$A16,Data_Actuals!$B$2:$B$5000,$B$2),"") | S16: =IF($D16="Actual",SUMIFS(Data_Actuals!$D$2:$D$5000,Data_Actuals!$A$2:$A$5000,$A16,Data_Actuals!$B$2:$B$5000,$B$2),"") | T16: =IF($D16="Actual",SUMIFS(Data_Actuals!$E$2:$E$5000,Data_Actuals!$A$2:$A$5000,$A16,Data_Actuals!$B$2:$B$5000,$B$2),"") | U16: =IF($D16="Actual",SUMIFS(Data_Actuals!$F$2:$F$5000,Data_Actuals!$A$2:$A$5000,$A16,Data_Actuals!$B$2:$B$5000,$B$2),"") | V16: =IF($D16="Actual",SUMIFS(Data_Actuals!$G$2:$G$5000,Data_Actuals!$A$2:$A$5000,$A16,Data_Actuals!$B$2:$B$5000,$B$2),"") | W16: =SUMIFS(Plan_Inputs!$C$2:$C$5000,Plan_Inputs!$A$2:$A$5000,$A16,Plan_Inputs!$B$2:$B$5000,$B$2) | X16: =SUMIFS(Plan_Inputs!$D$2:$D$5000,Plan_Inputs!$A$2:$A$5000,$A16,Plan_Inputs!$B$2:$B$5000,$B$2) | Y16: =E16 | Z16: =INDEX(Calendar!$H$5:$L$52,MATCH($A16,Calendar!$A$5:$A$52,0),MATCH($D$2,Calendar!$H$4:$L$4,0)) | AA16: =INDEX(Calendar!$M$5:$M$52,MATCH($A16,Calendar!$A$5:$A$52,0)) | AB16: =IF($D16="Actual",IFERROR(S16/Y16,""),"") | AC16: =IF($D16="Actual",IFERROR(U16/T16/Z16/AA16,""),"") | AD16: =IF($D16="Actual",IFERROR(V16/(U16+V16),""),"") | AE16: =IFERROR(AC16*Z16*AA16,"") | AG16: =IF($D16="Forecast",IFERROR(K16/AF16-1,""),"")
A17: 45717 | B17: =YEAR(A17) | C17: =MONTH(A17) | D17: =IF(A17<=LastActual,"Actual","Forecast") | E17: =IF($D17="Actual",R17,W17) | F17: =IF($D17="Actual",S17,Cases_Forecast!AK10) | G17: =IF($D17="Actual",T17,IFERROR(H17/AE17,0)) | H17: =IF($D17="Actual",U17,J17-I17) | I17: =IF($D17="Actual",V17,IFERROR(J17*AD17,0)) | J17: =IF($D17="Actual",U17+V17,E17*X17) | K17: =IFERROR(F17/G17,0) | L17: =IFERROR(H17/G17,0) | M17: =IFERROR(J17/F17,0) | N17: =IFERROR(J17/E17,0) | O17: =IFERROR(I17/J17,0) | R17: =IF($D17="Actual",SUMIFS(Data_Actuals!$C$2:$C$5000,Data_Actuals!$A$2:$A$5000,$A17,Data_Actuals!$B$2:$B$5000,$B$2),"") | S17: =IF($D17="Actual",SUMIFS(Data_Actuals!$D$2:$D$5000,Data_Actuals!$A$2:$A$5000,$A17,Data_Actuals!$B$2:$B$5000,$B$2),"") | T17: =IF($D17="Actual",SUMIFS(Data_Actuals!$E$2:$E$5000,Data_Actuals!$A$2:$A$5000,$A17,Data_Actuals!$B$2:$B$5000,$B$2),"") | U17: =IF($D17="Actual",SUMIFS(Data_Actuals!$F$2:$F$5000,Data_Actuals!$A$2:$A$5000,$A17,Data_Actuals!$B$2:$B$5000,$B$2),"") | V17: =IF($D17="Actual",SUMIFS(Data_Actuals!$G$2:$G$5000,Data_Actuals!$A$2:$A$5000,$A17,Data_Actuals!$B$2:$B$5000,$B$2),"") | W17: =SUMIFS(Plan_Inputs!$C$2:$C$5000,Plan_Inputs!$A$2:$A$5000,$A17,Plan_Inputs!$B$2:$B$5000,$B$2) | X17: =SUMIFS(Plan_Inputs!$D$2:$D$5000,Plan_Inputs!$A$2:$A$5000,$A17,Plan_Inputs!$B$2:$B$5000,$B$2) | Y17: =E17 | Z17: =INDEX(Calendar!$H$5:$L$52,MATCH($A17,Calendar!$A$5:$A$52,0),MATCH($D$2,Calendar!$H$4:$L$4,0)) | AA17: =INDEX(Calendar!$M$5:$M$52,MATCH($A17,Calendar!$A$5:$A$52,0)) | AB17: =IF($D17="Actual",IFERROR(S17/Y17,""),"") | AC17: =IF($D17="Actual",IFERROR(U17/T17/Z17/AA17,""),"") | AD17: =IF($D17="Actual",IFERROR(V17/(U17+V17),""),"") | AE17: =IFERROR(AC17*Z17*AA17,"") | AG17: =IF($D17="Forecast",IFERROR(K17/AF17-1,""),"")
A18: 45748 | B18: =YEAR(A18) | C18: =MONTH(A18) | D18: =IF(A18<=LastActual,"Actual","Forecast") | E18: =IF($D18="Actual",R18,W18) | F18: =IF($D18="Actual",S18,Cases_Forecast!AK11) | G18: =IF($D18="Actual",T18,IFERROR(H18/AE18,0)) | H18: =IF($D18="Actual",U18,J18-I18) | I18: =IF($D18="Actual",V18,IFERROR(J18*AD18,0)) | J18: =IF($D18="Actual",U18+V18,E18*X18) | K18: =IFERROR(F18/G18,0) | L18: =IFERROR(H18/G18,0) | M18: =IFERROR(J18/F18,0) | N18: =IFERROR(J18/E18,0) | O18: =IFERROR(I18/J18,0) | R18: =IF($D18="Actual",SUMIFS(Data_Actuals!$C$2:$C$5000,Data_Actuals!$A$2:$A$5000,$A18,Data_Actuals!$B$2:$B$5000,$B$2),"") | S18: =IF($D18="Actual",SUMIFS(Data_Actuals!$D$2:$D$5000,Data_Actuals!$A$2:$A$5000,$A18,Data_Actuals!$B$2:$B$5000,$B$2),"") | T18: =IF($D18="Actual",SUMIFS(Data_Actuals!$E$2:$E$5000,Data_Actuals!$A$2:$A$5000,$A18,Data_Actuals!$B$2:$B$5000,$B$2),"") | U18: =IF($D18="Actual",SUMIFS(Data_Actuals!$F$2:$F$5000,Data_Actuals!$A$2:$A$5000,$A18,Data_Actuals!$B$2:$B$5000,$B$2),"") | V18: =IF($D18="Actual",SUMIFS(Data_Actuals!$G$2:$G$5000,Data_Actuals!$A$2:$A$5000,$A18,Data_Actuals!$B$2:$B$5000,$B$2),"") | W18: =SUMIFS(Plan_Inputs!$C$2:$C$5000,Plan_Inputs!$A$2:$A$5000,$A18,Plan_Inputs!$B$2:$B$5000,$B$2) | X18: =SUMIFS(Plan_Inputs!$D$2:$D$5000,Plan_Inputs!$A$2:$A$5000,$A18,Plan_Inputs!$B$2:$B$5000,$B$2) | Y18: =E18 | Z18: =INDEX(Calendar!$H$5:$L$52,MATCH($A18,Calendar!$A$5:$A$52,0),MATCH($D$2,Calendar!$H$4:$L$4,0)) | AA18: =INDEX(Calendar!$M$5:$M$52,MATCH($A18,Calendar!$A$5:$A$52,0)) | AB18: =IF($D18="Actual",IFERROR(S18/Y18,""),"") | AC18: =IF($D18="Actual",IFERROR(U18/T18/Z18/AA18,""),"") | AD18: =IF($D18="Actual",IFERROR(V18/(U18+V18),""),"") | AE18: =IFERROR(AC18*Z18*AA18,"") | AG18: =IF($D18="Forecast",IFERROR(K18/AF18-1,""),"")
A19: 45778 | B19: =YEAR(A19) | C19: =MONTH(A19) | D19: =IF(A19<=LastActual,"Actual","Forecast") | E19: =IF($D19="Actual",R19,W19) | F19: =IF($D19="Actual",S19,Cases_Forecast!AK12) | G19: =IF($D19="Actual",T19,IFERROR(H19/AE19,0)) | H19: =IF($D19="Actual",U19,J19-I19) | I19: =IF($D19="Actual",V19,IFERROR(J19*AD19,0)) | J19: =IF($D19="Actual",U19+V19,E19*X19) | K19: =IFERROR(F19/G19,0) | L19: =IFERROR(H19/G19,0) | M19: =IFERROR(J19/F19,0) | N19: =IFERROR(J19/E19,0) | O19: =IFERROR(I19/J19,0) | R19: =IF($D19="Actual",SUMIFS(Data_Actuals!$C$2:$C$5000,Data_Actuals!$A$2:$A$5000,$A19,Data_Actuals!$B$2:$B$5000,$B$2),"") | S19: =IF($D19="Actual",SUMIFS(Data_Actuals!$D$2:$D$5000,Data_Actuals!$A$2:$A$5000,$A19,Data_Actuals!$B$2:$B$5000,$B$2),"") | T19: =IF($D19="Actual",SUMIFS(Data_Actuals!$E$2:$E$5000,Data_Actuals!$A$2:$A$5000,$A19,Data_Actuals!$B$2:$B$5000,$B$2),"") | U19: =IF($D19="Actual",SUMIFS(Data_Actuals!$F$2:$F$5000,Data_Actuals!$A$2:$A$5000,$A19,Data_Actuals!$B$2:$B$5000,$B$2),"") | V19: =IF($D19="Actual",SUMIFS(Data_Actuals!$G$2:$G$5000,Data_Actuals!$A$2:$A$5000,$A19,Data_Actuals!$B$2:$B$5000,$B$2),"") | W19: =SUMIFS(Plan_Inputs!$C$2:$C$5000,Plan_Inputs!$A$2:$A$5000,$A19,Plan_Inputs!$B$2:$B$5000,$B$2) | X19: =SUMIFS(Plan_Inputs!$D$2:$D$5000,Plan_Inputs!$A$2:$A$5000,$A19,Plan_Inputs!$B$2:$B$5000,$B$2) | Y19: =E19 | Z19: =INDEX(Calendar!$H$5:$L$52,MATCH($A19,Calendar!$A$5:$A$52,0),MATCH($D$2,Calendar!$H$4:$L$4,0)) | AA19: =INDEX(Calendar!$M$5:$M$52,MATCH($A19,Calendar!$A$5:$A$52,0)) | AB19: =IF($D19="Actual",IFERROR(S19/Y19,""),"") | AC19: =IF($D19="Actual",IFERROR(U19/T19/Z19/AA19,""),"") | AD19: =IF($D19="Actual",IFERROR(V19/(U19+V19),""),"") | AE19: =IFERROR(AC19*Z19*AA19,"") | AG19: =IF($D19="Forecast",IFERROR(K19/AF19-1,""),"")
A20: 45809 | B20: =YEAR(A20) | C20: =MONTH(A20) | D20: =IF(A20<=LastActual,"Actual","Forecast") | E20: =IF($D20="Actual",R20,W20) | F20: =IF($D20="Actual",S20,Cases_Forecast!AK13) | G20: =IF($D20="Actual",T20,IFERROR(H20/AE20,0)) | H20: =IF($D20="Actual",U20,J20-I20) | I20: =IF($D20="Actual",V20,IFERROR(J20*AD20,0)) | J20: =IF($D20="Actual",U20+V20,E20*X20) | K20: =IFERROR(F20/G20,0) | L20: =IFERROR(H20/G20,0) | M20: =IFERROR(J20/F20,0) | N20: =IFERROR(J20/E20,0) | O20: =IFERROR(I20/J20,0) | R20: =IF($D20="Actual",SUMIFS(Data_Actuals!$C$2:$C$5000,Data_Actuals!$A$2:$A$5000,$A20,Data_Actuals!$B$2:$B$5000,$B$2),"") | S20: =IF($D20="Actual",SUMIFS(Data_Actuals!$D$2:$D$5000,Data_Actuals!$A$2:$A$5000,$A20,Data_Actuals!$B$2:$B$5000,$B$2),"") | T20: =IF($D20="Actual",SUMIFS(Data_Actuals!$E$2:$E$5000,Data_Actuals!$A$2:$A$5000,$A20,Data_Actuals!$B$2:$B$5000,$B$2),"") | U20: =IF($D20="Actual",SUMIFS(Data_Actuals!$F$2:$F$5000,Data_Actuals!$A$2:$A$5000,$A20,Data_Actuals!$B$2:$B$5000,$B$2),"") | V20: =IF($D20="Actual",SUMIFS(Data_Actuals!$G$2:$G$5000,Data_Actuals!$A$2:$A$5000,$A20,Data_Actuals!$B$2:$B$5000,$B$2),"") | W20: =SUMIFS(Plan_Inputs!$C$2:$C$5000,Plan_Inputs!$A$2:$A$5000,$A20,Plan_Inputs!$B$2:$B$5000,$B$2) | X20: =SUMIFS(Plan_Inputs!$D$2:$D$5000,Plan_Inputs!$A$2:$A$5000,$A20,Plan_Inputs!$B$2:$B$5000,$B$2) | Y20: =E20 | Z20: =INDEX(Calendar!$H$5:$L$52,MATCH($A20,Calendar!$A$5:$A$52,0),MATCH($D$2,Calendar!$H$4:$L$4,0)) | AA20: =INDEX(Calendar!$M$5:$M$52,MATCH($A20,Calendar!$A$5:$A$52,0)) | AB20: =IF($D20="Actual",IFERROR(S20/Y20,""),"") | AC20: =IF($D20="Actual",IFERROR(U20/T20/Z20/AA20,""),"") | AD20: =IF($D20="Actual",IFERROR(V20/(U20+V20),""),"") | AE20: =IFERROR(AC20*Z20*AA20,"") | AG20: =IF($D20="Forecast",IFERROR(K20/AF20-1,""),"")
A21: 45839 | B21: =YEAR(A21) | C21: =MONTH(A21) | D21: =IF(A21<=LastActual,"Actual","Forecast") | E21: =IF($D21="Actual",R21,W21) | F21: =IF($D21="Actual",S21,Cases_Forecast!AK14) | G21: =IF($D21="Actual",T21,IFERROR(H21/AE21,0)) | H21: =IF($D21="Actual",U21,J21-I21) | I21: =IF($D21="Actual",V21,IFERROR(J21*AD21,0)) | J21: =IF($D21="Actual",U21+V21,E21*X21) | K21: =IFERROR(F21/G21,0) | L21: =IFERROR(H21/G21,0) | M21: =IFERROR(J21/F21,0) | N21: =IFERROR(J21/E21,0) | O21: =IFERROR(I21/J21,0) | R21: =IF($D21="Actual",SUMIFS(Data_Actuals!$C$2:$C$5000,Data_Actuals!$A$2:$A$5000,$A21,Data_Actuals!$B$2:$B$5000,$B$2),"") | S21: =IF($D21="Actual",SUMIFS(Data_Actuals!$D$2:$D$5000,Data_Actuals!$A$2:$A$5000,$A21,Data_Actuals!$B$2:$B$5000,$B$2),"") | T21: =IF($D21="Actual",SUMIFS(Data_Actuals!$E$2:$E$5000,Data_Actuals!$A$2:$A$5000,$A21,Data_Actuals!$B$2:$B$5000,$B$2),"") | U21: =IF($D21="Actual",SUMIFS(Data_Actuals!$F$2:$F$5000,Data_Actuals!$A$2:$A$5000,$A21,Data_Actuals!$B$2:$B$5000,$B$2),"") | V21: =IF($D21="Actual",SUMIFS(Data_Actuals!$G$2:$G$5000,Data_Actuals!$A$2:$A$5000,$A21,Data_Actuals!$B$2:$B$5000,$B$2),"") | W21: =SUMIFS(Plan_Inputs!$C$2:$C$5000,Plan_Inputs!$A$2:$A$5000,$A21,Plan_Inputs!$B$2:$B$5000,$B$2) | X21: =SUMIFS(Plan_Inputs!$D$2:$D$5000,Plan_Inputs!$A$2:$A$5000,$A21,Plan_Inputs!$B$2:$B$5000,$B$2) | Y21: =E21 | Z21: =INDEX(Calendar!$H$5:$L$52,MATCH($A21,Calendar!$A$5:$A$52,0),MATCH($D$2,Calendar!$H$4:$L$4,0)) | AA21: =INDEX(Calendar!$M$5:$M$52,MATCH($A21,Calendar!$A$5:$A$52,0)) | AB21: =IF($D21="Actual",IFERROR(S21/Y21,""),"") | AC21: =IF($D21="Actual",IFERROR(U21/T21/Z21/AA21,""),"") | AD21: =IF($D21="Actual",IFERROR(V21/(U21+V21),""),"") | AE21: =IFERROR(AC21*Z21*AA21,"") | AG21: =IF($D21="Forecast",IFERROR(K21/AF21-1,""),"")
A22: 45870 | B22: =YEAR(A22) | C22: =MONTH(A22) | D22: =IF(A22<=LastActual,"Actual","Forecast") | E22: =IF($D22="Actual",R22,W22) | F22: =IF($D22="Actual",S22,Cases_Forecast!AK15) | G22: =IF($D22="Actual",T22,IFERROR(H22/AE22,0)) | H22: =IF($D22="Actual",U22,J22-I22) | I22: =IF($D22="Actual",V22,IFERROR(J22*AD22,0)) | J22: =IF($D22="Actual",U22+V22,E22*X22) | K22: =IFERROR(F22/G22,0) | L22: =IFERROR(H22/G22,0) | M22: =IFERROR(J22/F22,0) | N22: =IFERROR(J22/E22,0) | O22: =IFERROR(I22/J22,0) | R22: =IF($D22="Actual",SUMIFS(Data_Actuals!$C$2:$C$5000,Data_Actuals!$A$2:$A$5000,$A22,Data_Actuals!$B$2:$B$5000,$B$2),"") | S22: =IF($D22="Actual",SUMIFS(Data_Actuals!$D$2:$D$5000,Data_Actuals!$A$2:$A$5000,$A22,Data_Actuals!$B$2:$B$5000,$B$2),"") | T22: =IF($D22="Actual",SUMIFS(Data_Actuals!$E$2:$E$5000,Data_Actuals!$A$2:$A$5000,$A22,Data_Actuals!$B$2:$B$5000,$B$2),"") | U22: =IF($D22="Actual",SUMIFS(Data_Actuals!$F$2:$F$5000,Data_Actuals!$A$2:$A$5000,$A22,Data_Actuals!$B$2:$B$5000,$B$2),"") | V22: =IF($D22="Actual",SUMIFS(Data_Actuals!$G$2:$G$5000,Data_Actuals!$A$2:$A$5000,$A22,Data_Actuals!$B$2:$B$5000,$B$2),"") | W22: =SUMIFS(Plan_Inputs!$C$2:$C$5000,Plan_Inputs!$A$2:$A$5000,$A22,Plan_Inputs!$B$2:$B$5000,$B$2) | X22: =SUMIFS(Plan_Inputs!$D$2:$D$5000,Plan_Inputs!$A$2:$A$5000,$A22,Plan_Inputs!$B$2:$B$5000,$B$2) | Y22: =E22 | Z22: =INDEX(Calendar!$H$5:$L$52,MATCH($A22,Calendar!$A$5:$A$52,0),MATCH($D$2,Calendar!$H$4:$L$4,0)) | AA22: =INDEX(Calendar!$M$5:$M$52,MATCH($A22,Calendar!$A$5:$A$52,0)) | AB22: =IF($D22="Actual",IFERROR(S22/Y22,""),"") | AC22: =IF($D22="Actual",IFERROR(U22/T22/Z22/AA22,""),"") | AD22: =IF($D22="Actual",IFERROR(V22/(U22+V22),""),"") | AE22: =IFERROR(AC22*Z22*AA22,"") | AG22: =IF($D22="Forecast",IFERROR(K22/AF22-1,""),"")
