Workbook
Name LastActual: Inputs!$B$3
Name CPLHTol: Inputs!$B$7
Name CPLHSource: Inputs!$B$9
Name WageDates: Inputs!$A$21:$A$28
Name WageRates: Inputs!$B$21:$B$28
Name PH_Roster: Inputs!$B$31
Name PH_Loading: Inputs!$B$32
Name SiteCodes: Inputs!$A$36:$A$45

Sheet README
A1: Warehouse payroll forecast model (CPLH-driven version, with chambers)
A2: Synthetic data only. Monthly, Jan 2025 to Dec 2028.
A4: THE MODEL (per site, per forecast month)
A5: CPLH and cases are the inputs. Payroll, and payroll % of sales, are the result.
A6: CPLH comes from the CPLH_Forecast tab: plan CPLH (Plan_Inputs, or CPLH_Breakdown if picked on Inputs),
A7: else CPLH in the same month last year; plus your adjustments, or your override.
A8: Cases come from the Cases_Forecast tab: volume driver sales x cases per $ in the same month last year,
A9: plus your adjustments, or your override.
A10: Hours = cases / CPLH.
A11: Cost per hour = same month last year's cost per hour, with last year's public holidays and wage index taken out
A12: and this month's put back in. Staff payroll = hours x cost per hour.
A13: Total payroll = staff payroll / (1 - leadership share of total payroll in the last actual month).
... A44: Public holidays are generated by rule; check against the official state lists (AFL Grand Final Friday in particular).

Sheet Inputs
A1: Inputs
A3: Last actual month | B3: 46266
A5: Model status | B5: =Checks!B3
A7: Warn if forecast CPLH moves more than this vs LY | B7: 0.1
A9: Plan CPLH source | B9: Plan_Inputs | C9: Plan_Inputs = CPLH typed per site per month. National breakdown = the CPLH_Breakdown tab.
A19: Wage increases (staff cost per hour)
A20: Effective month | B20: Increase
A21: 46023 | B21: 0.04 | C21: Include past increases too: last year's cost per hour is divided by its wage index before this year's is applied.
A22: 46388 | B22: 0.045
A23: 46753 | B23: 0.045
A30: Public holidays
A31: Share of normal hours worked on a PH | B31: 0.5
A32: PH pay loading (1.5 = paid 250%) | B32: 1.5
A34: Sites | B34: Type your own codes in the Code column; every tab follows. Renaming the tabs to match is optional.
A35: Code | B35: Type | C35: State | D35: Payroll % basis | E35: In national sales? | F35: Volume driver
A36: NSW-1 | B36: Region | C36: NSW | D36: =A36 | E36: Yes | F36: =A36
A37: VIC-1 | B37: Region | C37: VIC | D37: =A37 | E37: Yes | F37: =A37
A38: QLD-1 | B38: Region | C38: QLD | D38: =A38 | E38: Yes | F38: =A38
A39: NSW-2 | B39: Region | C39: NSW | D39: =A39 | E39: Yes | F39: =A39
A40: VIC-2 | B40: Region | C40: VIC | D40: =A40 | E40: Yes | F40: =A40
A41: QLD-2 | B41: Region | C41: QLD | D41: =A41 | E41: Yes | F41: =A41
A42: SA-1 | B42: Region | C42: SA | D42: =A42 | E42: Yes | F42: =A42
A43: WA-1 | B43: Region | C43: WA | D43: =A43 | E43: Yes | F43: =A43
A44: IDC-NSW | B44: IDC | C44: NSW | D44: =A36 | E44: No | F44: =A36&"+"&A39
A45: IDC-VIC | B45: IDC | C45: VIC | D45: =A37 | E45: No | F45: =A37&"+"&A40

Sheet Data_Actuals
A1: Month | B1: Site | C1: Sales $ | D1: Cases picked | E1: WH hours worked | F1: Staff payroll $ | G1: Leadership payroll $
A2: 45658 | B2: =Inputs!$A$36 | C2: 145185523 | D2: 3043624 | E2: 40295 | F2: 2808121 | G2: 319183
A3: 45658 | B3: =Inputs!$A$37 | C3: 133443243 | D3: 2887489 | E3: 38547 | F3: 2623810 | G3: 302699
A4: 45658 | B4: =Inputs!$A$38 | C4: 111417052 | D4: 2452995 | E4: 34693 | F4: 2319628 | G4: 267794
A5: 45658 | B5: =Inputs!$A$39 | C5: 125154901 | D5: 2690106 | E5: 36126 | F5: 2481070 | G5: 301012
A6: 45658 | B6: =Inputs!$A$40 | C6: 129729431 | D6: 2666780 | E6: 34264 | F6: 2298653 | G6: 303403
A7: 45658 | B7: =Inputs!$A$41 | C7: 117129351 | D7: 2537615 | E7: 35430 | F7: 2331622 | G7: 266309
A8: 45658 | B8: =Inputs!$A$42 | C8: 78517402 | D8: 1794006 | E8: 26280 | F8: 1687827 | G8: 204809
A9: 45658 | B9: =Inputs!$A$43 | C9: 99253181 | D9: 2212340 | E9: 31507 | F9: 2336629 | G9: 248935
A10: 45658 | B10: =Inputs!$A$44 | D10: 814235 | E10: 7750 | F10: 564304 | G10: 149724
A11: 45658 | B11: =Inputs!$A$45 | D11: 745617 | E11: 7313 | F11: 524974 | G11: 142777
A12: 45689 | B12: =Inputs!$A$36 | C12: 132346726 | D12: 2785007 | E12: 36181 | F12: 2383806 | G12: 320742
A13: 45689 | B13: =Inputs!$A$37 | C13: 129246596 | D13: 2777283 | E13: 34519 | F13: 2236585 | G13: 295534
A14: 45689 | B14: =Inputs!$A$38 | C14: 100727414 | D14: 2181145 | E14: 29392 | F14: 1832372 | G14: 257979
A15: 45689 | B15: =Inputs!$A$39 | C15: 110794435 | D15: 2337164 | E15: 31366 | F15: 2097121 | G15: 282353
A16: 45689 | B16: =Inputs!$A$40 | C16: 122688392 | D16: 2600981 | E16: 33068 | F16: 2113994 | G16: 294983
A17: 45689 | B17: =Inputs!$A$41 | C17: 109162992 | D17: 2365350 | E17: 31471 | F17: 1991983 | G17: 275619
A18: 45689 | B18: =Inputs!$A$42 | C18: 70749655 | D18: 1615239 | E18: 22417 | F18: 1358641 | G18: 210920
A19: 45689 | B19: =Inputs!$A$43 | C19: 94123598 | D19: 2117036 | E19: 29338 | F19: 2028412 | G19: 245629
A20: 45689 | B20: =Inputs!$A$44 | D20: 736093 | E20: 6714 | F20: 471815 | G20: 145495
A21: 45689 | B21: =Inputs!$A$45 | D21: 699658 | E21: 6848 | F21: 467508 | G21: 140341
A22: 45717 | B22: =Inputs!$A$36 | C22: 151388181 | D22: 3208052 | E22: 40660 | F22: 2685948 | G22: 315275
A23: 45717 | B23: =Inputs!$A$37 | C23: 139380637 | D23: 3034799 | E23: 37316 | F23: 2494850 | G23: 319982
A24: 45717 | B24: =Inputs!$A$38 | C24: 115886017 | D24: 2560673 | E24: 34662 | F24: 2185396 | G24: 255961
A25: 45717 | B25: =Inputs!$A$39 | C25: 123027509 | D25: 2608583 | E25: 33988 | F25: 2237477 | G25: 273167
A26: 45717 | B26: =Inputs!$A$40 | C26: 135907959 | D26: 2829800 | E26: 35242 | F26: 2310290 | G26: 298020
A27: 45717 | B27: =Inputs!$A$41 | C27: 122320621 | D27: 2680744 | E27: 35277 | F27: 2213243 | G27: 268586
A28: 45717 | B28: =Inputs!$A$42 | C28: 81234768 | D28: 1826489 | E28: 24500 | F28: 1538671 | G28: 197429
A29: 45717 | B29: =Inputs!$A$43 | C29: 108067323 | D29: 2388750 | E29: 32485 | F29: 2317422 | G29: 248477
A30: 45717 | B30: =Inputs!$A$44 | D30: 809173 | E30: 7223 | F30: 505153 | G30: 146059
A31: 45717 | B31: =Inputs!$A$45 | D31: 778599 | E31: 7397 | F31: 527308 | G31: 140256
A32: 45748 | B32: =Inputs!$A$36 | C32: 147502978 | D32: 3093483 | E32: 39190 | F32: 2940258 | G32: 319320
A33: 45748 | B33: =Inputs!$A$37 | C33: 139729332 | D33: 3011417 | E33: 37754 | F33: 2783718 | G33: 313897
A34: 45748 | B34: =Inputs!$A$38 | C34: 117059467 | D34: 2552888 | E34: 34584 | F34: 2465776 | G34: 260553
A35: 45748 | B35: =Inputs!$A$39 | C35: 123461416 | D35: 2596120 | E35: 34407 | F35: 2569797 | G35: 284117
A36: 45748 | B36: =Inputs!$A$40 | C36: 136765517 | D36: 2877751 | E36: 35707 | F36: 2629214 | G36: 306586
A37: 45748 | B37: =Inputs!$A$41 | C37: 116536673 | D37: 2538303 | E37: 34449 | F37: 2474166 | G37: 272848
A38: 45748 | B38: =Inputs!$A$42 | C38: 79536351 | D38: 1769687 | E38: 24842 | F38: 1722163 | G38: 207265
A39: 45748 | B39: =Inputs!$A$43 | C39: 104847628 | D39: 2342946 | E39: 32011 | F39: 2424086 | G39: 250907
A40: 45748 | B40: =Inputs!$A$44 | D40: 816972 | E40: 7455 | F40: 606629 | G40: 153750
A41: 45748 | B41: =Inputs!$A$45 | D41: 767977 | E41: 7081 | F41: 562453 | G41: 140551
A42: 45778 | B42: =Inputs!$A$36 | C42: 149881462 | D42: 3086173 | E42: 39621 | F42: 2625238 | G42: 325590
A43: 45778 | B43: =Inputs!$A$37 | C43: 141918699 | D43: 2993432 | E43: 37519 | F43: 2447093 | G43: 304699
A44: 45778 | B44: =Inputs!$A$38 | C44: 113712227 | D44: 2485054 | E44: 33987 | F44: 2207839 | G44: 267353
A45: 45778 | B45: =Inputs!$A$39 | C45: 122147150 | D45: 2531897 | E45: 33577 | F45: 2239964 | G45: 276790
A46: 45778 | B46: =Inputs!$A$40 | C46: 137261905 | D46: 2874734 | E46: 35879 | F46: 2347584 | G46: 295261
A47: 45778 | B47: =Inputs!$A$41 | C47: 116543697 | D47: 2502257 | E47: 33428 | F47: 2148823 | G47: 270902
A48: 45778 | B48: =Inputs!$A$42 | C48: 78013621 | D48: 1770297 | E48: 24288 | F48: 1473644 | G48: 212855
A49: 45778 | B49: =Inputs!$A$43 | C49: 102610754 | D49: 2259751 | E49: 31156 | F49: 2170677 | G49: 257983
A50: 45778 | B50: =Inputs!$A$44 | D50: 814800 | E50: 7400 | F50: 518632 | G50: 149692
A51: 45778 | B51: =Inputs!$A$45 | D51: 771305 | E51: 7503 | F51: 518583 | G51: 139285
A52: 45809 | B52: =Inputs!$A$36 | C52: 145551686 | D52: 3048836 | E52: 38782 | F52: 2641082 | G52: 312875
A53: 45809 | B53: =Inputs!$A$37 | C53: 133582637 | D53: 2789624 | E53: 35748 | F53: 2381357 | G53: 299381
A54: 45809 | B54: =Inputs!$A$38 | C54: 112402328 | D54: 2475324 | E54: 32898 | F54: 2087983 | G54: 261577
A55: 45809 | B55: =Inputs!$A$39 | C55: 126006744 | D55: 2667620 | E55: 35576 | F55: 2391671 | G55: 281363
A56: 45809 | B56: =Inputs!$A$40 | C56: 128616983 | D56: 2684568 | E56: 34018 | F56: 2266901 | G56: 296528
A57: 45809 | B57: =Inputs!$A$41 | C57: 114837763 | D57: 2488921 | E57: 33907 | F57: 2099318 | G57: 273870
A58: 45809 | B58: =Inputs!$A$42 | C58: 78697811 | D58: 1781884 | E58: 25042 | F58: 1576197 | G58: 207447
A59: 45809 | B59: =Inputs!$A$43 | C59: 106251584 | D59: 2353205 | E59: 32513 | F59: 2282566 | G59: 258037
A60: 45809 | B60: =Inputs!$A$44 | D60: 797913 | E60: 7125 | F60: 512235 | G60: 141736
A61: 45809 | B61: =Inputs!$A$45 | D61: 732957 | E61: 6918 | F61: 490484 | G61: 143198
A62: 45839 | B62: =Inputs!$A$36 | C62: 150825108 | D62: 3095874 | E62: 41109 | F62: 2700039 | G62: 314139
A63: 45839 | B63: =Inputs!$A$37 | C63: 140303139 | D63: 2970766 | E63: 37642 | F63: 2407100 | G63: 301975
A64: 45839 | B64: =Inputs!$A$38 | C64: 115020335 | D64: 2533096 | E64: 34026 | F64: 2126937 | G64: 260124
A65: 45839 | B65: =Inputs!$A$39 | C65: 122423850 | D65: 2637012 | E65: 35046 | F65: 2325652 | G65: 288177
A66: 45839 | B66: =Inputs!$A$40 | C66: 133802087 | D66: 2768560 | E66: 35414 | F66: 2303169 | G66: 301476
A67: 45839 | B67: =Inputs!$A$41 | C67: 117297779 | D67: 2523631 | E67: 34209 | F67: 2130859 | G67: 267846
A68: 45839 | B68: =Inputs!$A$42 | C68: 81142099 | D68: 1808466 | E68: 25875 | F68: 1578800 | G68: 202507
A69: 45839 | B69: =Inputs!$A$43 | C69: 102269580 | D69: 2256268 | E69: 31018 | F69: 2170189 | G69: 244933
A70: 45839 | B70: =Inputs!$A$44 | D70: 808405 | E70: 7405 | F70: 522099 | G70: 149868
A71: 45839 | B71: =Inputs!$A$45 | D71: 764110 | E71: 7321 | F71: 501278 | G71: 141633
A72: 45870 | B72: =Inputs!$A$36 | C72: 150399966 | D72: 3151472 | E72: 40918 | F72: 2718887 | G72: 313586
A73: 45870 | B73: =Inputs!$A$37 | C73: 139321773 | D73: 2998609 | E73: 36829 | F73: 2390221 | G73: 308096
A74: 45870 | B74: =Inputs!$A$38 | C74: 110587301 | D74: 2411423 | E74: 32199 | F74: 2048566 | G74: 260787
A75: 45870 | B75: =Inputs!$A$39 | C75: 123505128 | D75: 2569481 | E75: 33752 | F75: 2234056 | G75: 284904
A76: 45870 | B76: =Inputs!$A$40 | C76: 133449358 | D76: 2730922 | E76: 33968 | F76: 2240982 | G76: 296393
A77: 45870 | B77: =Inputs!$A$41 | C77: 118028853 | D77: 2575504 | E77: 33913 | F77: 2132034 | G77: 274091
A78: 45870 | B78: =Inputs!$A$42 | C78: 78915082 | D78: 1758980 | E78: 24436 | F78: 1472864 | G78: 205314
A79: 45870 | B79: =Inputs!$A$43 | C79: 105631703 | D79: 2365576 | E79: 32298 | F79: 2236889 | G79: 242306
A80: 45870 | B80: =Inputs!$A$44 | D80: 826618 | E80: 7654 | F80: 530861 | G80: 153201
A81: 45870 | B81: =Inputs!$A$45 | D81: 748941 | E81: 7016 | F81: 486157 | G81: 139877
A82: 45901 | B82: =Inputs!$A$36 | C82: 147150090 | D82: 3050182 | E82: 38780 | F82: 2576228 | G82: 324086
A83: 45901 | B83: =Inputs!$A$37 | C83: 137236692 | D83: 2901706 | E83: 36315 | F83: 2409168 | G83: 287006
A84: 45901 | B84: =Inputs!$A$38 | C84: 114533859 | D84: 2494471 | E84: 34008 | F84: 2118331 | G84: 254957
A85: 45901 | B85: =Inputs!$A$39 | C85: 122888375 | D85: 2543002 | E85: 33218 | F85: 2180594 | G85: 267774
A86: 45901 | B86: =Inputs!$A$40 | C86: 135062098 | D86: 2805860 | E86: 36745 | F86: 2434219 | G86: 296185
A87: 45901 | B87: =Inputs!$A$41 | C87: 119846726 | D87: 2597104 | E87: 34610 | F87: 2198201 | G87: 279550
A88: 45901 | B88: =Inputs!$A$42 | C88: 77586165 | D88: 1723900 | E88: 23334 | F88: 1431434 | G88: 208017
A89: 45901 | B89: =Inputs!$A$43 | C89: 103002025 | D89: 2269028 | E89: 32120 | F89: 2280172 | G89: 251776
A90: 45901 | B90: =Inputs!$A$44 | D90: 796739 | E90: 7311 | F90: 509343 | G90: 147721
A91: 45901 | B91: =Inputs!$A$45 | D91: 748895 | E91: 7279 | F91: 509659 | G91: 135447
A92: 45931 | B92: =Inputs!$A$36 | C92: 154728337 | D92: 3233552 | E92: 40450 | F92: 2721618 | G92: 315409
A93: 45931 | B93: =Inputs!$A$37 | C93: 143996017 | D93: 3068669 | E93: 37902 | F93: 2449571 | G93: 302231
A94: 45931 | B94: =Inputs!$A$38 | C94: 115587533 | D94: 2530197 | E94: 33707 | F94: 2185659 | G94: 260382
A95: 45931 | B95: =Inputs!$A$39 | C95: 126924990 | D95: 2622371 | E95: 33613 | F95: 2308387 | G95: 290409
A96: 45931 | B96: =Inputs!$A$40 | C96: 140152932 | D96: 2887756 | E96: 35669 | F96: 2330290 | G96: 294606
A97: 45931 | B97: =Inputs!$A$41 | C97: 124356453 | D97: 2727876 | E97: 35254 | F97: 2291059 | G97: 264113
A98: 45931 | B98: =Inputs!$A$42 | C98: 83659551 | D98: 1835662 | E98: 24800 | F98: 1547850 | G98: 210993
A99: 45931 | B99: =Inputs!$A$43 | C99: 105007588 | D99: 2282578 | E99: 31078 | F99: 2135284 | G99: 248468
A100: 45931 | B100: =Inputs!$A$44 | D100: 839942 | E100: 7380 | F100: 522302 | G100: 149128
...

Sheet Plan_Inputs
A1: Month | B1: Site | C1: Sales forecast $ | D1: Plan CPLH (cases / hr) | F1: From the long-range plan. IDCs have no sales; their payroll % is shown against the host region's sales.
A2: 46023 | B2: =Inputs!$A$36 | C2: 153814000 | D2: 76.3 | F2: Plan CPLH: blank uses CPLH in the same month last year. CPLH_Breakdown's column-for-pasting matches these rows.
A3: 46023 | B3: =Inputs!$A$37 | C3: 142733000 | D3: 80.7
A4: 46023 | B4: =Inputs!$A$38 | C4: 117343000 | D4: 74.1
A5: 46023 | B5: =Inputs!$A$39 | C5: 126585000 | D5: 75.7
A6: 46023 | B6: =Inputs!$A$40 | C6: 135910000 | D6: 79.7
A7: 46023 | B7: =Inputs!$A$41 | C7: 120851000 | D7: 76.9
A8: 46023 | B8: =Inputs!$A$42 | C8: 79038000 | D8: 72.9
A9: 46023 | B9: =Inputs!$A$43 | C9: 106821000 | D9: 71.4
A10: 46023 | B10: =Inputs!$A$44 | D10: 111.4
A11: 46023 | B11: =Inputs!$A$45 | D11: 106
A12: 46054 | B12: =Inputs!$A$36 | C12: 137092000 | D12: 79.9
A13: 46054 | B13: =Inputs!$A$37 | C13: 131606000 | D13: 84.1
A14: 46054 | B14: =Inputs!$A$38 | C14: 109672000 | D14: 75.2
A15: 46054 | B15: =Inputs!$A$39 | C15: 120059000 | D15: 77.5
A16: 46054 | B16: =Inputs!$A$40 | C16: 129364000 | D16: 80.7
A17: 46054 | B17: =Inputs!$A$41 | C17: 114317000 | D17: 76.5
A18: 46054 | B18: =Inputs!$A$42 | C18: 74441000 | D18: 74.3
A19: 46054 | B19: =Inputs!$A$43 | C19: 96657000 | D19: 74.1
A20: 46054 | B20: =Inputs!$A$44 | D20: 111.5
A21: 46054 | B21: =Inputs!$A$45 | D21: 104.7
A22: 46082 | B22: =Inputs!$A$36 | C22: 157503000 | D22: 81.2
A23: 46082 | B23: =Inputs!$A$37 | C23: 146942000 | D23: 82.6
A24: 46082 | B24: =Inputs!$A$38 | C24: 118790000 | D24: 77.9
A25: 46082 | B25: =Inputs!$A$39 | C25: 132170000 | D25: 80.1
A26: 46082 | B26: =Inputs!$A$40 | C26: 140523000 | D26: 81.4
A27: 46082 | B27: =Inputs!$A$41 | C27: 122798000 | D27: 78
A28: 46082 | B28: =Inputs!$A$42 | C28: 81723000 | D28: 73.1
A29: 46082 | B29: =Inputs!$A$43 | C29: 108203000 | D29: 74.4
A30: 46082 | B30: =Inputs!$A$44 | D30: 110
A31: 46082 | B31: =Inputs!$A$45 | D31: 110
A32: 46113 | B32: =Inputs!$A$36 | C32: 153091000 | D32: 79.1
A33: 46113 | B33: =Inputs!$A$37 | C33: 140264000 | D33: 82.7
A34: 46113 | B34: =Inputs!$A$38 | C34: 116902000 | D34: 77.9
A35: 46113 | B35: =Inputs!$A$39 | C35: 132565000 | D35: 79.1
A36: 46113 | B36: =Inputs!$A$40 | C36: 139867000 | D36: 81.8
A37: 46113 | B37: =Inputs!$A$41 | C37: 125887000 | D37: 78
A38: 46113 | B38: =Inputs!$A$42 | C38: 84196000 | D38: 73
A39: 46113 | B39: =Inputs!$A$43 | C39: 111697000 | D39: 75.5
A40: 46113 | B40: =Inputs!$A$44 | D40: 112.7
A41: 46113 | B41: =Inputs!$A$45 | D41: 108.1
A42: 46143 | B42: =Inputs!$A$36 | C42: 152230000 | D42: 78.4
A43: 46143 | B43: =Inputs!$A$37 | C43: 147525000 | D43: 83.6
A44: 46143 | B44: =Inputs!$A$38 | C44: 116456000 | D44: 75.4
A45: 46143 | B45: =Inputs!$A$39 | C45: 127918000 | D45: 74.8
A46: 46143 | B46: =Inputs!$A$40 | C46: 138378000 | D46: 81.6
A47: 46143 | B47: =Inputs!$A$41 | C47: 123873000 | D47: 77.1
A48: 46143 | B48: =Inputs!$A$42 | C48: 82081000 | D48: 74.3
A49: 46143 | B49: =Inputs!$A$43 | C49: 106186000 | D49: 74.9
A50: 46143 | B50: =Inputs!$A$44 | D50: 114.5
A51: 46143 | B51: =Inputs!$A$45 | D51: 107.1
A52: 46174 | B52: =Inputs!$A$36 | C52: 152135000 | D52: 80.7
A53: 46174 | B53: =Inputs!$A$37 | C53: 141649000 | D53: 85.3
A54: 46174 | B54: =Inputs!$A$38 | C54: 113294000 | D54: 78.4
A55: 46174 | B55: =Inputs!$A$39 | C55: 126063000 | D55: 78.4
A56: 46174 | B56: =Inputs!$A$40 | C56: 133661000 | D56: 82.6
A57: 46174 | B57: =Inputs!$A$41 | C57: 118337000 | D57: 76.3
A58: 46174 | B58: =Inputs!$A$42 | C58: 81648000 | D58: 75.3
A59: 46174 | B59: =Inputs!$A$43 | C59: 107863000 | D59: 78.5
A60: 46174 | B60: =Inputs!$A$44 | D60: 117.1
A61: 46174 | B61: =Inputs!$A$45 | D61: 109.1
A62: 46204 | B62: =Inputs!$A$36 | C62: 157303000 | D62: 81.1
A63: 46204 | B63: =Inputs!$A$37 | C63: 145102000 | D63: 83
A64: 46204 | B64: =Inputs!$A$38 | C64: 118164000 | D64: 76.3
A65: 46204 | B65: =Inputs!$A$39 | C65: 127349000 | D65: 79.4
A66: 46204 | B66: =Inputs!$A$40 | C66: 140176000 | D66: 80.4
A67: 46204 | B67: =Inputs!$A$41 | C67: 124914000 | D67: 79.4
A68: 46204 | B68: =Inputs!$A$42 | C68: 81940000 | D68: 74
A69: 46204 | B69: =Inputs!$A$43 | C69: 109023000 | D69: 75.2
A70: 46204 | B70: =Inputs!$A$44 | D70: 116.9
A71: 46204 | B71: =Inputs!$A$45 | D71: 110.9
A72: 46235 | B72: =Inputs!$A$36 | C72: 154523000 | D72: 80.8
A73: 46235 | B73: =Inputs!$A$37 | C73: 140341000 | D73: 85.2
A74: 46235 | B74: =Inputs!$A$38 | C74: 120980000 | D74: 76.4
A75: 46235 | B75: =Inputs!$A$39 | C75: 127427000 | D75: 78.4
A76: 46235 | B76: =Inputs!$A$40 | C76: 138116000 | D76: 82
A77: 46235 | B77: =Inputs!$A$41 | C77: 124473000 | D77: 77.3
A78: 46235 | B78: =Inputs!$A$42 | C78: 80868000 | D78: 73.9
A79: 46235 | B79: =Inputs!$A$43 | C79: 106389000 | D79: 76.2
A80: 46235 | B80: =Inputs!$A$44 | D80: 112.5
A81: 46235 | B81: =Inputs!$A$45 | D81: 112.6
A82: 46266 | B82: =Inputs!$A$36 | C82: 156142000 | D82: 80.3
A83: 46266 | B83: =Inputs!$A$37 | C83: 142762000 | D83: 83.8
A84: 46266 | B84: =Inputs!$A$38 | C84: 116520000 | D84: 77
A85: 46266 | B85: =Inputs!$A$39 | C85: 127790000 | D85: 77.7
A86: 46266 | B86: =Inputs!$A$40 | C86: 137926000 | D86: 83.4
A87: 46266 | B87: =Inputs!$A$41 | C87: 123052000 | D87: 78.7
A88: 46266 | B88: =Inputs!$A$42 | C88: 81937000 | D88: 74.4
A89: 46266 | B89: =Inputs!$A$43 | C89: 109683000 | D89: 77.7
A90: 46266 | B90: =Inputs!$A$44 | D90: 116
A91: 46266 | B91: =Inputs!$A$45 | D91: 108.8
A92: 46296 | B92: =Inputs!$A$36 | C92: 162709000 | D92: 82.6
A93: 46296 | B93: =Inputs!$A$37 | C93: 152617000 | D93: 83.7
A94: 46296 | B94: =Inputs!$A$38 | C94: 121209000 | D94: 77.9
A95: 46296 | B95: =Inputs!$A$39 | C95: 132476000 | D95: 80
A96: 46296 | B96: =Inputs!$A$40 | C96: 144069000 | D96: 81.7
A97: 46296 | B97: =Inputs!$A$41 | C97: 125299000 | D97: 77.6
A98: 46296 | B98: =Inputs!$A$42 | C98: 84261000 | D98: 74
A99: 46296 | B99: =Inputs!$A$43 | C99: 112849000 | D99: 75.5
A100: 46296 | B100: =Inputs!$A$44 | D100: 116.9
...

Sheet Cases_Forecast
A1: Cases forecast
A2: 1. Run rate: volume driver sales x cases per $ of sales in the same month last year. Actual months show actuals.
A3: 2. Adjustments: type extra cases (or negative) for a site and month, e.g. a new store or volume moving between sites.
A4: 3. Override: type the cases you want for a site and month. It replaces 1 + 2. Leave blank to use the model.
A5: 4. Cases used = override if there is one, otherwise run rate + adjustment. This feeds Cases picked on each site tab.
C6: 1. Run-rate forecast | N6: 2. Adjustments (+/- cases) | Y6: 3. Override (replaces 1 + 2) | AJ6: 4. Cases forecast used
A7: Month | B7: Status | C7: =Inputs!$A$36 | D7: =Inputs!$A$37 | E7: =Inputs!$A$38 | F7: =Inputs!$A$39 | G7: =Inputs!$A$40 | H7: =Inputs!$A$41 | I7: =Inputs!$A$42 | J7: =Inputs!$A$43 | K7: =Inputs!$A$44 | L7: =Inputs!$A$45 | N7: =Inputs!$A$36 | O7: =Inputs!$A$37 | P7: =Inputs!$A$38 | Q7: =Inputs!$A$39 | R7: =Inputs!$A$40 | S7: =Inputs!$A$41 | T7: =Inputs!$A$42 | U7: =Inputs!$A$43 | V7: =Inputs!$A$44 | W7: =Inputs!$A$45 | Y7: =Inputs!$A$36 | Z7: =Inputs!$A$37 | AA7: =Inputs!$A$38 | AB7: =Inputs!$A$39 | AC7: =Inputs!$A$40 | AD7: =Inputs!$A$41 | AE7: =Inputs!$A$42 | AF7: =Inputs!$A$43 | AG7: =Inputs!$A$44 | AH7: =Inputs!$A$45 | AJ7: =Inputs!$A$36 | AK7: =Inputs!$A$37 | AL7: =Inputs!$A$38 | AM7: =Inputs!$A$39 | AN7: =Inputs!$A$40 | AO7: =Inputs!$A$41 | AP7: =Inputs!$A$42 | AQ7: =Inputs!$A$43 | AR7: =Inputs!$A$44 | AS7: =Inputs!$A$45
A8: 45658 | B8: =IF(A8<=LastActual,"Actual","Forecast") | C8: =IF($B8="Actual",'NSW-1'!S15,IFERROR('NSW-1'!Y15*'NSW-1'!AB15,0)) | D8: =IF($B8="Actual",'VIC-1'!S15,IFERROR('VIC-1'!Y15*'VIC-1'!AB15,0)) | E8: =IF($B8="Actual",'QLD-1'!S15,IFERROR('QLD-1'!Y15*'QLD-1'!AB15,0)) | F8: =IF($B8="Actual",'NSW-2'!S15,IFERROR('NSW-2'!Y15*'NSW-2'!AB15,0)) | G8: =IF($B8="Actual",'VIC-2'!S15,IFERROR('VIC-2'!Y15*'VIC-2'!AB15,0)) | H8: =IF($B8="Actual",'QLD-2'!S15,IFERROR('QLD-2'!Y15*'QLD-2'!AB15,0)) | I8: =IF($B8="Actual",'SA-1'!S15,IFERROR('SA-1'!Y15*'SA-1'!AB15,0)) | J8: =IF($B8="Actual",'WA-1'!S15,IFERROR('WA-1'!Y15*'WA-1'!AB15,0)) | K8: =IF($B8="Actual",'IDC-NSW'!S15,IFERROR('IDC-NSW'!Y15*'IDC-NSW'!AB15,0)) | L8: =IF($B8="Actual",'IDC-VIC'!S15,IFERROR('IDC-VIC'!Y15*'IDC-VIC'!AB15,0)) | AJ8: =IF($B8="Actual",C8,IF(Y8<>"",Y8,C8+N(N8))) | AK8: =IF($B8="Actual",D8,IF(Z8<>"",Z8,D8+N(O8))) | AL8: =IF($B8="Actual",E8,IF(AA8<>"",AA8,E8+N(P8))) | AM8: =IF($B8="Actual",F8,IF(AB8<>"",AB8,F8+N(Q8))) | AN8: =IF($B8="Actual",G8,IF(AC8<>"",AC8,G8+N(R8))) | AO8: =IF($B8="Actual",H8,IF(AD8<>"",AD8,H8+N(S8))) | AP8: =IF($B8="Actual",I8,IF(AE8<>"",AE8,I8+N(T8))) | AQ8: =IF($B8="Actual",J8,IF(AF8<>"",AF8,J8+N(U8))) | ... AS8: =IF($B8="Actual",L8,IF(AH8<>"",AH8,L8+N(W8)))
A9: 45689 | B9: =IF(A9<=LastActual,"Actual","Forecast") | C9: =IF($B9="Actual",'NSW-1'!S16,IFERROR('NSW-1'!Y16*'NSW-1'!AB16,0)) | D9: =IF($B9="Actual",'VIC-1'!S16,IFERROR('VIC-1'!Y16*'VIC-1'!AB16,0)) | E9: =IF($B9="Actual",'QLD-1'!S16,IFERROR('QLD-1'!Y16*'QLD-1'!AB16,0)) | F9: =IF($B9="Actual",'NSW-2'!S16,IFERROR('NSW-2'!Y16*'NSW-2'!AB16,0)) | G9: =IF($B9="Actual",'VIC-2'!S16,IFERROR('VIC-2'!Y16*'VIC-2'!AB16,0)) | H9: =IF($B9="Actual",'QLD-2'!S16,IFERROR('QLD-2'!Y16*'QLD-2'!AB16,0)) | I9: =IF($B9="Actual",'SA-1'!S16,IFERROR('SA-1'!Y16*'SA-1'!AB16,0)) | J9: =IF($B9="Actual",'WA-1'!S16,IFERROR('WA-1'!Y16*'WA-1'!AB16,0)) | K9: =IF($B9="Actual",'IDC-NSW'!S16,IFERROR('IDC-NSW'!Y16*'IDC-NSW'!AB16,0)) | L9: =IF($B9="Actual",'IDC-VIC'!S16,IFERROR('IDC-VIC'!Y16*'IDC-VIC'!AB16,0)) | AJ9: =IF($B9="Actual",C9,IF(Y9<>"",Y9,C9+N(N9))) | AK9: =IF($B9="Actual",D9,IF(Z9<>"",Z9,D9+N(O9))) | AL9: =IF($B9="Actual",E9,IF(AA9<>"",AA9,E9+N(P9))) | AM9: =IF($B9="Actual",F9,IF(AB9<>"",AB9,F9+N(Q9))) | AN9: =IF($B9="Actual",G9,IF(AC9<>"",AC9,G9+N(R9))) | AO9: =IF($B9="Actual",H9,IF(AD9<>"",AD9,H9+N(S9))) | AP9: =IF($B9="Actual",I9,IF(AE9<>"",AE9,I9+N(T9))) | AQ9: =IF($B9="Actual",J9,IF(AF9<>"",AF9,J9+N(U9))) | ... AS9: =IF($B9="Actual",L9,IF(AH9<>"",AH9,L9+N(W9)))
A10: 45717 | B10: =IF(A10<=LastActual,"Actual","Forecast") | C10: =IF($B10="Actual",'NSW-1'!S17,IFERROR('NSW-1'!Y17*'NSW-1'!AB17,0)) | D10: =IF($B10="Actual",'VIC-1'!S17,IFERROR('VIC-1'!Y17*'VIC-1'!AB17,0)) | E10: =IF($B10="Actual",'QLD-1'!S17,IFERROR('QLD-1'!Y17*'QLD-1'!AB17,0)) | F10: =IF($B10="Actual",'NSW-2'!S17,IFERROR('NSW-2'!Y17*'NSW-2'!AB17,0)) | G10: =IF($B10="Actual",'VIC-2'!S17,IFERROR('VIC-2'!Y17*'VIC-2'!AB17,0)) | H10: =IF($B10="Actual",'QLD-2'!S17,IFERROR('QLD-2'!Y17*'QLD-2'!AB17,0)) | I10: =IF($B10="Actual",'SA-1'!S17,IFERROR('SA-1'!Y17*'SA-1'!AB17,0)) | J10: =IF($B10="Actual",'WA-1'!S17,IFERROR('WA-1'!Y17*'WA-1'!AB17,0)) | K10: =IF($B10="Actual",'IDC-NSW'!S17,IFERROR('IDC-NSW'!Y17*'IDC-NSW'!AB17,0)) | L10: =IF($B10="Actual",'IDC-VIC'!S17,IFERROR('IDC-VIC'!Y17*'IDC-VIC'!AB17,0)) | AJ10: =IF($B10="Actual",C10,IF(Y10<>"",Y10,C10+N(N10))) | AK10: =IF($B10="Actual",D10,IF(Z10<>"",Z10,D10+N(O10))) | AL10: =IF($B10="Actual",E10,IF(AA10<>"",AA10,E10+N(P10))) | AM10: =IF($B10="Actual",F10,IF(AB10<>"",AB10,F10+N(Q10))) | AN10: =IF($B10="Actual",G10,IF(AC10<>"",AC10,G10+N(R10))) | AO10: =IF($B10="Actual",H10,IF(AD10<>"",AD10,H10+N(S10))) | AP10: =IF($B10="Actual",I10,IF(AE10<>"",AE10,I10+N(T10))) | AQ10: =IF($B10="Actual",J10,IF(AF10<>"",AF10,J10+N(U10))) | ... AS10: =IF($B10="Actual",L10,IF(AH10<>"",AH10,L10+N(W10)))
A11: 45748 | B11: =IF(A11<=LastActual,"Actual","Forecast") | C11: =IF($B11="Actual",'NSW-1'!S18,IFERROR('NSW-1'!Y18*'NSW-1'!AB18,0)) | D11: =IF($B11="Actual",'VIC-1'!S18,IFERROR('VIC-1'!Y18*'VIC-1'!AB18,0)) | E11: =IF($B11="Actual",'QLD-1'!S18,IFERROR('QLD-1'!Y18*'QLD-1'!AB18,0)) | F11: =IF($B11="Actual",'NSW-2'!S18,IFERROR('NSW-2'!Y18*'NSW-2'!AB18,0)) | G11: =IF($B11="Actual",'VIC-2'!S18,IFERROR('VIC-2'!Y18*'VIC-2'!AB18,0)) | H11: =IF($B11="Actual",'QLD-2'!S18,IFERROR('QLD-2'!Y18*'QLD-2'!AB18,0)) | I11: =IF($B11="Actual",'SA-1'!S18,IFERROR('SA-1'!Y18*'SA-1'!AB18,0)) | J11: =IF($B11="Actual",'WA-1'!S18,IFERROR('WA-1'!Y18*'WA-1'!AB18,0)) | K11: =IF($B11="Actual",'IDC-NSW'!S18,IFERROR('IDC-NSW'!Y18*'IDC-NSW'!AB18,0)) | L11: =IF($B11="Actual",'IDC-VIC'!S18,IFERROR('IDC-VIC'!Y18*'IDC-VIC'!AB18,0)) | AJ11: =IF($B11="Actual",C11,IF(Y11<>"",Y11,C11+N(N11))) | AK11: =IF($B11="Actual",D11,IF(Z11<>"",Z11,D11+N(O11))) | AL11: =IF($B11="Actual",E11,IF(AA11<>"",AA11,E11+N(P11))) | AM11: =IF($B11="Actual",F11,IF(AB11<>"",AB11,F11+N(Q11))) | AN11: =IF($B11="Actual",G11,IF(AC11<>"",AC11,G11+N(R11))) | AO11: =IF($B11="Actual",H11,IF(AD11<>"",AD11,H11+N(S11))) | AP11: =IF($B11="Actual",I11,IF(AE11<>"",AE11,I11+N(T11))) | AQ11: =IF($B11="Actual",J11,IF(AF11<>"",AF11,J11+N(U11))) | ... AS11: =IF($B11="Actual",L11,IF(AH11<>"",AH11,L11+N(W11)))
A12: 45778 | B12: =IF(A12<=LastActual,"Actual","Forecast") | C12: =IF($B12="Actual",'NSW-1'!S19,IFERROR('NSW-1'!Y19*'NSW-1'!AB19,0)) | D12: =IF($B12="Actual",'VIC-1'!S19,IFERROR('VIC-1'!Y19*'VIC-1'!AB19,0)) | E12: =IF($B12="Actual",'QLD-1'!S19,IFERROR('QLD-1'!Y19*'QLD-1'!AB19,0)) | F12: =IF($B12="Actual",'NSW-2'!S19,IFERROR('NSW-2'!Y19*'NSW-2'!AB19,0)) | G12: =IF($B12="Actual",'VIC-2'!S19,IFERROR('VIC-2'!Y19*'VIC-2'!AB19,0)) | H12: =IF($B12="Actual",'QLD-2'!S19,IFERROR('QLD-2'!Y19*'QLD-2'!AB19,0)) | I12: =IF($B12="Actual",'SA-1'!S19,IFERROR('SA-1'!Y19*'SA-1'!AB19,0)) | J12: =IF($B12="Actual",'WA-1'!S19,IFERROR('WA-1'!Y19*'WA-1'!AB19,0)) | K12: =IF($B12="Actual",'IDC-NSW'!S19,IFERROR('IDC-NSW'!Y19*'IDC-NSW'!AB19,0)) | L12: =IF($B12="Actual",'IDC-VIC'!S19,IFERROR('IDC-VIC'!Y19*'IDC-VIC'!AB19,0)) | AJ12: =IF($B12="Actual",C12,IF(Y12<>"",Y12,C12+N(N12))) | AK12: =IF($B12="Actual",D12,IF(Z12<>"",Z12,D12+N(O12))) | AL12: =IF($B12="Actual",E12,IF(AA12<>"",AA12,E12+N(P12))) | AM12: =IF($B12="Actual",F12,IF(AB12<>"",AB12,F12+N(Q12))) | AN12: =IF($B12="Actual",G12,IF(AC12<>"",AC12,G12+N(R12))) | AO12: =IF($B12="Actual",H12,IF(AD12<>"",AD12,H12+N(S12))) | AP12: =IF($B12="Actual",I12,IF(AE12<>"",AE12,I12+N(T12))) | AQ12: =IF($B12="Actual",J12,IF(AF12<>"",AF12,J12+N(U12))) | ... AS12: =IF($B12="Actual",L12,IF(AH12<>"",AH12,L12+N(W12)))
A13: 45809 | B13: =IF(A13<=LastActual,"Actual","Forecast") | C13: =IF($B13="Actual",'NSW-1'!S20,IFERROR('NSW-1'!Y20*'NSW-1'!AB20,0)) | D13: =IF($B13="Actual",'VIC-1'!S20,IFERROR('VIC-1'!Y20*'VIC-1'!AB20,0)) | E13: =IF($B13="Actual",'QLD-1'!S20,IFERROR('QLD-1'!Y20*'QLD-1'!AB20,0)) | F13: =IF($B13="Actual",'NSW-2'!S20,IFERROR('NSW-2'!Y20*'NSW-2'!AB20,0)) | G13: =IF($B13="Actual",'VIC-2'!S20,IFERROR('VIC-2'!Y20*'VIC-2'!AB20,0)) | H13: =IF($B13="Actual",'QLD-2'!S20,IFERROR('QLD-2'!Y20*'QLD-2'!AB20,0)) | I13: =IF($B13="Actual",'SA-1'!S20,IFERROR('SA-1'!Y20*'SA-1'!AB20,0)) | J13: =IF($B13="Actual",'WA-1'!S20,IFERROR('WA-1'!Y20*'WA-1'!AB20,0)) | K13: =IF($B13="Actual",'IDC-NSW'!S20,IFERROR('IDC-NSW'!Y20*'IDC-NSW'!AB20,0)) | L13: =IF($B13="Actual",'IDC-VIC'!S20,IFERROR('IDC-VIC'!Y20*'IDC-VIC'!AB20,0)) | AJ13: =IF($B13="Actual",C13,IF(Y13<>"",Y13,C13+N(N13))) | AK13: =IF($B13="Actual",D13,IF(Z13<>"",Z13,D13+N(O13))) | AL13: =IF($B13="Actual",E13,IF(AA13<>"",AA13,E13+N(P13))) | AM13: =IF($B13="Actual",F13,IF(AB13<>"",AB13,F13+N(Q13))) | AN13: =IF($B13="Actual",G13,IF(AC13<>"",AC13,G13+N(R13))) | AO13: =IF($B13="Actual",H13,IF(AD13<>"",AD13,H13+N(S13))) | AP13: =IF($B13="Actual",I13,IF(AE13<>"",AE13,I13+N(T13))) | AQ13: =IF($B13="Actual",J13,IF(AF13<>"",AF13,J13+N(U13))) | ... AS13: =IF($B13="Actual",L13,IF(AH13<>"",AH13,L13+N(W13)))
A14: 45839 | B14: =IF(A14<=LastActual,"Actual","Forecast") | C14: =IF($B14="Actual",'NSW-1'!S21,IFERROR('NSW-1'!Y21*'NSW-1'!AB21,0)) | D14: =IF($B14="Actual",'VIC-1'!S21,IFERROR('VIC-1'!Y21*'VIC-1'!AB21,0)) | E14: =IF($B14="Actual",'QLD-1'!S21,IFERROR('QLD-1'!Y21*'QLD-1'!AB21,0)) | F14: =IF($B14="Actual",'NSW-2'!S21,IFERROR('NSW-2'!Y21*'NSW-2'!AB21,0)) | G14: =IF($B14="Actual",'VIC-2'!S21,IFERROR('VIC-2'!Y21*'VIC-2'!AB21,0)) | H14: =IF($B14="Actual",'QLD-2'!S21,IFERROR('QLD-2'!Y21*'QLD-2'!AB21,0)) | I14: =IF($B14="Actual",'SA-1'!S21,IFERROR('SA-1'!Y21*'SA-1'!AB21,0)) | J14: =IF($B14="Actual",'WA-1'!S21,IFERROR('WA-1'!Y21*'WA-1'!AB21,0)) | K14: =IF($B14="Actual",'IDC-NSW'!S21,IFERROR('IDC-NSW'!Y21*'IDC-NSW'!AB21,0)) | L14: =IF($B14="Actual",'IDC-VIC'!S21,IFERROR('IDC-VIC'!Y21*'IDC-VIC'!AB21,0)) | AJ14: =IF($B14="Actual",C14,IF(Y14<>"",Y14,C14+N(N14))) | AK14: =IF($B14="Actual",D14,IF(Z14<>"",Z14,D14+N(O14))) | AL14: =IF($B14="Actual",E14,IF(AA14<>"",AA14,E14+N(P14))) | AM14: =IF($B14="Actual",F14,IF(AB14<>"",AB14,F14+N(Q14))) | AN14: =IF($B14="Actual",G14,IF(AC14<>"",AC14,G14+N(R14))) | AO14: =IF($B14="Actual",H14,IF(AD14<>"",AD14,H14+N(S14))) | AP14: =IF($B14="Actual",I14,IF(AE14<>"",AE14,I14+N(T14))) | AQ14: =IF($B14="Actual",J14,IF(AF14<>"",AF14,J14+N(U14))) | ... AS14: =IF($B14="Actual",L14,IF(AH14<>"",AH14,L14+N(W14)))
A15: 45870 | B15: =IF(A15<=LastActual,"Actual","Forecast") | C15: =IF($B15="Actual",'NSW-1'!S22,IFERROR('NSW-1'!Y22*'NSW-1'!AB22,0)) | D15: =IF($B15="Actual",'VIC-1'!S22,IFERROR('VIC-1'!Y22*'VIC-1'!AB22,0)) | E15: =IF($B15="Actual",'QLD-1'!S22,IFERROR('QLD-1'!Y22*'QLD-1'!AB22,0)) | F15: =IF($B15="Actual",'NSW-2'!S22,IFERROR('NSW-2'!Y22*'NSW-2'!AB22,0)) | G15: =IF($B15="Actual",'VIC-2'!S22,IFERROR('VIC-2'!Y22*'VIC-2'!AB22,0)) | H15: =IF($B15="Actual",'QLD-2'!S22,IFERROR('QLD-2'!Y22*'QLD-2'!AB22,0)) | I15: =IF($B15="Actual",'SA-1'!S22,IFERROR('SA-1'!Y22*'SA-1'!AB22,0)) | J15: =IF($B15="Actual",'WA-1'!S22,IFERROR('WA-1'!Y22*'WA-1'!AB22,0)) | K15: =IF($B15="Actual",'IDC-NSW'!S22,IFERROR('IDC-NSW'!Y22*'IDC-NSW'!AB22,0)) | L15: =IF($B15="Actual",'IDC-VIC'!S22,IFERROR('IDC-VIC'!Y22*'IDC-VIC'!AB22,0)) | AJ15: =IF($B15="Actual",C15,IF(Y15<>"",Y15,C15+N(N15))) | AK15: =IF($B15="Actual",D15,IF(Z15<>"",Z15,D15+N(O15))) | AL15: =IF($B15="Actual",E15,IF(AA15<>"",AA15,E15+N(P15))) | AM15: =IF($B15="Actual",F15,IF(AB15<>"",AB15,F15+N(Q15))) | AN15: =IF($B15="Actual",G15,IF(AC15<>"",AC15,G15+N(R15))) | AO15: =IF($B15="Actual",H15,IF(AD15<>"",AD15,H15+N(S15))) | AP15: =IF($B15="Actual",I15,IF(AE15<>"",AE15,I15+N(T15))) | AQ15: =IF($B15="Actual",J15,IF(AF15<>"",AF15,J15+N(U15))) | ... AS15: =IF($B15="Actual",L15,IF(AH15<>"",AH15,L15+N(W15)))
A16: 45901 | B16: =IF(A16<=LastActual,"Actual","Forecast") | C16: =IF($B16="Actual",'NSW-1'!S23,IFERROR('NSW-1'!Y23*'NSW-1'!AB23,0)) | D16: =IF($B16="Actual",'VIC-1'!S23,IFERROR('VIC-1'!Y23*'VIC-1'!AB23,0)) | E16: =IF($B16="Actual",'QLD-1'!S23,IFERROR('QLD-1'!Y23*'QLD-1'!AB23,0)) | F16: =IF($B16="Actual",'NSW-2'!S23,IFERROR('NSW-2'!Y23*'NSW-2'!AB23,0)) | G16: =IF($B16="Actual",'VIC-2'!S23,IFERROR('VIC-2'!Y23*'VIC-2'!AB23,0)) | H16: =IF($B16="Actual",'QLD-2'!S23,IFERROR('QLD-2'!Y23*'QLD-2'!AB23,0)) | I16: =IF($B16="Actual",'SA-1'!S23,IFERROR('SA-1'!Y23*'SA-1'!AB23,0)) | J16: =IF($B16="Actual",'WA-1'!S23,IFERROR('WA-1'!Y23*'WA-1'!AB23,0)) | K16: =IF($B16="Actual",'IDC-NSW'!S23,IFERROR('IDC-NSW'!Y23*'IDC-NSW'!AB23,0)) | L16: =IF($B16="Actual",'IDC-VIC'!S23,IFERROR('IDC-VIC'!Y23*'IDC-VIC'!AB23,0)) | AJ16: =IF($B16="Actual",C16,IF(Y16<>"",Y16,C16+N(N16))) | AK16: =IF($B16="Actual",D16,IF(Z16<>"",Z16,D16+N(O16))) | AL16: =IF($B16="Actual",E16,IF(AA16<>"",AA16,E16+N(P16))) | AM16: =IF($B16="Actual",F16,IF(AB16<>"",AB16,F16+N(Q16))) | AN16: =IF($B16="Actual",G16,IF(AC16<>"",AC16,G16+N(R16))) | AO16: =IF($B16="Actual",H16,IF(AD16<>"",AD16,H16+N(S16))) | AP16: =IF($B16="Actual",I16,IF(AE16<>"",AE16,I16+N(T16))) | AQ16: =IF($B16="Actual",J16,IF(AF16<>"",AF16,J16+N(U16))) | ... AS16: =IF($B16="Actual",L16,IF(AH16<>"",AH16,L16+N(W16)))
A17: 45931 | B17: =IF(A17<=LastActual,"Actual","Forecast") | C17: =IF($B17="Actual",'NSW-1'!S24,IFERROR('NSW-1'!Y24*'NSW-1'!AB24,0)) | D17: =IF($B17="Actual",'VIC-1'!S24,IFERROR('VIC-1'!Y24*'VIC-1'!AB24,0)) | E17: =IF($B17="Actual",'QLD-1'!S24,IFERROR('QLD-1'!Y24*'QLD-1'!AB24,0)) | F17: =IF($B17="Actual",'NSW-2'!S24,IFERROR('NSW-2'!Y24*'NSW-2'!AB24,0)) | G17: =IF($B17="Actual",'VIC-2'!S24,IFERROR('VIC-2'!Y24*'VIC-2'!AB24,0)) | H17: =IF($B17="Actual",'QLD-2'!S24,IFERROR('QLD-2'!Y24*'QLD-2'!AB24,0)) | I17: =IF($B17="Actual",'SA-1'!S24,IFERROR('SA-1'!Y24*'SA-1'!AB24,0)) | J17: =IF($B17="Actual",'WA-1'!S24,IFERROR('WA-1'!Y24*'WA-1'!AB24,0)) | K17: =IF($B17="Actual",'IDC-NSW'!S24,IFERROR('IDC-NSW'!Y24*'IDC-NSW'!AB24,0)) | L17: =IF($B17="Actual",'IDC-VIC'!S24,IFERROR('IDC-VIC'!Y24*'IDC-VIC'!AB24,0)) | AJ17: =IF($B17="Actual",C17,IF(Y17<>"",Y17,C17+N(N17))) | AK17: =IF($B17="Actual",D17,IF(Z17<>"",Z17,D17+N(O17))) | AL17: =IF($B17="Actual",E17,IF(AA17<>"",AA17,E17+N(P17))) | AM17: =IF($B17="Actual",F17,IF(AB17<>"",AB17,F17+N(Q17))) | AN17: =IF($B17="Actual",G17,IF(AC17<>"",AC17,G17+N(R17))) | AO17: =IF($B17="Actual",H17,IF(AD17<>"",AD17,H17+N(S17))) | AP17: =IF($B17="Actual",I17,IF(AE17<>"",AE17,I17+N(T17))) | AQ17: =IF($B17="Actual",J17,IF(AF17<>"",AF17,J17+N(U17))) | ... AS17: =IF($B17="Actual",L17,IF(AH17<>"",AH17,L17+N(W17)))
A18: 45962 | B18: =IF(A18<=LastActual,"Actual","Forecast") | C18: =IF($B18="Actual",'NSW-1'!S25,IFERROR('NSW-1'!Y25*'NSW-1'!AB25,0)) | D18: =IF($B18="Actual",'VIC-1'!S25,IFERROR('VIC-1'!Y25*'VIC-1'!AB25,0)) | E18: =IF($B18="Actual",'QLD-1'!S25,IFERROR('QLD-1'!Y25*'QLD-1'!AB25,0)) | F18: =IF($B18="Actual",'NSW-2'!S25,IFERROR('NSW-2'!Y25*'NSW-2'!AB25,0)) | G18: =IF($B18="Actual",'VIC-2'!S25,IFERROR('VIC-2'!Y25*'VIC-2'!AB25,0)) | H18: =IF($B18="Actual",'QLD-2'!S25,IFERROR('QLD-2'!Y25*'QLD-2'!AB25,0)) | I18: =IF($B18="Actual",'SA-1'!S25,IFERROR('SA-1'!Y25*'SA-1'!AB25,0)) | J18: =IF($B18="Actual",'WA-1'!S25,IFERROR('WA-1'!Y25*'WA-1'!AB25,0)) | K18: =IF($B18="Actual",'IDC-NSW'!S25,IFERROR('IDC-NSW'!Y25*'IDC-NSW'!AB25,0)) | L18: =IF($B18="Actual",'IDC-VIC'!S25,IFERROR('IDC-VIC'!Y25*'IDC-VIC'!AB25,0)) | AJ18: =IF($B18="Actual",C18,IF(Y18<>"",Y18,C18+N(N18))) | AK18: =IF($B18="Actual",D18,IF(Z18<>"",Z18,D18+N(O18))) | AL18: =IF($B18="Actual",E18,IF(AA18<>"",AA18,E18+N(P18))) | AM18: =IF($B18="Actual",F18,IF(AB18<>"",AB18,F18+N(Q18))) | AN18: =IF($B18="Actual",G18,IF(AC18<>"",AC18,G18+N(R18))) | AO18: =IF($B18="Actual",H18,IF(AD18<>"",AD18,H18+N(S18))) | AP18: =IF($B18="Actual",I18,IF(AE18<>"",AE18,I18+N(T18))) | AQ18: =IF($B18="Actual",J18,IF(AF18<>"",AF18,J18+N(U18))) | ... AS18: =IF($B18="Actual",L18,IF(AH18<>"",AH18,L18+N(W18)))
A19: 45992 | B19: =IF(A19<=LastActual,"Actual","Forecast") | C19: =IF($B19="Actual",'NSW-1'!S26,IFERROR('NSW-1'!Y26*'NSW-1'!AB26,0)) | D19: =IF($B19="Actual",'VIC-1'!S26,IFERROR('VIC-1'!Y26*'VIC-1'!AB26,0)) | E19: =IF($B19="Actual",'QLD-1'!S26,IFERROR('QLD-1'!Y26*'QLD-1'!AB26,0)) | F19: =IF($B19="Actual",'NSW-2'!S26,IFERROR('NSW-2'!Y26*'NSW-2'!AB26,0)) | G19: =IF($B19="Actual",'VIC-2'!S26,IFERROR('VIC-2'!Y26*'VIC-2'!AB26,0)) | H19: =IF($B19="Actual",'QLD-2'!S26,IFERROR('QLD-2'!Y26*'QLD-2'!AB26,0)) | I19: =IF($B19="Actual",'SA-1'!S26,IFERROR('SA-1'!Y26*'SA-1'!AB26,0)) | J19: =IF($B19="Actual",'WA-1'!S26,IFERROR('WA-1'!Y26*'WA-1'!AB26,0)) | K19: =IF($B19="Actual",'IDC-NSW'!S26,IFERROR('IDC-NSW'!Y26*'IDC-NSW'!AB26,0)) | L19: =IF($B19="Actual",'IDC-VIC'!S26,IFERROR('IDC-VIC'!Y26*'IDC-VIC'!AB26,0)) | AJ19: =IF($B19="Actual",C19,IF(Y19<>"",Y19,C19+N(N19))) | AK19: =IF($B19="Actual",D19,IF(Z19<>"",Z19,D19+N(O19))) | AL19: =IF($B19="Actual",E19,IF(AA19<>"",AA19,E19+N(P19))) | AM19: =IF($B19="Actual",F19,IF(AB19<>"",AB19,F19+N(Q19))) | AN19: =IF($B19="Actual",G19,IF(AC19<>"",AC19,G19+N(R19))) | AO19: =IF($B19="Actual",H19,IF(AD19<>"",AD19,H19+N(S19))) | AP19: =IF($B19="Actual",I19,IF(AE19<>"",AE19,I19+N(T19))) | AQ19: =IF($B19="Actual",J19,IF(AF19<>"",AF19,J19+N(U19))) | ... AS19: =IF($B19="Actual",L19,IF(AH19<>"",AH19,L19+N(W19)))
... A55: 47088 | B55: =IF(A55<=LastActual,"Actual","Forecast") | C55: =IF($B55="Actual",'NSW-1'!S62,IFERROR('NSW-1'!Y62*'NSW-1'!AB62,0)) | D55: =IF($B55="Actual",'VIC-1'!S62,IFERROR('VIC-1'!Y62*'VIC-1'!AB62,0)) | E55: =IF($B55="Actual",'QLD-1'!S62,IFERROR('QLD-1'!Y62*'QLD-1'!AB62,0)) | F55: =IF($B55="Actual",'NSW-2'!S62,IFERROR('NSW-2'!Y62*'NSW-2'!AB62,0)) | G55: =IF($B55="Actual",'VIC-2'!S62,IFERROR('VIC-2'!Y62*'VIC-2'!AB62,0)) | H55: =IF($B55="Actual",'QLD-2'!S62,IFERROR('QLD-2'!Y62*'QLD-2'!AB62,0)) | I55: =IF($B55="Actual",'SA-1'!S62,IFERROR('SA-1'!Y62*'SA-1'!AB62,0)) | J55: =IF($B55="Actual",'WA-1'!S62,IFERROR('WA-1'!Y62*'WA-1'!AB62,0)) | K55: =IF($B55="Actual",'IDC-NSW'!S62,IFERROR('IDC-NSW'!Y62*'IDC-NSW'!AB62,0)) | L55: =IF($B55="Actual",'IDC-VIC'!S62,IFERROR('IDC-VIC'!Y62*'IDC-VIC'!AB62,0)) | AJ55: =IF($B55="Actual",C55,IF(Y55<>"",Y55,C55+N(N55))) | AK55: =IF($B55="Actual",D55,IF(Z55<>"",Z55,D55+N(O55))) | AL55: =IF($B55="Actual",E55,IF(AA55<>"",AA55,E55+N(P55))) | AM55: =IF($B55="Actual",F55,IF(AB55<>"",AB55,F55+N(Q55))) | AN55: =IF($B55="Actual",G55,IF(AC55<>"",AC55,G55+N(R55))) | AO55: =IF($B55="Actual",H55,IF(AD55<>"",AD55,H55+N(S55))) | AP55: =IF($B55="Actual",I55,IF(AE55<>"",AE55,I55+N(T55))) | AQ55: =IF($B55="Actual",J55,IF(AF55<>"",AF55,J55+N(U55))) | ... AS55: =IF($B55="Actual",L55,IF(AH55<>"",AH55,L55+N(W55)))

Sheet CPLH_Forecast
A1: CPLH forecast (cases per labour hour)
A2: 1. Plan: plan CPLH (Plan_Inputs, or CPLH_Breakdown if picked on Inputs). Blank plan = same month last year. Actuals show actuals.
A3: 2. Adjustments: type a change in cases per hour for a site and month, e.g. +2 for a new pick system.
A4: 3. Override: type the CPLH you want for a site and month, e.g. a target. It replaces 1 + 2. Leave blank to use the model.
A5: 4. CPLH used = override if there is one, otherwise run rate + adjustment. This drives hours, and so payroll, on each site tab.
C6: 1. Plan CPLH (else same month LY) | N6: 2. Adjustments (+/- cases / hr) | Y6: 3. Override (replaces 1 + 2) | AJ6: 4. CPLH forecast used
A7: Month | B7: Status | C7: =Inputs!$A$36 | D7: =Inputs!$A$37 | E7: =Inputs!$A$38 | F7: =Inputs!$A$39 | G7: =Inputs!$A$40 | H7: =Inputs!$A$41 | I7: =Inputs!$A$42 | J7: =Inputs!$A$43 | K7: =Inputs!$A$44 | L7: =Inputs!$A$45 | N7: =Inputs!$A$36 | O7: =Inputs!$A$37 | P7: =Inputs!$A$38 | Q7: =Inputs!$A$39 | R7: =Inputs!$A$40 | S7: =Inputs!$A$41 | T7: =Inputs!$A$42 | U7: =Inputs!$A$43 | V7: =Inputs!$A$44 | W7: =Inputs!$A$45 | Y7: =Inputs!$A$36 | Z7: =Inputs!$A$37 | AA7: =Inputs!$A$38 | AB7: =Inputs!$A$39 | AC7: =Inputs!$A$40 | AD7: =Inputs!$A$41 | AE7: =Inputs!$A$42 | AF7: =Inputs!$A$43 | AG7: =Inputs!$A$44 | AH7: =Inputs!$A$45 | AJ7: =Inputs!$A$36 | AK7: =Inputs!$A$37 | AL7: =Inputs!$A$38 | AM7: =Inputs!$A$39 | AN7: =Inputs!$A$40 | AO7: =Inputs!$A$41 | AP7: =Inputs!$A$42 | AQ7: =Inputs!$A$43 | AR7: =Inputs!$A$44 | AS7: =Inputs!$A$45
A8: 45658 | B8: =IF(A8<=LastActual,"Actual","Forecast") | C8: =IF(AND($B8="Forecast",N('NSW-1'!AH15)>0),'NSW-1'!AH15,IFERROR('NSW-1'!X15*1,0)) | D8: =IF(AND($B8="Forecast",N('VIC-1'!AH15)>0),'VIC-1'!AH15,IFERROR('VIC-1'!X15*1,0)) | E8: =IF(AND($B8="Forecast",N('QLD-1'!AH15)>0),'QLD-1'!AH15,IFERROR('QLD-1'!X15*1,0)) | F8: =IF(AND($B8="Forecast",N('NSW-2'!AH15)>0),'NSW-2'!AH15,IFERROR('NSW-2'!X15*1,0)) | G8: =IF(AND($B8="Forecast",N('VIC-2'!AH15)>0),'VIC-2'!AH15,IFERROR('VIC-2'!X15*1,0)) | H8: =IF(AND($B8="Forecast",N('QLD-2'!AH15)>0),'QLD-2'!AH15,IFERROR('QLD-2'!X15*1,0)) | I8: =IF(AND($B8="Forecast",N('SA-1'!AH15)>0),'SA-1'!AH15,IFERROR('SA-1'!X15*1,0)) | J8: =IF(AND($B8="Forecast",N('WA-1'!AH15)>0),'WA-1'!AH15,IFERROR('WA-1'!X15*1,0)) | K8: =IF(AND($B8="Forecast",N('IDC-NSW'!AH15)>0),'IDC-NSW'!AH15,IFERROR('IDC-NSW'!X15*1,0)) | L8: =IF(AND($B8="Forecast",N('IDC-VIC'!AH15)>0),'IDC-VIC'!AH15,IFERROR('IDC-VIC'!X15*1,0)) | AJ8: =IF($B8="Actual",C8,IF(Y8<>"",Y8,C8+N(N8))) | AK8: =IF($B8="Actual",D8,IF(Z8<>"",Z8,D8+N(O8))) | AL8: =IF($B8="Actual",E8,IF(AA8<>"",AA8,E8+N(P8))) | AM8: =IF($B8="Actual",F8,IF(AB8<>"",AB8,F8+N(Q8))) | AN8: =IF($B8="Actual",G8,IF(AC8<>"",AC8,G8+N(R8))) | AO8: =IF($B8="Actual",H8,IF(AD8<>"",AD8,H8+N(S8))) | AP8: =IF($B8="Actual",I8,IF(AE8<>"",AE8,I8+N(T8))) | AQ8: =IF($B8="Actual",J8,IF(AF8<>"",AF8,J8+N(U8))) | ... AS8: =IF($B8="Actual",L8,IF(AH8<>"",AH8,L8+N(W8)))
A9: 45689 | B9: =IF(A9<=LastActual,"Actual","Forecast") | C9: =IF(AND($B9="Forecast",N('NSW-1'!AH16)>0),'NSW-1'!AH16,IFERROR('NSW-1'!X16*1,0)) | D9: =IF(AND($B9="Forecast",N('VIC-1'!AH16)>0),'VIC-1'!AH16,IFERROR('VIC-1'!X16*1,0)) | E9: =IF(AND($B9="Forecast",N('QLD-1'!AH16)>0),'QLD-1'!AH16,IFERROR('QLD-1'!X16*1,0)) | F9: =IF(AND($B9="Forecast",N('NSW-2'!AH16)>0),'NSW-2'!AH16,IFERROR('NSW-2'!X16*1,0)) | G9: =IF(AND($B9="Forecast",N('VIC-2'!AH16)>0),'VIC-2'!AH16,IFERROR('VIC-2'!X16*1,0)) | H9: =IF(AND($B9="Forecast",N('QLD-2'!AH16)>0),'QLD-2'!AH16,IFERROR('QLD-2'!X16*1,0)) | I9: =IF(AND($B9="Forecast",N('SA-1'!AH16)>0),'SA-1'!AH16,IFERROR('SA-1'!X16*1,0)) | J9: =IF(AND($B9="Forecast",N('WA-1'!AH16)>0),'WA-1'!AH16,IFERROR('WA-1'!X16*1,0)) | K9: =IF(AND($B9="Forecast",N('IDC-NSW'!AH16)>0),'IDC-NSW'!AH16,IFERROR('IDC-NSW'!X16*1,0)) | L9: =IF(AND($B9="Forecast",N('IDC-VIC'!AH16)>0),'IDC-VIC'!AH16,IFERROR('IDC-VIC'!X16*1,0)) | AJ9: =IF($B9="Actual",C9,IF(Y9<>"",Y9,C9+N(N9))) | AK9: =IF($B9="Actual",D9,IF(Z9<>"",Z9,D9+N(O9))) | AL9: =IF($B9="Actual",E9,IF(AA9<>"",AA9,E9+N(P9))) | AM9: =IF($B9="Actual",F9,IF(AB9<>"",AB9,F9+N(Q9))) | AN9: =IF($B9="Actual",G9,IF(AC9<>"",AC9,G9+N(R9))) | AO9: =IF($B9="Actual",H9,IF(AD9<>"",AD9,H9+N(S9))) | AP9: =IF($B9="Actual",I9,IF(AE9<>"",AE9,I9+N(T9))) | AQ9: =IF($B9="Actual",J9,IF(AF9<>"",AF9,J9+N(U9))) | ... AS9: =IF($B9="Actual",L9,IF(AH9<>"",AH9,L9+N(W9)))
A10: 45717 | B10: =IF(A10<=LastActual,"Actual","Forecast") | C10: =IF(AND($B10="Forecast",N('NSW-1'!AH17)>0),'NSW-1'!AH17,IFERROR('NSW-1'!X17*1,0)) | D10: =IF(AND($B10="Forecast",N('VIC-1'!AH17)>0),'VIC-1'!AH17,IFERROR('VIC-1'!X17*1,0)) | E10: =IF(AND($B10="Forecast",N('QLD-1'!AH17)>0),'QLD-1'!AH17,IFERROR('QLD-1'!X17*1,0)) | F10: =IF(AND($B10="Forecast",N('NSW-2'!AH17)>0),'NSW-2'!AH17,IFERROR('NSW-2'!X17*1,0)) | G10: =IF(AND($B10="Forecast",N('VIC-2'!AH17)>0),'VIC-2'!AH17,IFERROR('VIC-2'!X17*1,0)) | H10: =IF(AND($B10="Forecast",N('QLD-2'!AH17)>0),'QLD-2'!AH17,IFERROR('QLD-2'!X17*1,0)) | I10: =IF(AND($B10="Forecast",N('SA-1'!AH17)>0),'SA-1'!AH17,IFERROR('SA-1'!X17*1,0)) | J10: =IF(AND($B10="Forecast",N('WA-1'!AH17)>0),'WA-1'!AH17,IFERROR('WA-1'!X17*1,0)) | K10: =IF(AND($B10="Forecast",N('IDC-NSW'!AH17)>0),'IDC-NSW'!AH17,IFERROR('IDC-NSW'!X17*1,0)) | L10: =IF(AND($B10="Forecast",N('IDC-VIC'!AH17)>0),'IDC-VIC'!AH17,IFERROR('IDC-VIC'!X17*1,0)) | AJ10: =IF($B10="Actual",C10,IF(Y10<>"",Y10,C10+N(N10))) | AK10: =IF($B10="Actual",D10,IF(Z10<>"",Z10,D10+N(O10))) | AL10: =IF($B10="Actual",E10,IF(AA10<>"",AA10,E10+N(P10))) | AM10: =IF($B10="Actual",F10,IF(AB10<>"",AB10,F10+N(Q10))) | AN10: =IF($B10="Actual",G10,IF(AC10<>"",AC10,G10+N(R10))) | AO10: =IF($B10="Actual",H10,IF(AD10<>"",AD10,H10+N(S10))) | AP10: =IF($B10="Actual",I10,IF(AE10<>"",AE10,I10+N(T10))) | AQ10: =IF($B10="Actual",J10,IF(AF10<>"",AF10,J10+N(U10))) | ... AS10: =IF($B10="Actual",L10,IF(AH10<>"",AH10,L10+N(W10)))
A11: 45748 | B11: =IF(A11<=LastActual,"Actual","Forecast") | C11: =IF(AND($B11="Forecast",N('NSW-1'!AH18)>0),'NSW-1'!AH18,IFERROR('NSW-1'!X18*1,0)) | D11: =IF(AND($B11="Forecast",N('VIC-1'!AH18)>0),'VIC-1'!AH18,IFERROR('VIC-1'!X18*1,0)) | E11: =IF(AND($B11="Forecast",N('QLD-1'!AH18)>0),'QLD-1'!AH18,IFERROR('QLD-1'!X18*1,0)) | F11: =IF(AND($B11="Forecast",N('NSW-2'!AH18)>0),'NSW-2'!AH18,IFERROR('NSW-2'!X18*1,0)) | G11: =IF(AND($B11="Forecast",N('VIC-2'!AH18)>0),'VIC-2'!AH18,IFERROR('VIC-2'!X18*1,0)) | H11: =IF(AND($B11="Forecast",N('QLD-2'!AH18)>0),'QLD-2'!AH18,IFERROR('QLD-2'!X18*1,0)) | I11: =IF(AND($B11="Forecast",N('SA-1'!AH18)>0),'SA-1'!AH18,IFERROR('SA-1'!X18*1,0)) | J11: =IF(AND($B11="Forecast",N('WA-1'!AH18)>0),'WA-1'!AH18,IFERROR('WA-1'!X18*1,0)) | K11: =IF(AND($B11="Forecast",N('IDC-NSW'!AH18)>0),'IDC-NSW'!AH18,IFERROR('IDC-NSW'!X18*1,0)) | L11: =IF(AND($B11="Forecast",N('IDC-VIC'!AH18)>0),'IDC-VIC'!AH18,IFERROR('IDC-VIC'!X18*1,0)) | AJ11: =IF($B11="Actual",C11,IF(Y11<>"",Y11,C11+N(N11))) | AK11: =IF($B11="Actual",D11,IF(Z11<>"",Z11,D11+N(O11))) | AL11: =IF($B11="Actual",E11,IF(AA11<>"",AA11,E11+N(P11))) | AM11: =IF($B11="Actual",F11,IF(AB11<>"",AB11,F11+N(Q11))) | AN11: =IF($B11="Actual",G11,IF(AC11<>"",AC11,G11+N(R11))) | AO11: =IF($B11="Actual",H11,IF(AD11<>"",AD11,H11+N(S11))) | AP11: =IF($B11="Actual",I11,IF(AE11<>"",AE11,I11+N(T11))) | AQ11: =IF($B11="Actual",J11,IF(AF11<>"",AF11,J11+N(U11))) | ... AS11: =IF($B11="Actual",L11,IF(AH11<>"",AH11,L11+N(W11)))
A12: 45778 | B12: =IF(A12<=LastActual,"Actual","Forecast") | C12: =IF(AND($B12="Forecast",N('NSW-1'!AH19)>0),'NSW-1'!AH19,IFERROR('NSW-1'!X19*1,0)) | D12: =IF(AND($B12="Forecast",N('VIC-1'!AH19)>0),'VIC-1'!AH19,IFERROR('VIC-1'!X19*1,0)) | E12: =IF(AND($B12="Forecast",N('QLD-1'!AH19)>0),'QLD-1'!AH19,IFERROR('QLD-1'!X19*1,0)) | F12: =IF(AND($B12="Forecast",N('NSW-2'!AH19)>0),'NSW-2'!AH19,IFERROR('NSW-2'!X19*1,0)) | G12: =IF(AND($B12="Forecast",N('VIC-2'!AH19)>0),'VIC-2'!AH19,IFERROR('VIC-2'!X19*1,0)) | H12: =IF(AND($B12="Forecast",N('QLD-2'!AH19)>0),'QLD-2'!AH19,IFERROR('QLD-2'!X19*1,0)) | I12: =IF(AND($B12="Forecast",N('SA-1'!AH19)>0),'SA-1'!AH19,IFERROR('SA-1'!X19*1,0)) | J12: =IF(AND($B12="Forecast",N('WA-1'!AH19)>0),'WA-1'!AH19,IFERROR('WA-1'!X19*1,0)) | K12: =IF(AND($B12="Forecast",N('IDC-NSW'!AH19)>0),'IDC-NSW'!AH19,IFERROR('IDC-NSW'!X19*1,0)) | L12: =IF(AND($B12="Forecast",N('IDC-VIC'!AH19)>0),'IDC-VIC'!AH19,IFERROR('IDC-VIC'!X19*1,0)) | AJ12: =IF($B12="Actual",C12,IF(Y12<>"",Y12,C12+N(N12))) | AK12: =IF($B12="Actual",D12,IF(Z12<>"",Z12,D12+N(O12))) | AL12: =IF($B12="Actual",E12,IF(AA12<>"",AA12,E12+N(P12))) | AM12: =IF($B12="Actual",F12,IF(AB12<>"",AB12,F12+N(Q12))) | AN12: =IF($B12="Actual",G12,IF(AC12<>"",AC12,G12+N(R12))) | AO12: =IF($B12="Actual",H12,IF(AD12<>"",AD12,H12+N(S12))) | AP12: =IF($B12="Actual",I12,IF(AE12<>"",AE12,I12+N(T12))) | AQ12: =IF($B12="Actual",J12,IF(AF12<>"",AF12,J12+N(U12))) | ... AS12: =IF($B12="Actual",L12,IF(AH12<>"",AH12,L12+N(W12)))
A13: 45809 | B13: =IF(A13<=LastActual,"Actual","Forecast") | C13: =IF(AND($B13="Forecast",N('NSW-1'!AH20)>0),'NSW-1'!AH20,IFERROR('NSW-1'!X20*1,0)) | D13: =IF(AND($B13="Forecast",N('VIC-1'!AH20)>0),'VIC-1'!AH20,IFERROR('VIC-1'!X20*1,0)) | E13: =IF(AND($B13="Forecast",N('QLD-1'!AH20)>0),'QLD-1'!AH20,IFERROR('QLD-1'!X20*1,0)) | F13: =IF(AND($B13="Forecast",N('NSW-2'!AH20)>0),'NSW-2'!AH20,IFERROR('NSW-2'!X20*1,0)) | G13: =IF(AND($B13="Forecast",N('VIC-2'!AH20)>0),'VIC-2'!AH20,IFERROR('VIC-2'!X20*1,0)) | H13: =IF(AND($B13="Forecast",N('QLD-2'!AH20)>0),'QLD-2'!AH20,IFERROR('QLD-2'!X20*1,0)) | I13: =IF(AND($B13="Forecast",N('SA-1'!AH20)>0),'SA-1'!AH20,IFERROR('SA-1'!X20*1,0)) | J13: =IF(AND($B13="Forecast",N('WA-1'!AH20)>0),'WA-1'!AH20,IFERROR('WA-1'!X20*1,0)) | K13: =IF(AND($B13="Forecast",N('IDC-NSW'!AH20)>0),'IDC-NSW'!AH20,IFERROR('IDC-NSW'!X20*1,0)) | L13: =IF(AND($B13="Forecast",N('IDC-VIC'!AH20)>0),'IDC-VIC'!AH20,IFERROR('IDC-VIC'!X20*1,0)) | AJ13: =IF($B13="Actual",C13,IF(Y13<>"",Y13,C13+N(N13))) | AK13: =IF($B13="Actual",D13,IF(Z13<>"",Z13,D13+N(O13))) | AL13: =IF($B13="Actual",E13,IF(AA13<>"",AA13,E13+N(P13))) | AM13: =IF($B13="Actual",F13,IF(AB13<>"",AB13,F13+N(Q13))) | AN13: =IF($B13="Actual",G13,IF(AC13<>"",AC13,G13+N(R13))) | AO13: =IF($B13="Actual",H13,IF(AD13<>"",AD13,H13+N(S13))) | AP13: =IF($B13="Actual",I13,IF(AE13<>"",AE13,I13+N(T13))) | AQ13: =IF($B13="Actual",J13,IF(AF13<>"",AF13,J13+N(U13))) | ... AS13: =IF($B13="Actual",L13,IF(AH13<>"",AH13,L13+N(W13)))
A14: 45839 | B14: =IF(A14<=LastActual,"Actual","Forecast") | C14: =IF(AND($B14="Forecast",N('NSW-1'!AH21)>0),'NSW-1'!AH21,IFERROR('NSW-1'!X21*1,0)) | D14: =IF(AND($B14="Forecast",N('VIC-1'!AH21)>0),'VIC-1'!AH21,IFERROR('VIC-1'!X21*1,0)) | E14: =IF(AND($B14="Forecast",N('QLD-1'!AH21)>0),'QLD-1'!AH21,IFERROR('QLD-1'!X21*1,0)) | F14: =IF(AND($B14="Forecast",N('NSW-2'!AH21)>0),'NSW-2'!AH21,IFERROR('NSW-2'!X21*1,0)) | G14: =IF(AND($B14="Forecast",N('VIC-2'!AH21)>0),'VIC-2'!AH21,IFERROR('VIC-2'!X21*1,0)) | H14: =IF(AND($B14="Forecast",N('QLD-2'!AH21)>0),'QLD-2'!AH21,IFERROR('QLD-2'!X21*1,0)) | I14: =IF(AND($B14="Forecast",N('SA-1'!AH21)>0),'SA-1'!AH21,IFERROR('SA-1'!X21*1,0)) | J14: =IF(AND($B14="Forecast",N('WA-1'!AH21)>0),'WA-1'!AH21,IFERROR('WA-1'!X21*1,0)) | K14: =IF(AND($B14="Forecast",N('IDC-NSW'!AH21)>0),'IDC-NSW'!AH21,IFERROR('IDC-NSW'!X21*1,0)) | L14: =IF(AND($B14="Forecast",N('IDC-VIC'!AH21)>0),'IDC-VIC'!AH21,IFERROR('IDC-VIC'!X21*1,0)) | AJ14: =IF($B14="Actual",C14,IF(Y14<>"",Y14,C14+N(N14))) | AK14: =IF($B14="Actual",D14,IF(Z14<>"",Z14,D14+N(O14))) | AL14: =IF($B14="Actual",E14,IF(AA14<>"",AA14,E14+N(P14))) | AM14: =IF($B14="Actual",F14,IF(AB14<>"",AB14,F14+N(Q14))) | AN14: =IF($B14="Actual",G14,IF(AC14<>"",AC14,G14+N(R14))) | AO14: =IF($B14="Actual",H14,IF(AD14<>"",AD14,H14+N(S14))) | AP14: =IF($B14="Actual",I14,IF(AE14<>"",AE14,I14+N(T14))) | AQ14: =IF($B14="Actual",J14,IF(AF14<>"",AF14,J14+N(U14))) | ... AS14: =IF($B14="Actual",L14,IF(AH14<>"",AH14,L14+N(W14)))
A15: 45870 | B15: =IF(A15<=LastActual,"Actual","Forecast") | C15: =IF(AND($B15="Forecast",N('NSW-1'!AH22)>0),'NSW-1'!AH22,IFERROR('NSW-1'!X22*1,0)) | D15: =IF(AND($B15="Forecast",N('VIC-1'!AH22)>0),'VIC-1'!AH22,IFERROR('VIC-1'!X22*1,0)) | E15: =IF(AND($B15="Forecast",N('QLD-1'!AH22)>0),'QLD-1'!AH22,IFERROR('QLD-1'!X22*1,0)) | F15: =IF(AND($B15="Forecast",N('NSW-2'!AH22)>0),'NSW-2'!AH22,IFERROR('NSW-2'!X22*1,0)) | G15: =IF(AND($B15="Forecast",N('VIC-2'!AH22)>0),'VIC-2'!AH22,IFERROR('VIC-2'!X22*1,0)) | H15: =IF(AND($B15="Forecast",N('QLD-2'!AH22)>0),'QLD-2'!AH22,IFERROR('QLD-2'!X22*1,0)) | I15: =IF(AND($B15="Forecast",N('SA-1'!AH22)>0),'SA-1'!AH22,IFERROR('SA-1'!X22*1,0)) | J15: =IF(AND($B15="Forecast",N('WA-1'!AH22)>0),'WA-1'!AH22,IFERROR('WA-1'!X22*1,0)) | K15: =IF(AND($B15="Forecast",N('IDC-NSW'!AH22)>0),'IDC-NSW'!AH22,IFERROR('IDC-NSW'!X22*1,0)) | L15: =IF(AND($B15="Forecast",N('IDC-VIC'!AH22)>0),'IDC-VIC'!AH22,IFERROR('IDC-VIC'!X22*1,0)) | AJ15: =IF($B15="Actual",C15,IF(Y15<>"",Y15,C15+N(N15))) | AK15: =IF($B15="Actual",D15,IF(Z15<>"",Z15,D15+N(O15))) | AL15: =IF($B15="Actual",E15,IF(AA15<>"",AA15,E15+N(P15))) | AM15: =IF($B15="Actual",F15,IF(AB15<>"",AB15,F15+N(Q15))) | AN15: =IF($B15="Actual",G15,IF(AC15<>"",AC15,G15+N(R15))) | AO15: =IF($B15="Actual",H15,IF(AD15<>"",AD15,H15+N(S15))) | AP15: =IF($B15="Actual",I15,IF(AE15<>"",AE15,I15+N(T15))) | AQ15: =IF($B15="Actual",J15,IF(AF15<>"",AF15,J15+N(U15))) | ... AS15: =IF($B15="Actual",L15,IF(AH15<>"",AH15,L15+N(W15)))
A16: 45901 | B16: =IF(A16<=LastActual,"Actual","Forecast") | C16: =IF(AND($B16="Forecast",N('NSW-1'!AH23)>0),'NSW-1'!AH23,IFERROR('NSW-1'!X23*1,0)) | D16: =IF(AND($B16="Forecast",N('VIC-1'!AH23)>0),'VIC-1'!AH23,IFERROR('VIC-1'!X23*1,0)) | E16: =IF(AND($B16="Forecast",N('QLD-1'!AH23)>0),'QLD-1'!AH23,IFERROR('QLD-1'!X23*1,0)) | F16: =IF(AND($B16="Forecast",N('NSW-2'!AH23)>0),'NSW-2'!AH23,IFERROR('NSW-2'!X23*1,0)) | G16: =IF(AND($B16="Forecast",N('VIC-2'!AH23)>0),'VIC-2'!AH23,IFERROR('VIC-2'!X23*1,0)) | H16: =IF(AND($B16="Forecast",N('QLD-2'!AH23)>0),'QLD-2'!AH23,IFERROR('QLD-2'!X23*1,0)) | I16: =IF(AND($B16="Forecast",N('SA-1'!AH23)>0),'SA-1'!AH23,IFERROR('SA-1'!X23*1,0)) | J16: =IF(AND($B16="Forecast",N('WA-1'!AH23)>0),'WA-1'!AH23,IFERROR('WA-1'!X23*1,0)) | K16: =IF(AND($B16="Forecast",N('IDC-NSW'!AH23)>0),'IDC-NSW'!AH23,IFERROR('IDC-NSW'!X23*1,0)) | L16: =IF(AND($B16="Forecast",N('IDC-VIC'!AH23)>0),'IDC-VIC'!AH23,IFERROR('IDC-VIC'!X23*1,0)) | AJ16: =IF($B16="Actual",C16,IF(Y16<>"",Y16,C16+N(N16))) | AK16: =IF($B16="Actual",D16,IF(Z16<>"",Z16,D16+N(O16))) | AL16: =IF($B16="Actual",E16,IF(AA16<>"",AA16,E16+N(P16))) | AM16: =IF($B16="Actual",F16,IF(AB16<>"",AB16,F16+N(Q16))) | AN16: =IF($B16="Actual",G16,IF(AC16<>"",AC16,G16+N(R16))) | AO16: =IF($B16="Actual",H16,IF(AD16<>"",AD16,H16+N(S16))) | AP16: =IF($B16="Actual",I16,IF(AE16<>"",AE16,I16+N(T16))) | AQ16: =IF($B16="Actual",J16,IF(AF16<>"",AF16,J16+N(U16))) | ... AS16: =IF($B16="Actual",L16,IF(AH16<>"",AH16,L16+N(W16)))
A17: 45931 | B17: =IF(A17<=LastActual,"Actual","Forecast") | C17: =IF(AND($B17="Forecast",N('NSW-1'!AH24)>0),'NSW-1'!AH24,IFERROR('NSW-1'!X24*1,0)) | D17: =IF(AND($B17="Forecast",N('VIC-1'!AH24)>0),'VIC-1'!AH24,IFERROR('VIC-1'!X24*1,0)) | E17: =IF(AND($B17="Forecast",N('QLD-1'!AH24)>0),'QLD-1'!AH24,IFERROR('QLD-1'!X24*1,0)) | F17: =IF(AND($B17="Forecast",N('NSW-2'!AH24)>0),'NSW-2'!AH24,IFERROR('NSW-2'!X24*1,0)) | G17: =IF(AND($B17="Forecast",N('VIC-2'!AH24)>0),'VIC-2'!AH24,IFERROR('VIC-2'!X24*1,0)) | H17: =IF(AND($B17="Forecast",N('QLD-2'!AH24)>0),'QLD-2'!AH24,IFERROR('QLD-2'!X24*1,0)) | I17: =IF(AND($B17="Forecast",N('SA-1'!AH24)>0),'SA-1'!AH24,IFERROR('SA-1'!X24*1,0)) | J17: =IF(AND($B17="Forecast",N('WA-1'!AH24)>0),'WA-1'!AH24,IFERROR('WA-1'!X24*1,0)) | K17: =IF(AND($B17="Forecast",N('IDC-NSW'!AH24)>0),'IDC-NSW'!AH24,IFERROR('IDC-NSW'!X24*1,0)) | L17: =IF(AND($B17="Forecast",N('IDC-VIC'!AH24)>0),'IDC-VIC'!AH24,IFERROR('IDC-VIC'!X24*1,0)) | AJ17: =IF($B17="Actual",C17,IF(Y17<>"",Y17,C17+N(N17))) | AK17: =IF($B17="Actual",D17,IF(Z17<>"",Z17,D17+N(O17))) | AL17: =IF($B17="Actual",E17,IF(AA17<>"",AA17,E17+N(P17))) | AM17: =IF($B17="Actual",F17,IF(AB17<>"",AB17,F17+N(Q17))) | AN17: =IF($B17="Actual",G17,IF(AC17<>"",AC17,G17+N(R17))) | AO17: =IF($B17="Actual",H17,IF(AD17<>"",AD17,H17+N(S17))) | AP17: =IF($B17="Actual",I17,IF(AE17<>"",AE17,I17+N(T17))) | AQ17: =IF($B17="Actual",J17,IF(AF17<>"",AF17,J17+N(U17))) | ... AS17: =IF($B17="Actual",L17,IF(AH17<>"",AH17,L17+N(W17)))
A18: 45962 | B18: =IF(A18<=LastActual,"Actual","Forecast") | C18: =IF(AND($B18="Forecast",N('NSW-1'!AH25)>0),'NSW-1'!AH25,IFERROR('NSW-1'!X25*1,0)) | D18: =IF(AND($B18="Forecast",N('VIC-1'!AH25)>0),'VIC-1'!AH25,IFERROR('VIC-1'!X25*1,0)) | E18: =IF(AND($B18="Forecast",N('QLD-1'!AH25)>0),'QLD-1'!AH25,IFERROR('QLD-1'!X25*1,0)) | F18: =IF(AND($B18="Forecast",N('NSW-2'!AH25)>0),'NSW-2'!AH25,IFERROR('NSW-2'!X25*1,0)) | G18: =IF(AND($B18="Forecast",N('VIC-2'!AH25)>0),'VIC-2'!AH25,IFERROR('VIC-2'!X25*1,0)) | H18: =IF(AND($B18="Forecast",N('QLD-2'!AH25)>0),'QLD-2'!AH25,IFERROR('QLD-2'!X25*1,0)) | I18: =IF(AND($B18="Forecast",N('SA-1'!AH25)>0),'SA-1'!AH25,IFERROR('SA-1'!X25*1,0)) | J18: =IF(AND($B18="Forecast",N('WA-1'!AH25)>0),'WA-1'!AH25,IFERROR('WA-1'!X25*1,0)) | K18: =IF(AND($B18="Forecast",N('IDC-NSW'!AH25)>0),'IDC-NSW'!AH25,IFERROR('IDC-NSW'!X25*1,0)) | L18: =IF(AND($B18="Forecast",N('IDC-VIC'!AH25)>0),'IDC-VIC'!AH25,IFERROR('IDC-VIC'!X25*1,0)) | AJ18: =IF($B18="Actual",C18,IF(Y18<>"",Y18,C18+N(N18))) | AK18: =IF($B18="Actual",D18,IF(Z18<>"",Z18,D18+N(O18))) | AL18: =IF($B18="Actual",E18,IF(AA18<>"",AA18,E18+N(P18))) | AM18: =IF($B18="Actual",F18,IF(AB18<>"",AB18,F18+N(Q18))) | AN18: =IF($B18="Actual",G18,IF(AC18<>"",AC18,G18+N(R18))) | AO18: =IF($B18="Actual",H18,IF(AD18<>"",AD18,H18+N(S18))) | AP18: =IF($B18="Actual",I18,IF(AE18<>"",AE18,I18+N(T18))) | AQ18: =IF($B18="Actual",J18,IF(AF18<>"",AF18,J18+N(U18))) | ... AS18: =IF($B18="Actual",L18,IF(AH18<>"",AH18,L18+N(W18)))
A19: 45992 | B19: =IF(A19<=LastActual,"Actual","Forecast") | C19: =IF(AND($B19="Forecast",N('NSW-1'!AH26)>0),'NSW-1'!AH26,IFERROR('NSW-1'!X26*1,0)) | D19: =IF(AND($B19="Forecast",N('VIC-1'!AH26)>0),'VIC-1'!AH26,IFERROR('VIC-1'!X26*1,0)) | E19: =IF(AND($B19="Forecast",N('QLD-1'!AH26)>0),'QLD-1'!AH26,IFERROR('QLD-1'!X26*1,0)) | F19: =IF(AND($B19="Forecast",N('NSW-2'!AH26)>0),'NSW-2'!AH26,IFERROR('NSW-2'!X26*1,0)) | G19: =IF(AND($B19="Forecast",N('VIC-2'!AH26)>0),'VIC-2'!AH26,IFERROR('VIC-2'!X26*1,0)) | H19: =IF(AND($B19="Forecast",N('QLD-2'!AH26)>0),'QLD-2'!AH26,IFERROR('QLD-2'!X26*1,0)) | I19: =IF(AND($B19="Forecast",N('SA-1'!AH26)>0),'SA-1'!AH26,IFERROR('SA-1'!X26*1,0)) | J19: =IF(AND($B19="Forecast",N('WA-1'!AH26)>0),'WA-1'!AH26,IFERROR('WA-1'!X26*1,0)) | K19: =IF(AND($B19="Forecast",N('IDC-NSW'!AH26)>0),'IDC-NSW'!AH26,IFERROR('IDC-NSW'!X26*1,0)) | L19: =IF(AND($B19="Forecast",N('IDC-VIC'!AH26)>0),'IDC-VIC'!AH26,IFERROR('IDC-VIC'!X26*1,0)) | AJ19: =IF($B19="Actual",C19,IF(Y19<>"",Y19,C19+N(N19))) | AK19: =IF($B19="Actual",D19,IF(Z19<>"",Z19,D19+N(O19))) | AL19: =IF($B19="Actual",E19,IF(AA19<>"",AA19,E19+N(P19))) | AM19: =IF($B19="Actual",F19,IF(AB19<>"",AB19,F19+N(Q19))) | AN19: =IF($B19="Actual",G19,IF(AC19<>"",AC19,G19+N(R19))) | AO19: =IF($B19="Actual",H19,IF(AD19<>"",AD19,H19+N(S19))) | AP19: =IF($B19="Actual",I19,IF(AE19<>"",AE19,I19+N(T19))) | AQ19: =IF($B19="Actual",J19,IF(AF19<>"",AF19,J19+N(U19))) | ... AS19: =IF($B19="Actual",L19,IF(AH19<>"",AH19,L19+N(W19)))
... A55: 47088 | B55: =IF(A55<=LastActual,"Actual","Forecast") | C55: =IF(AND($B55="Forecast",N('NSW-1'!AH62)>0),'NSW-1'!AH62,IFERROR('NSW-1'!X62*1,0)) | D55: =IF(AND($B55="Forecast",N('VIC-1'!AH62)>0),'VIC-1'!AH62,IFERROR('VIC-1'!X62*1,0)) | E55: =IF(AND($B55="Forecast",N('QLD-1'!AH62)>0),'QLD-1'!AH62,IFERROR('QLD-1'!X62*1,0)) | F55: =IF(AND($B55="Forecast",N('NSW-2'!AH62)>0),'NSW-2'!AH62,IFERROR('NSW-2'!X62*1,0)) | G55: =IF(AND($B55="Forecast",N('VIC-2'!AH62)>0),'VIC-2'!AH62,IFERROR('VIC-2'!X62*1,0)) | H55: =IF(AND($B55="Forecast",N('QLD-2'!AH62)>0),'QLD-2'!AH62,IFERROR('QLD-2'!X62*1,0)) | I55: =IF(AND($B55="Forecast",N('SA-1'!AH62)>0),'SA-1'!AH62,IFERROR('SA-1'!X62*1,0)) | J55: =IF(AND($B55="Forecast",N('WA-1'!AH62)>0),'WA-1'!AH62,IFERROR('WA-1'!X62*1,0)) | K55: =IF(AND($B55="Forecast",N('IDC-NSW'!AH62)>0),'IDC-NSW'!AH62,IFERROR('IDC-NSW'!X62*1,0)) | L55: =IF(AND($B55="Forecast",N('IDC-VIC'!AH62)>0),'IDC-VIC'!AH62,IFERROR('IDC-VIC'!X62*1,0)) | AJ55: =IF($B55="Actual",C55,IF(Y55<>"",Y55,C55+N(N55))) | AK55: =IF($B55="Actual",D55,IF(Z55<>"",Z55,D55+N(O55))) | AL55: =IF($B55="Actual",E55,IF(AA55<>"",AA55,E55+N(P55))) | AM55: =IF($B55="Actual",F55,IF(AB55<>"",AB55,F55+N(Q55))) | AN55: =IF($B55="Actual",G55,IF(AC55<>"",AC55,G55+N(R55))) | AO55: =IF($B55="Actual",H55,IF(AD55<>"",AD55,H55+N(S55))) | AP55: =IF($B55="Actual",I55,IF(AE55<>"",AE55,I55+N(T55))) | AQ55: =IF($B55="Actual",J55,IF(AF55<>"",AF55,J55+N(U55))) | ... AS55: =IF($B55="Actual",L55,IF(AH55<>"",AH55,L55+N(W55)))

Sheet CPLH_Breakdown
A1: CPLH breakdown: national CPLH target -> site CPLH by month
A2: Type a national CPLH target for a year. Every included site's CPLH (actual, else same month last year) is scaled by one
A3: factor, so the year's national CPLH (included sites' cases / hours, actual months included) hits the target. Each site keeps
A4: its own level and seasonal shape. Blank target = no change. Excluded sites keep their same-month-last-year CPLH.
A5: Copy the paste column (far right) into Plan_Inputs column D, or set 'Plan CPLH source' on Inputs to National breakdown.
A8: FY | B8: National CPLH target | C8: Included cases | D8: Actual hours | E8: Fcst hours at base CPLH | F8: Base national CPLH | G8: Uplift factor | H8: Resulting national CPLH
A9: 2026 | C9: =SUMIFS($BG$20:$BG$67,$C$20:$C$67,$A9) | D9: =SUMIFS($BH$20:$BH$67,$C$20:$C$67,$A9,$B$20:$B$67,"Actual") | E9: =SUMIFS($BH$20:$BH$67,$C$20:$C$67,$A9,$B$20:$B$67,"Forecast") | F9: =IFERROR(C9/(D9+E9),0) | G9: =IF(B9="",1,IF(C9/B9-D9<=0,NA(),E9/(C9/B9-D9))) | H9: =IFERROR(C9/SUMIFS($BI$20:$BI$67,$C$20:$C$67,$A9),0) | I9: Cases in m. Uplift factor 1.03 = every included site's CPLH +3% in that year's forecast months.
A10: 2027 | B10: 80.9 | C10: =SUMIFS($BG$20:$BG$67,$C$20:$C$67,$A10) | D10: =SUMIFS($BH$20:$BH$67,$C$20:$C$67,$A10,$B$20:$B$67,"Actual") | E10: =SUMIFS($BH$20:$BH$67,$C$20:$C$67,$A10,$B$20:$B$67,"Forecast") | F10: =IFERROR(C10/(D10+E10),0) | G10: =IF(B10="",1,IF(C10/B10-D10<=0,NA(),E10/(C10/B10-D10))) | H10: =IFERROR(C10/SUMIFS($BI$20:$BI$67,$C$20:$C$67,$A10),0)
A11: 2028 | B11: 81.4 | C11: =SUMIFS($BG$20:$BG$67,$C$20:$C$67,$A11) | D11: =SUMIFS($BH$20:$BH$67,$C$20:$C$67,$A11,$B$20:$B$67,"Actual") | E11: =SUMIFS($BH$20:$BH$67,$C$20:$C$67,$A11,$B$20:$B$67,"Forecast") | F11: =IFERROR(C11/(D11+E11),0) | G11: =IF(B11="",1,IF(C11/B11-D11<=0,NA(),E11/(C11/B11-D11))) | H11: =IFERROR(C11/SUMIFS($BI$20:$BI$67,$C$20:$C$67,$A11),0)
C14: Site | D14: =Inputs!$A$36 | E14: =Inputs!$A$37 | F14: =Inputs!$A$38 | G14: =Inputs!$A$39 | H14: =Inputs!$A$40 | I14: =Inputs!$A$41 | J14: =Inputs!$A$42 | K14: =Inputs!$A$43 | L14: =Inputs!$A$44 | M14: =Inputs!$A$45
C15: Include | D15: Yes | E15: Yes | F15: Yes | G15: Yes | H15: Yes | I15: Yes | J15: Yes | K15: Yes | L15: No | M15: No
D18: Base CPLH (actual, else same month LY) | O18: Cases (Cases_Forecast used) | Z18: Hours at base CPLH | AK18: Suggested CPLH | AV18: Hours at suggested CPLH | BG18: National (included sites) | BN18: To paste into Plan_Inputs column D (values)
A19: Month | B19: Status | C19: FY | D19: =Inputs!$A$36 | E19: =Inputs!$A$37 | F19: =Inputs!$A$38 | G19: =Inputs!$A$39 | H19: =Inputs!$A$40 | I19: =Inputs!$A$41 | J19: =Inputs!$A$42 | K19: =Inputs!$A$43 | L19: =Inputs!$A$44 | M19: =Inputs!$A$45 | O19: =Inputs!$A$36 | P19: =Inputs!$A$37 | Q19: =Inputs!$A$38 | R19: =Inputs!$A$39 | S19: =Inputs!$A$40 | T19: =Inputs!$A$41 | U19: =Inputs!$A$42 | V19: =Inputs!$A$43 | W19: =Inputs!$A$44 | X19: =Inputs!$A$45 | Z19: =Inputs!$A$36 | AA19: =Inputs!$A$37 | AB19: =Inputs!$A$38 | AC19: =Inputs!$A$39 | AD19: =Inputs!$A$40 | AE19: =Inputs!$A$41 | AF19: =Inputs!$A$42 | AG19: =Inputs!$A$43 | AH19: =Inputs!$A$44 | AI19: =Inputs!$A$45 | AK19: =Inputs!$A$36 | AL19: =Inputs!$A$37 | AM19: =Inputs!$A$38 | AN19: =Inputs!$A$39 | AO19: =Inputs!$A$40 | AP19: =Inputs!$A$41 | AQ19: =Inputs!$A$42 | AR19: =Inputs!$A$43 | AS19: =Inputs!$A$44 | AT19: =Inputs!$A$45 | AV19: =Inputs!$A$36 | AW19: =Inputs!$A$37 | AX19: =Inputs!$A$38 | AY19: =Inputs!$A$39 | AZ19: =Inputs!$A$40 | BA19: =Inputs!$A$41 | BB19: =Inputs!$A$42 | BC19: =Inputs!$A$43 | BD19: =Inputs!$A$44 | BE19: =Inputs!$A$45 | BG19: Cases | BH19: Hours at base CPLH | BI19: Hours at suggested CPLH | BJ19: Base CPLH | BK19: Suggested CPLH | BL19: Uplift factor | BN19: Month | BO19: Site | BP19: Suggested CPLH
A20: 45658 | B20: =IF(A20<=LastActual,"Actual","Forecast") | C20: =YEAR(A20) | D20: =IFERROR('NSW-1'!X15*1,0) | E20: =IFERROR('VIC-1'!X15*1,0) | F20: =IFERROR('QLD-1'!X15*1,0) | G20: =IFERROR('NSW-2'!X15*1,0) | H20: =IFERROR('VIC-2'!X15*1,0) | I20: =IFERROR('QLD-2'!X15*1,0) | J20: =IFERROR('SA-1'!X15*1,0) | K20: =IFERROR('WA-1'!X15*1,0) | L20: =IFERROR('IDC-NSW'!X15*1,0) | M20: =IFERROR('IDC-VIC'!X15*1,0) | O20: =Cases_Forecast!AJ8 | P20: =Cases_Forecast!AK8 | Q20: =Cases_Forecast!AL8 | R20: =Cases_Forecast!AM8 | S20: =Cases_Forecast!AN8 | T20: =Cases_Forecast!AO8 | U20: =Cases_Forecast!AP8 | V20: =Cases_Forecast!AQ8 | ... X20: =Cases_Forecast!AS8 | Z20: =IFERROR(O20/D20,0) | AA20: =IFERROR(P20/E20,0) | AB20: =IFERROR(Q20/F20,0) | AC20: =IFERROR(R20/G20,0) | AD20: =IFERROR(S20/H20,0) | AE20: =IFERROR(T20/I20,0) | AF20: =IFERROR(U20/J20,0) | AG20: =IFERROR(V20/K20,0) | ... AI20: =IFERROR(X20/M20,0) | AK20: =IF(D$15="Yes",D20*$BL20,D20) | AL20: =IF(E$15="Yes",E20*$BL20,E20) | AM20: =IF(F$15="Yes",F20*$BL20,F20) | AN20: =IF(G$15="Yes",G20*$BL20,G20) | AO20: =IF(H$15="Yes",H20*$BL20,H20) | AP20: =IF(I$15="Yes",I20*$BL20,I20) | AQ20: =IF(J$15="Yes",J20*$BL20,J20) | AR20: =IF(K$15="Yes",K20*$BL20,K20) | ... AT20: =IF(M$15="Yes",M20*$BL20,M20) | AV20: =IFERROR(O20/AK20,0) | AW20: =IFERROR(P20/AL20,0) | AX20: =IFERROR(Q20/AM20,0) | AY20: =IFERROR(R20/AN20,0) | AZ20: =IFERROR(S20/AO20,0) | BA20: =IFERROR(T20/AP20,0) | BB20: =IFERROR(U20/AQ20,0) | BC20: =IFERROR(V20/AR20,0) | ... BE20: =IFERROR(X20/AT20,0) | BG20: =SUMPRODUCT(($D$15:$M$15="Yes")*O20:X20) | BH20: =SUMPRODUCT(($D$15:$M$15="Yes")*Z20:AI20) | BI20: =SUMPRODUCT(($D$15:$M$15="Yes")*AV20:BE20) | BJ20: =IFERROR(BG20/BH20,0) | BK20: =IFERROR(BG20/BI20,0) | BL20: =IF(B20="Actual",1,INDEX($G$9:$G$11,MATCH(C20,$A$9:$A$11,0))) | BN20: 46023 | BO20: =Inputs!$A$36 | BP20: =AK32
A21: 45689 | B21: =IF(A21<=LastActual,"Actual","Forecast") | C21: =YEAR(A21) | D21: =IFERROR('NSW-1'!X16*1,0) | E21: =IFERROR('VIC-1'!X16*1,0) | F21: =IFERROR('QLD-1'!X16*1,0) | G21: =IFERROR('NSW-2'!X16*1,0) | H21: =IFERROR('VIC-2'!X16*1,0) | I21: =IFERROR('QLD-2'!X16*1,0) | J21: =IFERROR('SA-1'!X16*1,0) | K21: =IFERROR('WA-1'!X16*1,0) | L21: =IFERROR('IDC-NSW'!X16*1,0) | M21: =IFERROR('IDC-VIC'!X16*1,0) | O21: =Cases_Forecast!AJ9 | P21: =Cases_Forecast!AK9 | Q21: =Cases_Forecast!AL9 | R21: =Cases_Forecast!AM9 | S21: =Cases_Forecast!AN9 | T21: =Cases_Forecast!AO9 | U21: =Cases_Forecast!AP9 | V21: =Cases_Forecast!AQ9 | ... X21: =Cases_Forecast!AS9 | Z21: =IFERROR(O21/D21,0) | AA21: =IFERROR(P21/E21,0) | AB21: =IFERROR(Q21/F21,0) | AC21: =IFERROR(R21/G21,0) | AD21: =IFERROR(S21/H21,0) | AE21: =IFERROR(T21/I21,0) | AF21: =IFERROR(U21/J21,0) | AG21: =IFERROR(V21/K21,0) | ... AI21: =IFERROR(X21/M21,0) | AK21: =IF(D$15="Yes",D21*$BL21,D21) | AL21: =IF(E$15="Yes",E21*$BL21,E21) | AM21: =IF(F$15="Yes",F21*$BL21,F21) | AN21: =IF(G$15="Yes",G21*$BL21,G21) | AO21: =IF(H$15="Yes",H21*$BL21,H21) | AP21: =IF(I$15="Yes",I21*$BL21,I21) | AQ21: =IF(J$15="Yes",J21*$BL21,J21) | AR21: =IF(K$15="Yes",K21*$BL21,K21) | ... AT21: =IF(M$15="Yes",M21*$BL21,M21) | AV21: =IFERROR(O21/AK21,0) | AW21: =IFERROR(P21/AL21,0) | AX21: =IFERROR(Q21/AM21,0) | AY21: =IFERROR(R21/AN21,0) | AZ21: =IFERROR(S21/AO21,0) | BA21: =IFERROR(T21/AP21,0) | BB21: =IFERROR(U21/AQ21,0) | BC21: =IFERROR(V21/AR21,0) | ... BE21: =IFERROR(X21/AT21,0) | BG21: =SUMPRODUCT(($D$15:$M$15="Yes")*O21:X21) | BH21: =SUMPRODUCT(($D$15:$M$15="Yes")*Z21:AI21) | BI21: =SUMPRODUCT(($D$15:$M$15="Yes")*AV21:BE21) | BJ21: =IFERROR(BG21/BH21,0) | BK21: =IFERROR(BG21/BI21,0) | BL21: =IF(B21="Actual",1,INDEX($G$9:$G$11,MATCH(C21,$A$9:$A$11,0))) | BN21: 46023 | BO21: =Inputs!$A$37 | BP21: =AL32
A22: 45717 | B22: =IF(A22<=LastActual,"Actual","Forecast") | C22: =YEAR(A22) | D22: =IFERROR('NSW-1'!X17*1,0) | E22: =IFERROR('VIC-1'!X17*1,0) | F22: =IFERROR('QLD-1'!X17*1,0) | G22: =IFERROR('NSW-2'!X17*1,0) | H22: =IFERROR('VIC-2'!X17*1,0) | I22: =IFERROR('QLD-2'!X17*1,0) | J22: =IFERROR('SA-1'!X17*1,0) | K22: =IFERROR('WA-1'!X17*1,0) | L22: =IFERROR('IDC-NSW'!X17*1,0) | M22: =IFERROR('IDC-VIC'!X17*1,0) | O22: =Cases_Forecast!AJ10 | P22: =Cases_Forecast!AK10 | Q22: =Cases_Forecast!AL10 | R22: =Cases_Forecast!AM10 | S22: =Cases_Forecast!AN10 | T22: =Cases_Forecast!AO10 | U22: =Cases_Forecast!AP10 | V22: =Cases_Forecast!AQ10 | ... X22: =Cases_Forecast!AS10 | Z22: =IFERROR(O22/D22,0) | AA22: =IFERROR(P22/E22,0) | AB22: =IFERROR(Q22/F22,0) | AC22: =IFERROR(R22/G22,0) | AD22: =IFERROR(S22/H22,0) | AE22: =IFERROR(T22/I22,0) | AF22: =IFERROR(U22/J22,0) | AG22: =IFERROR(V22/K22,0) | ... AI22: =IFERROR(X22/M22,0) | AK22: =IF(D$15="Yes",D22*$BL22,D22) | AL22: =IF(E$15="Yes",E22*$BL22,E22) | AM22: =IF(F$15="Yes",F22*$BL22,F22) | AN22: =IF(G$15="Yes",G22*$BL22,G22) | AO22: =IF(H$15="Yes",H22*$BL22,H22) | AP22: =IF(I$15="Yes",I22*$BL22,I22) | AQ22: =IF(J$15="Yes",J22*$BL22,J22) | AR22: =IF(K$15="Yes",K22*$BL22,K22) | ... AT22: =IF(M$15="Yes",M22*$BL22,M22) | AV22: =IFERROR(O22/AK22,0) | AW22: =IFERROR(P22/AL22,0) | AX22: =IFERROR(Q22/AM22,0) | AY22: =IFERROR(R22/AN22,0) | AZ22: =IFERROR(S22/AO22,0) | BA22: =IFERROR(T22/AP22,0) | BB22: =IFERROR(U22/AQ22,0) | BC22: =IFERROR(V22/AR22,0) | ... BE22: =IFERROR(X22/AT22,0) | BG22: =SUMPRODUCT(($D$15:$M$15="Yes")*O22:X22) | BH22: =SUMPRODUCT(($D$15:$M$15="Yes")*Z22:AI22) | BI22: =SUMPRODUCT(($D$15:$M$15="Yes")*AV22:BE22) | BJ22: =IFERROR(BG22/BH22,0) | BK22: =IFERROR(BG22/BI22,0) | BL22: =IF(B22="Actual",1,INDEX($G$9:$G$11,MATCH(C22,$A$9:$A$11,0))) | BN22: 46023 | BO22: =Inputs!$A$38 | BP22: =AM32
A23: 45748 | B23: =IF(A23<=LastActual,"Actual","Forecast") | C23: =YEAR(A23) | D23: =IFERROR('NSW-1'!X18*1,0) | E23: =IFERROR('VIC-1'!X18*1,0) | F23: =IFERROR('QLD-1'!X18*1,0) | G23: =IFERROR('NSW-2'!X18*1,0) | H23: =IFERROR('VIC-2'!X18*1,0) | I23: =IFERROR('QLD-2'!X18*1,0) | J23: =IFERROR('SA-1'!X18*1,0) | K23: =IFERROR('WA-1'!X18*1,0) | L23: =IFERROR('IDC-NSW'!X18*1,0) | M23: =IFERROR('IDC-VIC'!X18*1,0) | O23: =Cases_Forecast!AJ11 | P23: =Cases_Forecast!AK11 | Q23: =Cases_Forecast!AL11 | R23: =Cases_Forecast!AM11 | S23: =Cases_Forecast!AN11 | T23: =Cases_Forecast!AO11 | U23: =Cases_Forecast!AP11 | V23: =Cases_Forecast!AQ11 | ... X23: =Cases_Forecast!AS11 | Z23: =IFERROR(O23/D23,0) | AA23: =IFERROR(P23/E23,0) | AB23: =IFERROR(Q23/F23,0) | AC23: =IFERROR(R23/G23,0) | AD23: =IFERROR(S23/H23,0) | AE23: =IFERROR(T23/I23,0) | AF23: =IFERROR(U23/J23,0) | AG23: =IFERROR(V23/K23,0) | ... AI23: =IFERROR(X23/M23,0) | AK23: =IF(D$15="Yes",D23*$BL23,D23) | AL23: =IF(E$15="Yes",E23*$BL23,E23) | AM23: =IF(F$15="Yes",F23*$BL23,F23) | AN23: =IF(G$15="Yes",G23*$BL23,G23) | AO23: =IF(H$15="Yes",H23*$BL23,H23) | AP23: =IF(I$15="Yes",I23*$BL23,I23) | AQ23: =IF(J$15="Yes",J23*$BL23,J23) | AR23: =IF(K$15="Yes",K23*$BL23,K23) | ... AT23: =IF(M$15="Yes",M23*$BL23,M23) | AV23: =IFERROR(O23/AK23,0) | AW23: =IFERROR(P23/AL23,0) | AX23: =IFERROR(Q23/AM23,0) | AY23: =IFERROR(R23/AN23,0) | AZ23: =IFERROR(S23/AO23,0) | BA23: =IFERROR(T23/AP23,0) | BB23: =IFERROR(U23/AQ23,0) | BC23: =IFERROR(V23/AR23,0) | ... BE23: =IFERROR(X23/AT23,0) | BG23: =SUMPRODUCT(($D$15:$M$15="Yes")*O23:X23) | BH23: =SUMPRODUCT(($D$15:$M$15="Yes")*Z23:AI23) | BI23: =SUMPRODUCT(($D$15:$M$15="Yes")*AV23:BE23) | BJ23: =IFERROR(BG23/BH23,0) | BK23: =IFERROR(BG23/BI23,0) | BL23: =IF(B23="Actual",1,INDEX($G$9:$G$11,MATCH(C23,$A$9:$A$11,0))) | BN23: 46023 | BO23: =Inputs!$A$39 | BP23: =AN32
A24: 45778 | B24: =IF(A24<=LastActual,"Actual","Forecast") | C24: =YEAR(A24) | D24: =IFERROR('NSW-1'!X19*1,0) | E24: =IFERROR('VIC-1'!X19*1,0) | F24: =IFERROR('QLD-1'!X19*1,0) | G24: =IFERROR('NSW-2'!X19*1,0) | H24: =IFERROR('VIC-2'!X19*1,0) | I24: =IFERROR('QLD-2'!X19*1,0) | J24: =IFERROR('SA-1'!X19*1,0) | K24: =IFERROR('WA-1'!X19*1,0) | L24: =IFERROR('IDC-NSW'!X19*1,0) | M24: =IFERROR('IDC-VIC'!X19*1,0) | O24: =Cases_Forecast!AJ12 | P24: =Cases_Forecast!AK12 | Q24: =Cases_Forecast!AL12 | R24: =Cases_Forecast!AM12 | S24: =Cases_Forecast!AN12 | T24: =Cases_Forecast!AO12 | U24: =Cases_Forecast!AP12 | V24: =Cases_Forecast!AQ12 | ... X24: =Cases_Forecast!AS12 | Z24: =IFERROR(O24/D24,0) | AA24: =IFERROR(P24/E24,0) | AB24: =IFERROR(Q24/F24,0) | AC24: =IFERROR(R24/G24,0) | AD24: =IFERROR(S24/H24,0) | AE24: =IFERROR(T24/I24,0) | AF24: =IFERROR(U24/J24,0) | AG24: =IFERROR(V24/K24,0) | ... AI24: =IFERROR(X24/M24,0) | AK24: =IF(D$15="Yes",D24*$BL24,D24) | AL24: =IF(E$15="Yes",E24*$BL24,E24) | AM24: =IF(F$15="Yes",F24*$BL24,F24) | AN24: =IF(G$15="Yes",G24*$BL24,G24) | AO24: =IF(H$15="Yes",H24*$BL24,H24) | AP24: =IF(I$15="Yes",I24*$BL24,I24) | AQ24: =IF(J$15="Yes",J24*$BL24,J24) | AR24: =IF(K$15="Yes",K24*$BL24,K24) | ... AT24: =IF(M$15="Yes",M24*$BL24,M24) | AV24: =IFERROR(O24/AK24,0) | AW24: =IFERROR(P24/AL24,0) | AX24: =IFERROR(Q24/AM24,0) | AY24: =IFERROR(R24/AN24,0) | AZ24: =IFERROR(S24/AO24,0) | BA24: =IFERROR(T24/AP24,0) | BB24: =IFERROR(U24/AQ24,0) | BC24: =IFERROR(V24/AR24,0) | ... BE24: =IFERROR(X24/AT24,0) | BG24: =SUMPRODUCT(($D$15:$M$15="Yes")*O24:X24) | BH24: =SUMPRODUCT(($D$15:$M$15="Yes")*Z24:AI24) | BI24: =SUMPRODUCT(($D$15:$M$15="Yes")*AV24:BE24) | BJ24: =IFERROR(BG24/BH24,0) | BK24: =IFERROR(BG24/BI24,0) | BL24: =IF(B24="Actual",1,INDEX($G$9:$G$11,MATCH(C24,$A$9:$A$11,0))) | BN24: 46023 | BO24: =Inputs!$A$40 | BP24: =AO32
A25: 45809 | B25: =IF(A25<=LastActual,"Actual","Forecast") | C25: =YEAR(A25) | D25: =IFERROR('NSW-1'!X20*1,0) | E25: =IFERROR('VIC-1'!X20*1,0) | F25: =IFERROR('QLD-1'!X20*1,0) | G25: =IFERROR('NSW-2'!X20*1,0) | H25: =IFERROR('VIC-2'!X20*1,0) | I25: =IFERROR('QLD-2'!X20*1,0) | J25: =IFERROR('SA-1'!X20*1,0) | K25: =IFERROR('WA-1'!X20*1,0) | L25: =IFERROR('IDC-NSW'!X20*1,0) | M25: =IFERROR('IDC-VIC'!X20*1,0) | O25: =Cases_Forecast!AJ13 | P25: =Cases_Forecast!AK13 | Q25: =Cases_Forecast!AL13 | R25: =Cases_Forecast!AM13 | S25: =Cases_Forecast!AN13 | T25: =Cases_Forecast!AO13 | U25: =Cases_Forecast!AP13 | V25: =Cases_Forecast!AQ13 | ... X25: =Cases_Forecast!AS13 | Z25: =IFERROR(O25/D25,0) | AA25: =IFERROR(P25/E25,0) | AB25: =IFERROR(Q25/F25,0) | AC25: =IFERROR(R25/G25,0) | AD25: =IFERROR(S25/H25,0) | AE25: =IFERROR(T25/I25,0) | AF25: =IFERROR(U25/J25,0) | AG25: =IFERROR(V25/K25,0) | ... AI25: =IFERROR(X25/M25,0) | AK25: =IF(D$15="Yes",D25*$BL25,D25) | AL25: =IF(E$15="Yes",E25*$BL25,E25) | AM25: =IF(F$15="Yes",F25*$BL25,F25) | AN25: =IF(G$15="Yes",G25*$BL25,G25) | AO25: =IF(H$15="Yes",H25*$BL25,H25) | AP25: =IF(I$15="Yes",I25*$BL25,I25) | AQ25: =IF(J$15="Yes",J25*$BL25,J25) | AR25: =IF(K$15="Yes",K25*$BL25,K25) | ... AT25: =IF(M$15="Yes",M25*$BL25,M25) | AV25: =IFERROR(O25/AK25,0) | AW25: =IFERROR(P25/AL25,0) | AX25: =IFERROR(Q25/AM25,0) | AY25: =IFERROR(R25/AN25,0) | AZ25: =IFERROR(S25/AO25,0) | BA25: =IFERROR(T25/AP25,0) | BB25: =IFERROR(U25/AQ25,0) | BC25: =IFERROR(V25/AR25,0) | ... BE25: =IFERROR(X25/AT25,0) | BG25: =SUMPRODUCT(($D$15:$M$15="Yes")*O25:X25) | BH25: =SUMPRODUCT(($D$15:$M$15="Yes")*Z25:AI25) | BI25: =SUMPRODUCT(($D$15:$M$15="Yes")*AV25:BE25) | BJ25: =IFERROR(BG25/BH25,0) | BK25: =IFERROR(BG25/BI25,0) | BL25: =IF(B25="Actual",1,INDEX($G$9:$G$11,MATCH(C25,$A$9:$A$11,0))) | BN25: 46023 | BO25: =Inputs!$A$41 | BP25: =AP32
A26: 45839 | B26: =IF(A26<=LastActual,"Actual","Forecast") | C26: =YEAR(A26) | D26: =IFERROR('NSW-1'!X21*1,0) | E26: =IFERROR('VIC-1'!X21*1,0) | F26: =IFERROR('QLD-1'!X21*1,0) | G26: =IFERROR('NSW-2'!X21*1,0) | H26: =IFERROR('VIC-2'!X21*1,0) | I26: =IFERROR('QLD-2'!X21*1,0) | J26: =IFERROR('SA-1'!X21*1,0) | K26: =IFERROR('WA-1'!X21*1,0) | L26: =IFERROR('IDC-NSW'!X21*1,0) | M26: =IFERROR('IDC-VIC'!X21*1,0) | O26: =Cases_Forecast!AJ14 | P26: =Cases_Forecast!AK14 | Q26: =Cases_Forecast!AL14 | R26: =Cases_Forecast!AM14 | S26: =Cases_Forecast!AN14 | T26: =Cases_Forecast!AO14 | U26: =Cases_Forecast!AP14 | V26: =Cases_Forecast!AQ14 | ... X26: =Cases_Forecast!AS14 | Z26: =IFERROR(O26/D26,0) | AA26: =IFERROR(P26/E26,0) | AB26: =IFERROR(Q26/F26,0) | AC26: =IFERROR(R26/G26,0) | AD26: =IFERROR(S26/H26,0) | AE26: =IFERROR(T26/I26,0) | AF26: =IFERROR(U26/J26,0) | AG26: =IFERROR(V26/K26,0) | ... AI26: =IFERROR(X26/M26,0) | AK26: =IF(D$15="Yes",D26*$BL26,D26) | AL26: =IF(E$15="Yes",E26*$BL26,E26) | AM26: =IF(F$15="Yes",F26*$BL26,F26) | AN26: =IF(G$15="Yes",G26*$BL26,G26) | AO26: =IF(H$15="Yes",H26*$BL26,H26) | AP26: =IF(I$15="Yes",I26*$BL26,I26) | AQ26: =IF(J$15="Yes",J26*$BL26,J26) | AR26: =IF(K$15="Yes",K26*$BL26,K26) | ... AT26: =IF(M$15="Yes",M26*$BL26,M26) | AV26: =IFERROR(O26/AK26,0) | AW26: =IFERROR(P26/AL26,0) | AX26: =IFERROR(Q26/AM26,0) | AY26: =IFERROR(R26/AN26,0) | AZ26: =IFERROR(S26/AO26,0) | BA26: =IFERROR(T26/AP26,0) | BB26: =IFERROR(U26/AQ26,0) | BC26: =IFERROR(V26/AR26,0) | ... BE26: =IFERROR(X26/AT26,0) | BG26: =SUMPRODUCT(($D$15:$M$15="Yes")*O26:X26) | BH26: =SUMPRODUCT(($D$15:$M$15="Yes")*Z26:AI26) | BI26: =SUMPRODUCT(($D$15:$M$15="Yes")*AV26:BE26) | BJ26: =IFERROR(BG26/BH26,0) | BK26: =IFERROR(BG26/BI26,0) | BL26: =IF(B26="Actual",1,INDEX($G$9:$G$11,MATCH(C26,$A$9:$A$11,0))) | BN26: 46023 | BO26: =Inputs!$A$42 | BP26: =AQ32
A27: 45870 | B27: =IF(A27<=LastActual,"Actual","Forecast") | C27: =YEAR(A27) | D27: =IFERROR('NSW-1'!X22*1,0) | E27: =IFERROR('VIC-1'!X22*1,0) | F27: =IFERROR('QLD-1'!X22*1,0) | G27: =IFERROR('NSW-2'!X22*1,0) | H27: =IFERROR('VIC-2'!X22*1,0) | I27: =IFERROR('QLD-2'!X22*1,0) | J27: =IFERROR('SA-1'!X22*1,0) | K27: =IFERROR('WA-1'!X22*1,0) | L27: =IFERROR('IDC-NSW'!X22*1,0) | M27: =IFERROR('IDC-VIC'!X22*1,0) | O27: =Cases_Forecast!AJ15 | P27: =Cases_Forecast!AK15 | Q27: =Cases_Forecast!AL15 | R27: =Cases_Forecast!AM15 | S27: =Cases_Forecast!AN15 | T27: =Cases_Forecast!AO15 | U27: =Cases_Forecast!AP15 | V27: =Cases_Forecast!AQ15 | ... X27: =Cases_Forecast!AS15 | Z27: =IFERROR(O27/D27,0) | AA27: =IFERROR(P27/E27,0) | AB27: =IFERROR(Q27/F27,0) | AC27: =IFERROR(R27/G27,0) | AD27: =IFERROR(S27/H27,0) | AE27: =IFERROR(T27/I27,0) | AF27: =IFERROR(U27/J27,0) | AG27: =IFERROR(V27/K27,0) | ... AI27: =IFERROR(X27/M27,0) | AK27: =IF(D$15="Yes",D27*$BL27,D27) | AL27: =IF(E$15="Yes",E27*$BL27,E27) | AM27: =IF(F$15="Yes",F27*$BL27,F27) | AN27: =IF(G$15="Yes",G27*$BL27,G27) | AO27: =IF(H$15="Yes",H27*$BL27,H27) | AP27: =IF(I$15="Yes",I27*$BL27,I27) | AQ27: =IF(J$15="Yes",J27*$BL27,J27) | AR27: =IF(K$15="Yes",K27*$BL27,K27) | ... AT27: =IF(M$15="Yes",M27*$BL27,M27) | AV27: =IFERROR(O27/AK27,0) | AW27: =IFERROR(P27/AL27,0) | AX27: =IFERROR(Q27/AM27,0) | AY27: =IFERROR(R27/AN27,0) | AZ27: =IFERROR(S27/AO27,0) | BA27: =IFERROR(T27/AP27,0) | BB27: =IFERROR(U27/AQ27,0) | BC27: =IFERROR(V27/AR27,0) | ... BE27: =IFERROR(X27/AT27,0) | BG27: =SUMPRODUCT(($D$15:$M$15="Yes")*O27:X27) | BH27: =SUMPRODUCT(($D$15:$M$15="Yes")*Z27:AI27) | BI27: =SUMPRODUCT(($D$15:$M$15="Yes")*AV27:BE27) | BJ27: =IFERROR(BG27/BH27,0) | BK27: =IFERROR(BG27/BI27,0) | BL27: =IF(B27="Actual",1,INDEX($G$9:$G$11,MATCH(C27,$A$9:$A$11,0))) | BN27: 46023 | BO27: =Inputs!$A$43 | BP27: =AR32
A28: 45901 | B28: =IF(A28<=LastActual,"Actual","Forecast") | C28: =YEAR(A28) | D28: =IFERROR('NSW-1'!X23*1,0) | E28: =IFERROR('VIC-1'!X23*1,0) | F28: =IFERROR('QLD-1'!X23*1,0) | G28: =IFERROR('NSW-2'!X23*1,0) | H28: =IFERROR('VIC-2'!X23*1,0) | I28: =IFERROR('QLD-2'!X23*1,0) | J28: =IFERROR('SA-1'!X23*1,0) | K28: =IFERROR('WA-1'!X23*1,0) | L28: =IFERROR('IDC-NSW'!X23*1,0) | M28: =IFERROR('IDC-VIC'!X23*1,0) | O28: =Cases_Forecast!AJ16 | P28: =Cases_Forecast!AK16 | Q28: =Cases_Forecast!AL16 | R28: =Cases_Forecast!AM16 | S28: =Cases_Forecast!AN16 | T28: =Cases_Forecast!AO16 | U28: =Cases_Forecast!AP16 | V28: =Cases_Forecast!AQ16 | ... X28: =Cases_Forecast!AS16 | Z28: =IFERROR(O28/D28,0) | AA28: =IFERROR(P28/E28,0) | AB28: =IFERROR(Q28/F28,0) | AC28: =IFERROR(R28/G28,0) | AD28: =IFERROR(S28/H28,0) | AE28: =IFERROR(T28/I28,0) | AF28: =IFERROR(U28/J28,0) | AG28: =IFERROR(V28/K28,0) | ... AI28: =IFERROR(X28/M28,0) | AK28: =IF(D$15="Yes",D28*$BL28,D28) | AL28: =IF(E$15="Yes",E28*$BL28,E28) | AM28: =IF(F$15="Yes",F28*$BL28,F28) | AN28: =IF(G$15="Yes",G28*$BL28,G28) | AO28: =IF(H$15="Yes",H28*$BL28,H28) | AP28: =IF(I$15="Yes",I28*$BL28,I28) | AQ28: =IF(J$15="Yes",J28*$BL28,J28) | AR28: =IF(K$15="Yes",K28*$BL28,K28) | ... AT28: =IF(M$15="Yes",M28*$BL28,M28) | AV28: =IFERROR(O28/AK28,0) | AW28: =IFERROR(P28/AL28,0) | AX28: =IFERROR(Q28/AM28,0) | AY28: =IFERROR(R28/AN28,0) | AZ28: =IFERROR(S28/AO28,0) | BA28: =IFERROR(T28/AP28,0) | BB28: =IFERROR(U28/AQ28,0) | BC28: =IFERROR(V28/AR28,0) | ... BE28: =IFERROR(X28/AT28,0) | BG28: =SUMPRODUCT(($D$15:$M$15="Yes")*O28:X28) | BH28: =SUMPRODUCT(($D$15:$M$15="Yes")*Z28:AI28) | BI28: =SUMPRODUCT(($D$15:$M$15="Yes")*AV28:BE28) | BJ28: =IFERROR(BG28/BH28,0) | BK28: =IFERROR(BG28/BI28,0) | BL28: =IF(B28="Actual",1,INDEX($G$9:$G$11,MATCH(C28,$A$9:$A$11,0))) | BN28: 46023 | BO28: =Inputs!$A$44 | BP28: =AS32
A29: 45931 | B29: =IF(A29<=LastActual,"Actual","Forecast") | C29: =YEAR(A29) | D29: =IFERROR('NSW-1'!X24*1,0) | E29: =IFERROR('VIC-1'!X24*1,0) | F29: =IFERROR('QLD-1'!X24*1,0) | G29: =IFERROR('NSW-2'!X24*1,0) | H29: =IFERROR('VIC-2'!X24*1,0) | I29: =IFERROR('QLD-2'!X24*1,0) | J29: =IFERROR('SA-1'!X24*1,0) | K29: =IFERROR('WA-1'!X24*1,0) | L29: =IFERROR('IDC-NSW'!X24*1,0) | M29: =IFERROR('IDC-VIC'!X24*1,0) | O29: =Cases_Forecast!AJ17 | P29: =Cases_Forecast!AK17 | Q29: =Cases_Forecast!AL17 | R29: =Cases_Forecast!AM17 | S29: =Cases_Forecast!AN17 | T29: =Cases_Forecast!AO17 | U29: =Cases_Forecast!AP17 | V29: =Cases_Forecast!AQ17 | ... X29: =Cases_Forecast!AS17 | Z29: =IFERROR(O29/D29,0) | AA29: =IFERROR(P29/E29,0) | AB29: =IFERROR(Q29/F29,0) | AC29: =IFERROR(R29/G29,0) | AD29: =IFERROR(S29/H29,0) | AE29: =IFERROR(T29/I29,0) | AF29: =IFERROR(U29/J29,0) | AG29: =IFERROR(V29/K29,0) | ... AI29: =IFERROR(X29/M29,0) | AK29: =IF(D$15="Yes",D29*$BL29,D29) | AL29: =IF(E$15="Yes",E29*$BL29,E29) | AM29: =IF(F$15="Yes",F29*$BL29,F29) | AN29: =IF(G$15="Yes",G29*$BL29,G29) | AO29: =IF(H$15="Yes",H29*$BL29,H29) | AP29: =IF(I$15="Yes",I29*$BL29,I29) | AQ29: =IF(J$15="Yes",J29*$BL29,J29) | AR29: =IF(K$15="Yes",K29*$BL29,K29) | ... AT29: =IF(M$15="Yes",M29*$BL29,M29) | AV29: =IFERROR(O29/AK29,0) | AW29: =IFERROR(P29/AL29,0) | AX29: =IFERROR(Q29/AM29,0) | AY29: =IFERROR(R29/AN29,0) | AZ29: =IFERROR(S29/AO29,0) | BA29: =IFERROR(T29/AP29,0) | BB29: =IFERROR(U29/AQ29,0) | BC29: =IFERROR(V29/AR29,0) | ... BE29: =IFERROR(X29/AT29,0) | BG29: =SUMPRODUCT(($D$15:$M$15="Yes")*O29:X29) | BH29: =SUMPRODUCT(($D$15:$M$15="Yes")*Z29:AI29) | BI29: =SUMPRODUCT(($D$15:$M$15="Yes")*AV29:BE29) | BJ29: =IFERROR(BG29/BH29,0) | BK29: =IFERROR(BG29/BI29,0) | BL29: =IF(B29="Actual",1,INDEX($G$9:$G$11,MATCH(C29,$A$9:$A$11,0))) | BN29: 46023 | BO29: =Inputs!$A$45 | BP29: =AT32
A30: 45962 | B30: =IF(A30<=LastActual,"Actual","Forecast") | C30: =YEAR(A30) | D30: =IFERROR('NSW-1'!X25*1,0) | E30: =IFERROR('VIC-1'!X25*1,0) | F30: =IFERROR('QLD-1'!X25*1,0) | G30: =IFERROR('NSW-2'!X25*1,0) | H30: =IFERROR('VIC-2'!X25*1,0) | I30: =IFERROR('QLD-2'!X25*1,0) | J30: =IFERROR('SA-1'!X25*1,0) | K30: =IFERROR('WA-1'!X25*1,0) | L30: =IFERROR('IDC-NSW'!X25*1,0) | M30: =IFERROR('IDC-VIC'!X25*1,0) | O30: =Cases_Forecast!AJ18 | P30: =Cases_Forecast!AK18 | Q30: =Cases_Forecast!AL18 | R30: =Cases_Forecast!AM18 | S30: =Cases_Forecast!AN18 | T30: =Cases_Forecast!AO18 | U30: =Cases_Forecast!AP18 | V30: =Cases_Forecast!AQ18 | ... X30: =Cases_Forecast!AS18 | Z30: =IFERROR(O30/D30,0) | AA30: =IFERROR(P30/E30,0) | AB30: =IFERROR(Q30/F30,0) | AC30: =IFERROR(R30/G30,0) | AD30: =IFERROR(S30/H30,0) | AE30: =IFERROR(T30/I30,0) | AF30: =IFERROR(U30/J30,0) | AG30: =IFERROR(V30/K30,0) | ... AI30: =IFERROR(X30/M30,0) | AK30: =IF(D$15="Yes",D30*$BL30,D30) | AL30: =IF(E$15="Yes",E30*$BL30,E30) | AM30: =IF(F$15="Yes",F30*$BL30,F30) | AN30: =IF(G$15="Yes",G30*$BL30,G30) | AO30: =IF(H$15="Yes",H30*$BL30,H30) | AP30: =IF(I$15="Yes",I30*$BL30,I30) | AQ30: =IF(J$15="Yes",J30*$BL30,J30) | AR30: =IF(K$15="Yes",K30*$BL30,K30) | ... AT30: =IF(M$15="Yes",M30*$BL30,M30) | AV30: =IFERROR(O30/AK30,0) | AW30: =IFERROR(P30/AL30,0) | AX30: =IFERROR(Q30/AM30,0) | AY30: =IFERROR(R30/AN30,0) | AZ30: =IFERROR(S30/AO30,0) | BA30: =IFERROR(T30/AP30,0) | BB30: =IFERROR(U30/AQ30,0) | BC30: =IFERROR(V30/AR30,0) | ... BE30: =IFERROR(X30/AT30,0) | BG30: =SUMPRODUCT(($D$15:$M$15="Yes")*O30:X30) | BH30: =SUMPRODUCT(($D$15:$M$15="Yes")*Z30:AI30) | BI30: =SUMPRODUCT(($D$15:$M$15="Yes")*AV30:BE30) | BJ30: =IFERROR(BG30/BH30,0) | BK30: =IFERROR(BG30/BI30,0) | BL30: =IF(B30="Actual",1,INDEX($G$9:$G$11,MATCH(C30,$A$9:$A$11,0))) | BN30: 46054 | BO30: =Inputs!$A$36 | BP30: =AK33
A31: 45992 | B31: =IF(A31<=LastActual,"Actual","Forecast") | C31: =YEAR(A31) | D31: =IFERROR('NSW-1'!X26*1,0) | E31: =IFERROR('VIC-1'!X26*1,0) | F31: =IFERROR('QLD-1'!X26*1,0) | G31: =IFERROR('NSW-2'!X26*1,0) | H31: =IFERROR('VIC-2'!X26*1,0) | I31: =IFERROR('QLD-2'!X26*1,0) | J31: =IFERROR('SA-1'!X26*1,0) | K31: =IFERROR('WA-1'!X26*1,0) | L31: =IFERROR('IDC-NSW'!X26*1,0) | M31: =IFERROR('IDC-VIC'!X26*1,0) | O31: =Cases_Forecast!AJ19 | P31: =Cases_Forecast!AK19 | Q31: =Cases_Forecast!AL19 | R31: =Cases_Forecast!AM19 | S31: =Cases_Forecast!AN19 | T31: =Cases_Forecast!AO19 | U31: =Cases_Forecast!AP19 | V31: =Cases_Forecast!AQ19 | ... X31: =Cases_Forecast!AS19 | Z31: =IFERROR(O31/D31,0) | AA31: =IFERROR(P31/E31,0) | AB31: =IFERROR(Q31/F31,0) | AC31: =IFERROR(R31/G31,0) | AD31: =IFERROR(S31/H31,0) | AE31: =IFERROR(T31/I31,0) | AF31: =IFERROR(U31/J31,0) | AG31: =IFERROR(V31/K31,0) | ... AI31: =IFERROR(X31/M31,0) | AK31: =IF(D$15="Yes",D31*$BL31,D31) | AL31: =IF(E$15="Yes",E31*$BL31,E31) | AM31: =IF(F$15="Yes",F31*$BL31,F31) | AN31: =IF(G$15="Yes",G31*$BL31,G31) | AO31: =IF(H$15="Yes",H31*$BL31,H31) | AP31: =IF(I$15="Yes",I31*$BL31,I31) | AQ31: =IF(J$15="Yes",J31*$BL31,J31) | AR31: =IF(K$15="Yes",K31*$BL31,K31) | ... AT31: =IF(M$15="Yes",M31*$BL31,M31) | AV31: =IFERROR(O31/AK31,0) | AW31: =IFERROR(P31/AL31,0) | AX31: =IFERROR(Q31/AM31,0) | AY31: =IFERROR(R31/AN31,0) | AZ31: =IFERROR(S31/AO31,0) | BA31: =IFERROR(T31/AP31,0) | BB31: =IFERROR(U31/AQ31,0) | BC31: =IFERROR(V31/AR31,0) | ... BE31: =IFERROR(X31/AT31,0) | BG31: =SUMPRODUCT(($D$15:$M$15="Yes")*O31:X31) | BH31: =SUMPRODUCT(($D$15:$M$15="Yes")*Z31:AI31) | BI31: =SUMPRODUCT(($D$15:$M$15="Yes")*AV31:BE31) | BJ31: =IFERROR(BG31/BH31,0) | BK31: =IFERROR(BG31/BI31,0) | BL31: =IF(B31="Actual",1,INDEX($G$9:$G$11,MATCH(C31,$A$9:$A$11,0))) | BN31: 46054 | BO31: =Inputs!$A$37 | BP31: =AL33
A32: 46023 | B32: =IF(A32<=LastActual,"Actual","Forecast") | C32: =YEAR(A32) | D32: =IFERROR('NSW-1'!X27*1,0) | E32: =IFERROR('VIC-1'!X27*1,0) | F32: =IFERROR('QLD-1'!X27*1,0) | G32: =IFERROR('NSW-2'!X27*1,0) | H32: =IFERROR('VIC-2'!X27*1,0) | I32: =IFERROR('QLD-2'!X27*1,0) | J32: =IFERROR('SA-1'!X27*1,0) | K32: =IFERROR('WA-1'!X27*1,0) | L32: =IFERROR('IDC-NSW'!X27*1,0) | M32: =IFERROR('IDC-VIC'!X27*1,0) | O32: =Cases_Forecast!AJ20 | P32: =Cases_Forecast!AK20 | Q32: =Cases_Forecast!AL20 | R32: =Cases_Forecast!AM20 | S32: =Cases_Forecast!AN20 | T32: =Cases_Forecast!AO20 | U32: =Cases_Forecast!AP20 | V32: =Cases_Forecast!AQ20 | ... X32: =Cases_Forecast!AS20 | Z32: =IFERROR(O32/D32,0) | AA32: =IFERROR(P32/E32,0) | AB32: =IFERROR(Q32/F32,0) | AC32: =IFERROR(R32/G32,0) | AD32: =IFERROR(S32/H32,0) | AE32: =IFERROR(T32/I32,0) | AF32: =IFERROR(U32/J32,0) | AG32: =IFERROR(V32/K32,0) | ... AI32: =IFERROR(X32/M32,0) | AK32: =IF(D$15="Yes",D32*$BL32,D32) | AL32: =IF(E$15="Yes",E32*$BL32,E32) | AM32: =IF(F$15="Yes",F32*$BL32,F32) | AN32: =IF(G$15="Yes",G32*$BL32,G32) | AO32: =IF(H$15="Yes",H32*$BL32,H32) | AP32: =IF(I$15="Yes",I32*$BL32,I32) | AQ32: =IF(J$15="Yes",J32*$BL32,J32) | AR32: =IF(K$15="Yes",K32*$BL32,K32) | ... AT32: =IF(M$15="Yes",M32*$BL32,M32) | AV32: =IFERROR(O32/AK32,0) | AW32: =IFERROR(P32/AL32,0) | AX32: =IFERROR(Q32/AM32,0) | AY32: =IFERROR(R32/AN32,0) | AZ32: =IFERROR(S32/AO32,0) | BA32: =IFERROR(T32/AP32,0) | BB32: =IFERROR(U32/AQ32,0) | BC32: =IFERROR(V32/AR32,0) | ... BE32: =IFERROR(X32/AT32,0) | BG32: =SUMPRODUCT(($D$15:$M$15="Yes")*O32:X32) | BH32: =SUMPRODUCT(($D$15:$M$15="Yes")*Z32:AI32) | BI32: =SUMPRODUCT(($D$15:$M$15="Yes")*AV32:BE32) | BJ32: =IFERROR(BG32/BH32,0) | BK32: =IFERROR(BG32/BI32,0) | BL32: =IF(B32="Actual",1,INDEX($G$9:$G$11,MATCH(C32,$A$9:$A$11,0))) | BN32: 46054 | BO32: =Inputs!$A$38 | BP32: =AM33
A33: 46054 | B33: =IF(A33<=LastActual,"Actual","Forecast") | C33: =YEAR(A33) | D33: =IFERROR('NSW-1'!X28*1,0) | E33: =IFERROR('VIC-1'!X28*1,0) | F33: =IFERROR('QLD-1'!X28*1,0) | G33: =IFERROR('NSW-2'!X28*1,0) | H33: =IFERROR('VIC-2'!X28*1,0) | I33: =IFERROR('QLD-2'!X28*1,0) | J33: =IFERROR('SA-1'!X28*1,0) | K33: =IFERROR('WA-1'!X28*1,0) | L33: =IFERROR('IDC-NSW'!X28*1,0) | M33: =IFERROR('IDC-VIC'!X28*1,0) | O33: =Cases_Forecast!AJ21 | P33: =Cases_Forecast!AK21 | Q33: =Cases_Forecast!AL21 | R33: =Cases_Forecast!AM21 | S33: =Cases_Forecast!AN21 | T33: =Cases_Forecast!AO21 | U33: =Cases_Forecast!AP21 | V33: =Cases_Forecast!AQ21 | ... X33: =Cases_Forecast!AS21 | Z33: =IFERROR(O33/D33,0) | AA33: =IFERROR(P33/E33,0) | AB33: =IFERROR(Q33/F33,0) | AC33: =IFERROR(R33/G33,0) | AD33: =IFERROR(S33/H33,0) | AE33: =IFERROR(T33/I33,0) | AF33: =IFERROR(U33/J33,0) | AG33: =IFERROR(V33/K33,0) | ... AI33: =IFERROR(X33/M33,0) | AK33: =IF(D$15="Yes",D33*$BL33,D33) | AL33: =IF(E$15="Yes",E33*$BL33,E33) | AM33: =IF(F$15="Yes",F33*$BL33,F33) | AN33: =IF(G$15="Yes",G33*$BL33,G33) | AO33: =IF(H$15="Yes",H33*$BL33,H33) | AP33: =IF(I$15="Yes",I33*$BL33,I33) | AQ33: =IF(J$15="Yes",J33*$BL33,J33) | AR33: =IF(K$15="Yes",K33*$BL33,K33) | ... AT33: =IF(M$15="Yes",M33*$BL33,M33) | AV33: =IFERROR(O33/AK33,0) | AW33: =IFERROR(P33/AL33,0) | AX33: =IFERROR(Q33/AM33,0) | AY33: =IFERROR(R33/AN33,0) | AZ33: =IFERROR(S33/AO33,0) | BA33: =IFERROR(T33/AP33,0) | BB33: =IFERROR(U33/AQ33,0) | BC33: =IFERROR(V33/AR33,0) | ... BE33: =IFERROR(X33/AT33,0) | BG33: =SUMPRODUCT(($D$15:$M$15="Yes")*O33:X33) | BH33: =SUMPRODUCT(($D$15:$M$15="Yes")*Z33:AI33) | BI33: =SUMPRODUCT(($D$15:$M$15="Yes")*AV33:BE33) | BJ33: =IFERROR(BG33/BH33,0) | BK33: =IFERROR(BG33/BI33,0) | BL33: =IF(B33="Actual",1,INDEX($G$9:$G$11,MATCH(C33,$A$9:$A$11,0))) | BN33: 46054 | BO33: =Inputs!$A$39 | BP33: =AN33
A34: 46082 | B34: =IF(A34<=LastActual,"Actual","Forecast") | C34: =YEAR(A34) | D34: =IFERROR('NSW-1'!X29*1,0) | E34: =IFERROR('VIC-1'!X29*1,0) | F34: =IFERROR('QLD-1'!X29*1,0) | G34: =IFERROR('NSW-2'!X29*1,0) | H34: =IFERROR('VIC-2'!X29*1,0) | I34: =IFERROR('QLD-2'!X29*1,0) | J34: =IFERROR('SA-1'!X29*1,0) | K34: =IFERROR('WA-1'!X29*1,0) | L34: =IFERROR('IDC-NSW'!X29*1,0) | M34: =IFERROR('IDC-VIC'!X29*1,0) | O34: =Cases_Forecast!AJ22 | P34: =Cases_Forecast!AK22 | Q34: =Cases_Forecast!AL22 | R34: =Cases_Forecast!AM22 | S34: =Cases_Forecast!AN22 | T34: =Cases_Forecast!AO22 | U34: =Cases_Forecast!AP22 | V34: =Cases_Forecast!AQ22 | ... X34: =Cases_Forecast!AS22 | Z34: =IFERROR(O34/D34,0) | AA34: =IFERROR(P34/E34,0) | AB34: =IFERROR(Q34/F34,0) | AC34: =IFERROR(R34/G34,0) | AD34: =IFERROR(S34/H34,0) | AE34: =IFERROR(T34/I34,0) | AF34: =IFERROR(U34/J34,0) | AG34: =IFERROR(V34/K34,0) | ... AI34: =IFERROR(X34/M34,0) | AK34: =IF(D$15="Yes",D34*$BL34,D34) | AL34: =IF(E$15="Yes",E34*$BL34,E34) | AM34: =IF(F$15="Yes",F34*$BL34,F34) | AN34: =IF(G$15="Yes",G34*$BL34,G34) | AO34: =IF(H$15="Yes",H34*$BL34,H34) | AP34: =IF(I$15="Yes",I34*$BL34,I34) | AQ34: =IF(J$15="Yes",J34*$BL34,J34) | AR34: =IF(K$15="Yes",K34*$BL34,K34) | ... AT34: =IF(M$15="Yes",M34*$BL34,M34) | AV34: =IFERROR(O34/AK34,0) | AW34: =IFERROR(P34/AL34,0) | AX34: =IFERROR(Q34/AM34,0) | AY34: =IFERROR(R34/AN34,0) | AZ34: =IFERROR(S34/AO34,0) | BA34: =IFERROR(T34/AP34,0) | BB34: =IFERROR(U34/AQ34,0) | BC34: =IFERROR(V34/AR34,0) | ... BE34: =IFERROR(X34/AT34,0) | BG34: =SUMPRODUCT(($D$15:$M$15="Yes")*O34:X34) | BH34: =SUMPRODUCT(($D$15:$M$15="Yes")*Z34:AI34) | BI34: =SUMPRODUCT(($D$15:$M$15="Yes")*AV34:BE34) | BJ34: =IFERROR(BG34/BH34,0) | BK34: =IFERROR(BG34/BI34,0) | BL34: =IF(B34="Actual",1,INDEX($G$9:$G$11,MATCH(C34,$A$9:$A$11,0))) | BN34: 46054 | BO34: =Inputs!$A$40 | BP34: =AO33
A35: 46113 | B35: =IF(A35<=LastActual,"Actual","Forecast") | C35: =YEAR(A35) | D35: =IFERROR('NSW-1'!X30*1,0) | E35: =IFERROR('VIC-1'!X30*1,0) | F35: =IFERROR('QLD-1'!X30*1,0) | G35: =IFERROR('NSW-2'!X30*1,0) | H35: =IFERROR('VIC-2'!X30*1,0) | I35: =IFERROR('QLD-2'!X30*1,0) | J35: =IFERROR('SA-1'!X30*1,0) | K35: =IFERROR('WA-1'!X30*1,0) | L35: =IFERROR('IDC-NSW'!X30*1,0) | M35: =IFERROR('IDC-VIC'!X30*1,0) | O35: =Cases_Forecast!AJ23 | P35: =Cases_Forecast!AK23 | Q35: =Cases_Forecast!AL23 | R35: =Cases_Forecast!AM23 | S35: =Cases_Forecast!AN23 | T35: =Cases_Forecast!AO23 | U35: =Cases_Forecast!AP23 | V35: =Cases_Forecast!AQ23 | ... X35: =Cases_Forecast!AS23 | Z35: =IFERROR(O35/D35,0) | AA35: =IFERROR(P35/E35,0) | AB35: =IFERROR(Q35/F35,0) | AC35: =IFERROR(R35/G35,0) | AD35: =IFERROR(S35/H35,0) | AE35: =IFERROR(T35/I35,0) | AF35: =IFERROR(U35/J35,0) | AG35: =IFERROR(V35/K35,0) | ... AI35: =IFERROR(X35/M35,0) | AK35: =IF(D$15="Yes",D35*$BL35,D35) | AL35: =IF(E$15="Yes",E35*$BL35,E35) | AM35: =IF(F$15="Yes",F35*$BL35,F35) | AN35: =IF(G$15="Yes",G35*$BL35,G35) | AO35: =IF(H$15="Yes",H35*$BL35,H35) | AP35: =IF(I$15="Yes",I35*$BL35,I35) | AQ35: =IF(J$15="Yes",J35*$BL35,J35) | AR35: =IF(K$15="Yes",K35*$BL35,K35) | ... AT35: =IF(M$15="Yes",M35*$BL35,M35) | AV35: =IFERROR(O35/AK35,0) | AW35: =IFERROR(P35/AL35,0) | AX35: =IFERROR(Q35/AM35,0) | AY35: =IFERROR(R35/AN35,0) | AZ35: =IFERROR(S35/AO35,0) | BA35: =IFERROR(T35/AP35,0) | BB35: =IFERROR(U35/AQ35,0) | BC35: =IFERROR(V35/AR35,0) | ... BE35: =IFERROR(X35/AT35,0) | BG35: =SUMPRODUCT(($D$15:$M$15="Yes")*O35:X35) | BH35: =SUMPRODUCT(($D$15:$M$15="Yes")*Z35:AI35) | BI35: =SUMPRODUCT(($D$15:$M$15="Yes")*AV35:BE35) | BJ35: =IFERROR(BG35/BH35,0) | BK35: =IFERROR(BG35/BI35,0) | BL35: =IF(B35="Actual",1,INDEX($G$9:$G$11,MATCH(C35,$A$9:$A$11,0))) | BN35: 46054 | BO35: =Inputs!$A$41 | BP35: =AP33
A36: 46143 | B36: =IF(A36<=LastActual,"Actual","Forecast") | C36: =YEAR(A36) | D36: =IFERROR('NSW-1'!X31*1,0) | E36: =IFERROR('VIC-1'!X31*1,0) | F36: =IFERROR('QLD-1'!X31*1,0) | G36: =IFERROR('NSW-2'!X31*1,0) | H36: =IFERROR('VIC-2'!X31*1,0) | I36: =IFERROR('QLD-2'!X31*1,0) | J36: =IFERROR('SA-1'!X31*1,0) | K36: =IFERROR('WA-1'!X31*1,0) | L36: =IFERROR('IDC-NSW'!X31*1,0) | M36: =IFERROR('IDC-VIC'!X31*1,0) | O36: =Cases_Forecast!AJ24 | P36: =Cases_Forecast!AK24 | Q36: =Cases_Forecast!AL24 | R36: =Cases_Forecast!AM24 | S36: =Cases_Forecast!AN24 | T36: =Cases_Forecast!AO24 | U36: =Cases_Forecast!AP24 | V36: =Cases_Forecast!AQ24 | ... X36: =Cases_Forecast!AS24 | Z36: =IFERROR(O36/D36,0) | AA36: =IFERROR(P36/E36,0) | AB36: =IFERROR(Q36/F36,0) | AC36: =IFERROR(R36/G36,0) | AD36: =IFERROR(S36/H36,0) | AE36: =IFERROR(T36/I36,0) | AF36: =IFERROR(U36/J36,0) | AG36: =IFERROR(V36/K36,0) | ... AI36: =IFERROR(X36/M36,0) | AK36: =IF(D$15="Yes",D36*$BL36,D36) | AL36: =IF(E$15="Yes",E36*$BL36,E36) | AM36: =IF(F$15="Yes",F36*$BL36,F36) | AN36: =IF(G$15="Yes",G36*$BL36,G36) | AO36: =IF(H$15="Yes",H36*$BL36,H36) | AP36: =IF(I$15="Yes",I36*$BL36,I36) | AQ36: =IF(J$15="Yes",J36*$BL36,J36) | AR36: =IF(K$15="Yes",K36*$BL36,K36) | ... AT36: =IF(M$15="Yes",M36*$BL36,M36) | AV36: =IFERROR(O36/AK36,0) | AW36: =IFERROR(P36/AL36,0) | AX36: =IFERROR(Q36/AM36,0) | AY36: =IFERROR(R36/AN36,0) | AZ36: =IFERROR(S36/AO36,0) | BA36: =IFERROR(T36/AP36,0) | BB36: =IFERROR(U36/AQ36,0) | BC36: =IFERROR(V36/AR36,0) | ... BE36: =IFERROR(X36/AT36,0) | BG36: =SUMPRODUCT(($D$15:$M$15="Yes")*O36:X36) | BH36: =SUMPRODUCT(($D$15:$M$15="Yes")*Z36:AI36) | BI36: =SUMPRODUCT(($D$15:$M$15="Yes")*AV36:BE36) | BJ36: =IFERROR(BG36/BH36,0) | BK36: =IFERROR(BG36/BI36,0) | BL36: =IF(B36="Actual",1,INDEX($G$9:$G$11,MATCH(C36,$A$9:$A$11,0))) | BN36: 46054 | BO36: =Inputs!$A$42 | BP36: =AQ33
A37: 46174 | B37: =IF(A37<=LastActual,"Actual","Forecast") | C37: =YEAR(A37) | D37: =IFERROR('NSW-1'!X32*1,0) | E37: =IFERROR('VIC-1'!X32*1,0) | F37: =IFERROR('QLD-1'!X32*1,0) | G37: =IFERROR('NSW-2'!X32*1,0) | H37: =IFERROR('VIC-2'!X32*1,0) | I37: =IFERROR('QLD-2'!X32*1,0) | J37: =IFERROR('SA-1'!X32*1,0) | K37: =IFERROR('WA-1'!X32*1,0) | L37: =IFERROR('IDC-NSW'!X32*1,0) | M37: =IFERROR('IDC-VIC'!X32*1,0) | O37: =Cases_Forecast!AJ25 | P37: =Cases_Forecast!AK25 | Q37: =Cases_Forecast!AL25 | R37: =Cases_Forecast!AM25 | S37: =Cases_Forecast!AN25 | T37: =Cases_Forecast!AO25 | U37: =Cases_Forecast!AP25 | V37: =Cases_Forecast!AQ25 | ... X37: =Cases_Forecast!AS25 | Z37: =IFERROR(O37/D37,0) | AA37: =IFERROR(P37/E37,0) | AB37: =IFERROR(Q37/F37,0) | AC37: =IFERROR(R37/G37,0) | AD37: =IFERROR(S37/H37,0) | AE37: =IFERROR(T37/I37,0) | AF37: =IFERROR(U37/J37,0) | AG37: =IFERROR(V37/K37,0) | ... AI37: =IFERROR(X37/M37,0) | AK37: =IF(D$15="Yes",D37*$BL37,D37) | AL37: =IF(E$15="Yes",E37*$BL37,E37) | AM37: =IF(F$15="Yes",F37*$BL37,F37) | AN37: =IF(G$15="Yes",G37*$BL37,G37) | AO37: =IF(H$15="Yes",H37*$BL37,H37) | AP37: =IF(I$15="Yes",I37*$BL37,I37) | AQ37: =IF(J$15="Yes",J37*$BL37,J37) | AR37: =IF(K$15="Yes",K37*$BL37,K37) | ... AT37: =IF(M$15="Yes",M37*$BL37,M37) | AV37: =IFERROR(O37/AK37,0) | AW37: =IFERROR(P37/AL37,0) | AX37: =IFERROR(Q37/AM37,0) | AY37: =IFERROR(R37/AN37,0) | AZ37: =IFERROR(S37/AO37,0) | BA37: =IFERROR(T37/AP37,0) | BB37: =IFERROR(U37/AQ37,0) | BC37: =IFERROR(V37/AR37,0) | ... BE37: =IFERROR(X37/AT37,0) | BG37: =SUMPRODUCT(($D$15:$M$15="Yes")*O37:X37) | BH37: =SUMPRODUCT(($D$15:$M$15="Yes")*Z37:AI37) | BI37: =SUMPRODUCT(($D$15:$M$15="Yes")*AV37:BE37) | BJ37: =IFERROR(BG37/BH37,0) | BK37: =IFERROR(BG37/BI37,0) | BL37: =IF(B37="Actual",1,INDEX($G$9:$G$11,MATCH(C37,$A$9:$A$11,0))) | BN37: 46054 | BO37: =Inputs!$A$43 | BP37: =AR33
A38: 46204 | B38: =IF(A38<=LastActual,"Actual","Forecast") | C38: =YEAR(A38) | D38: =IFERROR('NSW-1'!X33*1,0) | E38: =IFERROR('VIC-1'!X33*1,0) | F38: =IFERROR('QLD-1'!X33*1,0) | G38: =IFERROR('NSW-2'!X33*1,0) | H38: =IFERROR('VIC-2'!X33*1,0) | I38: =IFERROR('QLD-2'!X33*1,0) | J38: =IFERROR('SA-1'!X33*1,0) | K38: =IFERROR('WA-1'!X33*1,0) | L38: =IFERROR('IDC-NSW'!X33*1,0) | M38: =IFERROR('IDC-VIC'!X33*1,0) | O38: =Cases_Forecast!AJ26 | P38: =Cases_Forecast!AK26 | Q38: =Cases_Forecast!AL26 | R38: =Cases_Forecast!AM26 | S38: =Cases_Forecast!AN26 | T38: =Cases_Forecast!AO26 | U38: =Cases_Forecast!AP26 | V38: =Cases_Forecast!AQ26 | ... X38: =Cases_Forecast!AS26 | Z38: =IFERROR(O38/D38,0) | AA38: =IFERROR(P38/E38,0) | AB38: =IFERROR(Q38/F38,0) | AC38: =IFERROR(R38/G38,0) | AD38: =IFERROR(S38/H38,0) | AE38: =IFERROR(T38/I38,0) | AF38: =IFERROR(U38/J38,0) | AG38: =IFERROR(V38/K38,0) | ... AI38: =IFERROR(X38/M38,0) | AK38: =IF(D$15="Yes",D38*$BL38,D38) | AL38: =IF(E$15="Yes",E38*$BL38,E38) | AM38: =IF(F$15="Yes",F38*$BL38,F38) | AN38: =IF(G$15="Yes",G38*$BL38,G38) | AO38: =IF(H$15="Yes",H38*$BL38,H38) | AP38: =IF(I$15="Yes",I38*$BL38,I38) | AQ38: =IF(J$15="Yes",J38*$BL38,J38) | AR38: =IF(K$15="Yes",K38*$BL38,K38) | ... AT38: =IF(M$15="Yes",M38*$BL38,M38) | AV38: =IFERROR(O38/AK38,0) | AW38: =IFERROR(P38/AL38,0) | AX38: =IFERROR(Q38/AM38,0) | AY38: =IFERROR(R38/AN38,0) | AZ38: =IFERROR(S38/AO38,0) | BA38: =IFERROR(T38/AP38,0) | BB38: =IFERROR(U38/AQ38,0) | BC38: =IFERROR(V38/AR38,0) | ... BE38: =IFERROR(X38/AT38,0) | BG38: =SUMPRODUCT(($D$15:$M$15="Yes")*O38:X38) | BH38: =SUMPRODUCT(($D$15:$M$15="Yes")*Z38:AI38) | BI38: =SUMPRODUCT(($D$15:$M$15="Yes")*AV38:BE38) | BJ38: =IFERROR(BG38/BH38,0) | BK38: =IFERROR(BG38/BI38,0) | BL38: =IF(B38="Actual",1,INDEX($G$9:$G$11,MATCH(C38,$A$9:$A$11,0))) | BN38: 46054 | BO38: =Inputs!$A$44 | BP38: =AS33
A39: 46235 | B39: =IF(A39<=LastActual,"Actual","Forecast") | C39: =YEAR(A39) | D39: =IFERROR('NSW-1'!X34*1,0) | E39: =IFERROR('VIC-1'!X34*1,0) | F39: =IFERROR('QLD-1'!X34*1,0) | G39: =IFERROR('NSW-2'!X34*1,0) | H39: =IFERROR('VIC-2'!X34*1,0) | I39: =IFERROR('QLD-2'!X34*1,0) | J39: =IFERROR('SA-1'!X34*1,0) | K39: =IFERROR('WA-1'!X34*1,0) | L39: =IFERROR('IDC-NSW'!X34*1,0) | M39: =IFERROR('IDC-VIC'!X34*1,0) | O39: =Cases_Forecast!AJ27 | P39: =Cases_Forecast!AK27 | Q39: =Cases_Forecast!AL27 | R39: =Cases_Forecast!AM27 | S39: =Cases_Forecast!AN27 | T39: =Cases_Forecast!AO27 | U39: =Cases_Forecast!AP27 | V39: =Cases_Forecast!AQ27 | ... X39: =Cases_Forecast!AS27 | Z39: =IFERROR(O39/D39,0) | AA39: =IFERROR(P39/E39,0) | AB39: =IFERROR(Q39/F39,0) | AC39: =IFERROR(R39/G39,0) | AD39: =IFERROR(S39/H39,0) | AE39: =IFERROR(T39/I39,0) | AF39: =IFERROR(U39/J39,0) | AG39: =IFERROR(V39/K39,0) | ... AI39: =IFERROR(X39/M39,0) | AK39: =IF(D$15="Yes",D39*$BL39,D39) | AL39: =IF(E$15="Yes",E39*$BL39,E39) | AM39: =IF(F$15="Yes",F39*$BL39,F39) | AN39: =IF(G$15="Yes",G39*$BL39,G39) | AO39: =IF(H$15="Yes",H39*$BL39,H39) | AP39: =IF(I$15="Yes",I39*$BL39,I39) | AQ39: =IF(J$15="Yes",J39*$BL39,J39) | AR39: =IF(K$15="Yes",K39*$BL39,K39) | ... AT39: =IF(M$15="Yes",M39*$BL39,M39) | AV39: =IFERROR(O39/AK39,0) | AW39: =IFERROR(P39/AL39,0) | AX39: =IFERROR(Q39/AM39,0) | AY39: =IFERROR(R39/AN39,0) | AZ39: =IFERROR(S39/AO39,0) | BA39: =IFERROR(T39/AP39,0) | BB39: =IFERROR(U39/AQ39,0) | BC39: =IFERROR(V39/AR39,0) | ... BE39: =IFERROR(X39/AT39,0) | BG39: =SUMPRODUCT(($D$15:$M$15="Yes")*O39:X39) | BH39: =SUMPRODUCT(($D$15:$M$15="Yes")*Z39:AI39) | BI39: =SUMPRODUCT(($D$15:$M$15="Yes")*AV39:BE39) | BJ39: =IFERROR(BG39/BH39,0) | BK39: =IFERROR(BG39/BI39,0) | BL39: =IF(B39="Actual",1,INDEX($G$9:$G$11,MATCH(C39,$A$9:$A$11,0))) | BN39: 46054 | BO39: =Inputs!$A$45 | BP39: =AT33
A40: 46266 | B40: =IF(A40<=LastActual,"Actual","Forecast") | C40: =YEAR(A40) | D40: =IFERROR('NSW-1'!X35*1,0) | E40: =IFERROR('VIC-1'!X35*1,0) | F40: =IFERROR('QLD-1'!X35*1,0) | G40: =IFERROR('NSW-2'!X35*1,0) | H40: =IFERROR('VIC-2'!X35*1,0) | I40: =IFERROR('QLD-2'!X35*1,0) | J40: =IFERROR('SA-1'!X35*1,0) | K40: =IFERROR('WA-1'!X35*1,0) | L40: =IFERROR('IDC-NSW'!X35*1,0) | M40: =IFERROR('IDC-VIC'!X35*1,0) | O40: =Cases_Forecast!AJ28 | P40: =Cases_Forecast!AK28 | Q40: =Cases_Forecast!AL28 | R40: =Cases_Forecast!AM28 | S40: =Cases_Forecast!AN28 | T40: =Cases_Forecast!AO28 | U40: =Cases_Forecast!AP28 | V40: =Cases_Forecast!AQ28 | ... X40: =Cases_Forecast!AS28 | Z40: =IFERROR(O40/D40,0) | AA40: =IFERROR(P40/E40,0) | AB40: =IFERROR(Q40/F40,0) | AC40: =IFERROR(R40/G40,0) | AD40: =IFERROR(S40/H40,0) | AE40: =IFERROR(T40/I40,0) | AF40: =IFERROR(U40/J40,0) | AG40: =IFERROR(V40/K40,0) | ... AI40: =IFERROR(X40/M40,0) | AK40: =IF(D$15="Yes",D40*$BL40,D40) | AL40: =IF(E$15="Yes",E40*$BL40,E40) | AM40: =IF(F$15="Yes",F40*$BL40,F40) | AN40: =IF(G$15="Yes",G40*$BL40,G40) | AO40: =IF(H$15="Yes",H40*$BL40,H40) | AP40: =IF(I$15="Yes",I40*$BL40,I40) | AQ40: =IF(J$15="Yes",J40*$BL40,J40) | AR40: =IF(K$15="Yes",K40*$BL40,K40) | ... AT40: =IF(M$15="Yes",M40*$BL40,M40) | AV40: =IFERROR(O40/AK40,0) | AW40: =IFERROR(P40/AL40,0) | AX40: =IFERROR(Q40/AM40,0) | AY40: =IFERROR(R40/AN40,0) | AZ40: =IFERROR(S40/AO40,0) | BA40: =IFERROR(T40/AP40,0) | BB40: =IFERROR(U40/AQ40,0) | BC40: =IFERROR(V40/AR40,0) | ... BE40: =IFERROR(X40/AT40,0) | BG40: =SUMPRODUCT(($D$15:$M$15="Yes")*O40:X40) | BH40: =SUMPRODUCT(($D$15:$M$15="Yes")*Z40:AI40) | BI40: =SUMPRODUCT(($D$15:$M$15="Yes")*AV40:BE40) | BJ40: =IFERROR(BG40/BH40,0) | BK40: =IFERROR(BG40/BI40,0) | BL40: =IF(B40="Actual",1,INDEX($G$9:$G$11,MATCH(C40,$A$9:$A$11,0))) | BN40: 46082 | BO40: =Inputs!$A$36 | BP40: =AK34
A41: 46296 | B41: =IF(A41<=LastActual,"Actual","Forecast") | C41: =YEAR(A41) | D41: =IFERROR('NSW-1'!X36*1,0) | E41: =IFERROR('VIC-1'!X36*1,0) | F41: =IFERROR('QLD-1'!X36*1,0) | G41: =IFERROR('NSW-2'!X36*1,0) | H41: =IFERROR('VIC-2'!X36*1,0) | I41: =IFERROR('QLD-2'!X36*1,0) | J41: =IFERROR('SA-1'!X36*1,0) | K41: =IFERROR('WA-1'!X36*1,0) | L41: =IFERROR('IDC-NSW'!X36*1,0) | M41: =IFERROR('IDC-VIC'!X36*1,0) | O41: =Cases_Forecast!AJ29 | P41: =Cases_Forecast!AK29 | Q41: =Cases_Forecast!AL29 | R41: =Cases_Forecast!AM29 | S41: =Cases_Forecast!AN29 | T41: =Cases_Forecast!AO29 | U41: =Cases_Forecast!AP29 | V41: =Cases_Forecast!AQ29 | ... X41: =Cases_Forecast!AS29 | Z41: =IFERROR(O41/D41,0) | AA41: =IFERROR(P41/E41,0) | AB41: =IFERROR(Q41/F41,0) | AC41: =IFERROR(R41/G41,0) | AD41: =IFERROR(S41/H41,0) | AE41: =IFERROR(T41/I41,0) | AF41: =IFERROR(U41/J41,0) | AG41: =IFERROR(V41/K41,0) | ... AI41: =IFERROR(X41/M41,0) | AK41: =IF(D$15="Yes",D41*$BL41,D41) | AL41: =IF(E$15="Yes",E41*$BL41,E41) | AM41: =IF(F$15="Yes",F41*$BL41,F41) | AN41: =IF(G$15="Yes",G41*$BL41,G41) | AO41: =IF(H$15="Yes",H41*$BL41,H41) | AP41: =IF(I$15="Yes",I41*$BL41,I41) | AQ41: =IF(J$15="Yes",J41*$BL41,J41) | AR41: =IF(K$15="Yes",K41*$BL41,K41) | ... AT41: =IF(M$15="Yes",M41*$BL41,M41) | AV41: =IFERROR(O41/AK41,0) | AW41: =IFERROR(P41/AL41,0) | AX41: =IFERROR(Q41/AM41,0) | AY41: =IFERROR(R41/AN41,0) | AZ41: =IFERROR(S41/AO41,0) | BA41: =IFERROR(T41/AP41,0) | BB41: =IFERROR(U41/AQ41,0) | BC41: =IFERROR(V41/AR41,0) | ... BE41: =IFERROR(X41/AT41,0) | BG41: =SUMPRODUCT(($D$15:$M$15="Yes")*O41:X41) | BH41: =SUMPRODUCT(($D$15:$M$15="Yes")*Z41:AI41) | BI41: =SUMPRODUCT(($D$15:$M$15="Yes")*AV41:BE41) | BJ41: =IFERROR(BG41/BH41,0) | BK41: =IFERROR(BG41/BI41,0) | BL41: =IF(B41="Actual",1,INDEX($G$9:$G$11,MATCH(C41,$A$9:$A$11,0))) | BN41: 46082 | BO41: =Inputs!$A$37 | BP41: =AL34
A42: 46327 | B42: =IF(A42<=LastActual,"Actual","Forecast") | C42: =YEAR(A42) | D42: =IFERROR('NSW-1'!X37*1,0) | E42: =IFERROR('VIC-1'!X37*1,0) | F42: =IFERROR('QLD-1'!X37*1,0) | G42: =IFERROR('NSW-2'!X37*1,0) | H42: =IFERROR('VIC-2'!X37*1,0) | I42: =IFERROR('QLD-2'!X37*1,0) | J42: =IFERROR('SA-1'!X37*1,0) | K42: =IFERROR('WA-1'!X37*1,0) | L42: =IFERROR('IDC-NSW'!X37*1,0) | M42: =IFERROR('IDC-VIC'!X37*1,0) | O42: =Cases_Forecast!AJ30 | P42: =Cases_Forecast!AK30 | Q42: =Cases_Forecast!AL30 | R42: =Cases_Forecast!AM30 | S42: =Cases_Forecast!AN30 | T42: =Cases_Forecast!AO30 | U42: =Cases_Forecast!AP30 | V42: =Cases_Forecast!AQ30 | ... X42: =Cases_Forecast!AS30 | Z42: =IFERROR(O42/D42,0) | AA42: =IFERROR(P42/E42,0) | AB42: =IFERROR(Q42/F42,0) | AC42: =IFERROR(R42/G42,0) | AD42: =IFERROR(S42/H42,0) | AE42: =IFERROR(T42/I42,0) | AF42: =IFERROR(U42/J42,0) | AG42: =IFERROR(V42/K42,0) | ... AI42: =IFERROR(X42/M42,0) | AK42: =IF(D$15="Yes",D42*$BL42,D42) | AL42: =IF(E$15="Yes",E42*$BL42,E42) | AM42: =IF(F$15="Yes",F42*$BL42,F42) | AN42: =IF(G$15="Yes",G42*$BL42,G42) | AO42: =IF(H$15="Yes",H42*$BL42,H42) | AP42: =IF(I$15="Yes",I42*$BL42,I42) | AQ42: =IF(J$15="Yes",J42*$BL42,J42) | AR42: =IF(K$15="Yes",K42*$BL42,K42) | ... AT42: =IF(M$15="Yes",M42*$BL42,M42) | AV42: =IFERROR(O42/AK42,0) | AW42: =IFERROR(P42/AL42,0) | AX42: =IFERROR(Q42/AM42,0) | AY42: =IFERROR(R42/AN42,0) | AZ42: =IFERROR(S42/AO42,0) | BA42: =IFERROR(T42/AP42,0) | BB42: =IFERROR(U42/AQ42,0) | BC42: =IFERROR(V42/AR42,0) | ... BE42: =IFERROR(X42/AT42,0) | BG42: =SUMPRODUCT(($D$15:$M$15="Yes")*O42:X42) | BH42: =SUMPRODUCT(($D$15:$M$15="Yes")*Z42:AI42) | BI42: =SUMPRODUCT(($D$15:$M$15="Yes")*AV42:BE42) | BJ42: =IFERROR(BG42/BH42,0) | BK42: =IFERROR(BG42/BI42,0) | BL42: =IF(B42="Actual",1,INDEX($G$9:$G$11,MATCH(C42,$A$9:$A$11,0))) | BN42: 46082 | BO42: =Inputs!$A$38 | BP42: =AM34
A43: 46357 | B43: =IF(A43<=LastActual,"Actual","Forecast") | C43: =YEAR(A43) | D43: =IFERROR('NSW-1'!X38*1,0) | E43: =IFERROR('VIC-1'!X38*1,0) | F43: =IFERROR('QLD-1'!X38*1,0) | G43: =IFERROR('NSW-2'!X38*1,0) | H43: =IFERROR('VIC-2'!X38*1,0) | I43: =IFERROR('QLD-2'!X38*1,0) | J43: =IFERROR('SA-1'!X38*1,0) | K43: =IFERROR('WA-1'!X38*1,0) | L43: =IFERROR('IDC-NSW'!X38*1,0) | M43: =IFERROR('IDC-VIC'!X38*1,0) | O43: =Cases_Forecast!AJ31 | P43: =Cases_Forecast!AK31 | Q43: =Cases_Forecast!AL31 | R43: =Cases_Forecast!AM31 | S43: =Cases_Forecast!AN31 | T43: =Cases_Forecast!AO31 | U43: =Cases_Forecast!AP31 | V43: =Cases_Forecast!AQ31 | ... X43: =Cases_Forecast!AS31 | Z43: =IFERROR(O43/D43,0) | AA43: =IFERROR(P43/E43,0) | AB43: =IFERROR(Q43/F43,0) | AC43: =IFERROR(R43/G43,0) | AD43: =IFERROR(S43/H43,0) | AE43: =IFERROR(T43/I43,0) | AF43: =IFERROR(U43/J43,0) | AG43: =IFERROR(V43/K43,0) | ... AI43: =IFERROR(X43/M43,0) | AK43: =IF(D$15="Yes",D43*$BL43,D43) | AL43: =IF(E$15="Yes",E43*$BL43,E43) | AM43: =IF(F$15="Yes",F43*$BL43,F43) | AN43: =IF(G$15="Yes",G43*$BL43,G43) | AO43: =IF(H$15="Yes",H43*$BL43,H43) | AP43: =IF(I$15="Yes",I43*$BL43,I43) | AQ43: =IF(J$15="Yes",J43*$BL43,J43) | AR43: =IF(K$15="Yes",K43*$BL43,K43) | ... AT43: =IF(M$15="Yes",M43*$BL43,M43) | AV43: =IFERROR(O43/AK43,0) | AW43: =IFERROR(P43/AL43,0) | AX43: =IFERROR(Q43/AM43,0) | AY43: =IFERROR(R43/AN43,0) | AZ43: =IFERROR(S43/AO43,0) | BA43: =IFERROR(T43/AP43,0) | BB43: =IFERROR(U43/AQ43,0) | BC43: =IFERROR(V43/AR43,0) | ... BE43: =IFERROR(X43/AT43,0) | BG43: =SUMPRODUCT(($D$15:$M$15="Yes")*O43:X43) | BH43: =SUMPRODUCT(($D$15:$M$15="Yes")*Z43:AI43) | BI43: =SUMPRODUCT(($D$15:$M$15="Yes")*AV43:BE43) | BJ43: =IFERROR(BG43/BH43,0) | BK43: =IFERROR(BG43/BI43,0) | BL43: =IF(B43="Actual",1,INDEX($G$9:$G$11,MATCH(C43,$A$9:$A$11,0))) | BN43: 46082 | BO43: =Inputs!$A$39 | BP43: =AN34
A44: 46388 | B44: =IF(A44<=LastActual,"Actual","Forecast") | C44: =YEAR(A44) | D44: =IFERROR('NSW-1'!X39*1,0) | E44: =IFERROR('VIC-1'!X39*1,0) | F44: =IFERROR('QLD-1'!X39*1,0) | G44: =IFERROR('NSW-2'!X39*1,0) | H44: =IFERROR('VIC-2'!X39*1,0) | I44: =IFERROR('QLD-2'!X39*1,0) | J44: =IFERROR('SA-1'!X39*1,0) | K44: =IFERROR('WA-1'!X39*1,0) | L44: =IFERROR('IDC-NSW'!X39*1,0) | M44: =IFERROR('IDC-VIC'!X39*1,0) | O44: =Cases_Forecast!AJ32 | P44: =Cases_Forecast!AK32 | Q44: =Cases_Forecast!AL32 | R44: =Cases_Forecast!AM32 | S44: =Cases_Forecast!AN32 | T44: =Cases_Forecast!AO32 | U44: =Cases_Forecast!AP32 | V44: =Cases_Forecast!AQ32 | ... X44: =Cases_Forecast!AS32 | Z44: =IFERROR(O44/D44,0) | AA44: =IFERROR(P44/E44,0) | AB44: =IFERROR(Q44/F44,0) | AC44: =IFERROR(R44/G44,0) | AD44: =IFERROR(S44/H44,0) | AE44: =IFERROR(T44/I44,0) | AF44: =IFERROR(U44/J44,0) | AG44: =IFERROR(V44/K44,0) | ... AI44: =IFERROR(X44/M44,0) | AK44: =IF(D$15="Yes",D44*$BL44,D44) | AL44: =IF(E$15="Yes",E44*$BL44,E44) | AM44: =IF(F$15="Yes",F44*$BL44,F44) | AN44: =IF(G$15="Yes",G44*$BL44,G44) | AO44: =IF(H$15="Yes",H44*$BL44,H44) | AP44: =IF(I$15="Yes",I44*$BL44,I44) | AQ44: =IF(J$15="Yes",J44*$BL44,J44) | AR44: =IF(K$15="Yes",K44*$BL44,K44) | ... AT44: =IF(M$15="Yes",M44*$BL44,M44) | AV44: =IFERROR(O44/AK44,0) | AW44: =IFERROR(P44/AL44,0) | AX44: =IFERROR(Q44/AM44,0) | AY44: =IFERROR(R44/AN44,0) | AZ44: =IFERROR(S44/AO44,0) | BA44: =IFERROR(T44/AP44,0) | BB44: =IFERROR(U44/AQ44,0) | BC44: =IFERROR(V44/AR44,0) | ... BE44: =IFERROR(X44/AT44,0) | BG44: =SUMPRODUCT(($D$15:$M$15="Yes")*O44:X44) | BH44: =SUMPRODUCT(($D$15:$M$15="Yes")*Z44:AI44) | BI44: =SUMPRODUCT(($D$15:$M$15="Yes")*AV44:BE44) | BJ44: =IFERROR(BG44/BH44,0) | BK44: =IFERROR(BG44/BI44,0) | BL44: =IF(B44="Actual",1,INDEX($G$9:$G$11,MATCH(C44,$A$9:$A$11,0))) | BN44: 46082 | BO44: =Inputs!$A$40 | BP44: =AO34
A45: 46419 | B45: =IF(A45<=LastActual,"Actual","Forecast") | C45: =YEAR(A45) | D45: =IFERROR('NSW-1'!X40*1,0) | E45: =IFERROR('VIC-1'!X40*1,0) | F45: =IFERROR('QLD-1'!X40*1,0) | G45: =IFERROR('NSW-2'!X40*1,0) | H45: =IFERROR('VIC-2'!X40*1,0) | I45: =IFERROR('QLD-2'!X40*1,0) | J45: =IFERROR('SA-1'!X40*1,0) | K45: =IFERROR('WA-1'!X40*1,0) | L45: =IFERROR('IDC-NSW'!X40*1,0) | M45: =IFERROR('IDC-VIC'!X40*1,0) | O45: =Cases_Forecast!AJ33 | P45: =Cases_Forecast!AK33 | Q45: =Cases_Forecast!AL33 | R45: =Cases_Forecast!AM33 | S45: =Cases_Forecast!AN33 | T45: =Cases_Forecast!AO33 | U45: =Cases_Forecast!AP33 | V45: =Cases_Forecast!AQ33 | ... X45: =Cases_Forecast!AS33 | Z45: =IFERROR(O45/D45,0) | AA45: =IFERROR(P45/E45,0) | AB45: =IFERROR(Q45/F45,0) | AC45: =IFERROR(R45/G45,0) | AD45: =IFERROR(S45/H45,0) | AE45: =IFERROR(T45/I45,0) | AF45: =IFERROR(U45/J45,0) | AG45: =IFERROR(V45/K45,0) | ... AI45: =IFERROR(X45/M45,0) | AK45: =IF(D$15="Yes",D45*$BL45,D45) | AL45: =IF(E$15="Yes",E45*$BL45,E45) | AM45: =IF(F$15="Yes",F45*$BL45,F45) | AN45: =IF(G$15="Yes",G45*$BL45,G45) | AO45: =IF(H$15="Yes",H45*$BL45,H45) | AP45: =IF(I$15="Yes",I45*$BL45,I45) | AQ45: =IF(J$15="Yes",J45*$BL45,J45) | AR45: =IF(K$15="Yes",K45*$BL45,K45) | ... AT45: =IF(M$15="Yes",M45*$BL45,M45) | AV45: =IFERROR(O45/AK45,0) | AW45: =IFERROR(P45/AL45,0) | AX45: =IFERROR(Q45/AM45,0) | AY45: =IFERROR(R45/AN45,0) | AZ45: =IFERROR(S45/AO45,0) | BA45: =IFERROR(T45/AP45,0) | BB45: =IFERROR(U45/AQ45,0) | BC45: =IFERROR(V45/AR45,0) | ... BE45: =IFERROR(X45/AT45,0) | BG45: =SUMPRODUCT(($D$15:$M$15="Yes")*O45:X45) | BH45: =SUMPRODUCT(($D$15:$M$15="Yes")*Z45:AI45) | BI45: =SUMPRODUCT(($D$15:$M$15="Yes")*AV45:BE45) | BJ45: =IFERROR(BG45/BH45,0) | BK45: =IFERROR(BG45/BI45,0) | BL45: =IF(B45="Actual",1,INDEX($G$9:$G$11,MATCH(C45,$A$9:$A$11,0))) | BN45: 46082 | BO45: =Inputs!$A$41 | BP45: =AP34
A46: 46447 | B46: =IF(A46<=LastActual,"Actual","Forecast") | C46: =YEAR(A46) | D46: =IFERROR('NSW-1'!X41*1,0) | E46: =IFERROR('VIC-1'!X41*1,0) | F46: =IFERROR('QLD-1'!X41*1,0) | G46: =IFERROR('NSW-2'!X41*1,0) | H46: =IFERROR('VIC-2'!X41*1,0) | I46: =IFERROR('QLD-2'!X41*1,0) | J46: =IFERROR('SA-1'!X41*1,0) | K46: =IFERROR('WA-1'!X41*1,0) | L46: =IFERROR('IDC-NSW'!X41*1,0) | M46: =IFERROR('IDC-VIC'!X41*1,0) | O46: =Cases_Forecast!AJ34 | P46: =Cases_Forecast!AK34 | Q46: =Cases_Forecast!AL34 | R46: =Cases_Forecast!AM34 | S46: =Cases_Forecast!AN34 | T46: =Cases_Forecast!AO34 | U46: =Cases_Forecast!AP34 | V46: =Cases_Forecast!AQ34 | ... X46: =Cases_Forecast!AS34 | Z46: =IFERROR(O46/D46,0) | AA46: =IFERROR(P46/E46,0) | AB46: =IFERROR(Q46/F46,0) | AC46: =IFERROR(R46/G46,0) | AD46: =IFERROR(S46/H46,0) | AE46: =IFERROR(T46/I46,0) | AF46: =IFERROR(U46/J46,0) | AG46: =IFERROR(V46/K46,0) | ... AI46: =IFERROR(X46/M46,0) | AK46: =IF(D$15="Yes",D46*$BL46,D46) | AL46: =IF(E$15="Yes",E46*$BL46,E46) | AM46: =IF(F$15="Yes",F46*$BL46,F46) | AN46: =IF(G$15="Yes",G46*$BL46,G46) | AO46: =IF(H$15="Yes",H46*$BL46,H46) | AP46: =IF(I$15="Yes",I46*$BL46,I46) | AQ46: =IF(J$15="Yes",J46*$BL46,J46) | AR46: =IF(K$15="Yes",K46*$BL46,K46) | ... AT46: =IF(M$15="Yes",M46*$BL46,M46) | AV46: =IFERROR(O46/AK46,0) | AW46: =IFERROR(P46/AL46,0) | AX46: =IFERROR(Q46/AM46,0) | AY46: =IFERROR(R46/AN46,0) | AZ46: =IFERROR(S46/AO46,0) | BA46: =IFERROR(T46/AP46,0) | BB46: =IFERROR(U46/AQ46,0) | BC46: =IFERROR(V46/AR46,0) | ... BE46: =IFERROR(X46/AT46,0) | BG46: =SUMPRODUCT(($D$15:$M$15="Yes")*O46:X46) | BH46: =SUMPRODUCT(($D$15:$M$15="Yes")*Z46:AI46) | BI46: =SUMPRODUCT(($D$15:$M$15="Yes")*AV46:BE46) | BJ46: =IFERROR(BG46/BH46,0) | BK46: =IFERROR(BG46/BI46,0) | BL46: =IF(B46="Actual",1,INDEX($G$9:$G$11,MATCH(C46,$A$9:$A$11,0))) | BN46: 46082 | BO46: =Inputs!$A$42 | BP46: =AQ34
A47: 46478 | B47: =IF(A47<=LastActual,"Actual","Forecast") | C47: =YEAR(A47) | D47: =IFERROR('NSW-1'!X42*1,0) | E47: =IFERROR('VIC-1'!X42*1,0) | F47: =IFERROR('QLD-1'!X42*1,0) | G47: =IFERROR('NSW-2'!X42*1,0) | H47: =IFERROR('VIC-2'!X42*1,0) | I47: =IFERROR('QLD-2'!X42*1,0) | J47: =IFERROR('SA-1'!X42*1,0) | K47: =IFERROR('WA-1'!X42*1,0) | L47: =IFERROR('IDC-NSW'!X42*1,0) | M47: =IFERROR('IDC-VIC'!X42*1,0) | O47: =Cases_Forecast!AJ35 | P47: =Cases_Forecast!AK35 | Q47: =Cases_Forecast!AL35 | R47: =Cases_Forecast!AM35 | S47: =Cases_Forecast!AN35 | T47: =Cases_Forecast!AO35 | U47: =Cases_Forecast!AP35 | V47: =Cases_Forecast!AQ35 | ... X47: =Cases_Forecast!AS35 | Z47: =IFERROR(O47/D47,0) | AA47: =IFERROR(P47/E47,0) | AB47: =IFERROR(Q47/F47,0) | AC47: =IFERROR(R47/G47,0) | AD47: =IFERROR(S47/H47,0) | AE47: =IFERROR(T47/I47,0) | AF47: =IFERROR(U47/J47,0) | AG47: =IFERROR(V47/K47,0) | ... AI47: =IFERROR(X47/M47,0) | AK47: =IF(D$15="Yes",D47*$BL47,D47) | AL47: =IF(E$15="Yes",E47*$BL47,E47) | AM47: =IF(F$15="Yes",F47*$BL47,F47) | AN47: =IF(G$15="Yes",G47*$BL47,G47) | AO47: =IF(H$15="Yes",H47*$BL47,H47) | AP47: =IF(I$15="Yes",I47*$BL47,I47) | AQ47: =IF(J$15="Yes",J47*$BL47,J47) | AR47: =IF(K$15="Yes",K47*$BL47,K47) | ... AT47: =IF(M$15="Yes",M47*$BL47,M47) | AV47: =IFERROR(O47/AK47,0) | AW47: =IFERROR(P47/AL47,0) | AX47: =IFERROR(Q47/AM47,0) | AY47: =IFERROR(R47/AN47,0) | AZ47: =IFERROR(S47/AO47,0) | BA47: =IFERROR(T47/AP47,0) | BB47: =IFERROR(U47/AQ47,0) | BC47: =IFERROR(V47/AR47,0) | ... BE47: =IFERROR(X47/AT47,0) | BG47: =SUMPRODUCT(($D$15:$M$15="Yes")*O47:X47) | BH47: =SUMPRODUCT(($D$15:$M$15="Yes")*Z47:AI47) | BI47: =SUMPRODUCT(($D$15:$M$15="Yes")*AV47:BE47) | BJ47: =IFERROR(BG47/BH47,0) | BK47: =IFERROR(BG47/BI47,0) | BL47: =IF(B47="Actual",1,INDEX($G$9:$G$11,MATCH(C47,$A$9:$A$11,0))) | BN47: 46082 | BO47: =Inputs!$A$43 | BP47: =AR34
A48: 46508 | B48: =IF(A48<=LastActual,"Actual","Forecast") | C48: =YEAR(A48) | D48: =IFERROR('NSW-1'!X43*1,0) | E48: =IFERROR('VIC-1'!X43*1,0) | F48: =IFERROR('QLD-1'!X43*1,0) | G48: =IFERROR('NSW-2'!X43*1,0) | H48: =IFERROR('VIC-2'!X43*1,0) | I48: =IFERROR('QLD-2'!X43*1,0) | J48: =IFERROR('SA-1'!X43*1,0) | K48: =IFERROR('WA-1'!X43*1,0) | L48: =IFERROR('IDC-NSW'!X43*1,0) | M48: =IFERROR('IDC-VIC'!X43*1,0) | O48: =Cases_Forecast!AJ36 | P48: =Cases_Forecast!AK36 | Q48: =Cases_Forecast!AL36 | R48: =Cases_Forecast!AM36 | S48: =Cases_Forecast!AN36 | T48: =Cases_Forecast!AO36 | U48: =Cases_Forecast!AP36 | V48: =Cases_Forecast!AQ36 | ... X48: =Cases_Forecast!AS36 | Z48: =IFERROR(O48/D48,0) | AA48: =IFERROR(P48/E48,0) | AB48: =IFERROR(Q48/F48,0) | AC48: =IFERROR(R48/G48,0) | AD48: =IFERROR(S48/H48,0) | AE48: =IFERROR(T48/I48,0) | AF48: =IFERROR(U48/J48,0) | AG48: =IFERROR(V48/K48,0) | ... AI48: =IFERROR(X48/M48,0) | AK48: =IF(D$15="Yes",D48*$BL48,D48) | AL48: =IF(E$15="Yes",E48*$BL48,E48) | AM48: =IF(F$15="Yes",F48*$BL48,F48) | AN48: =IF(G$15="Yes",G48*$BL48,G48) | AO48: =IF(H$15="Yes",H48*$BL48,H48) | AP48: =IF(I$15="Yes",I48*$BL48,I48) | AQ48: =IF(J$15="Yes",J48*$BL48,J48) | AR48: =IF(K$15="Yes",K48*$BL48,K48) | ... AT48: =IF(M$15="Yes",M48*$BL48,M48) | AV48: =IFERROR(O48/AK48,0) | AW48: =IFERROR(P48/AL48,0) | AX48: =IFERROR(Q48/AM48,0) | AY48: =IFERROR(R48/AN48,0) | AZ48: =IFERROR(S48/AO48,0) | BA48: =IFERROR(T48/AP48,0) | BB48: =IFERROR(U48/AQ48,0) | BC48: =IFERROR(V48/AR48,0) | ... BE48: =IFERROR(X48/AT48,0) | BG48: =SUMPRODUCT(($D$15:$M$15="Yes")*O48:X48) | BH48: =SUMPRODUCT(($D$15:$M$15="Yes")*Z48:AI48) | BI48: =SUMPRODUCT(($D$15:$M$15="Yes")*AV48:BE48) | BJ48: =IFERROR(BG48/BH48,0) | BK48: =IFERROR(BG48/BI48,0) | BL48: =IF(B48="Actual",1,INDEX($G$9:$G$11,MATCH(C48,$A$9:$A$11,0))) | BN48: 46082 | BO48: =Inputs!$A$44 | BP48: =AS34
A49: 46539 | B49: =IF(A49<=LastActual,"Actual","Forecast") | C49: =YEAR(A49) | D49: =IFERROR('NSW-1'!X44*1,0) | E49: =IFERROR('VIC-1'!X44*1,0) | F49: =IFERROR('QLD-1'!X44*1,0) | G49: =IFERROR('NSW-2'!X44*1,0) | H49: =IFERROR('VIC-2'!X44*1,0) | I49: =IFERROR('QLD-2'!X44*1,0) | J49: =IFERROR('SA-1'!X44*1,0) | K49: =IFERROR('WA-1'!X44*1,0) | L49: =IFERROR('IDC-NSW'!X44*1,0) | M49: =IFERROR('IDC-VIC'!X44*1,0) | O49: =Cases_Forecast!AJ37 | P49: =Cases_Forecast!AK37 | Q49: =Cases_Forecast!AL37 | R49: =Cases_Forecast!AM37 | S49: =Cases_Forecast!AN37 | T49: =Cases_Forecast!AO37 | U49: =Cases_Forecast!AP37 | V49: =Cases_Forecast!AQ37 | ... X49: =Cases_Forecast!AS37 | Z49: =IFERROR(O49/D49,0) | AA49: =IFERROR(P49/E49,0) | AB49: =IFERROR(Q49/F49,0) | AC49: =IFERROR(R49/G49,0) | AD49: =IFERROR(S49/H49,0) | AE49: =IFERROR(T49/I49,0) | AF49: =IFERROR(U49/J49,0) | AG49: =IFERROR(V49/K49,0) | ... AI49: =IFERROR(X49/M49,0) | AK49: =IF(D$15="Yes",D49*$BL49,D49) | AL49: =IF(E$15="Yes",E49*$BL49,E49) | AM49: =IF(F$15="Yes",F49*$BL49,F49) | AN49: =IF(G$15="Yes",G49*$BL49,G49) | AO49: =IF(H$15="Yes",H49*$BL49,H49) | AP49: =IF(I$15="Yes",I49*$BL49,I49) | AQ49: =IF(J$15="Yes",J49*$BL49,J49) | AR49: =IF(K$15="Yes",K49*$BL49,K49) | ... AT49: =IF(M$15="Yes",M49*$BL49,M49) | AV49: =IFERROR(O49/AK49,0) | AW49: =IFERROR(P49/AL49,0) | AX49: =IFERROR(Q49/AM49,0) | AY49: =IFERROR(R49/AN49,0) | AZ49: =IFERROR(S49/AO49,0) | BA49: =IFERROR(T49/AP49,0) | BB49: =IFERROR(U49/AQ49,0) | BC49: =IFERROR(V49/AR49,0) | ... BE49: =IFERROR(X49/AT49,0) | BG49: =SUMPRODUCT(($D$15:$M$15="Yes")*O49:X49) | BH49: =SUMPRODUCT(($D$15:$M$15="Yes")*Z49:AI49) | BI49: =SUMPRODUCT(($D$15:$M$15="Yes")*AV49:BE49) | BJ49: =IFERROR(BG49/BH49,0) | BK49: =IFERROR(BG49/BI49,0) | BL49: =IF(B49="Actual",1,INDEX($G$9:$G$11,MATCH(C49,$A$9:$A$11,0))) | BN49: 46082 | BO49: =Inputs!$A$45 | BP49: =AT34
A50: 46569 | B50: =IF(A50<=LastActual,"Actual","Forecast") | C50: =YEAR(A50) | D50: =IFERROR('NSW-1'!X45*1,0) | E50: =IFERROR('VIC-1'!X45*1,0) | F50: =IFERROR('QLD-1'!X45*1,0) | G50: =IFERROR('NSW-2'!X45*1,0) | H50: =IFERROR('VIC-2'!X45*1,0) | I50: =IFERROR('QLD-2'!X45*1,0) | J50: =IFERROR('SA-1'!X45*1,0) | K50: =IFERROR('WA-1'!X45*1,0) | L50: =IFERROR('IDC-NSW'!X45*1,0) | M50: =IFERROR('IDC-VIC'!X45*1,0) | O50: =Cases_Forecast!AJ38 | P50: =Cases_Forecast!AK38 | Q50: =Cases_Forecast!AL38 | R50: =Cases_Forecast!AM38 | S50: =Cases_Forecast!AN38 | T50: =Cases_Forecast!AO38 | U50: =Cases_Forecast!AP38 | V50: =Cases_Forecast!AQ38 | ... X50: =Cases_Forecast!AS38 | Z50: =IFERROR(O50/D50,0) | AA50: =IFERROR(P50/E50,0) | AB50: =IFERROR(Q50/F50,0) | AC50: =IFERROR(R50/G50,0) | AD50: =IFERROR(S50/H50,0) | AE50: =IFERROR(T50/I50,0) | AF50: =IFERROR(U50/J50,0) | AG50: =IFERROR(V50/K50,0) | ... AI50: =IFERROR(X50/M50,0) | AK50: =IF(D$15="Yes",D50*$BL50,D50) | AL50: =IF(E$15="Yes",E50*$BL50,E50) | AM50: =IF(F$15="Yes",F50*$BL50,F50) | AN50: =IF(G$15="Yes",G50*$BL50,G50) | AO50: =IF(H$15="Yes",H50*$BL50,H50) | AP50: =IF(I$15="Yes",I50*$BL50,I50) | AQ50: =IF(J$15="Yes",J50*$BL50,J50) | AR50: =IF(K$15="Yes",K50*$BL50,K50) | ... AT50: =IF(M$15="Yes",M50*$BL50,M50) | AV50: =IFERROR(O50/AK50,0) | AW50: =IFERROR(P50/AL50,0) | AX50: =IFERROR(Q50/AM50,0) | AY50: =IFERROR(R50/AN50,0) | AZ50: =IFERROR(S50/AO50,0) | BA50: =IFERROR(T50/AP50,0) | BB50: =IFERROR(U50/AQ50,0) | BC50: =IFERROR(V50/AR50,0) | ... BE50: =IFERROR(X50/AT50,0) | BG50: =SUMPRODUCT(($D$15:$M$15="Yes")*O50:X50) | BH50: =SUMPRODUCT(($D$15:$M$15="Yes")*Z50:AI50) | BI50: =SUMPRODUCT(($D$15:$M$15="Yes")*AV50:BE50) | BJ50: =IFERROR(BG50/BH50,0) | BK50: =IFERROR(BG50/BI50,0) | BL50: =IF(B50="Actual",1,INDEX($G$9:$G$11,MATCH(C50,$A$9:$A$11,0))) | BN50: 46113 | BO50: =Inputs!$A$36 | BP50: =AK35
A51: 46600 | B51: =IF(A51<=LastActual,"Actual","Forecast") | C51: =YEAR(A51) | D51: =IFERROR('NSW-1'!X46*1,0) | E51: =IFERROR('VIC-1'!X46*1,0) | F51: =IFERROR('QLD-1'!X46*1,0) | G51: =IFERROR('NSW-2'!X46*1,0) | H51: =IFERROR('VIC-2'!X46*1,0) | I51: =IFERROR('QLD-2'!X46*1,0) | J51: =IFERROR('SA-1'!X46*1,0) | K51: =IFERROR('WA-1'!X46*1,0) | L51: =IFERROR('IDC-NSW'!X46*1,0) | M51: =IFERROR('IDC-VIC'!X46*1,0) | O51: =Cases_Forecast!AJ39 | P51: =Cases_Forecast!AK39 | Q51: =Cases_Forecast!AL39 | R51: =Cases_Forecast!AM39 | S51: =Cases_Forecast!AN39 | T51: =Cases_Forecast!AO39 | U51: =Cases_Forecast!AP39 | V51: =Cases_Forecast!AQ39 | ... X51: =Cases_Forecast!AS39 | Z51: =IFERROR(O51/D51,0) | AA51: =IFERROR(P51/E51,0) | AB51: =IFERROR(Q51/F51,0) | AC51: =IFERROR(R51/G51,0) | AD51: =IFERROR(S51/H51,0) | AE51: =IFERROR(T51/I51,0) | AF51: =IFERROR(U51/J51,0) | AG51: =IFERROR(V51/K51,0) | ... AI51: =IFERROR(X51/M51,0) | AK51: =IF(D$15="Yes",D51*$BL51,D51) | AL51: =IF(E$15="Yes",E51*$BL51,E51) | AM51: =IF(F$15="Yes",F51*$BL51,F51) | AN51: =IF(G$15="Yes",G51*$BL51,G51) | AO51: =IF(H$15="Yes",H51*$BL51,H51) | AP51: =IF(I$15="Yes",I51*$BL51,I51) | AQ51: =IF(J$15="Yes",J51*$BL51,J51) | AR51: =IF(K$15="Yes",K51*$BL51,K51) | ... AT51: =IF(M$15="Yes",M51*$BL51,M51) | AV51: =IFERROR(O51/AK51,0) | AW51: =IFERROR(P51/AL51,0) | AX51: =IFERROR(Q51/AM51,0) | AY51: =IFERROR(R51/AN51,0) | AZ51: =IFERROR(S51/AO51,0) | BA51: =IFERROR(T51/AP51,0) | BB51: =IFERROR(U51/AQ51,0) | BC51: =IFERROR(V51/AR51,0) | ... BE51: =IFERROR(X51/AT51,0) | BG51: =SUMPRODUCT(($D$15:$M$15="Yes")*O51:X51) | BH51: =SUMPRODUCT(($D$15:$M$15="Yes")*Z51:AI51) | BI51: =SUMPRODUCT(($D$15:$M$15="Yes")*AV51:BE51) | BJ51: =IFERROR(BG51/BH51,0) | BK51: =IFERROR(BG51/BI51,0) | BL51: =IF(B51="Actual",1,INDEX($G$9:$G$11,MATCH(C51,$A$9:$A$11,0))) | BN51: 46113 | BO51: =Inputs!$A$37 | BP51: =AL35
A52: 46631 | B52: =IF(A52<=LastActual,"Actual","Forecast") | C52: =YEAR(A52) | D52: =IFERROR('NSW-1'!X47*1,0) | E52: =IFERROR('VIC-1'!X47*1,0) | F52: =IFERROR('QLD-1'!X47*1,0) | G52: =IFERROR('NSW-2'!X47*1,0) | H52: =IFERROR('VIC-2'!X47*1,0) | I52: =IFERROR('QLD-2'!X47*1,0) | J52: =IFERROR('SA-1'!X47*1,0) | K52: =IFERROR('WA-1'!X47*1,0) | L52: =IFERROR('IDC-NSW'!X47*1,0) | M52: =IFERROR('IDC-VIC'!X47*1,0) | O52: =Cases_Forecast!AJ40 | P52: =Cases_Forecast!AK40 | Q52: =Cases_Forecast!AL40 | R52: =Cases_Forecast!AM40 | S52: =Cases_Forecast!AN40 | T52: =Cases_Forecast!AO40 | U52: =Cases_Forecast!AP40 | V52: =Cases_Forecast!AQ40 | ... X52: =Cases_Forecast!AS40 | Z52: =IFERROR(O52/D52,0) | AA52: =IFERROR(P52/E52,0) | AB52: =IFERROR(Q52/F52,0) | AC52: =IFERROR(R52/G52,0) | AD52: =IFERROR(S52/H52,0) | AE52: =IFERROR(T52/I52,0) | AF52: =IFERROR(U52/J52,0) | AG52: =IFERROR(V52/K52,0) | ... AI52: =IFERROR(X52/M52,0) | AK52: =IF(D$15="Yes",D52*$BL52,D52) | AL52: =IF(E$15="Yes",E52*$BL52,E52) | AM52: =IF(F$15="Yes",F52*$BL52,F52) | AN52: =IF(G$15="Yes",G52*$BL52,G52) | AO52: =IF(H$15="Yes",H52*$BL52,H52) | AP52: =IF(I$15="Yes",I52*$BL52,I52) | AQ52: =IF(J$15="Yes",J52*$BL52,J52) | AR52: =IF(K$15="Yes",K52*$BL52,K52) | ... AT52: =IF(M$15="Yes",M52*$BL52,M52) | AV52: =IFERROR(O52/AK52,0) | AW52: =IFERROR(P52/AL52,0) | AX52: =IFERROR(Q52/AM52,0) | AY52: =IFERROR(R52/AN52,0) | AZ52: =IFERROR(S52/AO52,0) | BA52: =IFERROR(T52/AP52,0) | BB52: =IFERROR(U52/AQ52,0) | BC52: =IFERROR(V52/AR52,0) | ... BE52: =IFERROR(X52/AT52,0) | BG52: =SUMPRODUCT(($D$15:$M$15="Yes")*O52:X52) | BH52: =SUMPRODUCT(($D$15:$M$15="Yes")*Z52:AI52) | BI52: =SUMPRODUCT(($D$15:$M$15="Yes")*AV52:BE52) | BJ52: =IFERROR(BG52/BH52,0) | BK52: =IFERROR(BG52/BI52,0) | BL52: =IF(B52="Actual",1,INDEX($G$9:$G$11,MATCH(C52,$A$9:$A$11,0))) | BN52: 46113 | BO52: =Inputs!$A$38 | BP52: =AM35
A53: 46661 | B53: =IF(A53<=LastActual,"Actual","Forecast") | C53: =YEAR(A53) | D53: =IFERROR('NSW-1'!X48*1,0) | E53: =IFERROR('VIC-1'!X48*1,0) | F53: =IFERROR('QLD-1'!X48*1,0) | G53: =IFERROR('NSW-2'!X48*1,0) | H53: =IFERROR('VIC-2'!X48*1,0) | I53: =IFERROR('QLD-2'!X48*1,0) | J53: =IFERROR('SA-1'!X48*1,0) | K53: =IFERROR('WA-1'!X48*1,0) | L53: =IFERROR('IDC-NSW'!X48*1,0) | M53: =IFERROR('IDC-VIC'!X48*1,0) | O53: =Cases_Forecast!AJ41 | P53: =Cases_Forecast!AK41 | Q53: =Cases_Forecast!AL41 | R53: =Cases_Forecast!AM41 | S53: =Cases_Forecast!AN41 | T53: =Cases_Forecast!AO41 | U53: =Cases_Forecast!AP41 | V53: =Cases_Forecast!AQ41 | ... X53: =Cases_Forecast!AS41 | Z53: =IFERROR(O53/D53,0) | AA53: =IFERROR(P53/E53,0) | AB53: =IFERROR(Q53/F53,0) | AC53: =IFERROR(R53/G53,0) | AD53: =IFERROR(S53/H53,0) | AE53: =IFERROR(T53/I53,0) | AF53: =IFERROR(U53/J53,0) | AG53: =IFERROR(V53/K53,0) | ... AI53: =IFERROR(X53/M53,0) | AK53: =IF(D$15="Yes",D53*$BL53,D53) | AL53: =IF(E$15="Yes",E53*$BL53,E53) | AM53: =IF(F$15="Yes",F53*$BL53,F53) | AN53: =IF(G$15="Yes",G53*$BL53,G53) | AO53: =IF(H$15="Yes",H53*$BL53,H53) | AP53: =IF(I$15="Yes",I53*$BL53,I53) | AQ53: =IF(J$15="Yes",J53*$BL53,J53) | AR53: =IF(K$15="Yes",K53*$BL53,K53) | ... AT53: =IF(M$15="Yes",M53*$BL53,M53) | AV53: =IFERROR(O53/AK53,0) | AW53: =IFERROR(P53/AL53,0) | AX53: =IFERROR(Q53/AM53,0) | AY53: =IFERROR(R53/AN53,0) | AZ53: =IFERROR(S53/AO53,0) | BA53: =IFERROR(T53/AP53,0) | BB53: =IFERROR(U53/AQ53,0) | BC53: =IFERROR(V53/AR53,0) | ... BE53: =IFERROR(X53/AT53,0) | BG53: =SUMPRODUCT(($D$15:$M$15="Yes")*O53:X53) | BH53: =SUMPRODUCT(($D$15:$M$15="Yes")*Z53:AI53) | BI53: =SUMPRODUCT(($D$15:$M$15="Yes")*AV53:BE53) | BJ53: =IFERROR(BG53/BH53,0) | BK53: =IFERROR(BG53/BI53,0) | BL53: =IF(B53="Actual",1,INDEX($G$9:$G$11,MATCH(C53,$A$9:$A$11,0))) | BN53: 46113 | BO53: =Inputs!$A$39 | BP53: =AN35
A54: 46692 | B54: =IF(A54<=LastActual,"Actual","Forecast") | C54: =YEAR(A54) | D54: =IFERROR('NSW-1'!X49*1,0) | E54: =IFERROR('VIC-1'!X49*1,0) | F54: =IFERROR('QLD-1'!X49*1,0) | G54: =IFERROR('NSW-2'!X49*1,0) | H54: =IFERROR('VIC-2'!X49*1,0) | I54: =IFERROR('QLD-2'!X49*1,0) | J54: =IFERROR('SA-1'!X49*1,0) | K54: =IFERROR('WA-1'!X49*1,0) | L54: =IFERROR('IDC-NSW'!X49*1,0) | M54: =IFERROR('IDC-VIC'!X49*1,0) | O54: =Cases_Forecast!AJ42 | P54: =Cases_Forecast!AK42 | Q54: =Cases_Forecast!AL42 | R54: =Cases_Forecast!AM42 | S54: =Cases_Forecast!AN42 | T54: =Cases_Forecast!AO42 | U54: =Cases_Forecast!AP42 | V54: =Cases_Forecast!AQ42 | ... X54: =Cases_Forecast!AS42 | Z54: =IFERROR(O54/D54,0) | AA54: =IFERROR(P54/E54,0) | AB54: =IFERROR(Q54/F54,0) | AC54: =IFERROR(R54/G54,0) | AD54: =IFERROR(S54/H54,0) | AE54: =IFERROR(T54/I54,0) | AF54: =IFERROR(U54/J54,0) | AG54: =IFERROR(V54/K54,0) | ... AI54: =IFERROR(X54/M54,0) | AK54: =IF(D$15="Yes",D54*$BL54,D54) | AL54: =IF(E$15="Yes",E54*$BL54,E54) | AM54: =IF(F$15="Yes",F54*$BL54,F54) | AN54: =IF(G$15="Yes",G54*$BL54,G54) | AO54: =IF(H$15="Yes",H54*$BL54,H54) | AP54: =IF(I$15="Yes",I54*$BL54,I54) | AQ54: =IF(J$15="Yes",J54*$BL54,J54) | AR54: =IF(K$15="Yes",K54*$BL54,K54) | ... AT54: =IF(M$15="Yes",M54*$BL54,M54) | AV54: =IFERROR(O54/AK54,0) | AW54: =IFERROR(P54/AL54,0) | AX54: =IFERROR(Q54/AM54,0) | AY54: =IFERROR(R54/AN54,0) | AZ54: =IFERROR(S54/AO54,0) | BA54: =IFERROR(T54/AP54,0) | BB54: =IFERROR(U54/AQ54,0) | BC54: =IFERROR(V54/AR54,0) | ... BE54: =IFERROR(X54/AT54,0) | BG54: =SUMPRODUCT(($D$15:$M$15="Yes")*O54:X54) | BH54: =SUMPRODUCT(($D$15:$M$15="Yes")*Z54:AI54) | BI54: =SUMPRODUCT(($D$15:$M$15="Yes")*AV54:BE54) | BJ54: =IFERROR(BG54/BH54,0) | BK54: =IFERROR(BG54/BI54,0) | BL54: =IF(B54="Actual",1,INDEX($G$9:$G$11,MATCH(C54,$A$9:$A$11,0))) | BN54: 46113 | BO54: =Inputs!$A$40 | BP54: =AO35
A55: 46722 | B55: =IF(A55<=LastActual,"Actual","Forecast") | C55: =YEAR(A55) | D55: =IFERROR('NSW-1'!X50*1,0) | E55: =IFERROR('VIC-1'!X50*1,0) | F55: =IFERROR('QLD-1'!X50*1,0) | G55: =IFERROR('NSW-2'!X50*1,0) | H55: =IFERROR('VIC-2'!X50*1,0) | I55: =IFERROR('QLD-2'!X50*1,0) | J55: =IFERROR('SA-1'!X50*1,0) | K55: =IFERROR('WA-1'!X50*1,0) | L55: =IFERROR('IDC-NSW'!X50*1,0) | M55: =IFERROR('IDC-VIC'!X50*1,0) | O55: =Cases_Forecast!AJ43 | P55: =Cases_Forecast!AK43 | Q55: =Cases_Forecast!AL43 | R55: =Cases_Forecast!AM43 | S55: =Cases_Forecast!AN43 | T55: =Cases_Forecast!AO43 | U55: =Cases_Forecast!AP43 | V55: =Cases_Forecast!AQ43 | ... X55: =Cases_Forecast!AS43 | Z55: =IFERROR(O55/D55,0) | AA55: =IFERROR(P55/E55,0) | AB55: =IFERROR(Q55/F55,0) | AC55: =IFERROR(R55/G55,0) | AD55: =IFERROR(S55/H55,0) | AE55: =IFERROR(T55/I55,0) | AF55: =IFERROR(U55/J55,0) | AG55: =IFERROR(V55/K55,0) | ... AI55: =IFERROR(X55/M55,0) | AK55: =IF(D$15="Yes",D55*$BL55,D55) | AL55: =IF(E$15="Yes",E55*$BL55,E55) | AM55: =IF(F$15="Yes",F55*$BL55,F55) | AN55: =IF(G$15="Yes",G55*$BL55,G55) | AO55: =IF(H$15="Yes",H55*$BL55,H55) | AP55: =IF(I$15="Yes",I55*$BL55,I55) | AQ55: =IF(J$15="Yes",J55*$BL55,J55) | AR55: =IF(K$15="Yes",K55*$BL55,K55) | ... AT55: =IF(M$15="Yes",M55*$BL55,M55) | AV55: =IFERROR(O55/AK55,0) | AW55: =IFERROR(P55/AL55,0) | AX55: =IFERROR(Q55/AM55,0) | AY55: =IFERROR(R55/AN55,0) | AZ55: =IFERROR(S55/AO55,0) | BA55: =IFERROR(T55/AP55,0) | BB55: =IFERROR(U55/AQ55,0) | BC55: =IFERROR(V55/AR55,0) | ... BE55: =IFERROR(X55/AT55,0) | BG55: =SUMPRODUCT(($D$15:$M$15="Yes")*O55:X55) | BH55: =SUMPRODUCT(($D$15:$M$15="Yes")*Z55:AI55) | BI55: =SUMPRODUCT(($D$15:$M$15="Yes")*AV55:BE55) | BJ55: =IFERROR(BG55/BH55,0) | BK55: =IFERROR(BG55/BI55,0) | BL55: =IF(B55="Actual",1,INDEX($G$9:$G$11,MATCH(C55,$A$9:$A$11,0))) | BN55: 46113 | BO55: =Inputs!$A$41 | BP55: =AP35
A56: 46753 | B56: =IF(A56<=LastActual,"Actual","Forecast") | C56: =YEAR(A56) | D56: =IFERROR('NSW-1'!X51*1,0) | E56: =IFERROR('VIC-1'!X51*1,0) | F56: =IFERROR('QLD-1'!X51*1,0) | G56: =IFERROR('NSW-2'!X51*1,0) | H56: =IFERROR('VIC-2'!X51*1,0) | I56: =IFERROR('QLD-2'!X51*1,0) | J56: =IFERROR('SA-1'!X51*1,0) | K56: =IFERROR('WA-1'!X51*1,0) | L56: =IFERROR('IDC-NSW'!X51*1,0) | M56: =IFERROR('IDC-VIC'!X51*1,0) | O56: =Cases_Forecast!AJ44 | P56: =Cases_Forecast!AK44 | Q56: =Cases_Forecast!AL44 | R56: =Cases_Forecast!AM44 | S56: =Cases_Forecast!AN44 | T56: =Cases_Forecast!AO44 | U56: =Cases_Forecast!AP44 | V56: =Cases_Forecast!AQ44 | ... X56: =Cases_Forecast!AS44 | Z56: =IFERROR(O56/D56,0) | AA56: =IFERROR(P56/E56,0) | AB56: =IFERROR(Q56/F56,0) | AC56: =IFERROR(R56/G56,0) | AD56: =IFERROR(S56/H56,0) | AE56: =IFERROR(T56/I56,0) | AF56: =IFERROR(U56/J56,0) | AG56: =IFERROR(V56/K56,0) | ... AI56: =IFERROR(X56/M56,0) | AK56: =IF(D$15="Yes",D56*$BL56,D56) | AL56: =IF(E$15="Yes",E56*$BL56,E56) | AM56: =IF(F$15="Yes",F56*$BL56,F56) | AN56: =IF(G$15="Yes",G56*$BL56,G56) | AO56: =IF(H$15="Yes",H56*$BL56,H56) | AP56: =IF(I$15="Yes",I56*$BL56,I56) | AQ56: =IF(J$15="Yes",J56*$BL56,J56) | AR56: =IF(K$15="Yes",K56*$BL56,K56) | ... AT56: =IF(M$15="Yes",M56*$BL56,M56) | AV56: =IFERROR(O56/AK56,0) | AW56: =IFERROR(P56/AL56,0) | AX56: =IFERROR(Q56/AM56,0) | AY56: =IFERROR(R56/AN56,0) | AZ56: =IFERROR(S56/AO56,0) | BA56: =IFERROR(T56/AP56,0) | BB56: =IFERROR(U56/AQ56,0) | BC56: =IFERROR(V56/AR56,0) | ... BE56: =IFERROR(X56/AT56,0) | BG56: =SUMPRODUCT(($D$15:$M$15="Yes")*O56:X56) | BH56: =SUMPRODUCT(($D$15:$M$15="Yes")*Z56:AI56) | BI56: =SUMPRODUCT(($D$15:$M$15="Yes")*AV56:BE56) | BJ56: =IFERROR(BG56/BH56,0) | BK56: =IFERROR(BG56/BI56,0) | BL56: =IF(B56="Actual",1,INDEX($G$9:$G$11,MATCH(C56,$A$9:$A$11,0))) | BN56: 46113 | BO56: =Inputs!$A$42 | BP56: =AQ35
A57: 46784 | B57: =IF(A57<=LastActual,"Actual","Forecast") | C57: =YEAR(A57) | D57: =IFERROR('NSW-1'!X52*1,0) | E57: =IFERROR('VIC-1'!X52*1,0) | F57: =IFERROR('QLD-1'!X52*1,0) | G57: =IFERROR('NSW-2'!X52*1,0) | H57: =IFERROR('VIC-2'!X52*1,0) | I57: =IFERROR('QLD-2'!X52*1,0) | J57: =IFERROR('SA-1'!X52*1,0) | K57: =IFERROR('WA-1'!X52*1,0) | L57: =IFERROR('IDC-NSW'!X52*1,0) | M57: =IFERROR('IDC-VIC'!X52*1,0) | O57: =Cases_Forecast!AJ45 | P57: =Cases_Forecast!AK45 | Q57: =Cases_Forecast!AL45 | R57: =Cases_Forecast!AM45 | S57: =Cases_Forecast!AN45 | T57: =Cases_Forecast!AO45 | U57: =Cases_Forecast!AP45 | V57: =Cases_Forecast!AQ45 | ... X57: =Cases_Forecast!AS45 | Z57: =IFERROR(O57/D57,0) | AA57: =IFERROR(P57/E57,0) | AB57: =IFERROR(Q57/F57,0) | AC57: =IFERROR(R57/G57,0) | AD57: =IFERROR(S57/H57,0) | AE57: =IFERROR(T57/I57,0) | AF57: =IFERROR(U57/J57,0) | AG57: =IFERROR(V57/K57,0) | ... AI57: =IFERROR(X57/M57,0) | AK57: =IF(D$15="Yes",D57*$BL57,D57) | AL57: =IF(E$15="Yes",E57*$BL57,E57) | AM57: =IF(F$15="Yes",F57*$BL57,F57) | AN57: =IF(G$15="Yes",G57*$BL57,G57) | AO57: =IF(H$15="Yes",H57*$BL57,H57) | AP57: =IF(I$15="Yes",I57*$BL57,I57) | AQ57: =IF(J$15="Yes",J57*$BL57,J57) | AR57: =IF(K$15="Yes",K57*$BL57,K57) | ... AT57: =IF(M$15="Yes",M57*$BL57,M57) | AV57: =IFERROR(O57/AK57,0) | AW57: =IFERROR(P57/AL57,0) | AX57: =IFERROR(Q57/AM57,0) | AY57: =IFERROR(R57/AN57,0) | AZ57: =IFERROR(S57/AO57,0) | BA57: =IFERROR(T57/AP57,0) | BB57: =IFERROR(U57/AQ57,0) | BC57: =IFERROR(V57/AR57,0) | ... BE57: =IFERROR(X57/AT57,0) | BG57: =SUMPRODUCT(($D$15:$M$15="Yes")*O57:X57) | BH57: =SUMPRODUCT(($D$15:$M$15="Yes")*Z57:AI57) | BI57: =SUMPRODUCT(($D$15:$M$15="Yes")*AV57:BE57) | BJ57: =IFERROR(BG57/BH57,0) | BK57: =IFERROR(BG57/BI57,0) | BL57: =IF(B57="Actual",1,INDEX($G$9:$G$11,MATCH(C57,$A$9:$A$11,0))) | BN57: 46113 | BO57: =Inputs!$A$43 | BP57: =AR35
A58: 46813 | B58: =IF(A58<=LastActual,"Actual","Forecast") | C58: =YEAR(A58) | D58: =IFERROR('NSW-1'!X53*1,0) | E58: =IFERROR('VIC-1'!X53*1,0) | F58: =IFERROR('QLD-1'!X53*1,0) | G58: =IFERROR('NSW-2'!X53*1,0) | H58: =IFERROR('VIC-2'!X53*1,0) | I58: =IFERROR('QLD-2'!X53*1,0) | J58: =IFERROR('SA-1'!X53*1,0) | K58: =IFERROR('WA-1'!X53*1,0) | L58: =IFERROR('IDC-NSW'!X53*1,0) | M58: =IFERROR('IDC-VIC'!X53*1,0) | O58: =Cases_Forecast!AJ46 | P58: =Cases_Forecast!AK46 | Q58: =Cases_Forecast!AL46 | R58: =Cases_Forecast!AM46 | S58: =Cases_Forecast!AN46 | T58: =Cases_Forecast!AO46 | U58: =Cases_Forecast!AP46 | V58: =Cases_Forecast!AQ46 | ... X58: =Cases_Forecast!AS46 | Z58: =IFERROR(O58/D58,0) | AA58: =IFERROR(P58/E58,0) | AB58: =IFERROR(Q58/F58,0) | AC58: =IFERROR(R58/G58,0) | AD58: =IFERROR(S58/H58,0) | AE58: =IFERROR(T58/I58,0) | AF58: =IFERROR(U58/J58,0) | AG58: =IFERROR(V58/K58,0) | ... AI58: =IFERROR(X58/M58,0) | AK58: =IF(D$15="Yes",D58*$BL58,D58) | AL58: =IF(E$15="Yes",E58*$BL58,E58) | AM58: =IF(F$15="Yes",F58*$BL58,F58) | AN58: =IF(G$15="Yes",G58*$BL58,G58) | AO58: =IF(H$15="Yes",H58*$BL58,H58) | AP58: =IF(I$15="Yes",I58*$BL58,I58) | AQ58: =IF(J$15="Yes",J58*$BL58,J58) | AR58: =IF(K$15="Yes",K58*$BL58,K58) | ... AT58: =IF(M$15="Yes",M58*$BL58,M58) | AV58: =IFERROR(O58/AK58,0) | AW58: =IFERROR(P58/AL58,0) | AX58: =IFERROR(Q58/AM58,0) | AY58: =IFERROR(R58/AN58,0) | AZ58: =IFERROR(S58/AO58,0) | BA58: =IFERROR(T58/AP58,0) | BB58: =IFERROR(U58/AQ58,0) | BC58: =IFERROR(V58/AR58,0) | ... BE58: =IFERROR(X58/AT58,0) | BG58: =SUMPRODUCT(($D$15:$M$15="Yes")*O58:X58) | BH58: =SUMPRODUCT(($D$15:$M$15="Yes")*Z58:AI58) | BI58: =SUMPRODUCT(($D$15:$M$15="Yes")*AV58:BE58) | BJ58: =IFERROR(BG58/BH58,0) | BK58: =IFERROR(BG58/BI58,0) | BL58: =IF(B58="Actual",1,INDEX($G$9:$G$11,MATCH(C58,$A$9:$A$11,0))) | BN58: 46113 | BO58: =Inputs!$A$44 | BP58: =AS35
A59: 46844 | B59: =IF(A59<=LastActual,"Actual","Forecast") | C59: =YEAR(A59) | D59: =IFERROR('NSW-1'!X54*1,0) | E59: =IFERROR('VIC-1'!X54*1,0) | F59: =IFERROR('QLD-1'!X54*1,0) | G59: =IFERROR('NSW-2'!X54*1,0) | H59: =IFERROR('VIC-2'!X54*1,0) | I59: =IFERROR('QLD-2'!X54*1,0) | J59: =IFERROR('SA-1'!X54*1,0) | K59: =IFERROR('WA-1'!X54*1,0) | L59: =IFERROR('IDC-NSW'!X54*1,0) | M59: =IFERROR('IDC-VIC'!X54*1,0) | O59: =Cases_Forecast!AJ47 | P59: =Cases_Forecast!AK47 | Q59: =Cases_Forecast!AL47 | R59: =Cases_Forecast!AM47 | S59: =Cases_Forecast!AN47 | T59: =Cases_Forecast!AO47 | U59: =Cases_Forecast!AP47 | V59: =Cases_Forecast!AQ47 | ... X59: =Cases_Forecast!AS47 | Z59: =IFERROR(O59/D59,0) | AA59: =IFERROR(P59/E59,0) | AB59: =IFERROR(Q59/F59,0) | AC59: =IFERROR(R59/G59,0) | AD59: =IFERROR(S59/H59,0) | AE59: =IFERROR(T59/I59,0) | AF59: =IFERROR(U59/J59,0) | AG59: =IFERROR(V59/K59,0) | ... AI59: =IFERROR(X59/M59,0) | AK59: =IF(D$15="Yes",D59*$BL59,D59) | AL59: =IF(E$15="Yes",E59*$BL59,E59) | AM59: =IF(F$15="Yes",F59*$BL59,F59) | AN59: =IF(G$15="Yes",G59*$BL59,G59) | AO59: =IF(H$15="Yes",H59*$BL59,H59) | AP59: =IF(I$15="Yes",I59*$BL59,I59) | AQ59: =IF(J$15="Yes",J59*$BL59,J59) | AR59: =IF(K$15="Yes",K59*$BL59,K59) | ... AT59: =IF(M$15="Yes",M59*$BL59,M59) | AV59: =IFERROR(O59/AK59,0) | AW59: =IFERROR(P59/AL59,0) | AX59: =IFERROR(Q59/AM59,0) | AY59: =IFERROR(R59/AN59,0) | AZ59: =IFERROR(S59/AO59,0) | BA59: =IFERROR(T59/AP59,0) | BB59: =IFERROR(U59/AQ59,0) | BC59: =IFERROR(V59/AR59,0) | ... BE59: =IFERROR(X59/AT59,0) | BG59: =SUMPRODUCT(($D$15:$M$15="Yes")*O59:X59) | BH59: =SUMPRODUCT(($D$15:$M$15="Yes")*Z59:AI59) | BI59: =SUMPRODUCT(($D$15:$M$15="Yes")*AV59:BE59) | BJ59: =IFERROR(BG59/BH59,0) | BK59: =IFERROR(BG59/BI59,0) | BL59: =IF(B59="Actual",1,INDEX($G$9:$G$11,MATCH(C59,$A$9:$A$11,0))) | BN59: 46113 | BO59: =Inputs!$A$45 | BP59: =AT35
A60: 46874 | B60: =IF(A60<=LastActual,"Actual","Forecast") | C60: =YEAR(A60) | D60: =IFERROR('NSW-1'!X55*1,0) | E60: =IFERROR('VIC-1'!X55*1,0) | F60: =IFERROR('QLD-1'!X55*1,0) | G60: =IFERROR('NSW-2'!X55*1,0) | H60: =IFERROR('VIC-2'!X55*1,0) | I60: =IFERROR('QLD-2'!X55*1,0) | J60: =IFERROR('SA-1'!X55*1,0) | K60: =IFERROR('WA-1'!X55*1,0) | L60: =IFERROR('IDC-NSW'!X55*1,0) | M60: =IFERROR('IDC-VIC'!X55*1,0) | O60: =Cases_Forecast!AJ48 | P60: =Cases_Forecast!AK48 | Q60: =Cases_Forecast!AL48 | R60: =Cases_Forecast!AM48 | S60: =Cases_Forecast!AN48 | T60: =Cases_Forecast!AO48 | U60: =Cases_Forecast!AP48 | V60: =Cases_Forecast!AQ48 | ... X60: =Cases_Forecast!AS48 | Z60: =IFERROR(O60/D60,0) | AA60: =IFERROR(P60/E60,0) | AB60: =IFERROR(Q60/F60,0) | AC60: =IFERROR(R60/G60,0) | AD60: =IFERROR(S60/H60,0) | AE60: =IFERROR(T60/I60,0) | AF60: =IFERROR(U60/J60,0) | AG60: =IFERROR(V60/K60,0) | ... AI60: =IFERROR(X60/M60,0) | AK60: =IF(D$15="Yes",D60*$BL60,D60) | AL60: =IF(E$15="Yes",E60*$BL60,E60) | AM60: =IF(F$15="Yes",F60*$BL60,F60) | AN60: =IF(G$15="Yes",G60*$BL60,G60) | AO60: =IF(H$15="Yes",H60*$BL60,H60) | AP60: =IF(I$15="Yes",I60*$BL60,I60) | AQ60: =IF(J$15="Yes",J60*$BL60,J60) | AR60: =IF(K$15="Yes",K60*$BL60,K60) | ... AT60: =IF(M$15="Yes",M60*$BL60,M60) | AV60: =IFERROR(O60/AK60,0) | AW60: =IFERROR(P60/AL60,0) | AX60: =IFERROR(Q60/AM60,0) | AY60: =IFERROR(R60/AN60,0) | AZ60: =IFERROR(S60/AO60,0) | BA60: =IFERROR(T60/AP60,0) | BB60: =IFERROR(U60/AQ60,0) | BC60: =IFERROR(V60/AR60,0) | ... BE60: =IFERROR(X60/AT60,0) | BG60: =SUMPRODUCT(($D$15:$M$15="Yes")*O60:X60) | BH60: =SUMPRODUCT(($D$15:$M$15="Yes")*Z60:AI60) | BI60: =SUMPRODUCT(($D$15:$M$15="Yes")*AV60:BE60) | BJ60: =IFERROR(BG60/BH60,0) | BK60: =IFERROR(BG60/BI60,0) | BL60: =IF(B60="Actual",1,INDEX($G$9:$G$11,MATCH(C60,$A$9:$A$11,0))) | BN60: 46143 | BO60: =Inputs!$A$36 | BP60: =AK36
A61: 46905 | B61: =IF(A61<=LastActual,"Actual","Forecast") | C61: =YEAR(A61) | D61: =IFERROR('NSW-1'!X56*1,0) | E61: =IFERROR('VIC-1'!X56*1,0) | F61: =IFERROR('QLD-1'!X56*1,0) | G61: =IFERROR('NSW-2'!X56*1,0) | H61: =IFERROR('VIC-2'!X56*1,0) | I61: =IFERROR('QLD-2'!X56*1,0) | J61: =IFERROR('SA-1'!X56*1,0) | K61: =IFERROR('WA-1'!X56*1,0) | L61: =IFERROR('IDC-NSW'!X56*1,0) | M61: =IFERROR('IDC-VIC'!X56*1,0) | O61: =Cases_Forecast!AJ49 | P61: =Cases_Forecast!AK49 | Q61: =Cases_Forecast!AL49 | R61: =Cases_Forecast!AM49 | S61: =Cases_Forecast!AN49 | T61: =Cases_Forecast!AO49 | U61: =Cases_Forecast!AP49 | V61: =Cases_Forecast!AQ49 | ... X61: =Cases_Forecast!AS49 | Z61: =IFERROR(O61/D61,0) | AA61: =IFERROR(P61/E61,0) | AB61: =IFERROR(Q61/F61,0) | AC61: =IFERROR(R61/G61,0) | AD61: =IFERROR(S61/H61,0) | AE61: =IFERROR(T61/I61,0) | AF61: =IFERROR(U61/J61,0) | AG61: =IFERROR(V61/K61,0) | ... AI61: =IFERROR(X61/M61,0) | AK61: =IF(D$15="Yes",D61*$BL61,D61) | AL61: =IF(E$15="Yes",E61*$BL61,E61) | AM61: =IF(F$15="Yes",F61*$BL61,F61) | AN61: =IF(G$15="Yes",G61*$BL61,G61) | AO61: =IF(H$15="Yes",H61*$BL61,H61) | AP61: =IF(I$15="Yes",I61*$BL61,I61) | AQ61: =IF(J$15="Yes",J61*$BL61,J61) | AR61: =IF(K$15="Yes",K61*$BL61,K61) | ... AT61: =IF(M$15="Yes",M61*$BL61,M61) | AV61: =IFERROR(O61/AK61,0) | AW61: =IFERROR(P61/AL61,0) | AX61: =IFERROR(Q61/AM61,0) | AY61: =IFERROR(R61/AN61,0) | AZ61: =IFERROR(S61/AO61,0) | BA61: =IFERROR(T61/AP61,0) | BB61: =IFERROR(U61/AQ61,0) | BC61: =IFERROR(V61/AR61,0) | ... BE61: =IFERROR(X61/AT61,0) | BG61: =SUMPRODUCT(($D$15:$M$15="Yes")*O61:X61) | BH61: =SUMPRODUCT(($D$15:$M$15="Yes")*Z61:AI61) | BI61: =SUMPRODUCT(($D$15:$M$15="Yes")*AV61:BE61) | BJ61: =IFERROR(BG61/BH61,0) | BK61: =IFERROR(BG61/BI61,0) | BL61: =IF(B61="Actual",1,INDEX($G$9:$G$11,MATCH(C61,$A$9:$A$11,0))) | BN61: 46143 | BO61: =Inputs!$A$37 | BP61: =AL36
A62: 46935 | B62: =IF(A62<=LastActual,"Actual","Forecast") | C62: =YEAR(A62) | D62: =IFERROR('NSW-1'!X57*1,0) | E62: =IFERROR('VIC-1'!X57*1,0) | F62: =IFERROR('QLD-1'!X57*1,0) | G62: =IFERROR('NSW-2'!X57*1,0) | H62: =IFERROR('VIC-2'!X57*1,0) | I62: =IFERROR('QLD-2'!X57*1,0) | J62: =IFERROR('SA-1'!X57*1,0) | K62: =IFERROR('WA-1'!X57*1,0) | L62: =IFERROR('IDC-NSW'!X57*1,0) | M62: =IFERROR('IDC-VIC'!X57*1,0) | O62: =Cases_Forecast!AJ50 | P62: =Cases_Forecast!AK50 | Q62: =Cases_Forecast!AL50 | R62: =Cases_Forecast!AM50 | S62: =Cases_Forecast!AN50 | T62: =Cases_Forecast!AO50 | U62: =Cases_Forecast!AP50 | V62: =Cases_Forecast!AQ50 | ... X62: =Cases_Forecast!AS50 | Z62: =IFERROR(O62/D62,0) | AA62: =IFERROR(P62/E62,0) | AB62: =IFERROR(Q62/F62,0) | AC62: =IFERROR(R62/G62,0) | AD62: =IFERROR(S62/H62,0) | AE62: =IFERROR(T62/I62,0) | AF62: =IFERROR(U62/J62,0) | AG62: =IFERROR(V62/K62,0) | ... AI62: =IFERROR(X62/M62,0) | AK62: =IF(D$15="Yes",D62*$BL62,D62) | AL62: =IF(E$15="Yes",E62*$BL62,E62) | AM62: =IF(F$15="Yes",F62*$BL62,F62) | AN62: =IF(G$15="Yes",G62*$BL62,G62) | AO62: =IF(H$15="Yes",H62*$BL62,H62) | AP62: =IF(I$15="Yes",I62*$BL62,I62) | AQ62: =IF(J$15="Yes",J62*$BL62,J62) | AR62: =IF(K$15="Yes",K62*$BL62,K62) | ... AT62: =IF(M$15="Yes",M62*$BL62,M62) | AV62: =IFERROR(O62/AK62,0) | AW62: =IFERROR(P62/AL62,0) | AX62: =IFERROR(Q62/AM62,0) | AY62: =IFERROR(R62/AN62,0) | AZ62: =IFERROR(S62/AO62,0) | BA62: =IFERROR(T62/AP62,0) | BB62: =IFERROR(U62/AQ62,0) | BC62: =IFERROR(V62/AR62,0) | ... BE62: =IFERROR(X62/AT62,0) | BG62: =SUMPRODUCT(($D$15:$M$15="Yes")*O62:X62) | BH62: =SUMPRODUCT(($D$15:$M$15="Yes")*Z62:AI62) | BI62: =SUMPRODUCT(($D$15:$M$15="Yes")*AV62:BE62) | BJ62: =IFERROR(BG62/BH62,0) | BK62: =IFERROR(BG62/BI62,0) | BL62: =IF(B62="Actual",1,INDEX($G$9:$G$11,MATCH(C62,$A$9:$A$11,0))) | BN62: 46143 | BO62: =Inputs!$A$38 | BP62: =AM36
A63: 46966 | B63: =IF(A63<=LastActual,"Actual","Forecast") | C63: =YEAR(A63) | D63: =IFERROR('NSW-1'!X58*1,0) | E63: =IFERROR('VIC-1'!X58*1,0) | F63: =IFERROR('QLD-1'!X58*1,0) | G63: =IFERROR('NSW-2'!X58*1,0) | H63: =IFERROR('VIC-2'!X58*1,0) | I63: =IFERROR('QLD-2'!X58*1,0) | J63: =IFERROR('SA-1'!X58*1,0) | K63: =IFERROR('WA-1'!X58*1,0) | L63: =IFERROR('IDC-NSW'!X58*1,0) | M63: =IFERROR('IDC-VIC'!X58*1,0) | O63: =Cases_Forecast!AJ51 | P63: =Cases_Forecast!AK51 | Q63: =Cases_Forecast!AL51 | R63: =Cases_Forecast!AM51 | S63: =Cases_Forecast!AN51 | T63: =Cases_Forecast!AO51 | U63: =Cases_Forecast!AP51 | V63: =Cases_Forecast!AQ51 | ... X63: =Cases_Forecast!AS51 | Z63: =IFERROR(O63/D63,0) | AA63: =IFERROR(P63/E63,0) | AB63: =IFERROR(Q63/F63,0) | AC63: =IFERROR(R63/G63,0) | AD63: =IFERROR(S63/H63,0) | AE63: =IFERROR(T63/I63,0) | AF63: =IFERROR(U63/J63,0) | AG63: =IFERROR(V63/K63,0) | ... AI63: =IFERROR(X63/M63,0) | AK63: =IF(D$15="Yes",D63*$BL63,D63) | AL63: =IF(E$15="Yes",E63*$BL63,E63) | AM63: =IF(F$15="Yes",F63*$BL63,F63) | AN63: =IF(G$15="Yes",G63*$BL63,G63) | AO63: =IF(H$15="Yes",H63*$BL63,H63) | AP63: =IF(I$15="Yes",I63*$BL63,I63) | AQ63: =IF(J$15="Yes",J63*$BL63,J63) | AR63: =IF(K$15="Yes",K63*$BL63,K63) | ... AT63: =IF(M$15="Yes",M63*$BL63,M63) | AV63: =IFERROR(O63/AK63,0) | AW63: =IFERROR(P63/AL63,0) | AX63: =IFERROR(Q63/AM63,0) | AY63: =IFERROR(R63/AN63,0) | AZ63: =IFERROR(S63/AO63,0) | BA63: =IFERROR(T63/AP63,0) | BB63: =IFERROR(U63/AQ63,0) | BC63: =IFERROR(V63/AR63,0) | ... BE63: =IFERROR(X63/AT63,0) | BG63: =SUMPRODUCT(($D$15:$M$15="Yes")*O63:X63) | BH63: =SUMPRODUCT(($D$15:$M$15="Yes")*Z63:AI63) | BI63: =SUMPRODUCT(($D$15:$M$15="Yes")*AV63:BE63) | BJ63: =IFERROR(BG63/BH63,0) | BK63: =IFERROR(BG63/BI63,0) | BL63: =IF(B63="Actual",1,INDEX($G$9:$G$11,MATCH(C63,$A$9:$A$11,0))) | BN63: 46143 | BO63: =Inputs!$A$39 | BP63: =AN36
A64: 46997 | B64: =IF(A64<=LastActual,"Actual","Forecast") | C64: =YEAR(A64) | D64: =IFERROR('NSW-1'!X59*1,0) | E64: =IFERROR('VIC-1'!X59*1,0) | F64: =IFERROR('QLD-1'!X59*1,0) | G64: =IFERROR('NSW-2'!X59*1,0) | H64: =IFERROR('VIC-2'!X59*1,0) | I64: =IFERROR('QLD-2'!X59*1,0) | J64: =IFERROR('SA-1'!X59*1,0) | K64: =IFERROR('WA-1'!X59*1,0) | L64: =IFERROR('IDC-NSW'!X59*1,0) | M64: =IFERROR('IDC-VIC'!X59*1,0) | O64: =Cases_Forecast!AJ52 | P64: =Cases_Forecast!AK52 | Q64: =Cases_Forecast!AL52 | R64: =Cases_Forecast!AM52 | S64: =Cases_Forecast!AN52 | T64: =Cases_Forecast!AO52 | U64: =Cases_Forecast!AP52 | V64: =Cases_Forecast!AQ52 | ... X64: =Cases_Forecast!AS52 | Z64: =IFERROR(O64/D64,0) | AA64: =IFERROR(P64/E64,0) | AB64: =IFERROR(Q64/F64,0) | AC64: =IFERROR(R64/G64,0) | AD64: =IFERROR(S64/H64,0) | AE64: =IFERROR(T64/I64,0) | AF64: =IFERROR(U64/J64,0) | AG64: =IFERROR(V64/K64,0) | ... AI64: =IFERROR(X64/M64,0) | AK64: =IF(D$15="Yes",D64*$BL64,D64) | AL64: =IF(E$15="Yes",E64*$BL64,E64) | AM64: =IF(F$15="Yes",F64*$BL64,F64) | AN64: =IF(G$15="Yes",G64*$BL64,G64) | AO64: =IF(H$15="Yes",H64*$BL64,H64) | AP64: =IF(I$15="Yes",I64*$BL64,I64) | AQ64: =IF(J$15="Yes",J64*$BL64,J64) | AR64: =IF(K$15="Yes",K64*$BL64,K64) | ... AT64: =IF(M$15="Yes",M64*$BL64,M64) | AV64: =IFERROR(O64/AK64,0) | AW64: =IFERROR(P64/AL64,0) | AX64: =IFERROR(Q64/AM64,0) | AY64: =IFERROR(R64/AN64,0) | AZ64: =IFERROR(S64/AO64,0) | BA64: =IFERROR(T64/AP64,0) | BB64: =IFERROR(U64/AQ64,0) | BC64: =IFERROR(V64/AR64,0) | ... BE64: =IFERROR(X64/AT64,0) | BG64: =SUMPRODUCT(($D$15:$M$15="Yes")*O64:X64) | BH64: =SUMPRODUCT(($D$15:$M$15="Yes")*Z64:AI64) | BI64: =SUMPRODUCT(($D$15:$M$15="Yes")*AV64:BE64) | BJ64: =IFERROR(BG64/BH64,0) | BK64: =IFERROR(BG64/BI64,0) | BL64: =IF(B64="Actual",1,INDEX($G$9:$G$11,MATCH(C64,$A$9:$A$11,0))) | BN64: 46143 | BO64: =Inputs!$A$40 | BP64: =AO36
A65: 47027 | B65: =IF(A65<=LastActual,"Actual","Forecast") | C65: =YEAR(A65) | D65: =IFERROR('NSW-1'!X60*1,0) | E65: =IFERROR('VIC-1'!X60*1,0) | F65: =IFERROR('QLD-1'!X60*1,0) | G65: =IFERROR('NSW-2'!X60*1,0) | H65: =IFERROR('VIC-2'!X60*1,0) | I65: =IFERROR('QLD-2'!X60*1,0) | J65: =IFERROR('SA-1'!X60*1,0) | K65: =IFERROR('WA-1'!X60*1,0) | L65: =IFERROR('IDC-NSW'!X60*1,0) | M65: =IFERROR('IDC-VIC'!X60*1,0) | O65: =Cases_Forecast!AJ53 | P65: =Cases_Forecast!AK53 | Q65: =Cases_Forecast!AL53 | R65: =Cases_Forecast!AM53 | S65: =Cases_Forecast!AN53 | T65: =Cases_Forecast!AO53 | U65: =Cases_Forecast!AP53 | V65: =Cases_Forecast!AQ53 | ... X65: =Cases_Forecast!AS53 | Z65: =IFERROR(O65/D65,0) | AA65: =IFERROR(P65/E65,0) | AB65: =IFERROR(Q65/F65,0) | AC65: =IFERROR(R65/G65,0) | AD65: =IFERROR(S65/H65,0) | AE65: =IFERROR(T65/I65,0) | AF65: =IFERROR(U65/J65,0) | AG65: =IFERROR(V65/K65,0) | ... AI65: =IFERROR(X65/M65,0) | AK65: =IF(D$15="Yes",D65*$BL65,D65) | AL65: =IF(E$15="Yes",E65*$BL65,E65) | AM65: =IF(F$15="Yes",F65*$BL65,F65) | AN65: =IF(G$15="Yes",G65*$BL65,G65) | AO65: =IF(H$15="Yes",H65*$BL65,H65) | AP65: =IF(I$15="Yes",I65*$BL65,I65) | AQ65: =IF(J$15="Yes",J65*$BL65,J65) | AR65: =IF(K$15="Yes",K65*$BL65,K65) | ... AT65: =IF(M$15="Yes",M65*$BL65,M65) | AV65: =IFERROR(O65/AK65,0) | AW65: =IFERROR(P65/AL65,0) | AX65: =IFERROR(Q65/AM65,0) | AY65: =IFERROR(R65/AN65,0) | AZ65: =IFERROR(S65/AO65,0) | BA65: =IFERROR(T65/AP65,0) | BB65: =IFERROR(U65/AQ65,0) | BC65: =IFERROR(V65/AR65,0) | ... BE65: =IFERROR(X65/AT65,0) | BG65: =SUMPRODUCT(($D$15:$M$15="Yes")*O65:X65) | BH65: =SUMPRODUCT(($D$15:$M$15="Yes")*Z65:AI65) | BI65: =SUMPRODUCT(($D$15:$M$15="Yes")*AV65:BE65) | BJ65: =IFERROR(BG65/BH65,0) | BK65: =IFERROR(BG65/BI65,0) | BL65: =IF(B65="Actual",1,INDEX($G$9:$G$11,MATCH(C65,$A$9:$A$11,0))) | BN65: 46143 | BO65: =Inputs!$A$41 | BP65: =AP36
A66: 47058 | B66: =IF(A66<=LastActual,"Actual","Forecast") | C66: =YEAR(A66) | D66: =IFERROR('NSW-1'!X61*1,0) | E66: =IFERROR('VIC-1'!X61*1,0) | F66: =IFERROR('QLD-1'!X61*1,0) | G66: =IFERROR('NSW-2'!X61*1,0) | H66: =IFERROR('VIC-2'!X61*1,0) | I66: =IFERROR('QLD-2'!X61*1,0) | J66: =IFERROR('SA-1'!X61*1,0) | K66: =IFERROR('WA-1'!X61*1,0) | L66: =IFERROR('IDC-NSW'!X61*1,0) | M66: =IFERROR('IDC-VIC'!X61*1,0) | O66: =Cases_Forecast!AJ54 | P66: =Cases_Forecast!AK54 | Q66: =Cases_Forecast!AL54 | R66: =Cases_Forecast!AM54 | S66: =Cases_Forecast!AN54 | T66: =Cases_Forecast!AO54 | U66: =Cases_Forecast!AP54 | V66: =Cases_Forecast!AQ54 | ... X66: =Cases_Forecast!AS54 | Z66: =IFERROR(O66/D66,0) | AA66: =IFERROR(P66/E66,0) | AB66: =IFERROR(Q66/F66,0) | AC66: =IFERROR(R66/G66,0) | AD66: =IFERROR(S66/H66,0) | AE66: =IFERROR(T66/I66,0) | AF66: =IFERROR(U66/J66,0) | AG66: =IFERROR(V66/K66,0) | ... AI66: =IFERROR(X66/M66,0) | AK66: =IF(D$15="Yes",D66*$BL66,D66) | AL66: =IF(E$15="Yes",E66*$BL66,E66) | AM66: =IF(F$15="Yes",F66*$BL66,F66) | AN66: =IF(G$15="Yes",G66*$BL66,G66) | AO66: =IF(H$15="Yes",H66*$BL66,H66) | AP66: =IF(I$15="Yes",I66*$BL66,I66) | AQ66: =IF(J$15="Yes",J66*$BL66,J66) | AR66: =IF(K$15="Yes",K66*$BL66,K66) | ... AT66: =IF(M$15="Yes",M66*$BL66,M66) | AV66: =IFERROR(O66/AK66,0) | AW66: =IFERROR(P66/AL66,0) | AX66: =IFERROR(Q66/AM66,0) | AY66: =IFERROR(R66/AN66,0) | AZ66: =IFERROR(S66/AO66,0) | BA66: =IFERROR(T66/AP66,0) | BB66: =IFERROR(U66/AQ66,0) | BC66: =IFERROR(V66/AR66,0) | ... BE66: =IFERROR(X66/AT66,0) | BG66: =SUMPRODUCT(($D$15:$M$15="Yes")*O66:X66) | BH66: =SUMPRODUCT(($D$15:$M$15="Yes")*Z66:AI66) | BI66: =SUMPRODUCT(($D$15:$M$15="Yes")*AV66:BE66) | BJ66: =IFERROR(BG66/BH66,0) | BK66: =IFERROR(BG66/BI66,0) | BL66: =IF(B66="Actual",1,INDEX($G$9:$G$11,MATCH(C66,$A$9:$A$11,0))) | BN66: 46143 | BO66: =Inputs!$A$42 | BP66: =AQ36
A67: 47088 | B67: =IF(A67<=LastActual,"Actual","Forecast") | C67: =YEAR(A67) | D67: =IFERROR('NSW-1'!X62*1,0) | E67: =IFERROR('VIC-1'!X62*1,0) | F67: =IFERROR('QLD-1'!X62*1,0) | G67: =IFERROR('NSW-2'!X62*1,0) | H67: =IFERROR('VIC-2'!X62*1,0) | I67: =IFERROR('QLD-2'!X62*1,0) | J67: =IFERROR('SA-1'!X62*1,0) | K67: =IFERROR('WA-1'!X62*1,0) | L67: =IFERROR('IDC-NSW'!X62*1,0) | M67: =IFERROR('IDC-VIC'!X62*1,0) | O67: =Cases_Forecast!AJ55 | P67: =Cases_Forecast!AK55 | Q67: =Cases_Forecast!AL55 | R67: =Cases_Forecast!AM55 | S67: =Cases_Forecast!AN55 | T67: =Cases_Forecast!AO55 | U67: =Cases_Forecast!AP55 | V67: =Cases_Forecast!AQ55 | ... X67: =Cases_Forecast!AS55 | Z67: =IFERROR(O67/D67,0) | AA67: =IFERROR(P67/E67,0) | AB67: =IFERROR(Q67/F67,0) | AC67: =IFERROR(R67/G67,0) | AD67: =IFERROR(S67/H67,0) | AE67: =IFERROR(T67/I67,0) | AF67: =IFERROR(U67/J67,0) | AG67: =IFERROR(V67/K67,0) | ... AI67: =IFERROR(X67/M67,0) | AK67: =IF(D$15="Yes",D67*$BL67,D67) | AL67: =IF(E$15="Yes",E67*$BL67,E67) | AM67: =IF(F$15="Yes",F67*$BL67,F67) | AN67: =IF(G$15="Yes",G67*$BL67,G67) | AO67: =IF(H$15="Yes",H67*$BL67,H67) | AP67: =IF(I$15="Yes",I67*$BL67,I67) | AQ67: =IF(J$15="Yes",J67*$BL67,J67) | AR67: =IF(K$15="Yes",K67*$BL67,K67) | ... AT67: =IF(M$15="Yes",M67*$BL67,M67) | AV67: =IFERROR(O67/AK67,0) | AW67: =IFERROR(P67/AL67,0) | AX67: =IFERROR(Q67/AM67,0) | AY67: =IFERROR(R67/AN67,0) | AZ67: =IFERROR(S67/AO67,0) | BA67: =IFERROR(T67/AP67,0) | BB67: =IFERROR(U67/AQ67,0) | BC67: =IFERROR(V67/AR67,0) | ... BE67: =IFERROR(X67/AT67,0) | BG67: =SUMPRODUCT(($D$15:$M$15="Yes")*O67:X67) | BH67: =SUMPRODUCT(($D$15:$M$15="Yes")*Z67:AI67) | BI67: =SUMPRODUCT(($D$15:$M$15="Yes")*AV67:BE67) | BJ67: =IFERROR(BG67/BH67,0) | BK67: =IFERROR(BG67/BI67,0) | BL67: =IF(B67="Actual",1,INDEX($G$9:$G$11,MATCH(C67,$A$9:$A$11,0))) | BN67: 46143 | BO67: =Inputs!$A$43 | BP67: =AR36
BN68: 46143 | BO68: =Inputs!$A$44 | BP68: =AS36
BN69: 46143 | BO69: =Inputs!$A$45 | BP69: =AT36
BN70: 46174 | BO70: =Inputs!$A$36 | BP70: =AK37
BN71: 46174 | BO71: =Inputs!$A$37 | BP71: =AL37
BN72: 46174 | BO72: =Inputs!$A$38 | BP72: =AM37
BN73: 46174 | BO73: =Inputs!$A$39 | BP73: =AN37
BN74: 46174 | BO74: =Inputs!$A$40 | BP74: =AO37
BN75: 46174 | BO75: =Inputs!$A$41 | BP75: =AP37
BN76: 46174 | BO76: =Inputs!$A$42 | BP76: =AQ37
BN77: 46174 | BO77: =Inputs!$A$43 | BP77: =AR37
BN78: 46174 | BO78: =Inputs!$A$44 | BP78: =AS37
BN79: 46174 | BO79: =Inputs!$A$45 | BP79: =AT37
BN80: 46204 | BO80: =Inputs!$A$36 | BP80: =AK38
BN81: 46204 | BO81: =Inputs!$A$37 | BP81: =AL38
BN82: 46204 | BO82: =Inputs!$A$38 | BP82: =AM38
BN83: 46204 | BO83: =Inputs!$A$39 | BP83: =AN38
BN84: 46204 | BO84: =Inputs!$A$40 | BP84: =AO38
BN85: 46204 | BO85: =Inputs!$A$41 | BP85: =AP38
BN86: 46204 | BO86: =Inputs!$A$42 | BP86: =AQ38
BN87: 46204 | BO87: =Inputs!$A$43 | BP87: =AR38
BN88: 46204 | BO88: =Inputs!$A$44 | BP88: =AS38
BN89: 46204 | BO89: =Inputs!$A$45 | BP89: =AT38
BN90: 46235 | BO90: =Inputs!$A$36 | BP90: =AK39
BN91: 46235 | BO91: =Inputs!$A$37 | BP91: =AL39
BN92: 46235 | BO92: =Inputs!$A$38 | BP92: =AM39
BN93: 46235 | BO93: =Inputs!$A$39 | BP93: =AN39
BN94: 46235 | BO94: =Inputs!$A$40 | BP94: =AO39
BN95: 46235 | BO95: =Inputs!$A$41 | BP95: =AP39
BN96: 46235 | BO96: =Inputs!$A$42 | BP96: =AQ39
BN97: 46235 | BO97: =Inputs!$A$43 | BP97: =AR39
BN98: 46235 | BO98: =Inputs!$A$44 | BP98: =AS39
BN99: 46235 | BO99: =Inputs!$A$45 | BP99: =AT39
BN100: 46266 | BO100: =Inputs!$A$36 | BP100: =AK40
BN101: 46266 | BO101: =Inputs!$A$37 | BP101: =AL40
BN102: 46266 | BO102: =Inputs!$A$38 | BP102: =AM40
BN103: 46266 | BO103: =Inputs!$A$39 | BP103: =AN40
BN104: 46266 | BO104: =Inputs!$A$40 | BP104: =AO40
BN105: 46266 | BO105: =Inputs!$A$41 | BP105: =AP40
BN106: 46266 | BO106: =Inputs!$A$42 | BP106: =AQ40
...

Sheet Chamber Weights
A1: Chamber weights: share of each site's cases by chamber
A2: Paste cases by chamber for each site (e.g. the last 3 months, if the mix has changed). The % table below splits every site tab's cases, hours and payroll by chamber, in actual and forecast months.
A4: Cases | B4: =Inputs!$A$36 | C4: =Inputs!$A$37 | D4: =Inputs!$A$38 | E4: =Inputs!$A$39 | F4: =Inputs!$A$40 | G4: =Inputs!$A$41 | H4: =Inputs!$A$42 | I4: =Inputs!$A$43 | J4: =Inputs!$A$44 | K4: =Inputs!$A$45 | L4: Total
A5: Ambient | B5: 5888234 | C5: 5232921 | D5: 4678306 | E5: 4735927 | F5: 4902900 | G5: 4642512 | H5: 3450065 | I5: 4491042 | J5: 958202 | K5: 959220 | L5: =SUM(B5:K5)
A6: Chiller | B6: 3318594 | C6: 3722258 | D6: 2627158 | E6: 3166203 | F6: 3459728 | G6: 3289068 | H6: 1968122 | I6: 2615720 | J6: 212817 | K6: 378386 | L6: =SUM(B6:K6)
A7: Freezer | B7: 459564 | C7: 0 | D7: 327452 | E7: 0 | F7: 0 | G7: 0 | H7: 0 | I7: 0 | J7: 1314009 | K7: 975144 | L7: =SUM(B7:K7)
A8: Total | B8: =SUM(B5:B7) | C8: =SUM(C5:C7) | D8: =SUM(D5:D7) | E8: =SUM(E5:E7) | F8: =SUM(F5:F7) | G8: =SUM(G5:G7) | H8: =SUM(H5:H7) | I8: =SUM(I5:I7) | ... K8: =SUM(K5:K7) | L8: =SUM(B8:K8)
A23: Share of cases | B23: =Inputs!$A$36 | C23: =Inputs!$A$37 | D23: =Inputs!$A$38 | E23: =Inputs!$A$39 | F23: =Inputs!$A$40 | G23: =Inputs!$A$41 | H23: =Inputs!$A$42 | I23: =Inputs!$A$43 | J23: =Inputs!$A$44 | K23: =Inputs!$A$45
A24: Ambient | B24: =IFERROR(B5/B8,0) | C24: =IFERROR(C5/C8,0) | D24: =IFERROR(D5/D8,0) | E24: =IFERROR(E5/E8,0) | F24: =IFERROR(F5/F8,0) | G24: =IFERROR(G5/G8,0) | H24: =IFERROR(H5/H8,0) | I24: =IFERROR(I5/I8,0) | ... K24: =IFERROR(K5/K8,0)
A25: Chiller | B25: =IFERROR(B6/B8,0) | C25: =IFERROR(C6/C8,0) | D25: =IFERROR(D6/D8,0) | E25: =IFERROR(E6/E8,0) | F25: =IFERROR(F6/F8,0) | G25: =IFERROR(G6/G8,0) | H25: =IFERROR(H6/H8,0) | I25: =IFERROR(I6/I8,0) | ... K25: =IFERROR(K6/K8,0)
A26: Freezer | B26: =IFERROR(B7/B8,0) | C26: =IFERROR(C7/C8,0) | D26: =IFERROR(D7/D8,0) | E26: =IFERROR(E7/E8,0) | F26: =IFERROR(F7/F8,0) | G26: =IFERROR(G7/G8,0) | H26: =IFERROR(H7/H8,0) | I26: =IFERROR(I7/I8,0) | ... K26: =IFERROR(K7/K8,0)
A27: check | B27: =SUM(B24:B26) | C27: =SUM(C24:C26) | D27: =SUM(D24:D26) | E27: =SUM(E24:E26) | F27: =SUM(F24:F26) | G27: =SUM(G24:G26) | H27: =SUM(H24:H26) | I27: =SUM(I24:I26) | ... K27: =SUM(K24:K26)

Sheet CLR
A1: CLR: cost-saving initiatives (placeholder)
A2: Placeholder only. Nothing on this tab feeds the forecast yet.
A4: Initiative | B4: Site | C4: Type | D4: Value | E4: Start month | F4: Ramp-up months | G4: End month | H4: Active | I4: Owner / notes

Sheet Holidays
A1: Date | B1: Holiday | C1: State | E1: Generated by rule. Add, remove or move rows freely; the Calendar tab counts them by state and month.
A2: 45658 | B2: New Year's Day | C2: NSW
A3: 45684 | B3: Australia Day | C3: NSW
A4: 45765 | B4: Good Friday | C4: NSW
A5: 45766 | B5: Easter Saturday | C5: NSW
A6: 45767 | B6: Easter Sunday | C6: NSW
A7: 45768 | B7: Easter Monday | C7: NSW
A8: 45772 | B8: Anzac Day | C8: NSW
A9: 45817 | B9: King's Birthday | C9: NSW
A10: 45936 | B10: Labour Day | C10: NSW
A11: 46016 | B11: Christmas Day | C11: NSW
A12: 46017 | B12: Boxing Day | C12: NSW
A13: 46023 | B13: New Year's Day | C13: NSW
... A256: 47113 | B256: Boxing Day | C256: WA

Sheet Calendar
A1: Calendar: public holidays, PH cost factor, wage index
A2: PH factor = average cost per hour in the month vs a month with no public holidays.
C3: Public holidays (count) | H3: PH cost factor
A4: Month | B4: Days | C4: PH NSW | D4: PH VIC | E4: PH QLD | F4: PH SA | G4: PH WA | H4: NSW | I4: VIC | J4: QLD | K4: SA | L4: WA | M4: Wage index
A5: 45658 | B5: =DAY(EOMONTH(A5,0)) | C5: =COUNTIFS(Holidays!$A$2:$A$1000,">="&$A5,Holidays!$A$2:$A$1000,"<="&EOMONTH($A5,0),Holidays!$C$2:$C$1000,"NSW") | D5: =COUNTIFS(Holidays!$A$2:$A$1000,">="&$A5,Holidays!$A$2:$A$1000,"<="&EOMONTH($A5,0),Holidays!$C$2:$C$1000,"VIC") | E5: =COUNTIFS(Holidays!$A$2:$A$1000,">="&$A5,Holidays!$A$2:$A$1000,"<="&EOMONTH($A5,0),Holidays!$C$2:$C$1000,"QLD") | F5: =COUNTIFS(Holidays!$A$2:$A$1000,">="&$A5,Holidays!$A$2:$A$1000,"<="&EOMONTH($A5,0),Holidays!$C$2:$C$1000,"SA") | G5: =COUNTIFS(Holidays!$A$2:$A$1000,">="&$A5,Holidays!$A$2:$A$1000,"<="&EOMONTH($A5,0),Holidays!$C$2:$C$1000,"WA") | H5: =($B5-C5+C5*PH_Roster*(1+PH_Loading))/($B5-C5+C5*PH_Roster) | I5: =($B5-D5+D5*PH_Roster*(1+PH_Loading))/($B5-D5+D5*PH_Roster) | J5: =($B5-E5+E5*PH_Roster*(1+PH_Loading))/($B5-E5+E5*PH_Roster) | K5: =($B5-F5+F5*PH_Roster*(1+PH_Loading))/($B5-F5+F5*PH_Roster) | L5: =($B5-G5+G5*PH_Roster*(1+PH_Loading))/($B5-G5+G5*PH_Roster) | M5: =EXP(SUMPRODUCT((WageDates<=$A5)*(WageDates<>"")*LN(1+WageRates)))
A6: 45689 | B6: =DAY(EOMONTH(A6,0)) | C6: =COUNTIFS(Holidays!$A$2:$A$1000,">="&$A6,Holidays!$A$2:$A$1000,"<="&EOMONTH($A6,0),Holidays!$C$2:$C$1000,"NSW") | D6: =COUNTIFS(Holidays!$A$2:$A$1000,">="&$A6,Holidays!$A$2:$A$1000,"<="&EOMONTH($A6,0),Holidays!$C$2:$C$1000,"VIC") | E6: =COUNTIFS(Holidays!$A$2:$A$1000,">="&$A6,Holidays!$A$2:$A$1000,"<="&EOMONTH($A6,0),Holidays!$C$2:$C$1000,"QLD") | F6: =COUNTIFS(Holidays!$A$2:$A$1000,">="&$A6,Holidays!$A$2:$A$1000,"<="&EOMONTH($A6,0),Holidays!$C$2:$C$1000,"SA") | G6: =COUNTIFS(Holidays!$A$2:$A$1000,">="&$A6,Holidays!$A$2:$A$1000,"<="&EOMONTH($A6,0),Holidays!$C$2:$C$1000,"WA") | H6: =($B6-C6+C6*PH_Roster*(1+PH_Loading))/($B6-C6+C6*PH_Roster) | I6: =($B6-D6+D6*PH_Roster*(1+PH_Loading))/($B6-D6+D6*PH_Roster) | J6: =($B6-E6+E6*PH_Roster*(1+PH_Loading))/($B6-E6+E6*PH_Roster) | K6: =($B6-F6+F6*PH_Roster*(1+PH_Loading))/($B6-F6+F6*PH_Roster) | L6: =($B6-G6+G6*PH_Roster*(1+PH_Loading))/($B6-G6+G6*PH_Roster) | M6: =EXP(SUMPRODUCT((WageDates<=$A6)*(WageDates<>"")*LN(1+WageRates)))
A7: 45717 | B7: =DAY(EOMONTH(A7,0)) | C7: =COUNTIFS(Holidays!$A$2:$A$1000,">="&$A7,Holidays!$A$2:$A$1000,"<="&EOMONTH($A7,0),Holidays!$C$2:$C$1000,"NSW") | D7: =COUNTIFS(Holidays!$A$2:$A$1000,">="&$A7,Holidays!$A$2:$A$1000,"<="&EOMONTH($A7,0),Holidays!$C$2:$C$1000,"VIC") | E7: =COUNTIFS(Holidays!$A$2:$A$1000,">="&$A7,Holidays!$A$2:$A$1000,"<="&EOMONTH($A7,0),Holidays!$C$2:$C$1000,"QLD") | F7: =COUNTIFS(Holidays!$A$2:$A$1000,">="&$A7,Holidays!$A$2:$A$1000,"<="&EOMONTH($A7,0),Holidays!$C$2:$C$1000,"SA") | G7: =COUNTIFS(Holidays!$A$2:$A$1000,">="&$A7,Holidays!$A$2:$A$1000,"<="&EOMONTH($A7,0),Holidays!$C$2:$C$1000,"WA") | H7: =($B7-C7+C7*PH_Roster*(1+PH_Loading))/($B7-C7+C7*PH_Roster) | I7: =($B7-D7+D7*PH_Roster*(1+PH_Loading))/($B7-D7+D7*PH_Roster) | J7: =($B7-E7+E7*PH_Roster*(1+PH_Loading))/($B7-E7+E7*PH_Roster) | K7: =($B7-F7+F7*PH_Roster*(1+PH_Loading))/($B7-F7+F7*PH_Roster) | L7: =($B7-G7+G7*PH_Roster*(1+PH_Loading))/($B7-G7+G7*PH_Roster) | M7: =EXP(SUMPRODUCT((WageDates<=$A7)*(WageDates<>"")*LN(1+WageRates)))
A8: 45748 | B8: =DAY(EOMONTH(A8,0)) | C8: =COUNTIFS(Holidays!$A$2:$A$1000,">="&$A8,Holidays!$A$2:$A$1000,"<="&EOMONTH($A8,0),Holidays!$C$2:$C$1000,"NSW") | D8: =COUNTIFS(Holidays!$A$2:$A$1000,">="&$A8,Holidays!$A$2:$A$1000,"<="&EOMONTH($A8,0),Holidays!$C$2:$C$1000,"VIC") | E8: =COUNTIFS(Holidays!$A$2:$A$1000,">="&$A8,Holidays!$A$2:$A$1000,"<="&EOMONTH($A8,0),Holidays!$C$2:$C$1000,"QLD") | F8: =COUNTIFS(Holidays!$A$2:$A$1000,">="&$A8,Holidays!$A$2:$A$1000,"<="&EOMONTH($A8,0),Holidays!$C$2:$C$1000,"SA") | G8: =COUNTIFS(Holidays!$A$2:$A$1000,">="&$A8,Holidays!$A$2:$A$1000,"<="&EOMONTH($A8,0),Holidays!$C$2:$C$1000,"WA") | H8: =($B8-C8+C8*PH_Roster*(1+PH_Loading))/($B8-C8+C8*PH_Roster) | I8: =($B8-D8+D8*PH_Roster*(1+PH_Loading))/($B8-D8+D8*PH_Roster) | J8: =($B8-E8+E8*PH_Roster*(1+PH_Loading))/($B8-E8+E8*PH_Roster) | K8: =($B8-F8+F8*PH_Roster*(1+PH_Loading))/($B8-F8+F8*PH_Roster) | L8: =($B8-G8+G8*PH_Roster*(1+PH_Loading))/($B8-G8+G8*PH_Roster) | M8: =EXP(SUMPRODUCT((WageDates<=$A8)*(WageDates<>"")*LN(1+WageRates)))
A9: 45778 | B9: =DAY(EOMONTH(A9,0)) | C9: =COUNTIFS(Holidays!$A$2:$A$1000,">="&$A9,Holidays!$A$2:$A$1000,"<="&EOMONTH($A9,0),Holidays!$C$2:$C$1000,"NSW") | D9: =COUNTIFS(Holidays!$A$2:$A$1000,">="&$A9,Holidays!$A$2:$A$1000,"<="&EOMONTH($A9,0),Holidays!$C$2:$C$1000,"VIC") | E9: =COUNTIFS(Holidays!$A$2:$A$1000,">="&$A9,Holidays!$A$2:$A$1000,"<="&EOMONTH($A9,0),Holidays!$C$2:$C$1000,"QLD") | F9: =COUNTIFS(Holidays!$A$2:$A$1000,">="&$A9,Holidays!$A$2:$A$1000,"<="&EOMONTH($A9,0),Holidays!$C$2:$C$1000,"SA") | G9: =COUNTIFS(Holidays!$A$2:$A$1000,">="&$A9,Holidays!$A$2:$A$1000,"<="&EOMONTH($A9,0),Holidays!$C$2:$C$1000,"WA") | H9: =($B9-C9+C9*PH_Roster*(1+PH_Loading))/($B9-C9+C9*PH_Roster) | I9: =($B9-D9+D9*PH_Roster*(1+PH_Loading))/($B9-D9+D9*PH_Roster) | J9: =($B9-E9+E9*PH_Roster*(1+PH_Loading))/($B9-E9+E9*PH_Roster) | K9: =($B9-F9+F9*PH_Roster*(1+PH_Loading))/($B9-F9+F9*PH_Roster) | L9: =($B9-G9+G9*PH_Roster*(1+PH_Loading))/($B9-G9+G9*PH_Roster) | M9: =EXP(SUMPRODUCT((WageDates<=$A9)*(WageDates<>"")*LN(1+WageRates)))
A10: 45809 | B10: =DAY(EOMONTH(A10,0)) | C10: =COUNTIFS(Holidays!$A$2:$A$1000,">="&$A10,Holidays!$A$2:$A$1000,"<="&EOMONTH($A10,0),Holidays!$C$2:$C$1000,"NSW") | D10: =COUNTIFS(Holidays!$A$2:$A$1000,">="&$A10,Holidays!$A$2:$A$1000,"<="&EOMONTH($A10,0),Holidays!$C$2:$C$1000,"VIC") | E10: =COUNTIFS(Holidays!$A$2:$A$1000,">="&$A10,Holidays!$A$2:$A$1000,"<="&EOMONTH($A10,0),Holidays!$C$2:$C$1000,"QLD") | F10: =COUNTIFS(Holidays!$A$2:$A$1000,">="&$A10,Holidays!$A$2:$A$1000,"<="&EOMONTH($A10,0),Holidays!$C$2:$C$1000,"SA") | G10: =COUNTIFS(Holidays!$A$2:$A$1000,">="&$A10,Holidays!$A$2:$A$1000,"<="&EOMONTH($A10,0),Holidays!$C$2:$C$1000,"WA") | H10: =($B10-C10+C10*PH_Roster*(1+PH_Loading))/($B10-C10+C10*PH_Roster) | I10: =($B10-D10+D10*PH_Roster*(1+PH_Loading))/($B10-D10+D10*PH_Roster) | J10: =($B10-E10+E10*PH_Roster*(1+PH_Loading))/($B10-E10+E10*PH_Roster) | K10: =($B10-F10+F10*PH_Roster*(1+PH_Loading))/($B10-F10+F10*PH_Roster) | L10: =($B10-G10+G10*PH_Roster*(1+PH_Loading))/($B10-G10+G10*PH_Roster) | M10: =EXP(SUMPRODUCT((WageDates<=$A10)*(WageDates<>"")*LN(1+WageRates)))
A11: 45839 | B11: =DAY(EOMONTH(A11,0)) | C11: =COUNTIFS(Holidays!$A$2:$A$1000,">="&$A11,Holidays!$A$2:$A$1000,"<="&EOMONTH($A11,0),Holidays!$C$2:$C$1000,"NSW") | D11: =COUNTIFS(Holidays!$A$2:$A$1000,">="&$A11,Holidays!$A$2:$A$1000,"<="&EOMONTH($A11,0),Holidays!$C$2:$C$1000,"VIC") | E11: =COUNTIFS(Holidays!$A$2:$A$1000,">="&$A11,Holidays!$A$2:$A$1000,"<="&EOMONTH($A11,0),Holidays!$C$2:$C$1000,"QLD") | F11: =COUNTIFS(Holidays!$A$2:$A$1000,">="&$A11,Holidays!$A$2:$A$1000,"<="&EOMONTH($A11,0),Holidays!$C$2:$C$1000,"SA") | G11: =COUNTIFS(Holidays!$A$2:$A$1000,">="&$A11,Holidays!$A$2:$A$1000,"<="&EOMONTH($A11,0),Holidays!$C$2:$C$1000,"WA") | H11: =($B11-C11+C11*PH_Roster*(1+PH_Loading))/($B11-C11+C11*PH_Roster) | I11: =($B11-D11+D11*PH_Roster*(1+PH_Loading))/($B11-D11+D11*PH_Roster) | J11: =($B11-E11+E11*PH_Roster*(1+PH_Loading))/($B11-E11+E11*PH_Roster) | K11: =($B11-F11+F11*PH_Roster*(1+PH_Loading))/($B11-F11+F11*PH_Roster) | L11: =($B11-G11+G11*PH_Roster*(1+PH_Loading))/($B11-G11+G11*PH_Roster) | M11: =EXP(SUMPRODUCT((WageDates<=$A11)*(WageDates<>"")*LN(1+WageRates)))
A12: 45870 | B12: =DAY(EOMONTH(A12,0)) | C12: =COUNTIFS(Holidays!$A$2:$A$1000,">="&$A12,Holidays!$A$2:$A$1000,"<="&EOMONTH($A12,0),Holidays!$C$2:$C$1000,"NSW") | D12: =COUNTIFS(Holidays!$A$2:$A$1000,">="&$A12,Holidays!$A$2:$A$1000,"<="&EOMONTH($A12,0),Holidays!$C$2:$C$1000,"VIC") | E12: =COUNTIFS(Holidays!$A$2:$A$1000,">="&$A12,Holidays!$A$2:$A$1000,"<="&EOMONTH($A12,0),Holidays!$C$2:$C$1000,"QLD") | F12: =COUNTIFS(Holidays!$A$2:$A$1000,">="&$A12,Holidays!$A$2:$A$1000,"<="&EOMONTH($A12,0),Holidays!$C$2:$C$1000,"SA") | G12: =COUNTIFS(Holidays!$A$2:$A$1000,">="&$A12,Holidays!$A$2:$A$1000,"<="&EOMONTH($A12,0),Holidays!$C$2:$C$1000,"WA") | H12: =($B12-C12+C12*PH_Roster*(1+PH_Loading))/($B12-C12+C12*PH_Roster) | I12: =($B12-D12+D12*PH_Roster*(1+PH_Loading))/($B12-D12+D12*PH_Roster) | J12: =($B12-E12+E12*PH_Roster*(1+PH_Loading))/($B12-E12+E12*PH_Roster) | K12: =($B12-F12+F12*PH_Roster*(1+PH_Loading))/($B12-F12+F12*PH_Roster) | L12: =($B12-G12+G12*PH_Roster*(1+PH_Loading))/($B12-G12+G12*PH_Roster) | M12: =EXP(SUMPRODUCT((WageDates<=$A12)*(WageDates<>"")*LN(1+WageRates)))
A13: 45901 | B13: =DAY(EOMONTH(A13,0)) | C13: =COUNTIFS(Holidays!$A$2:$A$1000,">="&$A13,Holidays!$A$2:$A$1000,"<="&EOMONTH($A13,0),Holidays!$C$2:$C$1000,"NSW") | D13: =COUNTIFS(Holidays!$A$2:$A$1000,">="&$A13,Holidays!$A$2:$A$1000,"<="&EOMONTH($A13,0),Holidays!$C$2:$C$1000,"VIC") | E13: =COUNTIFS(Holidays!$A$2:$A$1000,">="&$A13,Holidays!$A$2:$A$1000,"<="&EOMONTH($A13,0),Holidays!$C$2:$C$1000,"QLD") | F13: =COUNTIFS(Holidays!$A$2:$A$1000,">="&$A13,Holidays!$A$2:$A$1000,"<="&EOMONTH($A13,0),Holidays!$C$2:$C$1000,"SA") | G13: =COUNTIFS(Holidays!$A$2:$A$1000,">="&$A13,Holidays!$A$2:$A$1000,"<="&EOMONTH($A13,0),Holidays!$C$2:$C$1000,"WA") | H13: =($B13-C13+C13*PH_Roster*(1+PH_Loading))/($B13-C13+C13*PH_Roster) | I13: =($B13-D13+D13*PH_Roster*(1+PH_Loading))/($B13-D13+D13*PH_Roster) | J13: =($B13-E13+E13*PH_Roster*(1+PH_Loading))/($B13-E13+E13*PH_Roster) | K13: =($B13-F13+F13*PH_Roster*(1+PH_Loading))/($B13-F13+F13*PH_Roster) | L13: =($B13-G13+G13*PH_Roster*(1+PH_Loading))/($B13-G13+G13*PH_Roster) | M13: =EXP(SUMPRODUCT((WageDates<=$A13)*(WageDates<>"")*LN(1+WageRates)))
A14: 45931 | B14: =DAY(EOMONTH(A14,0)) | C14: =COUNTIFS(Holidays!$A$2:$A$1000,">="&$A14,Holidays!$A$2:$A$1000,"<="&EOMONTH($A14,0),Holidays!$C$2:$C$1000,"NSW") | D14: =COUNTIFS(Holidays!$A$2:$A$1000,">="&$A14,Holidays!$A$2:$A$1000,"<="&EOMONTH($A14,0),Holidays!$C$2:$C$1000,"VIC") | E14: =COUNTIFS(Holidays!$A$2:$A$1000,">="&$A14,Holidays!$A$2:$A$1000,"<="&EOMONTH($A14,0),Holidays!$C$2:$C$1000,"QLD") | F14: =COUNTIFS(Holidays!$A$2:$A$1000,">="&$A14,Holidays!$A$2:$A$1000,"<="&EOMONTH($A14,0),Holidays!$C$2:$C$1000,"SA") | G14: =COUNTIFS(Holidays!$A$2:$A$1000,">="&$A14,Holidays!$A$2:$A$1000,"<="&EOMONTH($A14,0),Holidays!$C$2:$C$1000,"WA") | H14: =($B14-C14+C14*PH_Roster*(1+PH_Loading))/($B14-C14+C14*PH_Roster) | I14: =($B14-D14+D14*PH_Roster*(1+PH_Loading))/($B14-D14+D14*PH_Roster) | J14: =($B14-E14+E14*PH_Roster*(1+PH_Loading))/($B14-E14+E14*PH_Roster) | K14: =($B14-F14+F14*PH_Roster*(1+PH_Loading))/($B14-F14+F14*PH_Roster) | L14: =($B14-G14+G14*PH_Roster*(1+PH_Loading))/($B14-G14+G14*PH_Roster) | M14: =EXP(SUMPRODUCT((WageDates<=$A14)*(WageDates<>"")*LN(1+WageRates)))
A15: 45962 | B15: =DAY(EOMONTH(A15,0)) | C15: =COUNTIFS(Holidays!$A$2:$A$1000,">="&$A15,Holidays!$A$2:$A$1000,"<="&EOMONTH($A15,0),Holidays!$C$2:$C$1000,"NSW") | D15: =COUNTIFS(Holidays!$A$2:$A$1000,">="&$A15,Holidays!$A$2:$A$1000,"<="&EOMONTH($A15,0),Holidays!$C$2:$C$1000,"VIC") | E15: =COUNTIFS(Holidays!$A$2:$A$1000,">="&$A15,Holidays!$A$2:$A$1000,"<="&EOMONTH($A15,0),Holidays!$C$2:$C$1000,"QLD") | F15: =COUNTIFS(Holidays!$A$2:$A$1000,">="&$A15,Holidays!$A$2:$A$1000,"<="&EOMONTH($A15,0),Holidays!$C$2:$C$1000,"SA") | G15: =COUNTIFS(Holidays!$A$2:$A$1000,">="&$A15,Holidays!$A$2:$A$1000,"<="&EOMONTH($A15,0),Holidays!$C$2:$C$1000,"WA") | H15: =($B15-C15+C15*PH_Roster*(1+PH_Loading))/($B15-C15+C15*PH_Roster) | I15: =($B15-D15+D15*PH_Roster*(1+PH_Loading))/($B15-D15+D15*PH_Roster) | J15: =($B15-E15+E15*PH_Roster*(1+PH_Loading))/($B15-E15+E15*PH_Roster) | K15: =($B15-F15+F15*PH_Roster*(1+PH_Loading))/($B15-F15+F15*PH_Roster) | L15: =($B15-G15+G15*PH_Roster*(1+PH_Loading))/($B15-G15+G15*PH_Roster) | M15: =EXP(SUMPRODUCT((WageDates<=$A15)*(WageDates<>"")*LN(1+WageRates)))
A16: 45992 | B16: =DAY(EOMONTH(A16,0)) | C16: =COUNTIFS(Holidays!$A$2:$A$1000,">="&$A16,Holidays!$A$2:$A$1000,"<="&EOMONTH($A16,0),Holidays!$C$2:$C$1000,"NSW") | D16: =COUNTIFS(Holidays!$A$2:$A$1000,">="&$A16,Holidays!$A$2:$A$1000,"<="&EOMONTH($A16,0),Holidays!$C$2:$C$1000,"VIC") | E16: =COUNTIFS(Holidays!$A$2:$A$1000,">="&$A16,Holidays!$A$2:$A$1000,"<="&EOMONTH($A16,0),Holidays!$C$2:$C$1000,"QLD") | F16: =COUNTIFS(Holidays!$A$2:$A$1000,">="&$A16,Holidays!$A$2:$A$1000,"<="&EOMONTH($A16,0),Holidays!$C$2:$C$1000,"SA") | G16: =COUNTIFS(Holidays!$A$2:$A$1000,">="&$A16,Holidays!$A$2:$A$1000,"<="&EOMONTH($A16,0),Holidays!$C$2:$C$1000,"WA") | H16: =($B16-C16+C16*PH_Roster*(1+PH_Loading))/($B16-C16+C16*PH_Roster) | I16: =($B16-D16+D16*PH_Roster*(1+PH_Loading))/($B16-D16+D16*PH_Roster) | J16: =($B16-E16+E16*PH_Roster*(1+PH_Loading))/($B16-E16+E16*PH_Roster) | K16: =($B16-F16+F16*PH_Roster*(1+PH_Loading))/($B16-F16+F16*PH_Roster) | L16: =($B16-G16+G16*PH_Roster*(1+PH_Loading))/($B16-G16+G16*PH_Roster) | M16: =EXP(SUMPRODUCT((WageDates<=$A16)*(WageDates<>"")*LN(1+WageRates)))
... A52: 47088 | B52: =DAY(EOMONTH(A52,0)) | C52: =COUNTIFS(Holidays!$A$2:$A$1000,">="&$A52,Holidays!$A$2:$A$1000,"<="&EOMONTH($A52,0),Holidays!$C$2:$C$1000,"NSW") | D52: =COUNTIFS(Holidays!$A$2:$A$1000,">="&$A52,Holidays!$A$2:$A$1000,"<="&EOMONTH($A52,0),Holidays!$C$2:$C$1000,"VIC") | E52: =COUNTIFS(Holidays!$A$2:$A$1000,">="&$A52,Holidays!$A$2:$A$1000,"<="&EOMONTH($A52,0),Holidays!$C$2:$C$1000,"QLD") | F52: =COUNTIFS(Holidays!$A$2:$A$1000,">="&$A52,Holidays!$A$2:$A$1000,"<="&EOMONTH($A52,0),Holidays!$C$2:$C$1000,"SA") | G52: =COUNTIFS(Holidays!$A$2:$A$1000,">="&$A52,Holidays!$A$2:$A$1000,"<="&EOMONTH($A52,0),Holidays!$C$2:$C$1000,"WA") | H52: =($B52-C52+C52*PH_Roster*(1+PH_Loading))/($B52-C52+C52*PH_Roster) | I52: =($B52-D52+D52*PH_Roster*(1+PH_Loading))/($B52-D52+D52*PH_Roster) | J52: =($B52-E52+E52*PH_Roster*(1+PH_Loading))/($B52-E52+E52*PH_Roster) | K52: =($B52-F52+F52*PH_Roster*(1+PH_Loading))/($B52-F52+F52*PH_Roster) | L52: =($B52-G52+G52*PH_Roster*(1+PH_Loading))/($B52-G52+G52*PH_Roster) | M52: =EXP(SUMPRODUCT((WageDates<=$A52)*(WageDates<>"")*LN(1+WageRates)))

Sheet Checks
A1: Checks
A3: Overall | B3: =IF(COUNTIF(D6:D150,"ERROR")=0,"ALL CHECKS OK","CHECK ERRORS") | C3: =COUNTIF(D6:D150,"WARN")&" warning(s)"
A5: Check | B5: Value | C5: Expected | D5: Result
A6: =Inputs!$A$36&": actual rows in Data_Actuals (one per month)" | B6: =COUNTIFS(Data_Actuals!$B$2:$B$5000,Inputs!$A$36,Data_Actuals!$A$2:$A$5000,"<="&LastActual) | C6: =(YEAR(LastActual)-2025)*12+MONTH(LastActual) | D6: =IF(ABS(B6-C6)<=MAX(1,ABS(C6)*0.000001),"OK","ERROR")
A7: =Inputs!$A$37&": actual rows in Data_Actuals (one per month)" | B7: =COUNTIFS(Data_Actuals!$B$2:$B$5000,Inputs!$A$37,Data_Actuals!$A$2:$A$5000,"<="&LastActual) | C7: =(YEAR(LastActual)-2025)*12+MONTH(LastActual) | D7: =IF(ABS(B7-C7)<=MAX(1,ABS(C7)*0.000001),"OK","ERROR")
A8: =Inputs!$A$38&": actual rows in Data_Actuals (one per month)" | B8: =COUNTIFS(Data_Actuals!$B$2:$B$5000,Inputs!$A$38,Data_Actuals!$A$2:$A$5000,"<="&LastActual) | C8: =(YEAR(LastActual)-2025)*12+MONTH(LastActual) | D8: =IF(ABS(B8-C8)<=MAX(1,ABS(C8)*0.000001),"OK","ERROR")
A9: =Inputs!$A$39&": actual rows in Data_Actuals (one per month)" | B9: =COUNTIFS(Data_Actuals!$B$2:$B$5000,Inputs!$A$39,Data_Actuals!$A$2:$A$5000,"<="&LastActual) | C9: =(YEAR(LastActual)-2025)*12+MONTH(LastActual) | D9: =IF(ABS(B9-C9)<=MAX(1,ABS(C9)*0.000001),"OK","ERROR")
A10: =Inputs!$A$40&": actual rows in Data_Actuals (one per month)" | B10: =COUNTIFS(Data_Actuals!$B$2:$B$5000,Inputs!$A$40,Data_Actuals!$A$2:$A$5000,"<="&LastActual) | C10: =(YEAR(LastActual)-2025)*12+MONTH(LastActual) | D10: =IF(ABS(B10-C10)<=MAX(1,ABS(C10)*0.000001),"OK","ERROR")
A11: =Inputs!$A$41&": actual rows in Data_Actuals (one per month)" | B11: =COUNTIFS(Data_Actuals!$B$2:$B$5000,Inputs!$A$41,Data_Actuals!$A$2:$A$5000,"<="&LastActual) | C11: =(YEAR(LastActual)-2025)*12+MONTH(LastActual) | D11: =IF(ABS(B11-C11)<=MAX(1,ABS(C11)*0.000001),"OK","ERROR")
A12: =Inputs!$A$42&": actual rows in Data_Actuals (one per month)" | B12: =COUNTIFS(Data_Actuals!$B$2:$B$5000,Inputs!$A$42,Data_Actuals!$A$2:$A$5000,"<="&LastActual) | C12: =(YEAR(LastActual)-2025)*12+MONTH(LastActual) | D12: =IF(ABS(B12-C12)<=MAX(1,ABS(C12)*0.000001),"OK","ERROR")
A13: =Inputs!$A$43&": actual rows in Data_Actuals (one per month)" | B13: =COUNTIFS(Data_Actuals!$B$2:$B$5000,Inputs!$A$43,Data_Actuals!$A$2:$A$5000,"<="&LastActual) | C13: =(YEAR(LastActual)-2025)*12+MONTH(LastActual) | D13: =IF(ABS(B13-C13)<=MAX(1,ABS(C13)*0.000001),"OK","ERROR")
A14: =Inputs!$A$44&": actual rows in Data_Actuals (one per month)" | B14: =COUNTIFS(Data_Actuals!$B$2:$B$5000,Inputs!$A$44,Data_Actuals!$A$2:$A$5000,"<="&LastActual) | C14: =(YEAR(LastActual)-2025)*12+MONTH(LastActual) | D14: =IF(ABS(B14-C14)<=MAX(1,ABS(C14)*0.000001),"OK","ERROR")
A15: =Inputs!$A$45&": actual rows in Data_Actuals (one per month)" | B15: =COUNTIFS(Data_Actuals!$B$2:$B$5000,Inputs!$A$45,Data_Actuals!$A$2:$A$5000,"<="&LastActual) | C15: =(YEAR(LastActual)-2025)*12+MONTH(LastActual) | D15: =IF(ABS(B15-C15)<=MAX(1,ABS(C15)*0.000001),"OK","ERROR")
A16: =Inputs!$A$36&": plan sales present for every forecast month" | B16: =COUNTIFS(Plan_Inputs!$B$2:$B$5000,Inputs!$A$36,Plan_Inputs!$A$2:$A$5000,">"&LastActual,Plan_Inputs!$C$2:$C$5000,">0") | C16: =(2028-YEAR(LastActual))*12+12-MONTH(LastActual) | D16: =IF(ABS(B16-C16)<=MAX(1,ABS(C16)*0.000001),"OK","ERROR")
A17: =Inputs!$A$37&": plan sales present for every forecast month" | B17: =COUNTIFS(Plan_Inputs!$B$2:$B$5000,Inputs!$A$37,Plan_Inputs!$A$2:$A$5000,">"&LastActual,Plan_Inputs!$C$2:$C$5000,">0") | C17: =(2028-YEAR(LastActual))*12+12-MONTH(LastActual) | D17: =IF(ABS(B17-C17)<=MAX(1,ABS(C17)*0.000001),"OK","ERROR")
A18: =Inputs!$A$38&": plan sales present for every forecast month" | B18: =COUNTIFS(Plan_Inputs!$B$2:$B$5000,Inputs!$A$38,Plan_Inputs!$A$2:$A$5000,">"&LastActual,Plan_Inputs!$C$2:$C$5000,">0") | C18: =(2028-YEAR(LastActual))*12+12-MONTH(LastActual) | D18: =IF(ABS(B18-C18)<=MAX(1,ABS(C18)*0.000001),"OK","ERROR")
A19: =Inputs!$A$39&": plan sales present for every forecast month" | B19: =COUNTIFS(Plan_Inputs!$B$2:$B$5000,Inputs!$A$39,Plan_Inputs!$A$2:$A$5000,">"&LastActual,Plan_Inputs!$C$2:$C$5000,">0") | C19: =(2028-YEAR(LastActual))*12+12-MONTH(LastActual) | D19: =IF(ABS(B19-C19)<=MAX(1,ABS(C19)*0.000001),"OK","ERROR")
A20: =Inputs!$A$40&": plan sales present for every forecast month" | B20: =COUNTIFS(Plan_Inputs!$B$2:$B$5000,Inputs!$A$40,Plan_Inputs!$A$2:$A$5000,">"&LastActual,Plan_Inputs!$C$2:$C$5000,">0") | C20: =(2028-YEAR(LastActual))*12+12-MONTH(LastActual) | D20: =IF(ABS(B20-C20)<=MAX(1,ABS(C20)*0.000001),"OK","ERROR")
A21: =Inputs!$A$41&": plan sales present for every forecast month" | B21: =COUNTIFS(Plan_Inputs!$B$2:$B$5000,Inputs!$A$41,Plan_Inputs!$A$2:$A$5000,">"&LastActual,Plan_Inputs!$C$2:$C$5000,">0") | C21: =(2028-YEAR(LastActual))*12+12-MONTH(LastActual) | D21: =IF(ABS(B21-C21)<=MAX(1,ABS(C21)*0.000001),"OK","ERROR")
A22: =Inputs!$A$42&": plan sales present for every forecast month" | B22: =COUNTIFS(Plan_Inputs!$B$2:$B$5000,Inputs!$A$42,Plan_Inputs!$A$2:$A$5000,">"&LastActual,Plan_Inputs!$C$2:$C$5000,">0") | C22: =(2028-YEAR(LastActual))*12+12-MONTH(LastActual) | D22: =IF(ABS(B22-C22)<=MAX(1,ABS(C22)*0.000001),"OK","ERROR")
A23: =Inputs!$A$43&": plan sales present for every forecast month" | B23: =COUNTIFS(Plan_Inputs!$B$2:$B$5000,Inputs!$A$43,Plan_Inputs!$A$2:$A$5000,">"&LastActual,Plan_Inputs!$C$2:$C$5000,">0") | C23: =(2028-YEAR(LastActual))*12+12-MONTH(LastActual) | D23: =IF(ABS(B23-C23)<=MAX(1,ABS(C23)*0.000001),"OK","ERROR")
A24: Unknown site codes in Data_Actuals | B24: =SUMPRODUCT((Data_Actuals!$B$2:$B$5000<>"")*(COUNTIF(SiteCodes,Data_Actuals!$B$2:$B$5000)=0)) | C24: =0 | D24: =IF(ABS(B24-C24)<=MAX(1,ABS(C24)*0.000001),"OK","ERROR")
A25: At least 12 actual months (same month last year needs them) | B25: =(YEAR(LastActual)-2025)*12+MONTH(LastActual) | C25: =12 | D25: =IF(B25>=C25,"OK","ERROR")
A26: National sales = sum of 8 regions (IDCs excluded) | B26: =SUM(National!E15:E62) | C26: =SUM('NSW-1'!E15:E62)+SUM('VIC-1'!E15:E62)+SUM('QLD-1'!E15:E62)+SUM('NSW-2'!E15:E62)+SUM('VIC-2'!E15:E62)+SUM('QLD-2'!E15:E62)+SUM('SA-1'!E15:E62)+SUM('WA-1'!E15:E62) | D26: =IF(ABS(B26-C26)<=MAX(1,ABS(C26)*0.000001),"OK","ERROR")
A27: National total payroll = sum of all 10 sites | B27: =SUM(National!J15:J62) | C27: =SUM('NSW-1'!J15:J62)+SUM('VIC-1'!J15:J62)+SUM('QLD-1'!J15:J62)+SUM('NSW-2'!J15:J62)+SUM('VIC-2'!J15:J62)+SUM('QLD-2'!J15:J62)+SUM('SA-1'!J15:J62)+SUM('WA-1'!J15:J62)+SUM('IDC-NSW'!J15:J62)+SUM('IDC-VIC'!J15:J62) | D27: =IF(ABS(B27-C27)<=MAX(1,ABS(C27)*0.000001),"OK","ERROR")
A28: Staff + leadership = total payroll (national, all months) | B28: =SUM(National!H15:I62) | C28: =SUM(National!J15:J62) | D28: =IF(ABS(B28-C28)<=MAX(1,ABS(C28)*0.000001),"OK","ERROR")
A29: Cases_Forecast: adjustments typed in actual months (ignored) | B29: =SUMPRODUCT((Cases_Forecast!$B$8:$B$55="Actual")*(Cases_Forecast!$N$8:$W$55<>"")) | C29: =0 | D29: =IF(B29=C29,"OK","WARN")
A30: Cases_Forecast: overrides typed in actual months (ignored) | B30: =SUMPRODUCT((Cases_Forecast!$B$8:$B$55="Actual")*(Cases_Forecast!$Y$8:$AH$55<>"")) | C30: =0 | D30: =IF(B30=C30,"OK","WARN")
A31: CPLH_Forecast: adjustments typed in actual months (ignored) | B31: =SUMPRODUCT((CPLH_Forecast!$B$8:$B$55="Actual")*(CPLH_Forecast!$N$8:$W$55<>"")) | C31: =0 | D31: =IF(B31=C31,"OK","WARN")
A32: CPLH_Forecast: overrides typed in actual months (ignored) | B32: =SUMPRODUCT((CPLH_Forecast!$B$8:$B$55="Actual")*(CPLH_Forecast!$Y$8:$AH$55<>"")) | C32: =0 | D32: =IF(B32=C32,"OK","WARN")
A33: =Inputs!$A$36&": forecast months where CPLH moves more than the tolerance vs LY" | B33: =COUNTIF('NSW-1'!AG15:AG62,">"&CPLHTol)+COUNTIF('NSW-1'!AG15:AG62,"<"&-CPLHTol) | C33: =0 | D33: =IF(B33=C33,"OK","WARN")
A34: =Inputs!$A$37&": forecast months where CPLH moves more than the tolerance vs LY" | B34: =COUNTIF('VIC-1'!AG15:AG62,">"&CPLHTol)+COUNTIF('VIC-1'!AG15:AG62,"<"&-CPLHTol) | C34: =0 | D34: =IF(B34=C34,"OK","WARN")
A35: =Inputs!$A$38&": forecast months where CPLH moves more than the tolerance vs LY" | B35: =COUNTIF('QLD-1'!AG15:AG62,">"&CPLHTol)+COUNTIF('QLD-1'!AG15:AG62,"<"&-CPLHTol) | C35: =0 | D35: =IF(B35=C35,"OK","WARN")
A36: =Inputs!$A$39&": forecast months where CPLH moves more than the tolerance vs LY" | B36: =COUNTIF('NSW-2'!AG15:AG62,">"&CPLHTol)+COUNTIF('NSW-2'!AG15:AG62,"<"&-CPLHTol) | C36: =0 | D36: =IF(B36=C36,"OK","WARN")
A37: =Inputs!$A$40&": forecast months where CPLH moves more than the tolerance vs LY" | B37: =COUNTIF('VIC-2'!AG15:AG62,">"&CPLHTol)+COUNTIF('VIC-2'!AG15:AG62,"<"&-CPLHTol) | C37: =0 | D37: =IF(B37=C37,"OK","WARN")
A38: =Inputs!$A$41&": forecast months where CPLH moves more than the tolerance vs LY" | B38: =COUNTIF('QLD-2'!AG15:AG62,">"&CPLHTol)+COUNTIF('QLD-2'!AG15:AG62,"<"&-CPLHTol) | C38: =0 | D38: =IF(B38=C38,"OK","WARN")
A39: =Inputs!$A$42&": forecast months where CPLH moves more than the tolerance vs LY" | B39: =COUNTIF('SA-1'!AG15:AG62,">"&CPLHTol)+COUNTIF('SA-1'!AG15:AG62,"<"&-CPLHTol) | C39: =0 | D39: =IF(B39=C39,"OK","WARN")
A40: =Inputs!$A$43&": forecast months where CPLH moves more than the tolerance vs LY" | B40: =COUNTIF('WA-1'!AG15:AG62,">"&CPLHTol)+COUNTIF('WA-1'!AG15:AG62,"<"&-CPLHTol) | C40: =0 | D40: =IF(B40=C40,"OK","WARN")
A41: =Inputs!$A$44&": forecast months where CPLH moves more than the tolerance vs LY" | B41: =COUNTIF('IDC-NSW'!AG15:AG62,">"&CPLHTol)+COUNTIF('IDC-NSW'!AG15:AG62,"<"&-CPLHTol) | C41: =0 | D41: =IF(B41=C41,"OK","WARN")
A42: =Inputs!$A$45&": forecast months where CPLH moves more than the tolerance vs LY" | B42: =COUNTIF('IDC-VIC'!AG15:AG62,">"&CPLHTol)+COUNTIF('IDC-VIC'!AG15:AG62,"<"&-CPLHTol) | C42: =0 | D42: =IF(B42=C42,"OK","WARN")
A43: =Inputs!$A$36&": plan CPLH present for every forecast month (blank = same month LY)" | B43: =COUNTIFS('NSW-1'!AH15:AH62,">0",'NSW-1'!D15:D62,"Forecast") | C43: =(2028-YEAR(LastActual))*12+12-MONTH(LastActual) | D43: =IF(B43=C43,"OK","WARN")
A44: =Inputs!$A$37&": plan CPLH present for every forecast month (blank = same month LY)" | B44: =COUNTIFS('VIC-1'!AH15:AH62,">0",'VIC-1'!D15:D62,"Forecast") | C44: =(2028-YEAR(LastActual))*12+12-MONTH(LastActual) | D44: =IF(B44=C44,"OK","WARN")
A45: =Inputs!$A$38&": plan CPLH present for every forecast month (blank = same month LY)" | B45: =COUNTIFS('QLD-1'!AH15:AH62,">0",'QLD-1'!D15:D62,"Forecast") | C45: =(2028-YEAR(LastActual))*12+12-MONTH(LastActual) | D45: =IF(B45=C45,"OK","WARN")
A46: =Inputs!$A$39&": plan CPLH present for every forecast month (blank = same month LY)" | B46: =COUNTIFS('NSW-2'!AH15:AH62,">0",'NSW-2'!D15:D62,"Forecast") | C46: =(2028-YEAR(LastActual))*12+12-MONTH(LastActual) | D46: =IF(B46=C46,"OK","WARN")
A47: =Inputs!$A$40&": plan CPLH present for every forecast month (blank = same month LY)" | B47: =COUNTIFS('VIC-2'!AH15:AH62,">0",'VIC-2'!D15:D62,"Forecast") | C47: =(2028-YEAR(LastActual))*12+12-MONTH(LastActual) | D47: =IF(B47=C47,"OK","WARN")
A48: =Inputs!$A$41&": plan CPLH present for every forecast month (blank = same month LY)" | B48: =COUNTIFS('QLD-2'!AH15:AH62,">0",'QLD-2'!D15:D62,"Forecast") | C48: =(2028-YEAR(LastActual))*12+12-MONTH(LastActual) | D48: =IF(B48=C48,"OK","WARN")
A49: =Inputs!$A$42&": plan CPLH present for every forecast month (blank = same month LY)" | B49: =COUNTIFS('SA-1'!AH15:AH62,">0",'SA-1'!D15:D62,"Forecast") | C49: =(2028-YEAR(LastActual))*12+12-MONTH(LastActual) | D49: =IF(B49=C49,"OK","WARN")
A50: =Inputs!$A$43&": plan CPLH present for every forecast month (blank = same month LY)" | B50: =COUNTIFS('WA-1'!AH15:AH62,">0",'WA-1'!D15:D62,"Forecast") | C50: =(2028-YEAR(LastActual))*12+12-MONTH(LastActual) | D50: =IF(B50=C50,"OK","WARN")
A51: =Inputs!$A$44&": plan CPLH present for every forecast month (blank = same month LY)" | B51: =COUNTIFS('IDC-NSW'!AH15:AH62,">0",'IDC-NSW'!D15:D62,"Forecast") | C51: =(2028-YEAR(LastActual))*12+12-MONTH(LastActual) | D51: =IF(B51=C51,"OK","WARN")
A52: =Inputs!$A$45&": plan CPLH present for every forecast month (blank = same month LY)" | B52: =COUNTIFS('IDC-VIC'!AH15:AH62,">0",'IDC-VIC'!D15:D62,"Forecast") | C52: =(2028-YEAR(LastActual))*12+12-MONTH(LastActual) | D52: =IF(B52=C52,"OK","WARN")
A53: =Inputs!$A$36&": chamber weights add to 100%" | B53: ='Chamber Weights'!B27 | C53: =1 | D53: =IF(ABS(B53-C53)<=0.0001,"OK","ERROR")
A54: =Inputs!$A$37&": chamber weights add to 100%" | B54: ='Chamber Weights'!C27 | C54: =1 | D54: =IF(ABS(B54-C54)<=0.0001,"OK","ERROR")
A55: =Inputs!$A$38&": chamber weights add to 100%" | B55: ='Chamber Weights'!D27 | C55: =1 | D55: =IF(ABS(B55-C55)<=0.0001,"OK","ERROR")
A56: =Inputs!$A$39&": chamber weights add to 100%" | B56: ='Chamber Weights'!E27 | C56: =1 | D56: =IF(ABS(B56-C56)<=0.0001,"OK","ERROR")
A57: =Inputs!$A$40&": chamber weights add to 100%" | B57: ='Chamber Weights'!F27 | C57: =1 | D57: =IF(ABS(B57-C57)<=0.0001,"OK","ERROR")
A58: =Inputs!$A$41&": chamber weights add to 100%" | B58: ='Chamber Weights'!G27 | C58: =1 | D58: =IF(ABS(B58-C58)<=0.0001,"OK","ERROR")
A59: =Inputs!$A$42&": chamber weights add to 100%" | B59: ='Chamber Weights'!H27 | C59: =1 | D59: =IF(ABS(B59-C59)<=0.0001,"OK","ERROR")
A60: =Inputs!$A$43&": chamber weights add to 100%" | B60: ='Chamber Weights'!I27 | C60: =1 | D60: =IF(ABS(B60-C60)<=0.0001,"OK","ERROR")
A61: =Inputs!$A$44&": chamber weights add to 100%" | B61: ='Chamber Weights'!J27 | C61: =1 | D61: =IF(ABS(B61-C61)<=0.0001,"OK","ERROR")
A62: =Inputs!$A$45&": chamber weights add to 100%" | B62: ='Chamber Weights'!K27 | C62: =1 | D62: =IF(ABS(B62-C62)<=0.0001,"OK","ERROR")
A63: National cases: sum of chambers = total (all months) | B63: =SUM(National!AJ15:AJ62)+SUM(National!AP15:AP62)+SUM(National!AV15:AV62) | C63: =SUM(National!F15:F62) | D63: =IF(ABS(B63-C63)<=MAX(1,ABS(C63)*0.000001),"OK","ERROR")
A64: National hours: sum of chambers = total (all months) | B64: =SUM(National!AK15:AK62)+SUM(National!AQ15:AQ62)+SUM(National!AW15:AW62) | C64: =SUM(National!G15:G62) | D64: =IF(ABS(B64-C64)<=MAX(1,ABS(C64)*0.000001),"OK","ERROR")
A65: National total payroll: sum of chambers = total (all months) | B65: =SUM(National!AN15:AN62)+SUM(National!AT15:AT62)+SUM(National!AZ15:AZ62) | C65: =SUM(National!J15:J62) | D65: =IF(ABS(B65-C65)<=MAX(1,ABS(C65)*0.000001),"OK","ERROR")
A66: CPLH_Breakdown FY2026: resulting national CPLH = target (blank target = skipped; -1 = unreachable) | B66: =IF(CPLH_Breakdown!B9="",0,IF(ISERROR(CPLH_Breakdown!G9),-1,CPLH_Breakdown!H9)) | C66: =IF(CPLH_Breakdown!B9="",0,CPLH_Breakdown!B9) | D66: =IF(ABS(B66-C66)<=0.0001,"OK","ERROR")
A67: CPLH_Breakdown FY2027: resulting national CPLH = target (blank target = skipped; -1 = unreachable) | B67: =IF(CPLH_Breakdown!B10="",0,IF(ISERROR(CPLH_Breakdown!G10),-1,CPLH_Breakdown!H10)) | C67: =IF(CPLH_Breakdown!B10="",0,CPLH_Breakdown!B10) | D67: =IF(ABS(B67-C67)<=0.0001,"OK","ERROR")
A68: CPLH_Breakdown FY2028: resulting national CPLH = target (blank target = skipped; -1 = unreachable) | B68: =IF(CPLH_Breakdown!B11="",0,IF(ISERROR(CPLH_Breakdown!G11),-1,CPLH_Breakdown!H11)) | C68: =IF(CPLH_Breakdown!B11="",0,CPLH_Breakdown!B11) | D68: =IF(ABS(B68-C68)<=0.0001,"OK","ERROR")

Sheet National
A1: National | 8 regions + 2 IDCs | sales exclude IDCs
A2: Model status | B2: =Checks!B3
R4: Total payroll ($m)
A5: FY | D5: Status | E5: Sales | F5: Cases picked | G5: WH hours worked | H5: Staff payroll | I5: Leadership payroll | J5: Total payroll | K5: CPLH (cases / hr) | L5: Cost per hour (staff) | M5: Cost per case (total payroll) | N5: Total payroll % sales | O5: Leadership % of total payroll | R5: Site | S5: FY2025 | T5: FY2026 | U5: FY2027 | V5: FY2028 | AJ5: Cases picked | AK5: WH hours worked | AL5: Staff payroll | AM5: Leadership payroll | AN5: Total payroll | AP5: Cases picked | AQ5: WH hours worked | AR5: Staff payroll | AS5: Leadership payroll | AT5: Total payroll | AV5: Cases picked | AW5: WH hours worked | AX5: Staff payroll | AY5: Leadership payroll | AZ5: Total payroll
A6: 2025 | D6: =IF(DATE(A6,12,1)<=LastActual,"Actual",IF(DATE(A6,1,1)>LastActual,"Forecast","Blended")) | E6: =SUMIFS($E$15:$E$62,$B$15:$B$62,$A6) | F6: =SUMIFS($F$15:$F$62,$B$15:$B$62,$A6) | G6: =SUMIFS($G$15:$G$62,$B$15:$B$62,$A6) | H6: =SUMIFS($H$15:$H$62,$B$15:$B$62,$A6) | I6: =SUMIFS($I$15:$I$62,$B$15:$B$62,$A6) | J6: =SUMIFS($J$15:$J$62,$B$15:$B$62,$A6) | K6: =IFERROR(F6/G6,0) | L6: =IFERROR(H6/G6,0) | M6: =IFERROR(J6/F6,0) | N6: =IFERROR(J6/E6,0) | O6: =IFERROR(I6/J6,0) | R6: =Inputs!$A$36 | S6: =SUMIFS('NSW-1'!$J$15:$J$62,'NSW-1'!$B$15:$B$62,2025) | T6: =SUMIFS('NSW-1'!$J$15:$J$62,'NSW-1'!$B$15:$B$62,2026) | U6: =SUMIFS('NSW-1'!$J$15:$J$62,'NSW-1'!$B$15:$B$62,2027) | V6: =SUMIFS('NSW-1'!$J$15:$J$62,'NSW-1'!$B$15:$B$62,2028) | AJ6: =SUMIFS($AJ$15:$AJ$62,$B$15:$B$62,$A6) | AK6: =SUMIFS($AK$15:$AK$62,$B$15:$B$62,$A6) | AL6: =SUMIFS($AL$15:$AL$62,$B$15:$B$62,$A6) | AM6: =SUMIFS($AM$15:$AM$62,$B$15:$B$62,$A6) | AN6: =SUMIFS($AN$15:$AN$62,$B$15:$B$62,$A6) | AP6: =SUMIFS($AP$15:$AP$62,$B$15:$B$62,$A6) | AQ6: =SUMIFS($AQ$15:$AQ$62,$B$15:$B$62,$A6) | AR6: =SUMIFS($AR$15:$AR$62,$B$15:$B$62,$A6) | AS6: =SUMIFS($AS$15:$AS$62,$B$15:$B$62,$A6) | AT6: =SUMIFS($AT$15:$AT$62,$B$15:$B$62,$A6) | AV6: =SUMIFS($AV$15:$AV$62,$B$15:$B$62,$A6) | AW6: =SUMIFS($AW$15:$AW$62,$B$15:$B$62,$A6) | AX6: =SUMIFS($AX$15:$AX$62,$B$15:$B$62,$A6) | AY6: =SUMIFS($AY$15:$AY$62,$B$15:$B$62,$A6) | AZ6: =SUMIFS($AZ$15:$AZ$62,$B$15:$B$62,$A6)
A7: 2026 | D7: =IF(DATE(A7,12,1)<=LastActual,"Actual",IF(DATE(A7,1,1)>LastActual,"Forecast","Blended")) | E7: =SUMIFS($E$15:$E$62,$B$15:$B$62,$A7) | F7: =SUMIFS($F$15:$F$62,$B$15:$B$62,$A7) | G7: =SUMIFS($G$15:$G$62,$B$15:$B$62,$A7) | H7: =SUMIFS($H$15:$H$62,$B$15:$B$62,$A7) | I7: =SUMIFS($I$15:$I$62,$B$15:$B$62,$A7) | J7: =SUMIFS($J$15:$J$62,$B$15:$B$62,$A7) | K7: =IFERROR(F7/G7,0) | L7: =IFERROR(H7/G7,0) | M7: =IFERROR(J7/F7,0) | N7: =IFERROR(J7/E7,0) | O7: =IFERROR(I7/J7,0) | R7: =Inputs!$A$37 | S7: =SUMIFS('VIC-1'!$J$15:$J$62,'VIC-1'!$B$15:$B$62,2025) | T7: =SUMIFS('VIC-1'!$J$15:$J$62,'VIC-1'!$B$15:$B$62,2026) | U7: =SUMIFS('VIC-1'!$J$15:$J$62,'VIC-1'!$B$15:$B$62,2027) | V7: =SUMIFS('VIC-1'!$J$15:$J$62,'VIC-1'!$B$15:$B$62,2028) | AJ7: =SUMIFS($AJ$15:$AJ$62,$B$15:$B$62,$A7) | AK7: =SUMIFS($AK$15:$AK$62,$B$15:$B$62,$A7) | AL7: =SUMIFS($AL$15:$AL$62,$B$15:$B$62,$A7) | AM7: =SUMIFS($AM$15:$AM$62,$B$15:$B$62,$A7) | AN7: =SUMIFS($AN$15:$AN$62,$B$15:$B$62,$A7) | AP7: =SUMIFS($AP$15:$AP$62,$B$15:$B$62,$A7) | AQ7: =SUMIFS($AQ$15:$AQ$62,$B$15:$B$62,$A7) | AR7: =SUMIFS($AR$15:$AR$62,$B$15:$B$62,$A7) | AS7: =SUMIFS($AS$15:$AS$62,$B$15:$B$62,$A7) | AT7: =SUMIFS($AT$15:$AT$62,$B$15:$B$62,$A7) | AV7: =SUMIFS($AV$15:$AV$62,$B$15:$B$62,$A7) | AW7: =SUMIFS($AW$15:$AW$62,$B$15:$B$62,$A7) | AX7: =SUMIFS($AX$15:$AX$62,$B$15:$B$62,$A7) | AY7: =SUMIFS($AY$15:$AY$62,$B$15:$B$62,$A7) | AZ7: =SUMIFS($AZ$15:$AZ$62,$B$15:$B$62,$A7)
A8: 2027 | D8: =IF(DATE(A8,12,1)<=LastActual,"Actual",IF(DATE(A8,1,1)>LastActual,"Forecast","Blended")) | E8: =SUMIFS($E$15:$E$62,$B$15:$B$62,$A8) | F8: =SUMIFS($F$15:$F$62,$B$15:$B$62,$A8) | G8: =SUMIFS($G$15:$G$62,$B$15:$B$62,$A8) | H8: =SUMIFS($H$15:$H$62,$B$15:$B$62,$A8) | I8: =SUMIFS($I$15:$I$62,$B$15:$B$62,$A8) | J8: =SUMIFS($J$15:$J$62,$B$15:$B$62,$A8) | K8: =IFERROR(F8/G8,0) | L8: =IFERROR(H8/G8,0) | M8: =IFERROR(J8/F8,0) | N8: =IFERROR(J8/E8,0) | O8: =IFERROR(I8/J8,0) | R8: =Inputs!$A$38 | S8: =SUMIFS('QLD-1'!$J$15:$J$62,'QLD-1'!$B$15:$B$62,2025) | T8: =SUMIFS('QLD-1'!$J$15:$J$62,'QLD-1'!$B$15:$B$62,2026) | U8: =SUMIFS('QLD-1'!$J$15:$J$62,'QLD-1'!$B$15:$B$62,2027) | V8: =SUMIFS('QLD-1'!$J$15:$J$62,'QLD-1'!$B$15:$B$62,2028) | AJ8: =SUMIFS($AJ$15:$AJ$62,$B$15:$B$62,$A8) | AK8: =SUMIFS($AK$15:$AK$62,$B$15:$B$62,$A8) | AL8: =SUMIFS($AL$15:$AL$62,$B$15:$B$62,$A8) | AM8: =SUMIFS($AM$15:$AM$62,$B$15:$B$62,$A8) | AN8: =SUMIFS($AN$15:$AN$62,$B$15:$B$62,$A8) | AP8: =SUMIFS($AP$15:$AP$62,$B$15:$B$62,$A8) | AQ8: =SUMIFS($AQ$15:$AQ$62,$B$15:$B$62,$A8) | AR8: =SUMIFS($AR$15:$AR$62,$B$15:$B$62,$A8) | AS8: =SUMIFS($AS$15:$AS$62,$B$15:$B$62,$A8) | AT8: =SUMIFS($AT$15:$AT$62,$B$15:$B$62,$A8) | AV8: =SUMIFS($AV$15:$AV$62,$B$15:$B$62,$A8) | AW8: =SUMIFS($AW$15:$AW$62,$B$15:$B$62,$A8) | AX8: =SUMIFS($AX$15:$AX$62,$B$15:$B$62,$A8) | AY8: =SUMIFS($AY$15:$AY$62,$B$15:$B$62,$A8) | AZ8: =SUMIFS($AZ$15:$AZ$62,$B$15:$B$62,$A8)
A9: 2028 | D9: =IF(DATE(A9,12,1)<=LastActual,"Actual",IF(DATE(A9,1,1)>LastActual,"Forecast","Blended")) | E9: =SUMIFS($E$15:$E$62,$B$15:$B$62,$A9) | F9: =SUMIFS($F$15:$F$62,$B$15:$B$62,$A9) | G9: =SUMIFS($G$15:$G$62,$B$15:$B$62,$A9) | H9: =SUMIFS($H$15:$H$62,$B$15:$B$62,$A9) | I9: =SUMIFS($I$15:$I$62,$B$15:$B$62,$A9) | J9: =SUMIFS($J$15:$J$62,$B$15:$B$62,$A9) | K9: =IFERROR(F9/G9,0) | L9: =IFERROR(H9/G9,0) | M9: =IFERROR(J9/F9,0) | N9: =IFERROR(J9/E9,0) | O9: =IFERROR(I9/J9,0) | R9: =Inputs!$A$39 | S9: =SUMIFS('NSW-2'!$J$15:$J$62,'NSW-2'!$B$15:$B$62,2025) | T9: =SUMIFS('NSW-2'!$J$15:$J$62,'NSW-2'!$B$15:$B$62,2026) | U9: =SUMIFS('NSW-2'!$J$15:$J$62,'NSW-2'!$B$15:$B$62,2027) | V9: =SUMIFS('NSW-2'!$J$15:$J$62,'NSW-2'!$B$15:$B$62,2028) | AJ9: =SUMIFS($AJ$15:$AJ$62,$B$15:$B$62,$A9) | AK9: =SUMIFS($AK$15:$AK$62,$B$15:$B$62,$A9) | AL9: =SUMIFS($AL$15:$AL$62,$B$15:$B$62,$A9) | AM9: =SUMIFS($AM$15:$AM$62,$B$15:$B$62,$A9) | AN9: =SUMIFS($AN$15:$AN$62,$B$15:$B$62,$A9) | AP9: =SUMIFS($AP$15:$AP$62,$B$15:$B$62,$A9) | AQ9: =SUMIFS($AQ$15:$AQ$62,$B$15:$B$62,$A9) | AR9: =SUMIFS($AR$15:$AR$62,$B$15:$B$62,$A9) | AS9: =SUMIFS($AS$15:$AS$62,$B$15:$B$62,$A9) | AT9: =SUMIFS($AT$15:$AT$62,$B$15:$B$62,$A9) | AV9: =SUMIFS($AV$15:$AV$62,$B$15:$B$62,$A9) | AW9: =SUMIFS($AW$15:$AW$62,$B$15:$B$62,$A9) | AX9: =SUMIFS($AX$15:$AX$62,$B$15:$B$62,$A9) | AY9: =SUMIFS($AY$15:$AY$62,$B$15:$B$62,$A9) | AZ9: =SUMIFS($AZ$15:$AZ$62,$B$15:$B$62,$A9)
R10: =Inputs!$A$40 | S10: =SUMIFS('VIC-2'!$J$15:$J$62,'VIC-2'!$B$15:$B$62,2025) | T10: =SUMIFS('VIC-2'!$J$15:$J$62,'VIC-2'!$B$15:$B$62,2026) | U10: =SUMIFS('VIC-2'!$J$15:$J$62,'VIC-2'!$B$15:$B$62,2027) | V10: =SUMIFS('VIC-2'!$J$15:$J$62,'VIC-2'!$B$15:$B$62,2028) | AJ10: Chamber split (same CPLH and cost per hour in every chamber; mix from Chamber Weights)
R11: =Inputs!$A$41 | S11: =SUMIFS('QLD-2'!$J$15:$J$62,'QLD-2'!$B$15:$B$62,2025) | T11: =SUMIFS('QLD-2'!$J$15:$J$62,'QLD-2'!$B$15:$B$62,2026) | U11: =SUMIFS('QLD-2'!$J$15:$J$62,'QLD-2'!$B$15:$B$62,2027) | V11: =SUMIFS('QLD-2'!$J$15:$J$62,'QLD-2'!$B$15:$B$62,2028) | AJ11: Share of cases, all months | AK11: =IFERROR(SUM($AJ$15:$AJ$62)/SUM($F$15:$F$62),0) | AP11: Share of cases, all months | AQ11: =IFERROR(SUM($AP$15:$AP$62)/SUM($F$15:$F$62),0) | AV11: Share of cases, all months | AW11: =IFERROR(SUM($AV$15:$AV$62)/SUM($F$15:$F$62),0)
E12: Drivers | K12: Metrics | R12: =Inputs!$A$42 | S12: =SUMIFS('SA-1'!$J$15:$J$62,'SA-1'!$B$15:$B$62,2025) | T12: =SUMIFS('SA-1'!$J$15:$J$62,'SA-1'!$B$15:$B$62,2026) | U12: =SUMIFS('SA-1'!$J$15:$J$62,'SA-1'!$B$15:$B$62,2027) | V12: =SUMIFS('SA-1'!$J$15:$J$62,'SA-1'!$B$15:$B$62,2028) | AJ12: Ambient | AP12: Chiller | AV12: Freezer
A13: Month | B13: Year | C13: Mth | D13: Status | E13: Sales | F13: Cases picked | G13: WH hours worked | H13: Staff payroll | I13: Leadership payroll | J13: Total payroll | K13: CPLH (cases / hr) | L13: Cost per hour (staff) | M13: Cost per case (total payroll) | N13: Total payroll % sales | O13: Leadership % of total payroll | R13: =Inputs!$A$43 | S13: =SUMIFS('WA-1'!$J$15:$J$62,'WA-1'!$B$15:$B$62,2025) | T13: =SUMIFS('WA-1'!$J$15:$J$62,'WA-1'!$B$15:$B$62,2026) | U13: =SUMIFS('WA-1'!$J$15:$J$62,'WA-1'!$B$15:$B$62,2027) | V13: =SUMIFS('WA-1'!$J$15:$J$62,'WA-1'!$B$15:$B$62,2028) | AJ13: Cases picked | AK13: WH hours worked | AL13: Staff payroll | AM13: Leadership payroll | AN13: Total payroll | AP13: Cases picked | AQ13: WH hours worked | AR13: Staff payroll | AS13: Leadership payroll | AT13: Total payroll | AV13: Cases picked | AW13: WH hours worked | AX13: Staff payroll | AY13: Leadership payroll | AZ13: Total payroll
E14: $m | F14: m | G14: # | H14: $m | I14: $m | J14: $m | K14: # | L14: $ | M14: $ | N14: % | O14: % | R14: =Inputs!$A$44 | S14: =SUMIFS('IDC-NSW'!$J$15:$J$62,'IDC-NSW'!$B$15:$B$62,2025) | T14: =SUMIFS('IDC-NSW'!$J$15:$J$62,'IDC-NSW'!$B$15:$B$62,2026) | U14: =SUMIFS('IDC-NSW'!$J$15:$J$62,'IDC-NSW'!$B$15:$B$62,2027) | V14: =SUMIFS('IDC-NSW'!$J$15:$J$62,'IDC-NSW'!$B$15:$B$62,2028) | AJ14: m | AK14: # | AL14: $m | AM14: $m | AN14: $m | AP14: m | AQ14: # | AR14: $m | AS14: $m | AT14: $m | AV14: m | AW14: # | AX14: $m | AY14: $m | AZ14: $m
A15: 45658 | B15: =YEAR(A15) | C15: =MONTH(A15) | D15: =IF(A15<=LastActual,"Actual","Forecast") | E15: ='NSW-1'!E15+'VIC-1'!E15+'QLD-1'!E15+'NSW-2'!E15+'VIC-2'!E15+'QLD-2'!E15+'SA-1'!E15+'WA-1'!E15 | F15: ='NSW-1'!F15+'VIC-1'!F15+'QLD-1'!F15+'NSW-2'!F15+'VIC-2'!F15+'QLD-2'!F15+'SA-1'!F15+'WA-1'!F15+'IDC-NSW'!F15+'IDC-VIC'!F15 | G15: ='NSW-1'!G15+'VIC-1'!G15+'QLD-1'!G15+'NSW-2'!G15+'VIC-2'!G15+'QLD-2'!G15+'SA-1'!G15+'WA-1'!G15+'IDC-NSW'!G15+'IDC-VIC'!G15 | H15: ='NSW-1'!H15+'VIC-1'!H15+'QLD-1'!H15+'NSW-2'!H15+'VIC-2'!H15+'QLD-2'!H15+'SA-1'!H15+'WA-1'!H15+'IDC-NSW'!H15+'IDC-VIC'!H15 | I15: ='NSW-1'!I15+'VIC-1'!I15+'QLD-1'!I15+'NSW-2'!I15+'VIC-2'!I15+'QLD-2'!I15+'SA-1'!I15+'WA-1'!I15+'IDC-NSW'!I15+'IDC-VIC'!I15 | J15: ='NSW-1'!J15+'VIC-1'!J15+'QLD-1'!J15+'NSW-2'!J15+'VIC-2'!J15+'QLD-2'!J15+'SA-1'!J15+'WA-1'!J15+'IDC-NSW'!J15+'IDC-VIC'!J15 | K15: =IFERROR(F15/G15,0) | L15: =IFERROR(H15/G15,0) | M15: =IFERROR(J15/F15,0) | N15: =IFERROR(J15/E15,0) | O15: =IFERROR(I15/J15,0) | R15: =Inputs!$A$45 | S15: =SUMIFS('IDC-VIC'!$J$15:$J$62,'IDC-VIC'!$B$15:$B$62,2025) | T15: =SUMIFS('IDC-VIC'!$J$15:$J$62,'IDC-VIC'!$B$15:$B$62,2026) | U15: =SUMIFS('IDC-VIC'!$J$15:$J$62,'IDC-VIC'!$B$15:$B$62,2027) | V15: =SUMIFS('IDC-VIC'!$J$15:$J$62,'IDC-VIC'!$B$15:$B$62,2028) | AJ15: ='NSW-1'!AJ15+'VIC-1'!AJ15+'QLD-1'!AJ15+'NSW-2'!AJ15+'VIC-2'!AJ15+'QLD-2'!AJ15+'SA-1'!AJ15+'WA-1'!AJ15+'IDC-NSW'!AJ15+'IDC-VIC'!AJ15 | AK15: ='NSW-1'!AK15+'VIC-1'!AK15+'QLD-1'!AK15+'NSW-2'!AK15+'VIC-2'!AK15+'QLD-2'!AK15+'SA-1'!AK15+'WA-1'!AK15+'IDC-NSW'!AK15+'IDC-VIC'!AK15 | AL15: ='NSW-1'!AL15+'VIC-1'!AL15+'QLD-1'!AL15+'NSW-2'!AL15+'VIC-2'!AL15+'QLD-2'!AL15+'SA-1'!AL15+'WA-1'!AL15+'IDC-NSW'!AL15+'IDC-VIC'!AL15 | AM15: ='NSW-1'!AM15+'VIC-1'!AM15+'QLD-1'!AM15+'NSW-2'!AM15+'VIC-2'!AM15+'QLD-2'!AM15+'SA-1'!AM15+'WA-1'!AM15+'IDC-NSW'!AM15+'IDC-VIC'!AM15 | AN15: ='NSW-1'!AN15+'VIC-1'!AN15+'QLD-1'!AN15+'NSW-2'!AN15+'VIC-2'!AN15+'QLD-2'!AN15+'SA-1'!AN15+'WA-1'!AN15+'IDC-NSW'!AN15+'IDC-VIC'!AN15 | AP15: ='NSW-1'!AP15+'VIC-1'!AP15+'QLD-1'!AP15+'NSW-2'!AP15+'VIC-2'!AP15+'QLD-2'!AP15+'SA-1'!AP15+'WA-1'!AP15+'IDC-NSW'!AP15+'IDC-VIC'!AP15 | AQ15: ='NSW-1'!AQ15+'VIC-1'!AQ15+'QLD-1'!AQ15+'NSW-2'!AQ15+'VIC-2'!AQ15+'QLD-2'!AQ15+'SA-1'!AQ15+'WA-1'!AQ15+'IDC-NSW'!AQ15+'IDC-VIC'!AQ15 | AR15: ='NSW-1'!AR15+'VIC-1'!AR15+'QLD-1'!AR15+'NSW-2'!AR15+'VIC-2'!AR15+'QLD-2'!AR15+'SA-1'!AR15+'WA-1'!AR15+'IDC-NSW'!AR15+'IDC-VIC'!AR15 | AS15: ='NSW-1'!AS15+'VIC-1'!AS15+'QLD-1'!AS15+'NSW-2'!AS15+'VIC-2'!AS15+'QLD-2'!AS15+'SA-1'!AS15+'WA-1'!AS15+'IDC-NSW'!AS15+'IDC-VIC'!AS15 | AT15: ='NSW-1'!AT15+'VIC-1'!AT15+'QLD-1'!AT15+'NSW-2'!AT15+'VIC-2'!AT15+'QLD-2'!AT15+'SA-1'!AT15+'WA-1'!AT15+'IDC-NSW'!AT15+'IDC-VIC'!AT15 | AV15: ='NSW-1'!AV15+'VIC-1'!AV15+'QLD-1'!AV15+'NSW-2'!AV15+'VIC-2'!AV15+'QLD-2'!AV15+'SA-1'!AV15+'WA-1'!AV15+'IDC-NSW'!AV15+'IDC-VIC'!AV15 | AW15: ='NSW-1'!AW15+'VIC-1'!AW15+'QLD-1'!AW15+'NSW-2'!AW15+'VIC-2'!AW15+'QLD-2'!AW15+'SA-1'!AW15+'WA-1'!AW15+'IDC-NSW'!AW15+'IDC-VIC'!AW15 | AX15: ='NSW-1'!AX15+'VIC-1'!AX15+'QLD-1'!AX15+'NSW-2'!AX15+'VIC-2'!AX15+'QLD-2'!AX15+'SA-1'!AX15+'WA-1'!AX15+'IDC-NSW'!AX15+'IDC-VIC'!AX15 | AY15: ='NSW-1'!AY15+'VIC-1'!AY15+'QLD-1'!AY15+'NSW-2'!AY15+'VIC-2'!AY15+'QLD-2'!AY15+'SA-1'!AY15+'WA-1'!AY15+'IDC-NSW'!AY15+'IDC-VIC'!AY15 | AZ15: ='NSW-1'!AZ15+'VIC-1'!AZ15+'QLD-1'!AZ15+'NSW-2'!AZ15+'VIC-2'!AZ15+'QLD-2'!AZ15+'SA-1'!AZ15+'WA-1'!AZ15+'IDC-NSW'!AZ15+'IDC-VIC'!AZ15
